Workbook

Sheet Project Input
A1: Easy Housing - Calculation Template - January 2026 | B1: Last update: 16-04-2026 by Wolf
A3: Instructions
A4: Open floor plan (.pdf) for which quote has to be made
A5: Fill out the input fields below
A6: Check if parameters like floor area correspond with plan
A7: Open Google Slide: "Easy Housing - Quotation Template Uganda - July 2025"
A8: Update the two tables in the slide
A9: Check if quotation values are properly linked to the template
A10: Do not adjust text or fields in slide template
A11: Create a copy of Google slide doc quote template (from the right country)
A12: Copy the input column in this spreadsheet to the Input Database from column K onwards (for future reference)
A13: Download Google Slide as .pdf and save in the shared quotation folder on the drive
A14: File name format: "YYMMDD - Easy Housing Quotation - Client Name in Location"
... A17: Sign the contract! :)
A20: Project input | B20: Input values | C20: Unit | D20: Comment
A21: Client input
A22: ='Price Calc'!A13 -> Client Name | B22: Funky Jackfruit | C22: name | D22: Full name
A23: ='Price Calc'!A14 -> Contact Details | B23: +256 712 345 678 | C23: phone/mail | D23: Add phone or email
A24: ='Price Calc'!A23 -> Project Location | B24: Sagala | C24: location | D24: Add name municipality (village/town/city)
A25: ='Price Calc'!A24 -> Distance from factory | B25: 50 | C25: km | D25: With Google maps
A26: Date of input | B26: 46023 | C26: date | D26: DD/MM/YYYY
A27: ='Price Calc'!A15 -> Created by | B27: Wolf Bierens | C27: name | D27: Add your full name
A29: Building input (structure parameters)
A30: ='Price Calc'!A18 -> Easy Housing Typology | B30: Mono Pitch (4884) | D30: Select right typology (mm depth of building between brackets to check if not sure)
A31: Number of units (of exactly this type) | B31: 1 | C31: home(s) | D31: Make separate quotes for different models / plans
A32: ='Price Calc'!A59 -> Columns A (1221) | B32: 2 | C32: columns
A33: ='Price Calc'!A60 -> Columns B (2442) | B33: 4 | C33: columns
A34: ='Price Calc'!A61 -> Columns C (3053) | B34: 0 | C34: columns | D34: Not used for A-Frames and Compact Gable | H34: Total GFA | I34: ='Price Calc'!H19 -> 61.2 | J34: sqm (without extra terraces)
A35: ='Price Calc'!A64 -> Interior doors | B35: 6 | C35: pcs
A36: ='Price Calc'!A65 -> Partitions (length) | B36: 27 | C36: linear metres
A37: ='Price Calc'!A66 -> Exterior doors & windows (area) | B37: =D81 -> 10.5 | C37: sqm | D37: Total alu - fill tool below - cell linked to D81
A38: Bedrooms | B38: 2 | C38: number
A39: Bathrooms | B39: 2 | C39: number | D39: Count for plumbing
A40: Kitchen areas | B40: 1 | C40: number | D40: Count for plumbing. Kitchen islands count separately.
A42: Additional options
A43: ='Price Calc'!A41 -> Terrace | B43: 0 | C43: sqm | D43: Inside verandas under roof section are not counted (as they are within typology GFA)
A44: ='Price Calc'!A42 -> Pergola | B44: 0 | C44: sqm | D44: Price for open pergola without sheets
A45: ='Price Calc'!A43 -> Railing open | B45: 0 | C45: linear metres
A46: ='Price Calc'!A44 -> Railing semi-closed | B46: 0 | C46: linear metres
A47: ='Price Calc'!A67 -> Extra staircase (beyond the first) | B47: 0 | C47: pcs | D47: First staircase included - not counted
A48: ='Price Calc'!A40 -> Burglar bars | B48: 0 | C48: sqm | D48: Pro tip: use window tool below
A49: ='Price Calc'!A45 -> Wheelchair ramp | B49: 0 | C49: pcs
A50: ='Price Calc'!A46 -> Tiles | B50: 0 | C50: quote price | D50: case by case
A51: ='Price Calc'!A47 -> Sanitary wares | B51: 0 | C51: quote price | D51: case by case
A52: ='Price Calc'!A48 -> Biodigester | B52: 0 | C52: quote price | D52: Default 3M for normal home and 3.5M for large home (>90sqm)
A53: Other option(s) description | C53: text input | D53: Leave empty if no other options
A54: Other option(s) price | C54: price | D54: Leave empty if no other options
A58: Calculation Tool for Surface Of Windows and Exterior Doors
A59: Instructions: First put all orange cells below to zero and then fill out the amounts of standard windows/doors and in the last orange cell extra surface area of non-standard doors/windows
A60: Standard type | B60: Amount | C60: Surface per item | D60: Total area sqm per line | E60: Default name
A61: Entrance door 950 x 2388 | B61: 0 | C61: 2.2686 | D61: =B61*C61 -> 0
A62: Terrace swing doors 1700 x 2388 | B62: 0 | C62: 4.0596 | D62: =B62*C62 -> 0
A63: Sliding doors 1700 x 2388 | B63: 0 | C63: 4.0596 | D63: =B63*C63 -> 0
A64: Sliding doors 2100 x 2388 | B64: 0 | C64: =2.1*2.388 -> 5.0148 | D64: =B64*C64 -> 0
A65: Sliding doors 2300 x 2388 | B65: 0 | C65: 5.4924 | D65: =B65*C65 -> 0
A66: Sliding doors 2900 x 2388 | B66: 0 | C66: 6.9252 | D66: =B66*C66 -> 0
A67: Sliding doors 3510 x 2388 | B67: 0 | C67: 8.38188 | D67: =B67*C67 -> 0
A68: Bathroom window 500 x 1316 | B68: 2 | C68: 0.658 | D68: =B68*C68 -> 1.316
A69: Bathroom window 900 x 1316 | B69: 0 | C69: 1.1844 | D69: =B69*C69 -> 0
A70: Sliding window 1100 x 1316 | B70: 0 | C70: 1.4476 | D70: =B70*C70 -> 0
A71: Sliding window 1400 x 1316 | B71: 5 | C71: 1.8424 | D71: =B71*C71 -> 9.212 | E71: WS3
A72: Sliding window 1700 x 1316 | B72: 0 | C72: =1.7*1.316 -> 2.2372 | D72: =B72*C72 -> 0 | E72: WS4
A73: High window (fixed) 1100 x 1766 | B73: 0 | C73: 1.9426 | D73: =B73*C73 -> 0
A74: High window (fixed) 1700 x 1766 | B74: 0 | C74: 3.0022 | D74: =B74*C74 -> 0
A75: Full height window (fixed) 500 x 2366 | B75: 0 | C75: 1.183 | D75: =B75*C75 -> 0
A76: Full height window (fixed) 1100 x 2366 | B76: 0 | C76: 2.6026 | D76: =B76*C76 -> 0
A77: Panorama window (fixed) 1400 x 846 | B77: 0 | C77: =1.4*0.846 -> 1.1844 | D77: =B77*C77 -> 0
A78: Panorama window (fixed) 1700 x 846 | B78: 0 | C78: 1.4382 | D78: =B78*C78 -> 0
A79: Panorama window (fixed) 2300 x 846 | B79: 0 | C79: 1.9458 | D79: =B79*C79 -> 0 | E79: =sum(B61:B79) -> 7 | F79: Sum count standard size windows
A80: Other windows and doors in sqm | B80: 0 | C80: sqm | D80: =B80 -> 0
A81: Total windows and doors area (sqm) | C81: Surface: | D81: =round(SUM(D61:D80),1) -> 10.5 | E81: sqm - use this as input for aluminium surface area

Sheet Project Costs
A5: Easy Housing - Calculation Template 2026
A6: ! Do not share sheets or extracts externally unless authorised !
A8: Project parameters | I8: Calculations | J8: Typologies | L8: Floor frame A | M8: Floor frame B | N8: Floor frame C | O8: Floor frame D (3363) | P8: Foundation | Q8: Wall B low | R8: Wall C low | S8: Wall B high | T8: Wall C high | U8: Roof frame 1221 x 5685 (mono pitch) | V8: Roof frame 1598x 5685 (mono pitch edge) | W8: Roof frame 1221 x 3574 (compact gable) | X8: Roof frame 1689 x 3574 (compact gable edge) | Y8: Roof frame 1221 x 4194 (standard gable) | Z8: Roof frame 1689 x 4194 (standard gable edge) | AA8: Roof frame 1221 x 5435 (large gable) | AB8: Roof frame 1689 x 5435 (large gable edge) | AC8: Roof frame 1221 x 5780 (clerestory upper) | AD8: Roof frame 1689 x 5780 (clerestory upper edge) | AE8: Roof frame 1221 x 4194 (clerestory lower) | AF8: Roof frame 1689 x 4194 (clerestory lower edge)
J9: Mono Pitch (4884) | L9: =2*$E$24 -> 4 | M9: =2*$E$25 -> 8 | N9: =2*$E$26 -> 0 | O9: =2*$E$26 -> 0 | P9: =3*(sum($E$24:$E$26)+1) -> 21 | Q9: =E25+0.5*E24 -> 5 | R9: =E26 -> 0 | S9: =4+E25+0.5*E24 -> 9 | T9: =E26 -> 0 | U9: =E24+2*E25+2.5*E26-2 -> 8 | V9: 2
A10: Project location parameters | B10: Kampala, Uganda | J10: Compact Gable (6106) | L10: 0 | M10: 0 | N10: =E25*2+E24 -> 10 | O10: =2*$E$26 -> 0 | P10: =3*(sum($E$24:$E$26)+1) -> 21 | Q10: =E25*2+E24 -> 10 | R10: 0 | S10: 0 | T10: 4 | W10: =(E24+2*E25+2.5*E26-2)*2 -> 16 | X10: 4
A11: Project code | B11: EH-000 | J11: Standard Gable (7326) | L11: =3*$E$24 -> 6 | M11: =3*$E$25 -> 12 | N11: =3*$E$26 -> 0 | O11: =2*$E$26 -> 0 | P11: =4*(sum($E$24:$E$26)+1) -> 28 | Q11: =E25*2+E24 -> 10 | R11: =E26*2 -> 0 | S11: 6 | T11: 0 | Y11: =(E24+2*E25+2.5*E26-2)*2 -> 16 | Z11: 4
A12: Project name | J12: Large Gable (9768) | L12: =4*$E$24 -> 8 | M12: =4*$E$25 -> 16 | N12: =4*$E$26 -> 0 | O12: =2*$E$26 -> 0 | P12: =5*(sum($E$24:$E$26)+1) -> 35 | Q12: =E25*2+E24 -> 10 | R12: =E26*2 -> 0 | S12: 8 | T12: 0 | AA12: =Y11 -> 16 | AB12: =Z11 -> 4
A13: Project Location | B13: Greater Kampala (<100km from factory) | J13: Standard Clerestory (7326) | L13: =3*$E$24 -> 6 | M13: =3*$E$25 -> 12 | N13: =3*$E$26 -> 0 | O13: =2*$E$26 -> 0 | P13: =4*(sum($E$24:$E$26)+1) -> 28 | Q13: =E25+0.5*E24 -> 5 | R13: =E26 -> 0 | S13: =6+E25+0.5*E24 -> 11 | T13: =E26 -> 0 | AC13: =U9 -> 8 | AD13: 2 | AE13: =AC13 -> 8 | AF13: 2
A14: Client name | B14: Example calculation | J14: Large Clerestory (8547) | L14: =3.5*$E$24 -> 7 | M14: =3.5*$E$25 -> 14 | N14: =3.5*$E$26 -> 0 | O14: =2*$E$26 -> 0 | P14: =5*(sum($E$24:$E$26)+1) -> 35 | Q14: =Q13 -> 5 | R14: =R13 -> 0 | S14: =S13+1 -> 12 | T14: =T13 -> 0 | AC14: =AC13 -> 8 | AD14: 2 | AE14: =AC13 -> 8 | AF14: 2
J15: A Frame Compact (3663) | O15: =E25+0.5*E24 -> 5 | P15: =2*(sum($E$24:$E$26)+1) -> 14 | T15: 2 | U15: =2*(E24+2*E25+2.5*E26-2) -> 16 | V15: 4
J16: A Frame Standard (4884) | M16: =2*E25+E24 -> 10 | O16: =2*$E$26 -> 0 | P16: =3*(sum($E$24:$E$26)+1) -> 21 | S16: 4 | U16: =2*(E24+2*E25+2.5*E26-2) -> 16 | V16: 4
J17: A Frame Large (6106) | N17: =2*E25 -> 8 | O17: =2*$E$26 -> 0 | P17: =3*(sum($E$24:$E$26)+1) -> 21 | T17: 4 | U17: =2*(E24+2*E25+2.5*E26-2) -> 16 | V17: 4
A18: Date created | B18: =today() -> 46128 | I18: Selected: | J18: =E22 -> Mono Pitch (4884) | L18: =index(L9:L17,match($J$18,$J$9:$J$17,0),1) -> 4 | M18: =index(M9:M17,match($J$18,$J$9:$J$17,0),1) -> 8 | N18: =index(N9:N17,match($J$18,$J$9:$J$17,0),1) -> 0 | O18: =index(O9:O17,match($J$18,$J$9:$J$17,0),1) -> 0 | P18: =index(P9:P17,match($J$18,$J$9:$J$17,0),1) -> 21 | Q18: =index(Q9:Q17,match($J$18,$J$9:$J$17,0),1) -> 5 | R18: =index(R9:R17,match($J$18,$J$9:$J$17,0),1) -> 0 | S18: =index(S9:S17,match($J$18,$J$9:$J$17,0),1) -> 9 | ... AF18: =index(AF9:AF17,match($J$18,$J$9:$J$17,0),1)
A21: Building parameters | D21: Quick Input Tool - now linked to input tab, do not overwrite | J21: Subcontractor / supplier budget overview * | O21: Labour time overview
A22: Building typology | B22: =E22 -> Mono Pitch (4884) | D22: Typology | E22: ='Project Input'!B30 -> Mono Pitch (4884)
A23: Gross floor surface (sqm) | B23: =sum(V68:V70)+0.044*(A75*2.442+A76*3.053+A77*2.442+A78*3.053) -> 61.137912 | D23: Name | E23: ='Project Input'!B22 -> Funky Jackfruit | J23: Description | M23: =B37&" ex VAT **" -> UGX ex VAT ** | O23: Description | R23: Labour days
A24: Decking surface area (sqm) | B24: =sum(V72:V74) -> 0 | D24: Floor A - 1221 | E24: ='Project Input'!B32 -> 2 | F24: columns | J24: Foundation blocks | M24: =J121 -> 3364420.2 | O24: Prefabrication labour | R24: =roundup(sum(T68:T94)/8,0) -> 50
A25: Net floor surface without decking/walls | B25: =sum(V68:V70)-0.099*(A75*2.442+A76*3.053+A77*2.442+A78*3.053) -> 56.249028 | D25: Floor B - 2442 | E25: ='Project Input'!B33 -> 4 | F25: columns | G25: use for compact gable | J25: Aluminium doors and windows | M25: =sum(J99:J114) -> 0 | O25: Foundation casting and placement | R25: =round(T121/8,0) -> 9
A26: Exterior wall surface (sqm) | B26: =sum(V75:V78) -> 104.1977 | D26: Floor C - 3053 | E26: ='Project Input'!B34 -> 0 | F26: columns | J26: Interior doors | M26: =J122 -> 4440000 | O26: Site placement labour | R26: =roundup(0.5*$B$23,0) -> 31
A27: Outer windows and doors (sqm) | B27: =sum(V99:V114)+A115 -> 10.5 | D27: Partitions | E27: ='Project Input'!B36 -> 27 | F27: m1 / default at 30% of GFA | G27: 0.3 | H27: =G23*B19 | J27: Roof sheets, inc screws, ridges, gutters, labour | M27: =J123 -> 3372996.5 | O27: Site finishings (steps, fascia, skirts, substrate) | R27: =roundup(B23*0.2+2+A125*0.2+A126,0) -> 20
A28: Net facade surface (sqm) | B28: =B26-B27 -> 93.697698 | D28: Interior doors | E28: ='Project Input'!B35 -> 6 | F28: pcs | J28: Paint works interior and exterior | M28: =J124 -> 8096898.2 | O28: Paint works (on site) | R28: =Round(T124/8,0) -> 32
A29: Partition wall surface (sqm) | B29: =V79*2 -> 162 | D29: Aluminium | E29: ='Project Input'!B37 -> 10.5 | F29: sqm / default at 20% of ext wall surface | G29: 0.2 | H29: =G25*B22 | J29: Truck frames transport to sites <100 km | M29: =J137 -> 1131051.4 | O29: Project manager | R29: =round(2+0.1*B23,0) -> 8
A30: Roof surface (sqm) | B30: =sum(V82:V93) -> 74.522832 | D30: Extra ext. wall | E30: 0 | F30: grid steps 61cm (indents etc) | J30: Electricity | M30: =J155 -> 5585343.4 | O30: Total | R30: =SUM(R24:R29) -> 150 | S30: days
A31: Number ext doors and windows (if filled) | B31: =sum(A99:A114) -> 0 | D31: Veranda A | E31: 0 | F31: frames | J31: Plumbing | M31: =J156 -> 2528447.8 | R31: =R30*8 -> 1200 | S31: hours
A32: Foundation type | B32: ='Bill of Quantities'!C35 -> Foundation block | D32: Veranda B | E32: 0 | F32: frames | J32: Cement boards bathrooms | M32: =J126 -> 2640698.3
A33: Foundation average height (mm) | B33: 400 | D33: Veranda C | E33: =roundup('Project Input'!B43/(3.05*2.44),0) -> 0 | F33: frames | J33: Plywood | M33: =sum('Bill of Quantities'!P52:P55)*B38 -> 4537575.9
A34: Distance from workshop (km) | B34: 100 | D34: Bathrooms | E34: ='Project Input'!B39 -> 2 | F34: bathroom(s) | J34: Timber | M34: ='Timber Order'!H35*'Bill of Quantities'!D14*B38 -> 10051388
J35: Roof insulation | M35: ='Bill of Quantities'!P83*B38 -> 396825
A36: Price information | J36: Wall insulation | M36: ='Bill of Quantities'!P84*B38 -> 982364.73
A37: ='Location Data'!C5 -> Currency | B37: {=index('Location Data'!C:C,MATCH($B$10,'Location Data'!A:A,0),1)} -> UGX | J37: Total | M37: =SUM(M23:M36) -> 47128009
A38: ='Location Data'!D5 -> Conversion rate from USD | B38: {=index('Location Data'!D:D,MATCH($B$10,'Location Data'!A:A,0),1)} -> 3700
A39: Margin | B39: 0.1
A40: ='Location Data'!E5 -> Value added tax (VAT) | B40: {=index('Location Data'!E:E,MATCH($B$10,'Location Data'!A:A,0),1)} -> 0.18 | J40: * subcontractor budgets are exclusive of VAT
A41: Cost price in USD ex VAT | B41: =D63 -> 20866.883 | J41: ** budgets incl all material, labour,transportation costs
A42: Margin | B42: =B41*B39 -> 2086.6883 | D42: Standard models
A43: Licence Fee Easy Building | B43: =C134 -> 1528.4478
A44: Sales price in USD ex VAT | B44: =B41+B42 -> 22953.572 | D44: Typology | E44: =J9 -> Mono Pitch (4884) | F44: =E44 -> Mono Pitch (4884) | G44: =F44 -> Mono Pitch (4884) | H44: =G44 -> Mono Pitch (4884) | I44: Compact Gable 6106 | J44: Compact Gable 6106 | K44: Compact Gable 6106 | L44: Compact Gable 6106 | M44: Compact Gable 6106 | N44: Standard Gable 7326 | O44: Standard Gable 7326 | P44: Standard Gable 7326 | Q44: Large Gable 9768 | R44: Clerestory 8547 | S44: Clerestory 8547 | T44: Clerestory 8547 | U44: Compact Gable 6106 | V44: Clerestory 7326 | W44: Clerestory 8547 | X44: Compact Gable 6106 | Y44: Mono Pitch 4884 | Z44: Clerestory 8547 | AA44: Mono Pitch 4884 | AB44: Clerestory 8547 | AC44: A Frame Large | AD44: A Frame Compact | AE44: A Frame Standard
A45: Price in USD in VAT | B45: =B44*B40+B44 -> 27085.214 | D45: Building width | E45: Studio | F45: 1BR Mono | G45: 2BR Mono | H45: 3BR Mono | I45: 1BR Compact Gable | J45: 2BR Compact Gable | K45: 3BR Compact Gable | L45: 4BR Compact Gable | M45: 2BR Comfort Compact Gable | N45: 2BR Gable | O45: 3BR Gable | P45: 4BR Gable | Q45: 3BR Large Gable | R45: 2BR Clerestory | S45: 4BR Clerestory | T45: Nisha's | U45: John's | V45: Sarah's | W45: Naomi & Jesse | X45: Mlango Farm | Y45: Milly | Z45: Naomi & Jesse | AA45: Janet | AB45: Pius O | AC45: Zziwa test | AD45: Compact A Frame | AE45: Standard A Frame
A46: Price per sqm GFA in USD in VAT | B46: =B45/B23 -> 443.01831 | D46: Floor A - 1221 | E46: 0 | F46: 0 | G46: 0 | H46: 0 | I46: 0 | J46: 0 | K46: 1 | L46: 0 | M46: 0 | N46: 0 | O46: 0 | P46: 0 | Q46: 0 | R46: 1 | S46: 1 | T46: 2 | U46: 0 | V46: 0 | W46: 2 | X46: 0 | Y46: 0 | Z46: 2 | AA46: 0 | AB46: 2 | AC46: 0 | AD46: 0 | AE46: 0
D47: Floor B - 2442 | E47: 2 | F47: 0 | G47: 1 | H47: 0 | I47: 3 | J47: 4 | K47: 4 | L47: 5 | M47: 5 | N47: 1 | O47: 4 | P47: 2 | Q47: 2 | R47: 0 | S47: 0 | T47: 0 | U47: 4 | V47: 2 | W47: 2 | X47: 4 | Y47: 1 | Z47: 2 | AA47: 0 | AB47: 4 | AC47: 4 | AD47: 3 | AE47: 3
A48: ="Price in "&B37&" ex VAT" -> Price in UGX ex VAT | B48: =round(B41*B38,0) -> 77207468 | D48: Floor C - 3053 | E48: 0 | F48: 2 | G48: 2 | H48: 3 | I48: 0 | J48: 0 | K48: 0 | L48: 0 | M48: 0 | N48: 3 | O48: 1 | P48: 3 | Q48: 2 | R48: 2 | S48: 3 | T48: 3 | U48: 0 | V48: 3 | W48: 1 | X48: 0 | Y48: 2 | Z48: 1 | AA48: 3 | AB48: 0 | AC48: 0 | AD48: 0 | AE48: 0
A49: Margin | B49: =B48*B39 -> 7720746.8 | D49: Partitions | E49: 4.5 | F49: 6 | G49: 12.5 | H49: 14 | I49: 10 | J49: 22 | K49: 24 | L49: 29 | M49: 24 | N49: 20 | O49: 38 | P49: 42.5 | Q49: 33 | R49: 15.5 | S49: 28.5 | T49: 29 | U49: 19.5 | V49: 35 | W49: 35 | X49: 17 | Y49: 12 | Z49: 35 | AA49: 14.5 | AB49: 32 | AC49: 9 | AD49: 5 | AE49: 6
A50: VAT | B50: =(B48+B49)*B40 -> 15287079 | D50: Interior doors | E50: 1 | F50: 2 | G50: 3 | H50: 4 | I50: 2 | J50: 4 | K50: 5 | L50: 6 | M50: 4 | N50: 4 | O50: 6 | P50: 7 | Q50: 5 | R50: 3 | S50: 6 | T50: 6 | U50: 4 | V50: 7 | W50: 5 | X50: 4 | Y50: 3 | Z50: 5 | AA50: 4 | AB50: 7 | AC50: 2 | AD50: 1 | AE50: 1
A51: ="Price in "&B37&" inclusive VAT" -> Price in UGX inclusive VAT | B51: =B48+B49+B50 -> 1.0021529e+08 | D51: Aluminium | E51: 7.2 | F51: 7.9 | G51: 10.2 | H51: 9.4 | I51: 16 | J51: 18.5 | K51: 20 | L51: 26 | M51: 26 | N51: 21 | O51: 19 | P51: 20.8 | Q51: 23.7 | R51: 18.9 | S51: 27.5 | T51: 34 | U51: 15 | V51: ? | W51: 27.6 | X51: 22 | Y51: 10.2 | Z51: 27.6 | AA51: 13.2 | AB51: 23 | AC51: 16 | AD51: 9 | AE51: 11
A52: ="Price per GFA sqm in "&B37&" inclusive VAT" -> Price per GFA sqm in UGX inclusive VAT | B52: =B51/B23 -> 1639167.7 | D52: Extra ext. wall | E52: 0 | F52: 0 | G52: 0 | H52: 4 | I52: 2 | J52: 2 | K52: 2 | L52: 2 | M52: 6 | N52: 0 | O52: 4 | P52: 4 | Q52: 0 | R52: 0 | S52: 4 | T52: 4 | U52: 0 | V52: 4 | W52: 0 | X52: 2 | Y52: 0 | Z52: 0 | AA52: 2 | AB52: 4 | AC52: 0 | AD52: 0 | AE52: 0
D53: Veranda A | E53: 0 | F53: 0 | G53: 0 | H53: 0 | I53: 0 | J53: 0 | K53: 0 | L53: 0 | M53: 0 | N53: 0 | O53: 0 | P53: 0 | Q53: 0 | R53: 0 | S53: 0 | T53: 2 | U53: 2 | V53: 0 | W53: 3 | X53: 0 | Y53: 0 | Z53: 3 | AA53: 0 | AB53: 1 | AC53: 2 | AD53: 0 | AE53: 2
D54: Veranda B | E54: 0 | F54: 0 | G54: 0 | H54: 0 | I54: 0 | J54: 0 | K54: 0 | L54: 0 | M54: 0 | N54: 0 | O54: 0 | P54: 0 | Q54: 0 | R54: 0 | S54: 0 | T54: 0 | U54: 0 | V54: 0 | W54: 1 | X54: 4 | Y54: 1 | Z54: 1 | AA54: 0 | AB54: 3 | AC54: 0 | AD54: 0 | AE54: 0
D55: Veranda C | E55: 0 | F55: 0 | G55: 0 | H55: 0 | I55: 0 | J55: 0 | K55: 0 | L55: 0 | M55: 0 | N55: 0 | O55: 0 | P55: 0 | Q55: 0 | R55: 0 | S55: 0 | T55: 3 | U55: 0 | V55: 2 | W55: 1 | X55: 0 | Y55: 2 | Z55: 1 | AA55: 0 | AB55: 0 | AC55: 2 | AD55: 0 | AE55: 0
D56: Bathrooms | E56: 1 | F56: 1 | G56: 1 | H56: 1 | I56: 1 | J56: 2 | K56: 2 | L56: 2 | M56: 2 | N56: 2 | O56: 3 | P56: 3 | Q56: 2 | R56: 1 | S56: 2 | T56: 2 | U56: 2 | V56: 3 | W56: 2 | X56: 2 | Y56: 1 | Z56: 2 | AA56: 1 | AB56: 2 | AC56: 1 | AD56: 1 | AE56: 1
C61: USD | I61: =B37 -> UGX | O61: Specs
A63: Building parameters (all prices below ex vat) | D63: =SUM(D64:D1089) -> 20866.883 | F63: =SUM(F67:F1089) -> 2071.6883 | H63: =sum(H64:H1089) -> 22788.572 | I63: Totals | J63: =sum(J64:J1089) -> 76652468 | L63: =sum(L64:L1089) -> 7665246.8 | N63: =sum(N64:N1089) -> 84317715 | P63: =SUM(P64:P1089) -> 9980.8518 | R63: =SUM(R64:R1089) -> 12446.624 | T63: =SUM(T64:T1089) -> 770.61103
AG64: Input Database
A65: Frames | C65: ! All costs and prices below are exclusive of VAT ! | AF65: Name | AG65: One Bedroom Urban | AH65: Two Bed Space | AI65: Three Bed Urban Test | AJ65: Studio BB Mono | AK65: 1BR CC Mono | AL65: 2BR CBC Mono | AM65: 3BR CCC Mono | AN65: 2BR Gable CBCC | AO65: 3BR Gable CBBBB | AP65: 4BR Gable CBBCC | AQ65: 2BR Clerestory CAC | AR65: 4BR Clerestory CCAC | AS65: 4BR Large Gable CBBC | AU65: Combined order for Busoga
A66: Amount | B66: Description | C66: Cost item ($) | D66: Cost total | E66: Margin item | F66: Margin total | G66: Price item | H66: Price total | I66: Cost item | J66: Cost total | K66: Margin item | L66: Margin total | M66: Price item | N66: Price total | O66: Weight item | P66: Weight total | Q66: Carbon item | R66: Carbon total | S66: Labour item | T66: Labour total | U66: Surface item | V66: Surface total | W66: Facade surface | X66: Facade total
A67: # | B67: Name | C67: USD | D67: USD | E67: USD | F67: USD | G67: USD | H67: USD | I67: =$B$37 -> UGX | J67: =$B$37 -> UGX | K67: =$B$37 -> UGX | L67: =$B$37 -> UGX | M67: =$B$37 -> UGX | N67: =$B$37 -> UGX | O67: kg | P67: kg | Q67: kg CO2 stored | R67: kg CO2 stored | S67: hours | T67: hours | U67: sqm | V67: sqm
A68: =L18 -> 4 | B68: ='Structures Database'!A22 -> Floor frame 2442 x 1221 | C68: =sumif('Structures Database'!$V:$V,$B68,'Structures Database'!U:U) -> 57.061748 | D68: =$A68*C68 -> 228.24699 | E68: =C68*$B$39 -> 5.7061748 | F68: =A68*E68 -> 22.824699 | G68: =C68+E68 -> 62.767923 | H68: =A68*G68 -> 251.07169 | I68: =C68*$B$38 -> 211128.47 | J68: =I68*A68 -> 844513.87 | K68: =E68*$B$38 -> 21112.847 | L68: =K68*A68 -> 84451.387 | M68: =G68*$B$38 -> 232241.31 | N68: =M68*A68 -> 928965.26 | O68: =sumif('Structures Database'!$V:$V,$B68,'Structures Database'!P:P) -> 92.523228 | P68: =$A68*O68 -> 370.09291 | Q68: =sumif('Structures Database'!$V:$V,$B68,'Structures Database'!Q:Q) -> 146.8144 | R68: =$A68*Q68 -> 587.2576 | S68: =sumif('Structures Database'!$V:$V,$B68,'Structures Database'!R:R)/60 -> 4.1833333 | T68: =A68*S68 -> 16.733333 | U68: =sumif('Structures Database'!$V:$V,$B68,'Structures Database'!Y:Y) -> 2.981682 | V68: =A68*U68 -> 11.926728 | AG68: 0 | AH68: 3.5 | AI68: 0 | AJ68: 0 | AK68: 0 | AL68: 0 | AM68: 0 | AN68: 0 | AO68: 0 | AP68: 0 | AQ68: 3.5 | AR68: 0.5 | AS68: 0 | AU68: =AJ68+AK68+AL68+AM68+AN68+AO68+AP68+AQ68+AR68+AS68 -> 4
A69: =M18 -> 8 | B69: ='Structures Database'!A31 -> Floor frame 2442 x 2442 | C69: =sumif('Structures Database'!$V:$V,$B69,'Structures Database'!U:U) -> 93.878539 | D69: =$A69*C69 -> 751.02831 | E69: =C69*$B$39 -> 9.3878539 | F69: =A69*E69 -> 75.102831 | G69: =C69+E69 -> 103.26639 | H69: =A69*G69 -> 826.13114 | I69: =C69*$B$38 -> 347350.59 | J69: =I69*A69 -> 2778804.8 | K69: =E69*$B$38 -> 34735.059 | L69: =K69*A69 -> 277880.48 | M69: =G69*$B$38 -> 382085.65 | N69: =M69*A69 -> 3056685.2 | O69: =sumif('Structures Database'!$V:$V,$B69,'Structures Database'!P:P) -> 156.20618 | P69: =$A69*O69 -> 1249.6495 | Q69: =sumif('Structures Database'!$V:$V,$B69,'Structures Database'!Q:Q) -> 249.06193 | R69: =$A69*Q69 -> 1992.4954 | S69: =sumif('Structures Database'!$V:$V,$B69,'Structures Database'!R:R)/60 -> 6.5166667 | T69: =A69*S69 -> 52.133333 | U69: =sumif('Structures Database'!$V:$V,$B69,'Structures Database'!Y:Y) -> 5.963364 | V69: =A69*U69 -> 47.706912 | AG69: 6 | AH69: 0 | AI69: 8 | AJ69: 4 | AK69: 0 | AL69: 2 | AM69: 0 | AN69: 3 | AO69: 12 | AP69: 6 | AQ69: 0 | AR69: 1.5 | AS69: 8 | AU69: =AJ69+AK69+AL69+AM69+AN69+AO69+AP69+AQ69+AR69+AS69 -> 36.5
A70: =N18 -> 0 | B70: ='Structures Database'!A40 -> Floor frame 2442 x 3053 | C70: =sumif('Structures Database'!$V:$V,$B70,'Structures Database'!U:U) -> 118.41262 | D70: =$A70*C70 -> 0 | E70: =C70*$B$39 -> 11.841262 | F70: =A70*E70 -> 0 | G70: =C70+E70 -> 130.25388 | H70: =A70*G70 -> 0 | I70: =C70*$B$38 -> 438126.68 | J70: =I70*A70 -> 0 | K70: =E70*$B$38 -> 43812.668 | L70: =K70*A70 -> 0 | M70: =G70*$B$38 -> 481939.35 | N70: =M70*A70 -> 0 | O70: =sumif('Structures Database'!$V:$V,$B70,'Structures Database'!P:P) -> 196.71499 | P70: =$A70*O70 -> 0 | Q70: =sumif('Structures Database'!$V:$V,$B70,'Structures Database'!Q:Q) -> 313.47386 | R70: =$A70*Q70 -> 0 | S70: =sumif('Structures Database'!$V:$V,$B70,'Structures Database'!R:R)/60 -> 8.2833333 | T70: =A70*S70 -> 0 | U70: =sumif('Structures Database'!$V:$V,$B70,'Structures Database'!Y:Y) -> 7.455426 | V70: =A70*U70 -> 0 | AG70: 0 | AH70: 7.5 | AI70: 0 | AJ70: 0 | AK70: 4 | AL70: 4 | AM70: 6 | AN70: 9 | AO70: 3 | AP70: 9 | AQ70: 7 | AR70: 10.5 | AS70: 8 | AU70: =AJ70+AK70+AL70+AM70+AN70+AO70+AP70+AQ70+AR70+AS70 -> 60.5
A71: =N19 | B71: ='Structures Database'!A49 -> Floor frame 2442 x 3663 | C71: =sumif('Structures Database'!$V:$V,$B71,'Structures Database'!U:U) -> 118.41262 | D71: =$A71*C71 -> 0 | E71: =C71*$B$39 -> 11.841262 | F71: =A71*E71 -> 0 | G71: =C71+E71 -> 130.25388 | H71: =A71*G71 -> 0 | I71: =C71*$B$38 -> 438126.68 | J71: =I71*A71 -> 0 | K71: =E71*$B$38 -> 43812.668 | L71: =K71*A71 -> 0 | M71: =G71*$B$38 -> 481939.35 | N71: =M71*A71 -> 0 | O71: =sumif('Structures Database'!$V:$V,$B71,'Structures Database'!P:P) -> 196.71499 | P71: =$A71*O71 -> 0 | Q71: =sumif('Structures Database'!$V:$V,$B71,'Structures Database'!Q:Q) -> 313.47386 | R71: =$A71*Q71 -> 0 | S71: =sumif('Structures Database'!$V:$V,$B71,'Structures Database'!R:R)/60 -> 8.2833333 | T71: =A71*S71 -> 0 | U71: =sumif('Structures Database'!$V:$V,$B71,'Structures Database'!Y:Y) -> 7.455426 | V71: =A71*U71 -> 0 | AG71: 0 | AH71: 7.5 | AI71: 0 | AJ71: 0 | AK71: 4 | AL71: 4 | AM71: 6 | AN71: 9 | AO71: 3 | AP71: 9 | AQ71: 7 | AR71: 10.5 | AS71: 8 | AU71: =AJ71+AK71+AL71+AM71+AN71+AO71+AP71+AQ71+AR71+AS71 -> 60.5
A72: =E31 -> 0 | B72: ='Structures Database'!A58 -> Decking frame 2442 x 1221 | C72: =sumif('Structures Database'!$V:$V,$B72,'Structures Database'!U:U) -> 52.821108 | D72: =$A72*C72 -> 0 | E72: =C72*$B$39 -> 5.2821108 | F72: =A72*E72 -> 0 | G72: =C72+E72 -> 58.103219 | H72: =A72*G72 -> 0 | I72: =C72*$B$38 -> 195438.1 | J72: =I72*A72 -> 0 | K72: =E72*$B$38 -> 19543.81 | L72: =K72*A72 -> 0 | M72: =G72*$B$38 -> 214981.91 | N72: =M72*A72 -> 0 | O72: =sumif('Structures Database'!$V:$V,$B72,'Structures Database'!P:P) -> 83.850258 | P72: =$A72*O72 -> 0 | Q72: =sumif('Structures Database'!$V:$V,$B72,'Structures Database'!Q:Q) -> 132.84382 | R72: =$A72*Q72 -> 0 | S72: =sumif('Structures Database'!$V:$V,$B72,'Structures Database'!R:R)/60 -> 3.6833333 | T72: =A72*S72 -> 0 | U72: =sumif('Structures Database'!$V:$V,$B72,'Structures Database'!Y:Y) -> 2.981682 | V72: =A72*U72 -> 0 | AG72: 0 | AH72: 0 | AI72: 0 | AJ72: 0 | AK72: 0 | AL72: 0 | AM72: 0 | AN72: 0 | AO72: 0 | AP72: 0 | AQ72: 0 | AR72: 0 | AS72: 0 | AU72: =AJ72+AK72+AL72+AM72+AN72+AO72+AP72+AQ72+AR72+AS72 -> 0
A73: =E32 -> 0 | B73: ='Structures Database'!A67 -> Decking frame 2442 x 2442 | C73: =sumif('Structures Database'!$V:$V,$B73,'Structures Database'!U:U) -> 87.286591 | D73: =$A73*C73 -> 0 | E73: =C73*$B$39 -> 8.7286591 | F73: =A73*E73 -> 0 | G73: =C73+E73 -> 96.01525 | H73: =A73*G73 -> 0 | I73: =C73*$B$38 -> 322960.39 | J73: =I73*A73 -> 0 | K73: =E73*$B$38 -> 32296.039 | L73: =K73*A73 -> 0 | M73: =G73*$B$38 -> 355256.43 | N73: =M73*A73 -> 0 | O73: =sumif('Structures Database'!$V:$V,$B73,'Structures Database'!P:P) -> 141.76605 | P73: =$A73*O73 -> 0 | Q73: =sumif('Structures Database'!$V:$V,$B73,'Structures Database'!Q:Q) -> 225.77763 | R73: =$A73*Q73 -> 0 | S73: =sumif('Structures Database'!$V:$V,$B73,'Structures Database'!R:R)/60 -> 5.6833333 | T73: =A73*S73 -> 0 | U73: =sumif('Structures Database'!$V:$V,$B73,'Structures Database'!Y:Y) -> 5.963364 | V73: =A73*U73 -> 0 | AG73: 0 | AH73: 0 | AI73: 0 | AJ73: 0 | AK73: 0 | AL73: 0 | AM73: 0 | AN73: 0 | AO73: 0 | AP73: 0 | AQ73: 0 | AR73: 0 | AS73: 0 | AU73: =AJ73+AK73+AL73+AM73+AN73+AO73+AP73+AQ73+AR73+AS73 -> 0
A74: =E33 -> 0 | B74: ='Structures Database'!A76 -> Decking frame 2442 x 3053 | C74: =sumif('Structures Database'!$V:$V,$B74,'Structures Database'!U:U) -> 104.41356 | D74: =$A74*C74 -> 0 | E74: =C74*$B$39 -> 10.441356 | F74: =A74*E74 -> 0 | G74: =C74+E74 -> 114.85491 | H74: =A74*G74 -> 0 | I74: =C74*$B$38 -> 386330.16 | J74: =I74*A74 -> 0 | K74: =E74*$B$38 -> 38633.016 | L74: =K74*A74 -> 0 | M74: =G74*$B$38 -> 424963.17 | N74: =M74*A74 -> 0 | O74: =sumif('Structures Database'!$V:$V,$B74,'Structures Database'!P:P) -> 170.71453 | P74: =$A74*O74 -> 0 | Q74: =sumif('Structures Database'!$V:$V,$B74,'Structures Database'!Q:Q) -> 272.22936 | R74: =$A74*Q74 -> 0 | S74: =sumif('Structures Database'!$V:$V,$B74,'Structures Database'!R:R)/60 -> 6.6833333 | T74: =A74*S74 -> 0 | U74: =sumif('Structures Database'!$V:$V,$B74,'Structures Database'!Y:Y) -> 7.455426 | V74: =A74*U74 -> 0 | AG74: 0 | AH74: 0 | AI74: 0 | AJ74: 0 | AK74: 0 | AL74: 0 | AM74: 0 | AN74: 0 | AO74: 0 | AP74: 0 | AQ74: 0 | AR74: 0 | AS74: 0 | AU74: =AJ74+AK74+AL74+AM74+AN74+AO74+AP74+AQ74+AR74+AS74 -> 0
A75: =Q18 -> 5 | B75: ='Structures Database'!A87 -> Wall frame 2442 x 2654 | C75: =sumif('Structures Database'!$V:$V,$B75,'Structures Database'!U:U) -> 61.862474 | D75: =$A75*C75 -> 309.31237 | E75: =C75*$B$39 -> 6.1862474 | F75: =A75*E75 -> 30.931237 | G75: =C75+E75 -> 68.048722 | H75: =A75*G75 -> 340.24361 | I75: =C75*$B$38 -> 228891.16 | J75: =I75*A75 -> 1144455.8 | K75: =E75*$B$38 -> 22889.116 | L75: =K75*A75 -> 114445.58 | M75: =G75*$B$38 -> 251780.27 | N75: =M75*A75 -> 1258901.4 | O75: =sumif('Structures Database'!$V:$V,$B75,'Structures Database'!P:P) -> 92.330016 | P75: =$A75*O75 -> 461.65008 | Q75: =sumif('Structures Database'!$V:$V,$B75,'Structures Database'!Q:Q) -> 146.0858 | R75: =$A75*Q75 -> 730.42901 | S75: =sumif('Structures Database'!$V:$V,$B75,'Structures Database'!R:R)/60 -> 4.0166667 | T75: =A75*S75 -> 20.083333 | U75: =sumif('Structures Database'!$V:$V,$B75,'Structures Database'!Y:Y) -> 6.901092 | V75: =A75*U75 -> 34.50546 | AG75: 3 | AH75: 1 | AI75: 6 | AJ75: 4 | AK75: 0 | AL75: 1 | AM75: 2 | AN75: 3 | AO75: 11 | AP75: 8 | AQ75: 0 | AR75: 1.5 | AS75: 4 | AU75: =AJ75+AK75+AL75+AM75+AN75+AO75+AP75+AQ75+AR75+AS75 -> 34.5
A76: =R18 -> 0 | B76: ='Structures Database'!A101 -> Wall frame 3053 x 2654 | C76: =sumif('Structures Database'!$V:$V,$B76,'Structures Database'!U:U) -> 75.256547 | D76: =$A76*C76 -> 0 | E76: =C76*$B$39 -> 7.5256547 | F76: =A76*E76 -> 0 | G76: =C76+E76 -> 82.782202 | H76: =A76*G76 -> 0 | I76: =C76*$B$38 -> 278449.22 | J76: =I76*A76 -> 0 | K76: =E76*$B$38 -> 27844.922 | L76: =K76*A76 -> 0 | M76: =G76*$B$38 -> 306294.15 | N76: =M76*A76 -> 0 | O76: =sumif('Structures Database'!$V:$V,$B76,'Structures Database'!P:P) -> 112.99274 | P76: =$A76*O76 -> 0 | Q76: =sumif('Structures Database'!$V:$V,$B76,'Structures Database'!Q:Q) -> 178.95608 | R76: =$A76*Q76 -> 0 | S76: =sumif('Structures Database'!$V:$V,$B76,'Structures Database'!R:R)/60 -> 4.6666667 | T76: =A76*S76 -> 0 | U76: =sumif('Structures Database'!$V:$V,$B76,'Structures Database'!Y:Y) -> 8.627778 | V76: =A76*U76 -> 0 | AG76: 0 | AH76: 4 | AI76: 0 | AJ76: 0 | AK76: 2 | AL76: 2 | AM76: 3 | AN76: 3 | AO76: 4 | AP76: 6 | AQ76: 2 | AR76: 3 | AS76: 4 | AU76: =AJ76+AK76+AL76+AM76+AN76+AO76+AP76+AQ76+AR76+AS76 -> 29
A77: =S18+E30/4 -> 9 | B77: ='Structures Database'!A115 -> Wall frame 2442 x 2999 | C77: =sumif('Structures Database'!$V:$V,$B77,'Structures Database'!U:U) -> 66.177913 | D77: =$A77*C77 -> 595.60122 | E77: =C77*$B$39 -> 6.6177913 | F77: =A77*E77 -> 59.560122 | G77: =C77+E77 -> 72.795705 | H77: =A77*G77 -> 655.16134 | I77: =C77*$B$38 -> 244858.28 | J77: =I77*A77 -> 2203724.5 | K77: =E77*$B$38 -> 24485.828 | L77: =K77*A77 -> 220372.45 | M77: =G77*$B$38 -> 269344.11 | N77: =M77*A77 -> 2424097 | O77: =sumif('Structures Database'!$V:$V,$B77,'Structures Database'!P:P) -> 98.240725 | P77: =$A77*O77 -> 884.16653 | Q77: =sumif('Structures Database'!$V:$V,$B77,'Structures Database'!Q:Q) -> 155.5849 | R77: =$A77*Q77 -> 1400.2641 | S77: =sumif('Structures Database'!$V:$V,$B77,'Structures Database'!R:R)/60 -> 4.1166667 | T77: =A77*S77 -> 37.05 | U77: =sumif('Structures Database'!$V:$V,$B77,'Structures Database'!Y:Y) -> 7.743582 | V77: =A77*U77 -> 69.692238 | AG77: 7 | AH77: 7 | AI77: 7 | AJ77: 4 | AK77: 4 | AL77: 5 | AM77: 2 | AN77: 5 | AO77: 2 | AP77: 2 | AQ77: 8 | AR77: 7.5 | AS77: 8 | AU77: =AJ77+AK77+AL77+AM77+AN77+AO77+AP77+AQ77+AR77+AS77 -> 47.5
A78: =T18 -> 0 | B78: ='Structures Database'!A129 -> Wall frame 3053 x 2999 | C78: =sumif('Structures Database'!$V:$V,$B78,'Structures Database'!U:U) -> 80.538193 | D78: =$A78*C78 -> 0 | E78: =C78*$B$39 -> 8.0538193 | F78: =A78*E78 -> 0 | G78: =C78+E78 -> 88.592012 | H78: =A78*G78 -> 0 | I78: =C78*$B$38 -> 297991.31 | J78: =I78*A78 -> 0 | K78: =E78*$B$38 -> 29799.131 | L78: =K78*A78 -> 0 | M78: =G78*$B$38 -> 327790.45 | N78: =M78*A78 -> 0 | O78: =sumif('Structures Database'!$V:$V,$B78,'Structures Database'!P:P) -> 120.2231 | P78: =$A78*O78 -> 0 | Q78: =sumif('Structures Database'!$V:$V,$B78,'Structures Database'!Q:Q) -> 190.57539 | R78: =$A78*Q78 -> 0 | S78: =sumif('Structures Database'!$V:$V,$B78,'Structures Database'!R:R)/60 -> 4.7916667 | T78: =A78*S78 -> 0 | U78: =sumif('Structures Database'!$V:$V,$B78,'Structures Database'!Y:Y) -> 9.681063 | V78: =A78*U78 -> 0 | AG78: 0 | AH78: 0 | AI78: 0 | AJ78: 0 | AK78: 2 | AL78: 2 | AM78: 3 | AN78: 3 | AO78: 0 | AP78: 0 | AQ78: 2 | AR78: 3 | AS78: 0 | AU78: =AJ78+AK78+AL78+AM78+AN78+AO78+AP78+AQ78+AR78+AS78 -> 15
A79: =E27 -> 27 | B79: ='Structures Database'!A154 -> Partition wall frame per m1 | C79: =sumif('Structures Database'!$V:$V,$B79,'Structures Database'!U:U) -> 48.248533 | D79: =$A79*C79 -> 1302.7104 | E79: =C79*$B$39 -> 4.8248533 | F79: =A79*E79 -> 130.27104 | G79: =C79+E79 -> 53.073387 | H79: =A79*G79 -> 1432.9814 | I79: =C79*$B$38 -> 178519.57 | J79: =I79*A79 -> 4820028.5 | K79: =E79*$B$38 -> 17851.957 | L79: =K79*A79 -> 482002.85 | M79: =G79*$B$38 -> 196371.53 | N79: =M79*A79 -> 5302031.3 | O79: =sumif('Structures Database'!$V:$V,$B79,'Structures Database'!P:P) -> 60.191411 | P79: =$A79*O79 -> 1625.1681 | Q79: =sumif('Structures Database'!$V:$V,$B79,'Structures Database'!Q:Q) -> 97.047642 | R79: =$A79*Q79 -> 2620.2863 | S79: =sumif('Structures Database'!$V:$V,$B79,'Structures Database'!R:R)/60 -> 2.4356811 | T79: =A79*S79 -> 65.763391 | U79: =sumif('Structures Database'!$V:$V,$B79,'Structures Database'!Y:Y) -> 3 | V79: =A79*U79 -> 81 | AG79: 6.5 | AH79: 6.5 | AI79: 13 | AJ79: 4.5 | AK79: 6 | AL79: 12.5 | AM79: 14 | AN79: 20 | AO79: 38 | AP79: 42.5 | AQ79: 16.5 | AR79: 29 | AS79: 33 | AU79: =AJ79+AK79+AL79+AM79+AN79+AO79+AP79+AQ79+AR79+AS79 -> 216
A80: =B28 -> 93.697698 | B80: ='Structures Database'!A181 -> Facade per m2 - vertical cladding | C80: =sumif('Structures Database'!$V:$V,$B80,'Structures Database'!U:U) -> 10.583216 | D80: =$A80*C80 -> 991.62294 | E80: =C80*$B$39 -> 1.0583216 | F80: =A80*E80 -> 99.162294 | G80: =C80+E80 -> 11.641537 | H80: =A80*G80 -> 1090.7852 | I80: =C80*$B$38 -> 39157.898 | J80: =I80*A80 -> 3669004.9 | K80: =E80*$B$38 -> 3915.7898 | L80: =K80*A80 -> 366900.49 | M80: =G80*$B$38 -> 43073.688 | N80: =M80*A80 -> 4035905.4 | O80: =sumif('Structures Database'!$V:$V,$B80,'Structures Database'!P:P) -> 15.602939 | P80: =$A80*O80 -> 1461.9595 | Q80: =sumif('Structures Database'!$V:$V,$B80,'Structures Database'!Q:Q) -> 24.879539 | R80: =$A80*Q80 -> 2331.1555 | S80: =sumif('Structures Database'!$V:$V,$B80,'Structures Database'!R:R)/60 -> 1.2960827 | T80: =A80*S80 -> 121.43996 | U80: =sumif('Structures Database'!$V:$V,$B80,'Structures Database'!Y:Y) -> 1 | V80: =A80*U80 -> 93.697698 | AG80: =AH28 | AH80: =AI28 | AI80: 84.01785 | AJ80: 51.319824 | AK80: 60.333138 | AL80: 72.087876 | AM80: 73.530135 | AN80: 90.822273 | AO80: 104.41429 | AP80: 99.214176 | AQ80: 79.63851 | AR80: 95.871882 | AS80: 100.40078 | AU80: =AJ80+AK80+AL80+AM80+AN80+AO80+AP80+AQ80+AR80+AS80 -> 827.63289
A81: 0 | B81: ='Structures Database'!A174 -> Facade frame 2442 x 2654 (vertical cladding) | C81: =sumif('Structures Database'!$V:$V,$B81,'Structures Database'!U:U) -> 69.89179 | D81: =$A81*C81 -> 0 | E81: =C81*$B$39 -> 6.989179 | F81: =A81*E81 -> 0 | G81: =C81+E81 -> 76.880969 | H81: =A81*G81 -> 0 | I81: =C81*$B$38 -> 258599.62 | J81: =I81*A81 -> 0 | K81: =E81*$B$38 -> 25859.962 | L81: =K81*A81 -> 0 | M81: =G81*$B$38 -> 284459.59 | N81: =M81*A81 -> 0 | O81: =sumif('Structures Database'!$V:$V,$B81,'Structures Database'!P:P) -> 101.2108 | P81: =$A81*O81 -> 0 | Q81: =sumif('Structures Database'!$V:$V,$B81,'Structures Database'!Q:Q) -> 161.24598 | R81: =$A81*Q81 -> 0 | S81: =sumif('Structures Database'!$V:$V,$B81,'Structures Database'!R:R)/60 -> 8.95 | T81: =A81*S81 -> 0 | U81: =sumif('Structures Database'!$V:$V,$B81,'Structures Database'!Y:Y) -> 6.481068 | V81: =A81*U81 -> 0 | AG81: 0 | AH81: 0 | AI81: 0 | AJ81: 0 | AK81: 0 | AL81: 0 | AM81: 0 | AN81: 0 | AO81: 0 | AP81: 0 | AQ81: 0 | AR81: 0 | AS81: 0 | AU81: =AJ81+AK81+AL81+AM81+AN81+AO81+AP81+AQ81+AR81+AS81 -> 0
A82: =U18 -> 8 | B82: ='Structures Database'!A191 -> Roof frame 1221 x 5685 (mono pitch) | C82: =sumif('Structures Database'!$V:$V,$B82,'Structures Database'!U:U) -> 81.838415 | D82: =$A82*C82 -> 654.70732 | E82: =C82*$B$39 -> 8.1838415 | F82: =A82*E82 -> 65.470732 | G82: =C82+E82 -> 90.022257 | H82: =A82*G82 -> 720.17805 | I82: =C82*$B$38 -> 302802.14 | J82: =I82*A82 -> 2422417.1 | K82: =E82*$B$38 -> 30280.214 | L82: =K82*A82 -> 242241.71 | M82: =G82*$B$38 -> 333082.35 | N82: =M82*A82 -> 2664658.8 | O82: =sumif('Structures Database'!$V:$V,$B82,'Structures Database'!P:P) -> 106.59204 | P82: =$A82*O82 -> 852.73635 | Q82: =sumif('Structures Database'!$V:$V,$B82,'Structures Database'!Q:Q) -> 167.05226 | R82: =$A82*Q82 -> 1336.418 | S82: =sumif('Structures Database'!$V:$V,$B82,'Structures Database'!R:R)/60 -> 7.1 | T82: =A82*S82 -> 56.8 | U82: =sumif('Structures Database'!$V:$V,$B82,'Structures Database'!Y:Y) -> 6.995109 | V82: =A82*U82 -> 55.960872 | AG82: 4 | AH82: 0 | AI82: 6 | AJ82: 2 | AK82: 3 | AL82: 5 | AM82: 5.5 | AN82: 0 | AO82: 0 | AP82: 0 | AQ82: 0 | AR82: 0 | AS82: 0 | AU82: =AJ82+AK82+AL82+AM82+AN82+AO82+AP82+AQ82+AR82+AS82 -> 15.5
A83: =V18 -> 2 | B83: ='Structures Database'!A207 -> Roof frame 1598x 5685 (mono pitch edge) | C83: =sumif('Structures Database'!$V:$V,$B83,'Structures Database'!U:U) -> 133.59487 | D83: =$A83*C83 -> 267.18974 | E83: =C83*$B$39 -> 13.359487 | F83: =A83*E83 -> 26.718974 | G83: =C83+E83 -> 146.95436 | H83: =A83*G83 -> 293.90871 | I83: =C83*$B$38 -> 494301.02 | J83: =I83*A83 -> 988602.04 | K83: =E83*$B$38 -> 49430.102 | L83: =K83*A83 -> 98860.204 | M83: =G83*$B$38 -> 543731.12 | N83: =M83*A83 -> 1087462.2 | O83: =sumif('Structures Database'!$V:$V,$B83,'Structures Database'!P:P) -> 170.36873 | P83: =$A83*O83 -> 340.73746 | Q83: =sumif('Structures Database'!$V:$V,$B83,'Structures Database'!Q:Q) -> 267.39082 | R83: =$A83*Q83 -> 534.78164 | S83: =sumif('Structures Database'!$V:$V,$B83,'Structures Database'!R:R)/60 -> 14.475 | T83: =A83*S83 -> 28.95 | U83: =sumif('Structures Database'!$V:$V,$B83,'Structures Database'!Y:Y) -> 9.28098 | V83: =A83*U83 -> 18.56196 | AG83: 2 | AH83: 0 | AI83: 2 | AJ83: 2 | AK83: 2 | AL83: 2 | AM83: 2 | AN83: 0 | AO83: 0 | AP83: 0 | AQ83: 0 | AR83: 0 | AS83: 0 | AU83: =AJ83+AK83+AL83+AM83+AN83+AO83+AP83+AQ83+AR83+AS83 -> 8
A84: =W18 | B84: ='Structures Database'!A223 -> Roof frame 1221 x 3574 (compact gable) | C84: =sumif('Structures Database'!$V:$V,$B84,'Structures Database'!U:U) -> 64.202047 | D84: =$A84*C84 -> 0 | E84: =C84*$B$39 -> 6.4202047 | F84: =A84*E84 -> 0 | G84: =C84+E84 -> 70.622251 | H84: =A84*G84 -> 0 | I84: =C84*$B$38 -> 237547.57 | J84: =I84*A84 -> 0 | K84: =E84*$B$38 -> 23754.757 | L84: =K84*A84 -> 0 | M84: =G84*$B$38 -> 261302.33 | N84: =M84*A84 -> 0 | O84: =sumif('Structures Database'!$V:$V,$B84,'Structures Database'!P:P) -> 78.19967 | P84: =$A84*O84 -> 0 | Q84: =sumif('Structures Database'!$V:$V,$B84,'Structures Database'!Q:Q) -> 121.98428 | R84: =$A84*Q84 -> 0 | S84: =sumif('Structures Database'!$V:$V,$B84,'Structures Database'!R:R)/60 -> 5.7833333 | T84: =A84*S84 -> 0 | U84: =sumif('Structures Database'!$V:$V,$B84,'Structures Database'!Y:Y) -> 4.390716 | V84: =A84*U84 -> 0 | AG84: 0 | AH84: 0 | AI84: 0 | AJ84: 0 | AK84: 0 | AL84: 0 | AM84: 0 | AN84: 15 | AO84: 18 | AP84: 19 | AQ84: 0 | AR84: 0 | AS84: 0 | AU84: =AJ84+AK84+AL84+AM84+AN84+AO84+AP84+AQ84+AR84+AS84 -> 52
A85: =X18 | B85: ='Structures Database'!A239 -> Roof frame 1689 x 3574 (compact gable edge) | C85: =sumif('Structures Database'!$V:$V,$B85,'Structures Database'!U:U) -> 101.31906 | D85: =$A85*C85 -> 0 | E85: =C85*$B$39 -> 10.131906 | F85: =A85*E85 -> 0 | G85: =C85+E85 -> 111.45097 | H85: =A85*G85 -> 0 | I85: =C85*$B$38 -> 374880.53 | J85: =I85*A85 -> 0 | K85: =E85*$B$38 -> 37488.053 | L85: =K85*A85 -> 0 | M85: =G85*$B$38 -> 412368.58 | N85: =M85*A85 -> 0 | O85: =sumif('Structures Database'!$V:$V,$B85,'Structures Database'!P:P) -> 122.04981 | P85: =$A85*O85 -> 0 | Q85: =sumif('Structures Database'!$V:$V,$B85,'Structures Database'!Q:Q) -> 190.6737 | R85: =$A85*Q85 -> 0 | S85: =sumif('Structures Database'!$V:$V,$B85,'Structures Database'!R:R)/60 -> 11.15 | T85: =A85*S85 -> 0 | U85: =sumif('Structures Database'!$V:$V,$B85,'Structures Database'!Y:Y) -> 6.152756 | V85: =A85*U85 -> 0 | AG85: 0 | AH85: 0 | AI85: 0 | AJ85: 0 | AK85: 0 | AL85: 0 | AM85: 0 | AN85: 4 | AO85: 4 | AP85: 4 | AQ85: 0 | AR85: 0 | AS85: 0 | AU85: =AJ85+AK85+AL85+AM85+AN85+AO85+AP85+AQ85+AR85+AS85 -> 12
A86: =Y18 | B86: ='Structures Database'!A255 -> Roof frame 1221 x 4194 (standard gable) | C86: =sumif('Structures Database'!$V:$V,$B86,'Structures Database'!U:U) -> 67.445159 | D86: =$A86*C86 -> 0 | E86: =C86*$B$39 -> 6.7445159 | F86: =A86*E86 -> 0 | G86: =C86+E86 -> 74.189675 | H86: =A86*G86 -> 0 | I86: =C86*$B$38 -> 249547.09 | J86: =I86*A86 -> 0 | K86: =E86*$B$38 -> 24954.709 | L86: =K86*A86 -> 0 | M86: =G86*$B$38 -> 274501.8 | N86: =M86*A86 -> 0 | O86: =sumif('Structures Database'!$V:$V,$B86,'Structures Database'!P:P) -> 85.584283 | P86: =$A86*O86 -> 0 | Q86: =sumif('Structures Database'!$V:$V,$B86,'Structures Database'!Q:Q) -> 133.71957 | R86: =$A86*Q86 -> 0 | S86: =sumif('Structures Database'!$V:$V,$B86,'Structures Database'!R:R)/60 -> 6 | T86: =A86*S86 -> 0 | U86: =sumif('Structures Database'!$V:$V,$B86,'Structures Database'!Y:Y) -> 5.147736 | V86: =A86*U86 -> 0 | AG86: 0 | AH86: 0 | AI86: 0 | AJ86: 0 | AK86: 0 | AL86: 0 | AM86: 0 | AN86: 15 | AO86: 18 | AP86: 19 | AQ86: 0 | AR86: 0 | AS86: 0 | AU86: =AJ86+AK86+AL86+AM86+AN86+AO86+AP86+AQ86+AR86+AS86 -> 52
A87: =Z18 | B87: ='Structures Database'!A271 -> Roof frame 1689 x 4194 (standard gable edge) | C87: =sumif('Structures Database'!$V:$V,$B87,'Structures Database'!U:U) -> 108.47197 | D87: =$A87*C87 -> 0 | E87: =C87*$B$39 -> 10.847197 | F87: =A87*E87 -> 0 | G87: =C87+E87 -> 119.31916 | H87: =A87*G87 -> 0 | I87: =C87*$B$38 -> 401346.27 | J87: =I87*A87 -> 0 | K87: =E87*$B$38 -> 40134.627 | L87: =K87*A87 -> 0 | M87: =G87*$B$38 -> 441480.9 | N87: =M87*A87 -> 0 | O87: =sumif('Structures Database'!$V:$V,$B87,'Structures Database'!P:P) -> 135.86262 | P87: =$A87*O87 -> 0 | Q87: =sumif('Structures Database'!$V:$V,$B87,'Structures Database'!Q:Q) -> 212.68883 | R87: =$A87*Q87 -> 0 | S87: =sumif('Structures Database'!$V:$V,$B87,'Structures Database'!R:R)/60 -> 11.875 | T87: =A87*S87 -> 0 | U87: =sumif('Structures Database'!$V:$V,$B87,'Structures Database'!Y:Y) -> 7.213576 | V87: =A87*U87 -> 0 | AG87: 0 | AH87: 0 | AI87: 0 | AJ87: 0 | AK87: 0 | AL87: 0 | AM87: 0 | AN87: 4 | AO87: 4 | AP87: 4 | AQ87: 0 | AR87: 0 | AS87: 0 | AU87: =AJ87+AK87+AL87+AM87+AN87+AO87+AP87+AQ87+AR87+AS87 -> 12
A88: =AA18 | B88: ='Structures Database'!A287 -> Roof frame 1221 x 5435 (large gable) | C88: =sumif('Structures Database'!$V:$V,$B88,'Structures Database'!U:U) -> 83.185323 | D88: =$A88*C88 -> 0 | E88: =C88*$B$39 -> 8.3185323 | F88: =A88*E88 -> 0 | G88: =C88+E88 -> 91.503855 | H88: =A88*G88 -> 0 | I88: =C88*$B$38 -> 307785.7 | J88: =I88*A88 -> 0 | K88: =E88*$B$38 -> 30778.57 | L88: =K88*A88 -> 0 | M88: =G88*$B$38 -> 338564.27 | N88: =M88*A88 -> 0 | O88: =sumif('Structures Database'!$V:$V,$B88,'Structures Database'!P:P) -> 106.20391 | P88: =$A88*O88 -> 0 | Q88: =sumif('Structures Database'!$V:$V,$B88,'Structures Database'!Q:Q) -> 166.38964 | R88: =$A88*Q88 -> 0 | S88: =sumif('Structures Database'!$V:$V,$B88,'Structures Database'!R:R)/60 -> 7.3333333 | T88: =A88*S88 -> 0 | U88: =sumif('Structures Database'!$V:$V,$B88,'Structures Database'!Y:Y) -> 6.662997 | V88: =A88*U88 -> 0 | AG88: 0 | AH88: 0 | AI88: 0 | AJ88: 0 | AK88: 0 | AL88: 0 | AM88: 0 | AN88: 0 | AO88: 0 | AP88: 0 | AQ88: 0 | AR88: 0 | AS88: 14 | AU88: =AJ88+AK88+AL88+AM88+AN88+AO88+AP88+AQ88+AR88+AS88 -> 14
A89: =AB18 | B89: ='Structures Database'!A303 -> Roof frame 1689 x 5435 (large gable edge) | C89: =sumif('Structures Database'!$V:$V,$B89,'Structures Database'!U:U) -> 133.59487 | D89: =$A89*C89 -> 0 | E89: =C89*$B$39 -> 13.359487 | F89: =A89*E89 -> 0 | G89: =C89+E89 -> 146.95436 | H89: =A89*G89 -> 0 | I89: =C89*$B$38 -> 494301.02 | J89: =I89*A89 -> 0 | K89: =E89*$B$38 -> 49430.102 | L89: =K89*A89 -> 0 | M89: =G89*$B$38 -> 543731.12 | N89: =M89*A89 -> 0 | O89: =sumif('Structures Database'!$V:$V,$B89,'Structures Database'!P:P) -> 169.01386 | P89: =$A89*O89 -> 0 | Q89: =sumif('Structures Database'!$V:$V,$B89,'Structures Database'!Q:Q) -> 265.20838 | R89: =$A89*Q89 -> 0 | S89: =sumif('Structures Database'!$V:$V,$B89,'Structures Database'!R:R)/60 -> 14.475 | T89: =A89*S89 -> 0 | U89: =sumif('Structures Database'!$V:$V,$B89,'Structures Database'!Y:Y) -> 9.336927 | V89: =A89*U89 -> 0 | AG89: 0 | AH89: 0 | AI89: 0 | AJ89: 0 | AK89: 0 | AL89: 0 | AM89: 0 | AN89: 0 | AO89: 0 | AP89: 0 | AQ89: 0 | AR89: 0 | AS89: 4 | AU89: =AJ89+AK89+AL89+AM89+AN89+AO89+AP89+AQ89+AR89+AS89 -> 4
A90: =AC18 | B90: ='Structures Database'!A319 -> Roof frame 1221 x 5780 (clerestory upper) | C90: =sumif('Structures Database'!$V:$V,$B90,'Structures Database'!U:U) -> 88.572955 | D90: =$A90*C90 -> 0 | E90: =C90*$B$39 -> 8.8572955 | F90: =A90*E90 -> 0 | G90: =C90+E90 -> 97.430251 | H90: =A90*G90 -> 0 | I90: =C90*$B$38 -> 327719.93 | J90: =I90*A90 -> 0 | K90: =E90*$B$38 -> 32771.993 | L90: =K90*A90 -> 0 | M90: =G90*$B$38 -> 360491.93 | N90: =M90*A90 -> 0 | O90: =sumif('Structures Database'!$V:$V,$B90,'Structures Database'!P:P) -> 114.64761 | P90: =$A90*O90 -> 0 | Q90: =sumif('Structures Database'!$V:$V,$B90,'Structures Database'!Q:Q) -> 179.84127 | R90: =$A90*Q90 -> 0 | S90: =sumif('Structures Database'!$V:$V,$B90,'Structures Database'!R:R)/60 -> 8.2666667 | T90: =A90*S90 -> 0 | U90: =sumif('Structures Database'!$V:$V,$B90,'Structures Database'!Y:Y) -> 7.111104 | V90: =A90*U90 -> 0 | AG90: 0 | AH90: 4 | AI90: 0 | AJ90: 0 | AK90: 0 | AL90: 0 | AM90: 0 | AN90: 0 | AO90: 0 | AP90: 0 | AQ90: 4 | AR90: 6.5 | AS90: 0 | AU90: =AJ90+AK90+AL90+AM90+AN90+AO90+AP90+AQ90+AR90+AS90 -> 10.5
A91: =AD18 | B91: ='Structures Database'!A335 -> Roof frame 1689 x 5780 (clerestory upper edge) | C91: =sumif('Structures Database'!$V:$V,$B91,'Structures Database'!U:U) -> 143.92618 | D91: =$A91*C91 -> 0 | E91: =C91*$B$39 -> 14.392618 | F91: =A91*E91 -> 0 | G91: =C91+E91 -> 158.31879 | H91: =A91*G91 -> 0 | I91: =C91*$B$38 -> 532526.86 | J91: =I91*A91 -> 0 | K91: =E91*$B$38 -> 53252.686 | L91: =K91*A91 -> 0 | M91: =G91*$B$38 -> 585779.54 | N91: =M91*A91 -> 0 | O91: =sumif('Structures Database'!$V:$V,$B91,'Structures Database'!P:P) -> 183.63161 | P91: =$A91*O91 -> 0 | Q91: =sumif('Structures Database'!$V:$V,$B91,'Structures Database'!Q:Q) -> 288.32472 | R91: =$A91*Q91 -> 0 | S91: =sumif('Structures Database'!$V:$V,$B91,'Structures Database'!R:R)/60 -> 16.258333 | T91: =A91*S91 -> 0 | U91: =sumif('Structures Database'!$V:$V,$B91,'Structures Database'!Y:Y) -> 9.964864 | V91: =A91*U91 -> 0 | AG91: 0 | AH91: 2 | AI91: 0 | AJ91: 0 | AK91: 0 | AL91: 0 | AM91: 0 | AN91: 0 | AO91: 0 | AP91: 0 | AQ91: 2 | AR91: 2 | AS91: 0 | AU91: =AJ91+AK91+AL91+AM91+AN91+AO91+AP91+AQ91+AR91+AS91 -> 4
A92: =AE18 | B92: ='Structures Database'!A351 -> Roof frame 1221 x 4194 (clerestory lower) | C92: =sumif('Structures Database'!$V:$V,$B92,'Structures Database'!U:U) -> 67.276231 | D92: =$A92*C92 -> 0 | E92: =C92*$B$39 -> 6.7276231 | F92: =A92*E92 -> 0 | G92: =C92+E92 -> 74.003854 | H92: =A92*G92 -> 0 | I92: =C92*$B$38 -> 248922.05 | J92: =I92*A92 -> 0 | K92: =E92*$B$38 -> 24892.205 | L92: =K92*A92 -> 0 | M92: =G92*$B$38 -> 273814.26 | N92: =M92*A92 -> 0 | O92: =sumif('Structures Database'!$V:$V,$B92,'Structures Database'!P:P) -> 86.230944 | P92: =$A92*O92 -> 0 | Q92: =sumif('Structures Database'!$V:$V,$B92,'Structures Database'!Q:Q) -> 134.83528 | R92: =$A92*Q92 -> 0 | S92: =sumif('Structures Database'!$V:$V,$B92,'Structures Database'!R:R)/60 -> 6.1166667 | T92: =A92*S92 -> 0 | U92: =sumif('Structures Database'!$V:$V,$B92,'Structures Database'!Y:Y) -> 5.147736 | V92: =A92*U92 -> 0 | AG92: 0 | AH92: 4 | AI92: 0 | AJ92: 0 | AK92: 0 | AL92: 0 | AM92: 0 | AN92: 0 | AO92: 0 | AP92: 0 | AQ92: 4 | AR92: 6.5 | AS92: 0 | AU92: =AJ92+AK92+AL92+AM92+AN92+AO92+AP92+AQ92+AR92+AS92 -> 10.5
A93: =AF18 | B93: ='Structures Database'!A367 -> Roof frame 1689 x 4194 (clerestory lower edge) | C93: =sumif('Structures Database'!$V:$V,$B93,'Structures Database'!U:U) -> 110.31947 | D93: =$A93*C93 -> 0 | E93: =C93*$B$39 -> 11.031947 | F93: =A93*E93 -> 0 | G93: =C93+E93 -> 121.35142 | H93: =A93*G93 -> 0 | I93: =C93*$B$38 -> 408182.03 | J93: =I93*A93 -> 0 | K93: =E93*$B$38 -> 40818.203 | L93: =K93*A93 -> 0 | M93: =G93*$B$38 -> 449000.24 | N93: =M93*A93 -> 0 | O93: =sumif('Structures Database'!$V:$V,$B93,'Structures Database'!P:P) -> 139.28806 | P93: =$A93*O93 -> 0 | Q93: =sumif('Structures Database'!$V:$V,$B93,'Structures Database'!Q:Q) -> 218.0936 | R93: =$A93*Q93 -> 0 | S93: =sumif('Structures Database'!$V:$V,$B93,'Structures Database'!R:R)/60 -> 12.325 | T93: =A93*S93 -> 0 | U93: =sumif('Structures Database'!$V:$V,$B93,'Structures Database'!Y:Y) -> 7.213576 | V93: =A93*U93 -> 0 | AG93: 0 | AH93: 2 | AI93: 0 | AJ93: 0 | AK93: 0 | AL93: 0 | AM93: 0 | AN93: 0 | AO93: 0 | AP93: 0 | AQ93: 2 | AR93: 2 | AS93: 0 | AU93: =AJ93+AK93+AL93+AM93+AN93+AO93+AP93+AQ93+AR93+AS93 -> 4
A94: =A90*0.5+A91*0.5 -> 0 | B94: ='Structures Database'!A383 -> Clerestory frame 2442 x 420 | C94: =sumif('Structures Database'!$V:$V,$B94,'Structures Database'!U:U) -> 40.334662 | D94: =$A94*C94 -> 0 | E94: =C94*$B$39 -> 4.0334662 | F94: =A94*E94 -> 0 | G94: =C94+E94 -> 44.368129 | H94: =A94*G94 -> 0 | I94: =C94*$B$38 -> 149238.25 | J94: =I94*A94 -> 0 | K94: =E94*$B$38 -> 14923.825 | L94: =K94*A94 -> 0 | M94: =G94*$B$38 -> 164162.08 | N94: =M94*A94 -> 0 | O94: =sumif('Structures Database'!$V:$V,$B94,'Structures Database'!P:P) -> 16.585816 | P94: =$A94*O94 -> 0 | Q94: =sumif('Structures Database'!$V:$V,$B94,'Structures Database'!Q:Q) -> 25.875065 | R94: =$A94*Q94 -> 0 | S94: =sumif('Structures Database'!$V:$V,$B94,'Structures Database'!R:R)/60 -> 2.9166667 | T94: =A94*S94 -> 0 | U94: =sumif('Structures Database'!$V:$V,$B94,'Structures Database'!Y:Y) -> 1.02564 | V94: =A94*U94 -> 0 | AG94: =AG90*0.5+AG91*0.5 -> 0 | AH94: =AH90*0.5+AH91*0.5 -> 3 | AI94: 0 | AJ94: 0 | AK94: 0 | AL94: 0 | AM94: 0 | AN94: 0 | AO94: 0 | AP94: 0 | AQ94: 3 | AR94: 4.25 | AS94: 0 | AU94: =AJ94+AK94+AL94+AM94+AN94+AO94+AP94+AQ94+AR94+AS94 -> 7.25
AU95: =AJ95+AK95+AL95+AM95+AN95+AO95+AP95+AQ95+AR95+AS95 -> 0
A96: Windows and exterior door table | AG96: Windows and exterior door table | AH96: Windows and exterior door table | AI96: Windows and exterior door table | AJ96: Windows and exterior door table | AK96: Windows and exterior door table | AL96: Windows and exterior door table | AM96: Windows and exterior door table | AN96: Windows and exterior door table | AO96: Windows and exterior door table | AP96: Windows and exterior door table | AQ96: Windows and exterior door table | AR96: Windows and exterior door table | AS96: Windows and exterior door table
A97: ='Structures Database'!U393 -> 160 | B97: price per sqm alu windows doors | C97: Cost item ($) | D97: Cost total | E97: Margin item | F97: Margin total | G97: Price item | H97: Price total | I97: Cost item | J97: Cost total | K97: Margin item | L97: Margin total | M97: Price item | N97: Price total | AG97: ='Structures Database'!AW393 | AH97: ='Structures Database'!AX393 | AI97: 130 | AJ97: 130 | AK97: 130 | AL97: 130 | AM97: 130 | AN97: 130 | AO97: 130 | AP97: 130 | AQ97: 130 | AR97: 130 | AS97: 130
B98: Net standard window and door dimensions | C98: USD | D98: USD | E98: USD | F98: USD | G98: USD | H98: USD | I98: =$B$37 -> UGX | J98: =$B$37 -> UGX | K98: =$B$37 -> UGX | L98: =$B$37 -> UGX | M98: =$B$37 -> UGX | N98: =$B$37 -> UGX | U98: Surface | V98: Surface total | W98: Width | X98: Height | AU98: =AJ98+AK98+AL98+AM98+AN98+AO98+AP98+AQ98+AR98+AS98 -> 0
A99: 0 | B99: =Y99&" "&W99&" x "&X99 -> Entrance door 950 x 2388 | C99: =U99*$A$97 -> 362.976 | D99: =A99*C99 -> 0 | E99: =C99*$B$39 -> 36.2976 | F99: =A99*E99 -> 0 | G99: =C99+E99 -> 399.2736 | H99: =A99*G99 -> 0 | I99: =C99*$B$38 -> 1343011.2 | J99: =I99*A99 -> 0 | K99: =E99*$B$38 -> 134301.12 | L99: =K99*A99 -> 0 | M99: =G99*$B$38 -> 1477312.3 | N99: =M99*A99 -> 0 | U99: =W99*X99/1000000 -> 2.2686 | V99: =U99*A99 -> 0 | W99: 950 | X99: 2388 | Y99: Entrance door | AG99: 1 | AH99: 2 | AI99: 1 | AJ99: 1 | AK99: 1 | AL99: 1 | AM99: 1 | AN99: 2 | AO99: 1 | AP99: 1 | AQ99: 2 | AR99: 2 | AS99: 1 | AU99: =AJ99+AK99+AL99+AM99+AN99+AO99+AP99+AQ99+AR99+AS99 -> 13
A100: 0 | B100: =Y100&" "&W100&" x "&X100 -> Terrace swing doors 1700 x 2388 | C100: =U100*$A$97 -> 649.536 | D100: =A100*C100 -> 0 | E100: =C100*$B$39 -> 64.9536 | F100: =A100*E100 -> 0 | G100: =C100+E100 -> 714.4896 | H100: =A100*G100 -> 0 | I100: =C100*$B$38 -> 2403283.2 | J100: =I100*A100 -> 0 | K100: =E100*$B$38 -> 240328.32 | L100: =K100*A100 -> 0 | M100: =G100*$B$38 -> 2643611.5 | N100: =M100*A100 -> 0 | U100: =W100*X100/1000000 -> 4.0596 | V100: =U100*A100 -> 0 | W100: 1700 | X100: 2388 | Y100: Terrace swing doors | AG100: 0 | AH100: 0 | AI100: 0 | AJ100: 0 | AK100: 0 | AL100: 0 | AM100: 0 | AN100: 0 | AO100: 1 | AP100: 0 | AQ100: 0 | AR100: 0 | AS100: 0 | AU100: =AJ100+AK100+AL100+AM100+AN100+AO100+AP100+AQ100+AR100+AS100 -> 1
A101: 0 | B101: =Y101&" "&W101&" x "&X101 -> Sliding doors 1700 x 2388 | C101: =U101*$A$97 -> 649.536 | D101: =A101*C101 -> 0 | E101: =C101*$B$39 -> 64.9536 | F101: =A101*E101 -> 0 | G101: =C101+E101 -> 714.4896 | H101: =A101*G101 -> 0 | I101: =C101*$B$38 -> 2403283.2 | J101: =I101*A101 -> 0 | K101: =E101*$B$38 -> 240328.32 | L101: =K101*A101 -> 0 | M101: =G101*$B$38 -> 2643611.5 | N101: =M101*A101 -> 0 | U101: =W101*X101/1000000 -> 4.0596 | V101: =U101*A101 -> 0 | W101: 1700 | X101: 2388 | Y101: Sliding doors | AG101: 0 | AH101: 0 | AI101: 0 | AJ101: 0 | AK101: 0 | AL101: 0 | AM101: 0 | AN101: 0 | AO101: 0 | AP101: 0 | AQ101: 0 | AR101: 0 | AS101: 0 | AU101: =AJ101+AK101+AL101+AM101+AN101+AO101+AP101+AQ101+AR101+AS101 -> 0
A102: 0 | B102: =Y102&" "&W102&" x "&X102 -> Sliding doors 2300 x 2388 | C102: =U102*$A$97 -> 878.784 | D102: =A102*C102 -> 0 | E102: =C102*$B$39 -> 87.8784 | F102: =A102*E102 -> 0 | G102: =C102+E102 -> 966.6624 | H102: =A102*G102 -> 0 | I102: =C102*$B$38 -> 3251500.8 | J102: =I102*A102 -> 0 | K102: =E102*$B$38 -> 325150.08 | L102: =K102*A102 -> 0 | M102: =G102*$B$38 -> 3576650.9 | N102: =M102*A102 -> 0 | U102: =W102*X102/1000000 -> 5.4924 | V102: =U102*A102 -> 0 | W102: 2300 | X102: 2388 | Y102: Sliding doors | AG102: 0 | AH102: 0 | AI102: 0 | AJ102: 0 | AK102: 0 | AL102: 0 | AM102: 0 | AN102: 1 | AO102: 0 | AP102: 1 | AQ102: 0 | AR102: 0 | AS102: 1 | AU102: =AJ102+AK102+AL102+AM102+AN102+AO102+AP102+AQ102+AR102+AS102 -> 3
A103: 0 | B103: =Y103&" "&W103&" x "&X103 -> Sliding doors 2900 x 2388 | C103: =U103*$A$97 -> 1108.032 | D103: =A103*C103 -> 0 | E103: =C103*$B$39 -> 110.8032 | F103: =A103*E103 -> 0 | G103: =C103+E103 -> 1218.8352 | H103: =A103*G103 -> 0 | I103: =C103*$B$38 -> 4099718.4 | J103: =I103*A103 -> 0 | K103: =E103*$B$38 -> 409971.84 | L103: =K103*A103 -> 0 | M103: =G103*$B$38 -> 4509690.2 | N103: =M103*A103 -> 0 | U103: =W103*X103/1000000 -> 6.9252 | V103: =U103*A103 -> 0 | W103: 2900 | X103: 2388 | Y103: Sliding doors | AG103: 0 | AH103: 0 | AI103: 0 | AJ103: 0 | AK103: 0 | AL103: 0 | AM103: 0 | AN103: 0 | AO103: 0 | AP103: 0 | AQ103: 0 | AR103: 0 | AS103: 0 | AU103: =AJ103+AK103+AL103+AM103+AN103+AO103+AP103+AQ103+AR103+AS103 -> 0
A104: 0 | B104: =Y104&" "&W104&" x "&X104 -> Sliding doors 3510 x 2388 | C104: =U104*$A$97 -> 1341.1008 | D104: =A104*C104 -> 0 | E104: =C104*$B$39 -> 134.11008 | F104: =A104*E104 -> 0 | G104: =C104+E104 -> 1475.2109 | H104: =A104*G104 -> 0 | I104: =C104*$B$38 -> 4962073 | J104: =I104*A104 -> 0 | K104: =E104*$B$38 -> 496207.3 | L104: =K104*A104 -> 0 | M104: =G104*$B$38 -> 5458280.3 | N104: =M104*A104 -> 0 | U104: =W104*X104/1000000 -> 8.38188 | V104: =U104*A104 -> 0 | W104: 3510 | X104: 2388 | Y104: Sliding doors | AG104: 0 | AH104: 0 | AI104: 0 | AJ104: 0 | AK104: 0 | AL104: 0 | AM104: 0 | AN104: 0 | AO104: 0 | AP104: 0 | AQ104: 0 | AR104: 0 | AS104: 0 | AU104: =AJ104+AK104+AL104+AM104+AN104+AO104+AP104+AQ104+AR104+AS104 -> 0
A105: 0 | B105: =Y105&" "&W105&" x "&X105 -> Bathroom window 500 x 1316 | C105: =U105*$A$97 -> 105.28 | D105: =A105*C105 -> 0 | E105: =C105*$B$39 -> 10.528 | F105: =A105*E105 -> 0 | G105: =C105+E105 -> 115.808 | H105: =A105*G105 -> 0 | I105: =C105*$B$38 -> 389536 | J105: =I105*A105 -> 0 | K105: =E105*$B$38 -> 38953.6 | L105: =K105*A105 -> 0 | M105: =G105*$B$38 -> 428489.6 | N105: =M105*A105 -> 0 | U105: =W105*X105/1000000 -> 0.658 | V105: =U105*A105 -> 0 | W105: 500 | X105: 1316 | Y105: Bathroom window | AG105: 1 | AH105: 1 | AI105: 1 | AJ105: 3 | AK105: 2 | AL105: 1 | AM105: 2 | AN105: 0 | AO105: 2 | AP105: 2 | AQ105: 1 | AR105: 2 | AS105: 2 | AU105: =AJ105+AK105+AL105+AM105+AN105+AO105+AP105+AQ105+AR105+AS105 -> 17
A106: 0 | B106: =Y106&" "&W106&" x "&X106 -> Bathroom window 900 x 1316 | C106: =U106*$A$97 -> 189.504 | D106: =A106*C106 -> 0 | E106: =C106*$B$39 -> 18.9504 | F106: =A106*E106 -> 0 | G106: =C106+E106 -> 208.4544 | H106: =A106*G106 -> 0 | I106: =C106*$B$38 -> 701164.8 | J106: =I106*A106 -> 0 | K106: =E106*$B$38 -> 70116.48 | L106: =K106*A106 -> 0 | M106: =G106*$B$38 -> 771281.28 | N106: =M106*A106 -> 0 | U106: =W106*X106/1000000 -> 1.1844 | V106: =U106*A106 -> 0 | W106: 900 | X106: 1316 | Y106: Bathroom window | AG106: 0 | AH106: 0 | AI106: 0 | AJ106: 0 | AK106: 0 | AL106: 0 | AM106: 0 | AN106: 2 | AO106: 1 | AP106: 1 | AQ106: 0 | AR106: 0 | AS106: 0 | AU106: =AJ106+AK106+AL106+AM106+AN106+AO106+AP106+AQ106+AR106+AS106 -> 4
A107: 0 | B107: =Y107&" "&W107&" x "&X107 -> Sliding window 1100 x 1316 | C107: =U107*$A$97 -> 231.616 | D107: =A107*C107 -> 0 | E107: =C107*$B$39 -> 23.1616 | F107: =A107*E107 -> 0 | G107: =C107+E107 -> 254.7776 | H107: =A107*G107 -> 0 | I107: =C107*$B$38 -> 856979.2 | J107: =I107*A107 -> 0 | K107: =E107*$B$38 -> 85697.92 | L107: =K107*A107 -> 0 | M107: =G107*$B$38 -> 942677.12 | N107: =M107*A107 -> 0 | U107: =W107*X107/1000000 -> 1.4476 | V107: =U107*A107 -> 0 | W107: 1100 | X107: 1316 | Y107: Sliding window | AG107: 4 | AH107: 8 | AI107: 6 | AJ107: 2 | AK107: 3 | AL107: 5 | AM107: 4 | AN107: 0 | AO107: 0 | AP107: 0 | AQ107: 0 | AR107: 4 | AS107: 0 | AU107: =AJ107+AK107+AL107+AM107+AN107+AO107+AP107+AQ107+AR107+AS107 -> 18
A108: 0 | B108: =Y108&" "&W108&" x "&X108 -> Sliding window 1400 x 1316 | C108: =U108*$A$97 -> 294.784 | D108: =A108*C108 -> 0 | E108: =C108*$B$39 -> 29.4784 | F108: =A108*E108 -> 0 | G108: =C108+E108 -> 324.2624 | H108: =A108*G108 -> 0 | I108: =C108*$B$38 -> 1090700.8 | J108: =I108*A108 -> 0 | K108: =E108*$B$38 -> 109070.08 | L108: =K108*A108 -> 0 | M108: =G108*$B$38 -> 1199770.9 | N108: =M108*A108 -> 0 | U108: =W108*X108/1000000 -> 1.8424 | V108: =U108*A108 -> 0 | W108: 1400 | X108: 1316 | Y108: Sliding window | AG108: 0 | AH108: 0 | AI108: 0 | AJ108: 0 | AK108: 0 | AL108: 0 | AM108: 0 | AN108: 4 | AO108: 5 | AP108: 6 | AQ108: 4 | AR108: 6 | AS108: 5 | AU108: =AJ108+AK108+AL108+AM108+AN108+AO108+AP108+AQ108+AR108+AS108 -> 30
A109: 0 | B109: =Y109&" "&W109&" x "&X109 -> High window (fixed) 1100 x 1766 | C109: =U109*$A$97 -> 310.816 | D109: =A109*C109 -> 0 | E109: =C109*$B$39 -> 31.0816 | F109: =A109*E109 -> 0 | G109: =C109+E109 -> 341.8976 | H109: =A109*G109 -> 0 | I109: =C109*$B$38 -> 1150019.2 | J109: =I109*A109 -> 0 | K109: =E109*$B$38 -> 115001.92 | L109: =K109*A109 -> 0 | M109: =G109*$B$38 -> 1265021.1 | N109: =M109*A109 -> 0 | U109: =W109*X109/1000000 -> 1.9426 | V109: =U109*A109 -> 0 | W109: 1100 | X109: 1766 | Y109: High window (fixed) | AG109: 0 | AH109: 0 | AI109: 0 | AJ109: 0 | AK109: 0 | AL109: 0 | AM109: 0 | AN109: 0 | AO109: 0 | AP109: 0 | AQ109: 0 | AR109: 0 | AS109: 0 | AU109: =AJ109+AK109+AL109+AM109+AN109+AO109+AP109+AQ109+AR109+AS109 -> 0
A110: 0 | B110: =Y110&" "&W110&" x "&X110 -> High window (fixed) 1700 x 1766 | C110: =U110*$A$97 -> 480.352 | D110: =A110*C110 -> 0 | E110: =C110*$B$39 -> 48.0352 | F110: =A110*E110 -> 0 | G110: =C110+E110 -> 528.3872 | H110: =A110*G110 -> 0 | I110: =C110*$B$38 -> 1777302.4 | J110: =I110*A110 -> 0 | K110: =E110*$B$38 -> 177730.24 | L110: =K110*A110 -> 0 | M110: =G110*$B$38 -> 1955032.6 | N110: =M110*A110 -> 0 | U110: =W110*X110/1000000 -> 3.0022 | V110: =U110*A110 -> 0 | W110: 1700 | X110: 1766 | Y110: High window (fixed) | AG110: 0 | AH110: 0 | AI110: 0 | AJ110: 0 | AK110: 0 | AL110: 0 | AM110: 0 | AN110: 0 | AO110: 0 | AP110: 0 | AQ110: 0 | AR110: 0 | AS110: 0 | AU110: =AJ110+AK110+AL110+AM110+AN110+AO110+AP110+AQ110+AR110+AS110 -> 0
... A114: 0 | B114: =Y114&" "&W114&" x "&X114 -> Panorama window (fixed) 2300 x 846 | C114: =U114*$A$97 -> 311.328 | D114: =A114*C114 -> 0 | E114: =C114*$B$39 -> 31.1328 | F114: =A114*E114 -> 0 | G114: =C114+E114 -> 342.4608 | H114: =A114*G114 -> 0 | I114: =C114*$B$38 -> 1151913.6 | J114: =I114*A114 -> 0 | K114: =E114*$B$38 -> 115191.36 | L114: =K114*A114 -> 0 | M114: =G114*$B$38 -> 1267105 | N114: =M114*A114 -> 0 | U114: =W114*X114/1000000 -> 1.9458 | V114: =U114*A114 -> 0 | W114: 2300 | X114: 846 | Y114: Panorama window (fixed) | AG114: 0 | AH114: 0 | AI114: 0 | AJ114: 0 | AK114: 0 | AL114: 0 | AM114: 0 | AN114: 0 | AO114: 0 | AP114: 0 | AQ114: 0 | AR114: 0 | AS114: 0 | AU114: =AJ114+AK114+AL114+AM114+AN114+AO114+AP114+AQ114+AR114+AS114 -> 0
A115: =E29 -> 10.5 | B115: sqm bulk aluminium input (for generic estimates) | C115: =A97 -> 160 | D115: =A115*C115 -> 1680 | E115: =C115*$B$39 -> 16 | F115: =A115*E115 -> 168 | G115: =C115+E115 -> 176 | H115: =A115*G115 -> 1848 | I115: =C115*$B$38 -> 592000 | J115: =I115*A115 -> 6216000 | K115: =E115*$B$38 -> 59200 | L115: =K115*A115 -> 621600 | M115: =G115*$B$38 -> 651200 | N115: =M115*A115 -> 6837600 | V115: =SUM(V99:V114) -> 0
...

Sheet Project Output
A1: Create printable output tab with following info
A2: Serves as direct quotation output to send to clients or for internal review
A3: Create macro buttons here for saving input to database tab and for creating PDF printing command
A5: Outputs
A6: Client info, name location, distance etc
A7: Building info, sqm gfa, facade, doors, alu etc
A8: Price breakdown (based on price calc tab) add dropdown function for Country
A9: Price columns should be in VAT in right country currency
A10: Print selection should fit on 2 A4 pages as PDF - add instructions for macros
A11: Add quotation and general disclaimers
A12: Add info on timeline, location reqs etc
A13: Integrate distance charge hidden or explicit in price?

Sheet Project Budget
A1: Project budget overview for PMs
A3: Together with BOQ should give a complete project budget and procurement overview
A4: Export as a copy tab to new spreadsheet, as work file for PM to keep track
A6: Suppliers
A7: Timber, ply, screws, sheets, boards, etc
A8: Labour overview
A9: Site estimated budget and tab to keep track of site expenses?
A10: Subcontractors for MEP and options?
A11: Extra options as separate lines, including cost vs price breakdown

Sheet Price Calc
A1: Easy Housing - Price Calculation
A4: General Information | G4: General Information
A5: Quotation Date | B5: =today() -> 46128 | G5: Quotation Date | H5: =today() -> 46128
A6: Validity | B6: One month | G6: Validity | H6: One month
A8: All prices are inclusive of VAT | G8: All prices are inclusive of VAT
A9: All prices are in Ugandan Shillings (UGX) | G9: All prices are in Kenyan Shillings (KES)
A10: No rights can be derived from this quote | G10: No rights can be derived from this quote
A12: Client Information | G12: Client Information
A13: Client Name | B13: ='Project Input'!B22 -> Funky Jackfruit | G13: Client Name | H13: =B13 -> Funky Jackfruit
A14: Contact Details | B14: ='Project Input'!B23 -> +256 712 345 678 | G14: Contact Details | H14: =B14 -> +256 712 345 678
A15: Created by | B15: ='Project Input'!B27 -> Wolf Bierens | G15: Quotation Made By | H15: =B15 -> Wolf Bierens
A17: Project information | G17: Project information
A18: Easy Housing Typology | B18: =B58 -> Mono Pitch (4884) | G18: Easy Housing Typology | H18: =B18 -> Mono Pitch (4884)
A19: Gross Floor Area (sqm) | B19: =B62 -> 61.2 | G19: Gross Floor Area (sqm) | H19: =B19 -> 61.2
A20: Terrace (sqm) | B20: =B41 -> 0 | G20: Terrace (sqm) | H20: =B20 -> 0
A21: Bedrooms | B21: =B69 -> 2 | G21: Bedrooms | H21: =B21 -> 2
A22: Bathrooms | B22: =B70 -> 2 | G22: Bathrooms | H22: =B22 -> 2
A23: Project Location | B23: ='Project Input'!B24 -> Sagala | G23: Project Location | H23: =B23 -> Sagala
A24: Distance from factory | B24: ='Project Input'!B25 -> 50 | G24: Distance from factory | H24: =B24 -> 50
A26: Quotation Price Breakdown | G26: Quotation Price Breakdown
A28: Price Breakdown | E28: Price (UGX) | G28: Price Breakdown | K28: Price (KES)
A30: Complete Easy Home | E30: =E81 -> 110966200 | G30: Complete Easy Home | K30: =G81 -> 4205080
A31: Includes: | G31: Includes:
A32: All labour and overhead | G32: All labour and overhead
A33: Full structure | G33: Full structure
A34: Paintworks | G34: Paintworks
A35: Electrical installations | G35: Electrical installations
A36: Plumbing (if any) | G36: Plumbing (if any)
A37: See price list for more details | G37: See price list for more details
A39: Additional options | B39: Size | C39: Unit | D39: Unit price | E39: Price (UGX) | G39: Additional options | H39: Size | I39: Unit | J39: Unit price | K39: Price (KES)
A40: Burglar bars | B40: ='Project Input'!B48 -> 0 | C40: sqm | D40: 250000 | E40: =B40*D40 -> 0 | F40: For standard design burglar bars of steel | G40: Burglar bars | H40: =B40 -> 0 | I40: =C40 -> sqm | J40: 7500 | K40: =H40*J40 -> 0
A41: Terrace | B41: ='Project Input'!B43 -> 0 | C41: sqm | D41: 300000 | E41: =B41*D41 -> 0 | F41: In standard size frames, including linseed oil finishing and foundation work | G41: Terrace | H41: =B41 -> 0 | I41: =C41 -> sqm | J41: 12000 | K41: =H41*J41 -> 0
A42: Pergola | B42: ='Project Input'!B44 -> 0 | C42: sqm | D42: 100000 | E42: =B42*D42 -> 0 | F42: For an open structure pergola with beams every 60 cm | G42: Pergola | H42: =B42 -> 0 | I42: =C42 -> sqm | J42: 4000 | K42: =H42*J42 -> 0
A43: Railing open | B43: ='Project Input'!B45 -> 0 | C43: m1 | D43: 90000 | E43: =B43*D43 -> 0 | F43: With studs every 1.2m | G43: Railing open | H43: =B43 -> 0 | I43: =C43 -> m1 | J43: 3500 | K43: =H43*J43 -> 0
A44: Railing semi-closed | B44: ='Project Input'!B46 -> 0 | C44: m1 | D44: 180000 | E44: =B44*D44 -> 0 | F44: With studs every 20 cm so that kids and animals cannot fall through | G44: Railing semi-closed | H44: =B44 -> 0 | I44: =C44 -> m1 | J44: 7000 | K44: =H44*J44 -> 0
A45: Wheelchair ramp | B45: ='Project Input'!B49 -> 0 | C45: pcs | D45: 1500000 | E45: =B45*D45 -> 0 | F45: For an average ramp of around 5m long (low inclination) | G45: Wheelchair ramp | H45: =B45 -> 0 | I45: =C45 -> pcs | J45: 6500 | K45: =H45*J45 -> 0
A46: Tiles | C46: total | E46: ='Project Input'!B50 -> 0 | G46: Tiles | I46: =C46 -> total | K46: ='Project Input'!B50 -> 0
A47: Sanitary wares | C47: total | E47: ='Project Input'!B51 -> 0 | G47: Sanitary wares | I47: =C47 -> total | K47: ='Project Input'!B51 -> 0
A48: Biodigester | C48: total | E48: ='Project Input'!B52 -> 0 | G48: Biodigester | I48: =C48 -> total | K48: ='Project Input'!B52 -> 0
A49: ="Other options: "&'Project Input'!B53 -> Other options: | E49: ='Project Input'!B54 | G49: ='Project Input'!A54 -> Other option(s) price | I49: =C49 | K49: ='Project Input'!B54
A50: Total Additional Options | E50: =SUM(E40:E49) -> 0 | G50: Total Additional Options | H50: =B50 | I50: =C50 | K50: =SUM(K40:K49) -> 0
A52: Total Price Per Home Including Options | D52: UGX | E52: =E30+E50 -> 110966200 | G52: Total Price Per Home Including Options | K52: =K30+K50 -> 4205080
A54: Number of Homes | B54: ='Project Input'!B31 -> 1 | C54: home(s) | D54: =E52 -> 110966200 | E54: =B54*D54 -> 110966200 | G54: Number of Homes | H54: =B54 -> 1 | J54: =K52 -> 4205080 | K54: =H54*J54 -> 4205080
D56: Uganda (UGX) | F56: Kenya (KES)
A57: Basic structure parameters | B57: Amount | C57: Unit | D57: Unit price | E57: Total price | F57: Unit price | G57: Total price
A58: Building typology | B58: ='Project Input'!B30 -> Mono Pitch (4884)
A59: Columns A (1221) | B59: ='Project Input'!B32 -> 2 | C59: pcs
A60: Columns B (2442) | B60: ='Project Input'!B33 -> 4 | C60: pcs
A61: Columns C (3053) | B61: ='Project Input'!B34 -> 0 | C61: pcs
A62: Floor area | B62: =H96 -> 61.2 | C62: sqm
A63: Core and shell price | D63: =I96 -> 1228500 | E63: =J96 -> 75184200 | F63: =K96 -> 44000 | G63: =L96 -> 2692800
A64: Interior doors | B64: ='Project Input'!B35 -> 6 | C64: pcs | D64: 850000 | E64: =B64*D64 -> 5100000 | F64: 47500 | G64: =B64*F64 -> 285000
A65: Partitions (length) | B65: ='Project Input'!B36 -> 27 | C65: linear metres | D65: 500000 | E65: =B65*D65 -> 13500000 | F65: 20000 | G65: =B65*F65 -> 540000
A66: Exterior doors & windows (area) | B66: ='Project Input'!B37 -> 10.5 | C66: sqm | D66: 500000 | E66: =B66*D66 -> 5250000 | F66: 20000 | G66: =B66*F66 -> 210000
A67: Extra staircase (beyond the first) | B67: ='Project Input'!B47 -> 0 | C67: pcs | D67: 300000 | E67: =B67*D67 -> 0 | F67: 16000 | G67: =B67*F67 -> 0
A68: Living rooms | B68: 0 | C68: #
A69: Bedrooms | B69: ='Project Input'!B38 -> 2 | C69: #
A70: Bathrooms | B70: ='Project Input'!B39 -> 2 | C70: #
A71: Kitchen areas | B71: ='Project Input'!B40 -> 1 | C71: #
A72: Corridors | B72: 0 | C72: #
A73: Other rooms | B73: 0 | C73: #
A74: Total sqm bathrooms | B74: 0 | C74: sqm
A75: Total circumference bathrooms | B75: 0 | C75: linear metres
A76: Distance from factory | B76: ='Project Input'!B25 -> 50 | C76: km | D76: 400 | E76: =if((B76-100)>0,(B76-100)*B62*D76,0) -> 0 | F76: 15 | G76: =if((B76-100)>0,(B76-100)*B62*F76,0) -> 0
A77: Electricity | B77: =B79 -> 61.2 | C77: sqm | E77: =2000000+B77*80000 -> 6896000 | G77: =80000+3200*B77 -> 275840
A78: Plumbing | B78: =B71+B70 -> 3 | C78: plumbing areas | E78: =if(B78>0,1500000+500000*B78,0) -> 3000000 | G78: =if(B78>0,60000+20000*B78,0) -> 120000
A79: Architecture costs | B79: =B62 -> 61.2 | C79: sqm | E79: =15000*B79 -> 918000 | G79: =600*B79 -> 36720
A80: Engineering costs | B80: =B79 -> 61.2 | C80: sqm | E80: =200000+B80*15000 -> 1118000 | G80: =8000+600*B80 -> 44720
A81: Full Easy Home Price | C81: Total | E81: =sum(E58:E80) -> 110966200 | G81: =sum(G58:G80) -> 4205080
C85: Width | I85: Uganda | K85: Kenya
A86: Typology Calculator | B86: Gross Depth | C86: Column A | D86: Column B | E86: Column C | F86: Flanks | G86: Width Total | H86: GFA | I86: Sqm Price | J86: Basic Structure Price | K86: Sqm Price | L86: Basic Structure Price
A87: Mono Pitch (4884) | B87: 4972 | C87: =1221*$B$59 -> 2442 | D87: =2442*$B$60 -> 9768 | E87: =3053*$B$61 -> 0 | F87: 88 | G87: =sum(C87:F87) -> 12298 | H87: =roundup(B87*G87/1000000,1) -> 61.2 | I87: 1228500 | J87: =H87*I87 -> 75184200 | K87: 44000 | L87: =K87*H87 -> 2692800
A88: Compact Gable (6106) | B88: 6194 | C88: =1221*$B$59 -> 2442 | D88: =2442*$B$60 -> 9768 | E88: =3053*$B$61 -> 0 | F88: 88 | G88: =sum(C88:F88) -> 12298 | H88: =roundup(B88*G88/1000000,1) -> 76.2 | I88: 1123500 | J88: =H88*I88 -> 85610700 | K88: 42500 | L88: =K88*H88 -> 3238500
A89: Standard Gable (7326) | B89: 7414 | C89: =1221*$B$59 -> 2442 | D89: =2442*$B$60 -> 9768 | E89: =3053*$B$61 -> 0 | F89: 88 | G89: =sum(C89:F89) -> 12298 | H89: =roundup(B89*G89/1000000,1) -> 91.2 | I89: 1123500 | J89: =H89*I89 -> 102463200 | K89: 42500 | L89: =K89*H89 -> 3876000
A90: Large Gable (9768) | B90: 9856 | C90: =1221*$B$59 -> 2442 | D90: =2442*$B$60 -> 9768 | E90: =3053*$B$61 -> 0 | F90: 88 | G90: =sum(C90:F90) -> 12298 | H90: =roundup(B90*G90/1000000,1) -> 121.3 | I90: 1123500 | J90: =H90*I90 -> 136280550 | K90: 42500 | L90: =K90*H90 -> 5155250
A91: Standard Clerestory (7326) | B91: 7414 | C91: =1221*$B$59 -> 2442 | D91: =2442*$B$60 -> 9768 | E91: =3053*$B$61 -> 0 | F91: 88 | G91: =sum(C91:F91) -> 12298 | H91: =roundup(B91*G91/1000000,1) -> 91.2 | I91: 1228500 | J91: =H91*I91 -> 112039200 | K91: 44000 | L91: =K91*H91 -> 4012800
A92: Large Clerestory (8547) | B92: 8635 | C92: =1221*$B$59 -> 2442 | D92: =2442*$B$60 -> 9768 | E92: =3053*$B$61 -> 0 | F92: 88 | G92: =sum(C92:F92) -> 12298 | H92: =roundup(B92*G92/1000000,1) -> 106.2 | I92: 1228500 | J92: =H92*I92 -> 130466700 | K92: 44000 | L92: =K92*H92 -> 4672800
A93: A Frame Compact (3663)
A94: A Frame Standard (4884)
A95: A Frame Large (6106)
A96: =B58 -> Mono Pitch (4884) | H96: =Index(H87:H92,MATCH($A$96,$A$87:$A$92,0)) -> 61.2 | I96: =Index(I87:I92,MATCH($A$96,$A$87:$A$92,0)) -> 1228500 | J96: =Index(J87:J92,MATCH($A$96,$A$87:$A$92,0)) -> 75184200 | K96: =Index(K87:K92,MATCH($A$96,$A$87:$A$92,0)) -> 44000 | L96: =Index(L87:L92,MATCH($A$96,$A$87:$A$92,0)) -> 2692800

Sheet Bill of Quantities
A1: Bill of Quantities | D1: Specifications | M1: Item costs | P1: Project costs | Q1: Cost database | X1: Orderlist | AB1: =sum(AB88:AB148) -> 10.168282 | AC1: =sum(AC88:AC148) -> 10.722991 | AE1: =sum(AE88:AE148) -> 0.55470827 | AF1: =AE1/AC1 -> 0.051730742
A2: # | B2: Unit | C2: Item | D2: Width (mm) | E2: Height (mm) | F2: Length (mm) | G2: Volume (m3) | H2: Weight (kg) | I2: Carbon storage (kg CO2) | J2: Labour (min) | K2: Structure | L2: Type | M2: Item cost ($) | N2: Labour cost ($) | O2: Total cost ($) | Q2: ='Location Data'!A6 -> Kampala, Uganda | R2: ='Location Data'!A7 -> West Nile, Uganda | S2: ='Location Data'!A8 -> Beira, Mozambique | T2: ='Location Data'!A9 -> Maputo, Mozambique | U2: ='Location Data'!A10 -> Accra, Ghana | V2: ='Location Data'!A11 -> Arusha, Tanzania | W2: ='Location Data'!A12 -> Nairobi, Kenya | X2: Sawn from | Y2: Gross fraction | Z2: Sum | AA2: Loss | AB2: Net vol | AC2: Gross vol | AD2: Gross vol / item | AE2: Project loss | AF2: Loss percentage
A4: Project name | C4: ='Project Costs'!B12
A5: ='Project Costs'!A13 -> Project Location | C5: ='Project Costs'!B13 -> Greater Kampala (<100km from factory)
A6: ='Project Costs'!A14 -> Client name | C6: ='Project Costs'!B14 -> Example calculation
A8: Country parameters | C8: Description | D8: Value
C9: Selected location | D9: ='Project Costs'!B10 -> Kampala, Uganda
C10: ='Location Data'!B5 -> Country | D10: {=index('Location Data'!B:B,match($D$9,'Location Data'!A:A,0),1)} -> Uganda
C11: ='Location Data'!G5 -> Distance from sawmill | D11: {=index('Location Data'!G:G,match($D$9,'Location Data'!A:A,0),1)} -> 100
C12: ='Location Data'!F5 -> Forestry partner | D12: {=index('Location Data'!F:F,match($D$9,'Location Data'!A:A,0),1)} -> Green Resources, Jinja
C13: ='Location Data'!H5 -> Timber species | D13: {=index('Location Data'!H:H,match($D$9,'Location Data'!A:A,0),1)} -> Pinus caribaea
C14: ='Location Data'!I5 -> Price per m3 (normal - ex vat, ex mill) | D14: =I14*G14 -> 252 | F14: Offcut loss | G14: 1 | H14: Bulk price | I14: {=index('Location Data'!I:I,match($D$9,'Location Data'!A:A,0),1)} -> 252
C15: ='Location Data'!J5 -> Price per m3 (profiled) | D15: =I15*G15 -> 260 | F15: Offcut loss | G15: 1 | H15: Bulk price | I15: {=index('Location Data'!J:J,match($D$9,'Location Data'!A:A,0),1)} -> 260
C16: ='Location Data'!K5 -> Timber density (wet) | D16: {=index('Location Data'!K:K,match($D$9,'Location Data'!A:A,0),1)} -> 561
C17: ='Location Data'!L5 -> Moisture content | D17: {=index('Location Data'!L:L,match($D$9,'Location Data'!A:A,0),1)} -> 0.12
C18: ='Location Data'!M5 -> Timber density (dry) | D18: {=index('Location Data'!M:M,match($D$9,'Location Data'!A:A,0),1)} -> 493
C19: ='Location Data'!N5 -> Carpenter cost (day) | D19: {=index('Location Data'!N:N,match($D$9,'Location Data'!A:A,0),1)} -> 15
C20: Carbon storage in CO2 per kg dry timber | D20: 1.833
A22: Screws and fasteners | Q22: Now calculating with mostly local prices
A23: =sumif('Structures Database'!B:B,C23,'Structures Database'!W:W) -> 1460 | B23: pcs | C23: Screw 3.5x40 small head screw SHS3540 | D23: 3.5 | F23: 40 | G23: =(D23/2)^2*PI()*F23/1000000000 -> 3.848451e-07 | H23: =G23*7700 -> 0.0029633073 | J23: 1 | K23: Screw | L23: Flooring | M23: =index(23:23,1,match($D$9,$2:$2,0)) -> 0.046297556 | N23: =J23*$D$19/(8*60) -> 0.03125 | O23: =M23+N23 -> 0.077547556 | P23: =A23*O23 -> 113.21943 | Q23: =0.0253*$X$26 -> 0.046297556 | R23: =$Q23 -> 0.046297556 | S23: =$Q23 -> 0.046297556 | T23: =$Q23 -> 0.046297556 | U23: =$Q23 -> 0.046297556 | V23: =$Q23 -> 0.046297556 | W23: =Q23 -> 0.046297556 | X23: Screw specs from Rotho Blaas now assumed with 25% import tax, 15% withholding tax, and 25% freight costs (USD 500 on USD 2500 order) across markets. VAT is added separately per country.
A24: =sumif('Structures Database'!B:B,C24,'Structures Database'!W:W) -> 0 | B24: pcs | C24: Screw 3.5x50 stainless small head screw SHS3550AS | D24: 3.5 | F24: 50 | G24: =(D24/2)^2*PI()*F24/1000000000 -> 4.8105638e-07 | H24: =G24*7700 -> 0.0037041341 | J24: 1 | K24: Screw | L24: Decking / Facade | M24: =index(24:24,1,match($D$9,$2:$2,0)) -> 0.070086815 | N24: =J24*$D$19/(8*60) -> 0.03125 | O24: =M24+N24 -> 0.10133681 | P24: =A24*O24 -> 0 | Q24: =0.0383*$X$26 -> 0.070086815 | R24: =$Q24 -> 0.070086815 | S24: =$Q24 -> 0.070086815 | T24: =$Q24 -> 0.070086815 | U24: =$Q24 -> 0.070086815 | V24: =$Q24 -> 0.070086815 | W24: =Q24 -> 0.070086815 | X24: Screw specs from Rotho Blaas now assumed with 25% import tax, 15% withholding tax, and 25% freight costs (USD 500 on USD 2500 order) across markets. VAT is added separately per country.
A25: =sumif('Structures Database'!B:B,C25,'Structures Database'!W:W) -> 0 | B25: pcs | C25: Screw 4 x 50 Stainless A2 SCA450 | D25: 4 | F25: 50 | G25: =(D25/2)^2*PI()*F25/1000000000 -> 6.2831853e-07 | H25: =G25*7700 -> 0.0048380527 | J25: 1 | K25: Screw | L25: Outdoor | M25: =index(25:25,1,match($D$9,$2:$2,0)) -> 0.1024768 | N25: =J25*$D$19/(8*60) -> 0.03125 | O25: =M25+N25 -> 0.1337268 | P25: =A25*O25 -> 0 | Q25: =0.056*$X$26 -> 0.1024768 | R25: =$Q25 -> 0.1024768 | S25: =$Q25 -> 0.1024768 | T25: =$Q25 -> 0.1024768 | U25: =$Q25 -> 0.1024768 | V25: =$Q25 -> 0.1024768 | W25: =Q25 -> 0.1024768 | X25: Import factor
A26: =sumif('Structures Database'!B:B,C26,'Structures Database'!W:W) -> 4966.8427 | B26: pcs | C26: Screw 4x40 semi threaded HBS440 | D26: 4 | F26: 40 | G26: =(D26/2)^2*PI()*F26/1000000000 -> 5.0265482e-07 | H26: =G26*7700 -> 0.0038704421 | J26: 1 | K26: Screw | L26: Boards | M26: =index(26:26,1,match($D$9,$2:$2,0)) -> 0.012 | N26: =J26*$D$19/(8*60) -> 0.03125 | O26: =M26+N26 -> 0.04325 | P26: =A26*O26 -> 214.81595 | Q26: 0.012 | R26: =$Q26 -> 0.012 | S26: =$Q26 -> 0.012 | T26: =$Q26 -> 0.012 | U26: =$Q26 -> 0.012 | V26: =$Q26 -> 0.012 | W26: =Q26 -> 0.012 | X26: =(2475+600+(0.35+0.06+0.015)*2475+680000/3700+218.45)/2475 -> 1.8299429
A27: =sumif('Structures Database'!B:B,C27,'Structures Database'!W:W) -> 2307.5998 | B27: pcs | C27: Screw 4x60 semi threaded HBS460 | D27: 4 | F27: 60 | G27: =(D27/2)^2*PI()*F27/1000000000 -> 7.5398224e-07 | H27: =G27*7700 -> 0.0058056632 | J27: 1 | K27: Screw | L27: Back Battens | M27: =index(27:27,1,match($D$9,$2:$2,0)) -> 0.018 | N27: =J27*$D$19/(8*60) -> 0.03125 | O27: =M27+N27 -> 0.04925 | P27: =A27*O27 -> 113.64929 | Q27: 0.018 | R27: =$Q27 -> 0.018 | S27: =$Q27 -> 0.018 | T27: =$Q27 -> 0.018 | U27: =$Q27 -> 0.018 | V27: =$Q27 -> 0.018 | W27: =Q27 -> 0.018
A28: =sumif('Structures Database'!B:B,C28,'Structures Database'!W:W) -> 0 | B28: pcs | C28: Screw 5x80 semi threaded HBS580 | D28: 5 | F28: 80 | G28: =(D28/2)^2*PI()*F28/1000000000 -> 1.5707963e-06 | H28: =G28*7700 -> 0.012095132 | J28: 1 | K28: Screw | L28: Frames | M28: =index(28:28,1,match($D$9,$2:$2,0)) -> 0.146 | N28: =J28*$D$19/(8*60) -> 0.03125 | O28: =M28+N28 -> 0.17725 | P28: =A28*O28 -> 0 | Q28: 0.146 | R28: =$Q28 -> 0.146 | S28: =$Q28 -> 0.146 | T28: =$Q28 -> 0.146 | U28: =$Q28 -> 0.146 | V28: =$Q28 -> 0.146 | W28: =Q28 -> 0.146
A29: =sumif('Structures Database'!B:B,C29,'Structures Database'!W:W) -> 760.22222 | B29: pcs | C29: Screw 6x100 semi threaded HBS6100 | D29: 6 | F29: 100 | G29: =(D29/2)^2*PI()*F29/1000000000 -> 2.8274334e-06 | H29: =G29*7700 -> 0.021771237 | J29: 1 | K29: Screw | L29: Frames | M29: =index(29:29,1,match($D$9,$2:$2,0)) -> 0.06 | N29: =J29*$D$19/(8*60) -> 0.03125 | O29: =M29+N29 -> 0.09125 | P29: =A29*O29 -> 69.370277 | Q29: 0.06 | R29: =$Q29 -> 0.06 | S29: =$Q29 -> 0.06 | T29: =$Q29 -> 0.06 | U29: =$Q29 -> 0.06 | V29: =$Q29 -> 0.06 | W29: =Q29 -> 0.06
A30: =sumif('Structures Database'!B:B,C30,'Structures Database'!W:W) -> 1782.0344 | B30: pcs | C30: Screw 6x120 semi threaded HBS6120 | D30: 6 | F30: 120 | G30: =(D30/2)^2*PI()*F30/1000000000 -> 3.3929201e-06 | H30: =G30*7700 -> 0.026125485 | J30: 1 | K30: Screw | L30: Frames | M30: =index(30:30,1,match($D$9,$2:$2,0)) -> 0.06 | N30: =J30*$D$19/(8*60) -> 0.03125 | O30: =M30+N30 -> 0.09125 | P30: =A30*O30 -> 162.61064 | Q30: 0.06 | R30: =$Q30 -> 0.06 | S30: =$Q30 -> 0.06 | T30: =$Q30 -> 0.06 | U30: =$Q30 -> 0.06 | V30: =$Q30 -> 0.06 | W30: =Q30 -> 0.06
A31: =sumif('Structures Database'!B:B,C31,'Structures Database'!W:W) -> 68 | B31: pcs | C31: Screw 6x160 semi threaded HBS6160 | D31: 6 | F31: 160 | G31: =(D31/2)^2*PI()*F31/1000000000 -> 4.5238934e-06 | H31: =G31*7700 -> 0.034833979 | J31: 1 | K31: Screw | L31: Frames | M31: =index(31:31,1,match($D$9,$2:$2,0)) -> 0.41891054 | N31: =J31*$D$19/(8*60) -> 0.03125 | O31: =M31+N31 -> 0.45016054 | P31: =A31*O31 -> 30.610917 | Q31: =0.22892*$X$26 -> 0.41891054 | R31: =$Q31 -> 0.41891054 | S31: =$Q31 -> 0.41891054 | T31: =$Q31 -> 0.41891054 | U31: =$Q31 -> 0.41891054 | V31: =$Q31 -> 0.41891054 | W31: =Q31 -> 0.41891054
A32: =sumif('Structures Database'!B:B,C32,'Structures Database'!W:W) -> 298.09133 | B32: pcs | C32: Corrugated roof screw 67 mm | D32: 6 | F32: 67 | G32: =(D32/2)^2*PI()*F32/1000000000 -> 1.8943804e-06 | H32: =G32*7700 -> 0.014586729 | J32: 1 | K32: Screw | L32: Roofing | M32: =index(32:32,1,match($D$9,$2:$2,0)) -> 0.11756757 | N32: =J32*$D$19/(8*60) -> 0.03125 | O32: =M32+N32 -> 0.14881757 | P32: =A32*O32 -> 44.361226 | Q32: =435/'Location Data'!$D$6 -> 0.11756757 | R32: =$Q32 -> 0.11756757 | S32: =$Q32 -> 0.11756757 | T32: =$Q32 -> 0.11756757 | U32: =$Q32 -> 0.11756757 | V32: =$Q32 -> 0.11756757 | W32: =Q32 -> 0.11756757
A34: Foundation materials
A35: =sumif('Structures Database'!B:B,C35,'Structures Database'!W:W) -> 21 | B35: pcs | C35: Foundation block | D35: 300 | E35: 400 | F35: 300 | G35: =D35*E35*F35/1000000000 -> 0.036 | H35: =G35*2400 -> 86.4 | I35: 0 | J35: 180 | K35: Foundation | L35: Point | M35: {=index(35:35,1,match($D$9,$2:$2,0))} -> 0 | N35: =J35*$D$19/(8*60) -> 5.625 | O35: =M35+N35 -> 5.625 | P35: =A35*O35 -> 118.125 | Q35: 0 | R35: 0 | S35: 0 | T35: 0 | U35: 0 | V35: 0 | W35: 0
A36: =sumif('Structures Database'!B:B,C36,'Structures Database'!W:W) -> 6.3 | B36: pcs | C36: Cement Bag 50 kg | I36: -0.6 | K36: Foundation | L36: Cement | M36: =37500/3700/1.18 -> 8.5890976 | N36: =J36*$D$19/(8*60) -> 0 | O36: =M36+N36 -> 8.5890976 | P36: =A36*O36 -> 54.111315
A37: =sumif('Structures Database'!B:B,C37,'Structures Database'!W:W) -> 0.63 | B37: tonnes | C37: Sand per tonne | K37: Foundation | L37: Anchor | M37: =135000/3/3700 -> 12.162162 | N37: =J37*$D$19/(8*60) -> 0 | O37: =M37+N37 -> 12.162162 | P37: =A37*O37 -> 7.6621622
A38: =sumif('Structures Database'!B:B,C38,'Structures Database'!W:W) -> 0.84 | B38: tonnes | C38: Aggregates per tonne | K38: Foundation | L38: Anchor | M38: =230000/3700 -> 62.162162 | N38: =J38*$D$19/(8*60) -> 0 | O38: =M38+N38 -> 62.162162 | P38: =A38*O38 -> 52.216216
A39: =sumif('Structures Database'!B:B,C39,'Structures Database'!W:W) -> 84 | B39: pcs | C39: M12 rod 200 mm (stainless steel) | D39: 16 | F39: 250 | G39: =(D39/2)^2*PI()*F39/1000000000 -> 5.0265482e-05 | K39: Foundation | L39: Rod | M39: 3 | N39: =J39*$D$19/(8*60) -> 0 | O39: =M39+N39 -> 3 | P39: =A39*O39 -> 252
A40: =sumif('Structures Database'!B:B,C40,'Structures Database'!W:W) -> 168 | B40: pcs | C40: M12 nut (stainless steel) | D40: 24 | E40: 24 | F40: 13 | K40: Foundation | L40: Nut | M40: 0.4 | N40: =J40*$D$19/(8*60) -> 0 | O40: =M40+N40 -> 0.4 | P40: =A40*O40 -> 67.2
A41: =sumif('Structures Database'!B:B,C41,'Structures Database'!W:W) -> 168 | B41: pcs | C41: M12 washer (stainless steel) | D41: 30 | F41: 3 | K41: Foundation | L41: Washer | M41: 0.2 | N41: =J41*$D$19/(8*60) -> 0 | O41: =M41+N41 -> 0.2 | P41: =A41*O41 -> 33.6
A42: =sumif('Structures Database'!B:B,C42,'Structures Database'!W:W) -> 84 | B42: pcs | C42: M12 drop anchor | D42: 20 | F42: 65 | K42: Foundation | L42: Anchor | M42: 1 | N42: =J42*$D$19/(8*60) -> 0 | O42: =M42+N42 -> 1 | P42: =A42*O42 -> 84
A43: =sumif('Structures Database'!B:B,C43,'Structures Database'!W:W) -> 2.1 | B43: pcs | C43: Y12 bar 12 metres | D43: 12 | F43: 12000 | G43: =(D43/2)^2*PI()*F43/1000000000 -> 0.001357168 | K43: Foundation | L43: Rebar | M43: =45000/1.18/3700 -> 10.306917 | N43: =J43*$D$19/(8*60) -> 0 | O43: =M43+N43 -> 10.306917 | P43: =A43*O43 -> 21.644526
A44: =sumif('Structures Database'!B:B,C44,'Structures Database'!W:W) -> 2.1 | B44: pcs | C44: 8 mm rebar 12 metres | D44: 8 | F44: 12000 | G44: =(D44/2)^2*PI()*F44/1000000000 -> 0.00060318579 | K44: Foundation | L44: Rebar | M44: =12000/1.18/3700 -> 2.7485112 | N44: =J44*$D$19/(8*60) -> 0 | O44: =M44+N44 -> 2.7485112 | P44: =A44*O44 -> 5.7718736
A45: =sumif('Structures Database'!B:B,C45,'Structures Database'!W:W) -> 4.2 | B45: pcs | C45: Binding wire per kg | D45: 12 | F45: 12000 | G45: =(D45/2)^2*PI()*F45/1000000000 -> 0.001357168 | K45: Foundation | L45: Wire | M45: =6000/3700 -> 1.6216216 | N45: =J45*$D$19/(8*60) -> 0 | O45: =M45+N45 -> 1.6216216 | P45: =A45*O45 -> 6.8108108
A46: =sumif('Structures Database'!B:B,C46,'Structures Database'!W:W) -> 4.2 | B46: liter | C46: Used engine oil per liter | K46: Foundation | L46: Oil | M46: =3000/3700/1.18 -> 0.68712781 | N46: =J46*$D$19/(8*60) -> 0 | O46: =M46+N46 -> 0.68712781 | P46: =A46*O46 -> 2.8859368
A47: =sumif('Structures Database'!B:B,C47,'Structures Database'!W:W) -> 42 | B47: pcs | C47: Foundation plate 5 x 100 x 250 mm (redoxide coated) | D47: 100 | E47: 5 | F47: 250 | G47: =D47*E47*F47/1000000000 -> 0.000125 | J47: 15 | K47: Foundation | L47: Plate | M47: =600000/114/1.18/3700+7000/3700+1 -> 4.0973793 | N47: =J47*$D$19/(8*60) -> 0.46875 | O47: =M47+N47 -> 4.5661293 | P47: =A47*O47 -> 191.77743
A49: Timber and boards
A50: =sumif('Structures Database'!B:B,C50,'Structures Database'!W:W) -> 0 | B50: pcs | C50: Gypsum board 10 x 1220 x 2440 | D50: 10 | E50: 1220 | F50: 2440 | G50: =D50*E50*F50/1000000000 -> 0.029768 | H50: =G50*800 -> 23.8144 | J50: 10 | K50: Board | L50: Gypsum | M50: 8 | Q50: 10 | R50: 10
A51: =5.5*'Project Costs'!A126 -> 11 | B51: pcs | C51: Cement fibre board 10 x 1220 x 2440 | D51: 10 | E51: 1220 | F51: 2440 | G51: =D51*E51*F51/1000000000 -> 0.029768 | H51: =G51*1350 -> 40.1868 | J51: 20 | K51: Board | L51: Cement Fibre | M51: 16 | P51: =A51*M51 -> 176
A52: =sumif('Structures Database'!B:B,C52,'Structures Database'!W:W) -> 0 | B52: pcs | C52: Plywood 6 x 1220 x 2440 | D52: 6 | E52: 1220 | F52: 2440 | G52: =D52*E52*F52/1000000000 -> 0.0178608 | H52: =G52*510 -> 9.109008 | I52: =H52*0.88*$D$20 -> 14.693194 | J52: 10 | K52: Board | L52: Plywood | M52: =index(52:52,1,match($D$9,$2:$2,0)) -> 8 | N52: =J52*$D$19/(8*60) -> 0.3125 | O52: =M52+N52 -> 8.3125 | P52: =A52*O52 -> 0 | Q52: =Q55/18*6*1.2 -> 8 | R52: =R55/18*6*1.2 -> 8 | S52: =S55/18*6*1.2 -> 10 | T52: =T55/18*6*1.2 -> 10 | U52: =475*0.009*1.22*2.44+2 -> 14.72582 | V52: =V55/18*6*1.2 -> 8.3
A53: =sumif('Structures Database'!B:B,C53,'Structures Database'!W:W) -> 20 | B53: pcs | C53: Plywood 9 x 1220 x 2440 | D53: 9 | E53: 1220 | F53: 2440 | G53: =D53*E53*F53/1000000000 -> 0.0267912 | H53: =G53*510 -> 13.663512 | I53: =H53*0.88*$D$20 -> 22.039791 | J53: 10 | K53: Board | L53: Plywood | M53: =index(53:53,1,match($D$9,$2:$2,0)) -> 7.7874485 | N53: =J53*$D$19/(8*60) -> 0.3125 | O53: =M53+N53 -> 8.0999485 | P53: =A53*O53 -> 161.99897 | Q53: =34000/1.18/3700 -> 7.7874485 | R53: 7.8 | S53: =S55/18*9*1.2 -> 15 | T53: =T55/18*9*1.2 -> 15 | U53: =475*0.009*1.22*2.44+2 -> 14.72582 | V53: =V55/18*9*1.2 -> 12.45 | W53: =Q53*1.2 -> 9.3449382
A54: =sumif('Structures Database'!B:B,C54,'Structures Database'!W:W) -> 85.47973 | B54: pcs | C54: Plywood 12 x 1220 x 2440 | D54: 12 | E54: 1220 | F54: 2440 | G54: =D54*E54*F54/1000000000 -> 0.0357216 | H54: =G54*510 -> 18.218016 | I54: =H54*0.88*$D$20 -> 29.386389 | J54: 10 | K54: Board | L54: Plywood | M54: =index(54:54,1,match($D$9,$2:$2,0)) -> 12.139258 | N54: =J54*$D$19/(8*60) -> 0.3125 | O54: =M54+N54 -> 12.451758 | P54: =A54*O54 -> 1064.3729 | Q54: =53000/1.18/3700 -> 12.139258 | R54: 12.15 | S54: =S55/18*12*1.1 -> 18.333333 | T54: =T55/18*12*1.1 -> 18.333333 | U54: =425*0.012*1.22*2.44+2 -> 17.18168 | V54: =V55/18*12*1.1 -> 15.216667 | W54: =Q54*1.2 -> 14.567109
A55: =sumif('Structures Database'!B:B,C55,'Structures Database'!W:W) -> 0 | B55: pcs | C55: Plywood 18 x 1220 x 2440 | D55: 18 | E55: 1220 | F55: 2440 | G55: =D55*E55*F55/1000000000 -> 0.0535824 | H55: =G55*510 -> 27.327024 | I55: =H55*0.88*$D$20 -> 44.079583 | J55: 10 | K55: Board | L55: Plywood | M55: =index(55:55,1,match($D$9,$2:$2,0)) -> 20 | N55: =J55*$D$19/(8*60) -> 0.3125 | O55: =M55+N55 -> 20.3125 | P55: =A55*O55 -> 0 | Q55: 20 | R55: 20 | S55: 25 | T55: 25 | U55: =400*0.018*1.22*2.44+2 -> 23.43296 | V55: =45000/2400 + 2 -> 20.75
A57: ='Timber Order'!H35 -> 10.780124 | B57: cbm | C57: Timber - dried, treated and planed | D57: 1000 | E57: 1000 | F57: 1000 | G57: 1 | H57: =D16 -> 561
A58: ='Timber Order'!A16 -> 90 | B58: ='Timber Order'!B16 -> pcs | C58: ='Timber Order'!C16 -> Wall Beam 46 x 71 x 2450 | D58: ='Timber Order'!D16 -> 46 | E58: ='Timber Order'!E16 -> 71 | F58: ='Timber Order'!F16 -> 2450 | G58: ='Timber Order'!G16 -> 0.0080017 | H58: ='Timber Order'!J16 -> 4.4889537 | I58: ='Timber Order'!K16 -> 7.2308882 | K58: ='Timber Order'!L16 -> Wall | L58: ='Timber Order'!M16 -> Beam
A59: ='Timber Order'!A17 -> 103 | B59: ='Timber Order'!B17 -> pcs | C59: ='Timber Order'!C17 -> Wall Beam 46 x 71 x 3650 | D59: ='Timber Order'!D17 -> 46 | E59: ='Timber Order'!E17 -> 71 | F59: ='Timber Order'!F17 -> 3650 | G59: ='Timber Order'!G17 -> 0.0119209 | H59: ='Timber Order'!J17 -> 6.6876249 | I59: ='Timber Order'!K17 -> 10.772548 | K59: ='Timber Order'!L17 -> Wall | L59: ='Timber Order'!M17 -> Beam
A60: ='Timber Order'!A18 -> 38 | B60: ='Timber Order'!B18 -> pcs | C60: ='Timber Order'!C18 -> Roof Beam 46 x 96 x 2450 | D60: ='Timber Order'!D18 -> 46 | E60: ='Timber Order'!E18 -> 96 | F60: ='Timber Order'!F18 -> 2450 | G60: ='Timber Order'!G18 -> 0.0108192 | H60: ='Timber Order'!J18 -> 6.0695712 | I60: ='Timber Order'!K18 -> 9.7769756 | K60: ='Timber Order'!L18 -> Roof | L60: ='Timber Order'!M18 -> Beam
A61: ='Timber Order'!A19 -> 0 | B61: ='Timber Order'!B19 -> pcs | C61: ='Timber Order'!C19 -> Roof Beam 46 x 96 x 4250 | D61: ='Timber Order'!D19 -> 46 | E61: ='Timber Order'!E19 -> 96 | F61: ='Timber Order'!F19 -> 4250 | G61: ='Timber Order'!G19 -> 0.018768 | H61: ='Timber Order'!J19 -> 10.528848 | I61: ='Timber Order'!K19 -> 16.96006 | K61: ='Timber Order'!L19 -> Roof | L61: ='Timber Order'!M19 -> Beam
A62: ='Timber Order'!A20 -> 34 | B62: ='Timber Order'!B20 -> pcs | C62: ='Timber Order'!C20 -> Roof Beam 46 x 96 x 5750 | D62: ='Timber Order'!D20 -> 46 | E62: ='Timber Order'!E20 -> 96 | F62: ='Timber Order'!F20 -> 5750 | G62: ='Timber Order'!G20 -> 0.025392 | H62: ='Timber Order'!J20 -> 14.244912 | I62: ='Timber Order'!K20 -> 22.945963 | K62: ='Timber Order'!L20 -> Roof | L62: ='Timber Order'!M20 -> Beam
A63: ='Timber Order'!A21 -> 86 | B63: ='Timber Order'!B21 -> pcs | C63: ='Timber Order'!C21 -> Floor Beam 46 x 146 x 2450 | D63: ='Timber Order'!D21 -> 46 | E63: ='Timber Order'!E21 -> 146 | F63: ='Timber Order'!F21 -> 2450 | G63: ='Timber Order'!G21 -> 0.0164542 | H63: ='Timber Order'!J21 -> 9.2308062 | I63: ='Timber Order'!K21 -> 14.86915 | K63: ='Timber Order'!L21 -> Floor | L63: ='Timber Order'!M21 -> Beam
A64: ='Timber Order'!A22 -> 0 | B64: ='Timber Order'!B22 -> pcs | C64: ='Timber Order'!C22 -> Floor Beam 46 x 146 x 3050 | D64: ='Timber Order'!D22 -> 46 | E64: ='Timber Order'!E22 -> 146 | F64: ='Timber Order'!F22 -> 3050 | G64: ='Timber Order'!G22 -> 0.0204838 | H64: ='Timber Order'!J22 -> 11.491412 | I64: ='Timber Order'!K22 -> 18.510575 | K64: ='Timber Order'!L22 -> Floor | L64: ='Timber Order'!M22 -> Beam
A65: ='Timber Order'!A23 -> 0 | B65: ='Timber Order'!B23 -> pcs | C65: ='Timber Order'!C23 -> Floor Beam 46 x 146 x 5450 | D65: ='Timber Order'!D23 -> 46 | E65: ='Timber Order'!E23 -> 146 | F65: ='Timber Order'!F23 -> 5450 | G65: ='Timber Order'!G23 -> 0.0366022 | H65: ='Timber Order'!J23 -> 20.533834 | I65: ='Timber Order'!K23 -> 33.076273 | K65: ='Timber Order'!L23 -> Floor | L65: ='Timber Order'!M23 -> Beam
A66: ='Timber Order'!A24 -> 0 | B66: ='Timber Order'!B24 -> pcs | C66: ='Timber Order'!C24 -> Timber Column 100 x 100 x 3050 | D66: ='Timber Order'!D24 -> 100 | E66: ='Timber Order'!E24 -> 100 | F66: ='Timber Order'!F24 -> 3050 | G66: ='Timber Order'!G24 -> 0.0305 | H66: ='Timber Order'!J24 -> 17.1105 | I66: ='Timber Order'!K24 -> 27.561905 | K66: ='Timber Order'!L24 -> Timber | L66: ='Timber Order'!M24 -> Column
A67: ='Timber Order'!A25 -> 249 | B67: ='Timber Order'!B25 -> pcs | C67: ='Timber Order'!C25 -> Timber Back Batten 22 x 46 x 2450 | D67: ='Timber Order'!D25 -> 22 | E67: ='Timber Order'!E25 -> 46 | F67: ='Timber Order'!F25 -> 2450 | G67: ='Timber Order'!G25 -> 0.0024794 | H67: ='Timber Order'!J25 -> 1.3909434 | I67: ='Timber Order'!K25 -> 2.2405569 | K67: ='Timber Order'!L25 -> Timber | L67: ='Timber Order'!M25 -> Back Batten
A68: ='Timber Order'!A26 -> 0 | B68: ='Timber Order'!B26 -> pcs | C68: ='Timber Order'!C26 -> Timber Back Batten 22 x 46 x 3050 | D68: ='Timber Order'!D26 -> 22 | E68: ='Timber Order'!E26 -> 46 | F68: ='Timber Order'!F26 -> 3050 | G68: ='Timber Order'!G26 -> 0.0030866 | H68: ='Timber Order'!J26 -> 1.7315826 | I68: ='Timber Order'!K26 -> 2.7892647 | K68: ='Timber Order'!L26 -> Timber | L68: ='Timber Order'!M26 -> Back Batten
A69: ='Timber Order'!A27 -> 328 | B69: ='Timber Order'!B27 -> pcs | C69: ='Timber Order'!C27 -> Timber Floor Plank 22 x 96 x 2450 | D69: ='Timber Order'!D27 -> 22 | E69: ='Timber Order'!E27 -> 96 | F69: ='Timber Order'!F27 -> 2450 | G69: ='Timber Order'!G27 -> 0.0051744 | H69: ='Timber Order'!J27 -> 2.9028384 | I69: ='Timber Order'!K27 -> 4.6759449 | K69: ='Timber Order'!L27 -> Timber | L69: ='Timber Order'!M27 -> Floor Plank
... A75: ='Timber Order'!A33 -> 36 | B75: ='Timber Order'!B33 -> pcs | C75: ='Timber Order'!C33 -> Interior Door Beams 50 x 150 x 2450 | D75: ='Timber Order'!D33 -> 50 | E75: ='Timber Order'!E33 -> 150 | F75: ='Timber Order'!F33 -> 2450 | G75: ='Timber Order'!G33 -> 0.018375 | H75: ='Timber Order'!J33 -> 10.308375 | I75: ='Timber Order'!K33 -> 16.604918 | K75: ='Timber Order'!L33 -> Interior Door | L75: ='Timber Order'!M33 -> Beams
A78: Others
A79: =sumif('Structures Database'!B:B,C79,'Structures Database'!W:W) -> 74.522832 | B79: sqm | C79: Roof sheets per sqm | D79: 1000 | E79: 50 | F79: 1000 | G79: =D79*E79*F79/1000000000 -> 0.05 | J79: 30 | M79: =index(79:79,1,match($D$9,$2:$2,0)) -> 10.7 | N79: =J79*$D$19/(8*60) -> 0.9375 | O79: =M79+N79 -> 11.6375 | P79: =A79*O79 -> 867.25946 | Q79: 10.7 | R79: 10.7 | S79: 11 | T79: 11 | U79: 12 | V79: 12 | W79: =Q79*1.2 -> 12.84
A80: ='Project Costs'!B27 -> 10.5 | B80: sqm | C80: Aluminium window frames per sqm | D80: 1000 | E80: 70 | F80: 1000 | G80: =D80*E80*F80/1000000000 -> 0.07 | H80: =D80*F80/1000000*25 -> 25 | J80: 0 | K80: Windows | L80: Aluminium | M80: =index(80:80,1,match($D$9,$2:$2,0)) -> 160 | N80: =J80*$D$19/(8*60) -> 0 | O80: =M80+N80 -> 160 | P80: =A80*O80 -> 1680 | Q80: 160 | R80: 130 | S80: 170 | T80: 170 | U80: 170 | V80: 100 | W80: =Q80*1.2 -> 192
A81: =sumif('Structures Database'!B:B,C81,'Structures Database'!W:W) -> 0 | B81: sqm | C81: Mosquito net sqm (facades & windows) | D81: 1000 | E81: 0.2 | F81: 1000 | J81: 6 | M81: =6000/3700/1.18 -> 1.3742556 | W81: =Q81*1.2 -> 0
A82: =sumif('Structures Database'!B:B,C82,'Structures Database'!W:W) -> 0 | B82: sqm | C82: Building membrane (sqm) | D82: 1000 | E82: 0.2 | F82: 1000 | G82: =D82*E82*F82/1000000000 -> 0.0002 | H82: =G82*920 -> 0.184 | J82: 5 | K82: Membrane | L82: Plastic | M82: =index(82:82,1,match($D$9,$2:$2,0)) -> 1 | N82: =J82*$D$19/(8*60) -> 0.15625 | O82: =M82+N82 -> 1.15625 | Q82: 1 | R82: =Q82 -> 1 | S82: =R82 -> 1 | T82: =S82 -> 1 | U82: =T82 -> 1 | V82: =U82 -> 1 | W82: =Q82*1.2 -> 1.2
A83: =sumif('Structures Database'!B:B,C83,'Structures Database'!W:W) -> 60 | B83: sqm | C83: Aluminium roof insulation membrane per sqm | D83: 1000 | E83: 4 | F83: 1000 | G83: =D83*E83*F83/1000000000 -> 0.004 | H83: 0.15 | J83: 6 | K83: Insulation | L83: Membrane | M83: =index(83:83,1,match($D$9,$2:$2,0)) -> 1.6 | N83: =J83*$D$19/(8*60) -> 0.1875 | O83: =M83+N83 -> 1.7875 | P83: =A83*O83 -> 107.25 | Q83: 1.6 | R83: 2.75 | S83: 2.75 | T83: 2.75 | U83: 2.75 | V83: 2.75 | W83: =Q83*1.2 -> 1.92
A84: =sumif('Structures Database'!B:B,C84,'Structures Database'!W:W) -> 67.860442 | B84: sqm | C84: Glass wool insulation (per sqm) | D84: 1000 | E84: 50 | F84: 1000 | G84: =D84*E84*F84/1000000000 -> 0.05 | H84: =G84*40 -> 2 | I84: =H84*$D$20 -> 3.666 | J84: 10 | K84: Insulation | L84: Glass wool | M84: =index(84:84,1,match($D$9,$2:$2,0)) -> 3.6 | N84: =J84*$D$19/(8*60) -> 0.3125 | O84: =M84+N84 -> 3.9125 | P84: =A84*O84 -> 265.50398 | Q84: 3.6 | R84: 3.6 | S84: =4.5 -> 4.5 | T84: =4.5 -> 4.5 | U84: =4.5 -> 4.5 | V84: =4.5 -> 4.5 | W84: =Q84*1.2 -> 4.32
A85: =sumif('Structures Database'!B:B,C85,'Structures Database'!W:W) -> 0 | B85: cbm | C85: Biobased insulation - papyrus (m3) | D85: 1000 | E85: 1000 | F85: 1000 | G85: =D85*E85*F85/1000000000 -> 1 | H85: =G85*90 -> 90 | I85: =H85*$D$20 -> 164.97 | J85: 180 | K85: Insulation | L85: Papyrus | M85: =index(85:85,1,match($D$9,$2:$2,0)) -> 35 | N85: =J85*$D$19/(8*60) -> 5.625 | O85: =M85+N85 -> 40.625 | Q85: 35 | R85: 35 | S85: 35 | T85: 35 | U85: 35 | V85: 35
A87: Beams and planks
A88: =sumif('Structures Database'!B:B,C88,'Structures Database'!W:W) -> 24 | B88: pcs | C88: =K88&" "&L88&" "&D88&" x "&E88&" x "&F88 -> Floor Main Beam 46 x 146 x 2442 | D88: 46 | E88: 146 | F88: 2442 | G88: =D88*E88*F88/1000000000 -> 0.016400472 | H88: =G88*$D$16 -> 9.2006648 | I88: =G88*$D$18*$D$20 -> 14.820598 | J88: 5 | K88: Floor | L88: Main Beam | M88: =AD88*if(D88>45,$D$14,$D$15) -> 4.1464584 | N88: =J88*$D$19/(8*60) -> 0.15625 | O88: =M88+N88 -> 4.3027084 | P88: =A88*O88 -> 103.265 | X88: ='Timber Order'!$C$21 -> Floor Beam 46 x 146 x 2450 | Y88: 1 | Z88: =A88*Y88 -> 24 | AA88: {=1-(G88/Y88/index('Timber Order'!G:G,match($X88,'Timber Order'!C:C,0),1))} -> 0.0032653061 | AB88: =A88*G88 -> 0.39361133 | AC88: {=A88*Y88*index('Timber Order'!G:G,match($X88,'Timber Order'!C:C,0),1)} -> 0.3949008 | AD88: {=Y88*index('Timber Order'!G:G,match($X88,'Timber Order'!C:C,0),1)} -> 0.0164542 | AE88: =AC88-AB88 -> 0.001289472
A89: =sumif('Structures Database'!B:B,C89,'Structures Database'!W:W) -> 40 | B89: pcs | C89: =K89&" "&L89&" "&D89&" x "&E89&" x "&F89 -> Floor Sub Beam 46 x 146 x 2342 | D89: 46 | E89: 146 | F89: 2342 | G89: =D89*E89*F89/1000000000 -> 0.015728872 | H89: =G89*$D$16 -> 8.8238972 | I89: =G89*$D$18*$D$20 -> 14.213694 | J89: 5 | K89: Floor | L89: Sub Beam | M89: =AD89*if(D89>45,$D$14,$D$15) -> 4.1464584 | N89: =J89*$D$19/(8*60) -> 0.15625 | O89: =M89+N89 -> 4.3027084 | P89: =A89*O89 -> 172.10834 | X89: ='Timber Order'!$C$21 -> Floor Beam 46 x 146 x 2450 | Y89: 1 | Z89: =A89*Y89 -> 40 | AA89: {=1-(G89/Y89/index('Timber Order'!G:G,match($X89,'Timber Order'!C:C,0),1))} -> 0.044081633 | AB89: =A89*G89 -> 0.62915488 | AC89: {=A89*Y89*index('Timber Order'!G:G,match($X89,'Timber Order'!C:C,0),1)} -> 0.658168 | AD89: {=Y89*index('Timber Order'!G:G,match($X89,'Timber Order'!C:C,0),1)} -> 0.0164542 | AE89: =AC89-AB89 -> 0.02901312
A90: =sumif('Structures Database'!B:B,C90,'Structures Database'!W:W) -> 0 | B90: pcs | C90: =K90&" "&L90&" "&D90&" x "&E90&" x "&F90 -> Floor Sub Beam 46 x 146 x 2952 | D90: 46 | E90: 146 | F90: 2952 | G90: =D90*E90*F90/1000000000 -> 0.019825632 | H90: =G90*$D$16 -> 11.12218 | I90: =G90*$D$18*$D$20 -> 17.915809 | J90: 5 | K90: Floor | L90: Sub Beam | M90: =AD90*if(D90>45,$D$14,$D$15) -> 5.1619176 | N90: =J90*$D$19/(8*60) -> 0.15625 | O90: =M90+N90 -> 5.3181676 | P90: =A90*O90 -> 0 | X90: ='Timber Order'!$C$22 -> Floor Beam 46 x 146 x 3050 | Y90: 1 | Z90: =A90*Y90 -> 0 | AA90: {=1-(G90/Y90/index('Timber Order'!G:G,match($X90,'Timber Order'!C:C,0),1))} -> 0.032131148 | AB90: =A90*G90 -> 0 | AC90: {=A90*Y90*index('Timber Order'!G:G,match($X90,'Timber Order'!C:C,0),1)} -> 0 | AD90: {=Y90*index('Timber Order'!G:G,match($X90,'Timber Order'!C:C,0),1)} -> 0.0204838 | AE90: =AC90-AB90 -> 0
A91: =sumif('Structures Database'!B:B,C91,'Structures Database'!W:W) -> 20 | B91: pcs | C91: =K91&" "&L91&" "&D91&" x "&E91&" x "&F91 -> Floor Sub Beam 46 x 146 x 1121 | D91: 46 | E91: 146 | F91: 1121 | G91: =D91*E91*F91/1000000000 -> 0.007528636 | H91: =G91*$D$16 -> 4.2235648 | I91: =G91*$D$18*$D$20 -> 6.803395 | J91: 5 | K91: Floor | L91: Sub Beam | M91: =AD91*if(D91>45,$D$14,$D$15) -> 2.0732292 | N91: =J91*$D$19/(8*60) -> 0.15625 | O91: =M91+N91 -> 2.2294792 | P91: =A91*O91 -> 44.589584 | X91: ='Timber Order'!$C$21 -> Floor Beam 46 x 146 x 2450 | Y91: 0.5 | Z91: =A91*Y91 -> 10 | AA91: {=1-(G91/Y91/index('Timber Order'!G:G,match($X91,'Timber Order'!C:C,0),1))} -> 0.084897959 | AB91: =A91*G91 -> 0.15057272 | AC91: {=A91*Y91*index('Timber Order'!G:G,match($X91,'Timber Order'!C:C,0),1)} -> 0.164542 | AD91: {=Y91*index('Timber Order'!G:G,match($X91,'Timber Order'!C:C,0),1)} -> 0.0082271 | AE91: =AC91-AB91 -> 0.01396928
A92: =sumif('Structures Database'!B:B,C92,'Structures Database'!W:W) -> 48 | B92: pcs | C92: =K92&" "&L92&" "&D92&" x "&E92&" x "&F92 -> Floor Support Block 46 x 146 x 548 | D92: 46 | E92: 146 | F92: 548 | G92: =D92*E92*F92/1000000000 -> 0.003680368 | H92: =G92*$D$16 -> 2.0646864 | I92: =G92*$D$18*$D$20 -> 3.3258345 | J92: 5 | K92: Floor | L92: Support Block | M92: =AD92*if(D92>45,$D$14,$D$15) -> 1.0366146 | N92: =J92*$D$19/(8*60) -> 0.15625 | O92: =M92+N92 -> 1.1928646 | P92: =A92*O92 -> 57.257501 | X92: ='Timber Order'!$C$21 -> Floor Beam 46 x 146 x 2450 | Y92: 0.25 | Z92: =A92*Y92 -> 12 | AA92: {=1-(G92/Y92/index('Timber Order'!G:G,match($X92,'Timber Order'!C:C,0),1))} -> 0.10530612 | AB92: =A92*G92 -> 0.17665766 | AC92: {=A92*Y92*index('Timber Order'!G:G,match($X92,'Timber Order'!C:C,0),1)} -> 0.1974504 | AD92: {=Y92*index('Timber Order'!G:G,match($X92,'Timber Order'!C:C,0),1)} -> 0.00411355 | AE92: =AC92-AB92 -> 0.020792736
A93: =sumif('Structures Database'!B:B,C93,'Structures Database'!W:W) -> 292 | B93: pcs | C93: =K93&" "&L93&" "&D93&" x "&E93&" x "&F93 -> Floor Plank Tongue Groove 22 x 96 x 2440 | D93: 22 | E93: 96 | F93: 2440 | G93: =D93*E93*F93/1000000000 -> 0.00515328 | H93: =G93*$D$16 -> 2.8909901 | I93: =G93*$D$18*$D$20 -> 4.6568594 | J93: 5 | K93: Floor | L93: Plank Tongue Groove | M93: =AD93*if(D93>45,$D$14,$D$15) -> 1.345344 | N93: =J93*$D$19/(8*60) -> 0.15625 | O93: =M93+N93 -> 1.501594 | P93: =A93*O93 -> 438.46545 | X93: ='Timber Order'!$C$27 -> Timber Floor Plank 22 x 96 x 2450 | Y93: 1 | Z93: =A93*Y93 -> 292 | AA93: {=1-(G93/Y93/index('Timber Order'!G:G,match($X93,'Timber Order'!C:C,0),1))} -> 0.0040816327 | AB93: =A93*G93 -> 1.5047578 | AC93: {=A93*Y93*index('Timber Order'!G:G,match($X93,'Timber Order'!C:C,0),1)} -> 1.5109248 | AD93: {=Y93*index('Timber Order'!G:G,match($X93,'Timber Order'!C:C,0),1)} -> 0.0051744 | AE93: =AC93-AB93 -> 0.00616704
A94: =sumif('Structures Database'!B:B,C94,'Structures Database'!W:W) -> 0 | B94: pcs | C94: =K94&" "&L94&" "&D94&" x "&E94&" x "&F94 -> Floor Decking Profile 22 x 96 x 2440 | D94: 22 | E94: 96 | F94: 2440 | G94: =D94*E94*F94/1000000000 -> 0.00515328 | H94: =G94*$D$16 -> 2.8909901 | I94: =G94*$D$18*$D$20 -> 4.6568594 | J94: 5 | K94: Floor | L94: Decking Profile | M94: =AD94*if(D94>45,$D$14,$D$15) -> 1.345344 | N94: =J94*$D$19/(8*60) -> 0.15625 | O94: =M94+N94 -> 1.501594 | P94: =A94*O94 -> 0 | X94: ='Timber Order'!$C$28 -> Timber Decking Plank 22 x 96 x 2450 | Y94: 1 | Z94: =A94*Y94 -> 0 | AA94: {=1-(G94/Y94/index('Timber Order'!G:G,match($X94,'Timber Order'!C:C,0),1))} -> 0.0040816327 | AB94: =A94*G94 -> 0 | AC94: {=A94*Y94*index('Timber Order'!G:G,match($X94,'Timber Order'!C:C,0),1)} -> 0 | AD94: {=Y94*index('Timber Order'!G:G,match($X94,'Timber Order'!C:C,0),1)} -> 0.0051744 | AE94: =AC94-AB94 -> 0
M95: =AD95*if(D95>45,$D$14,$D$15) -> 0 | P95: =A95*O95 -> 0
A96: =sumif('Structures Database'!B:B,C96,'Structures Database'!W:W) -> 50.113022 | B96: pcs | C96: =K96&" "&L96&" "&D96&" x "&E96&" x "&F96 -> Wall Batten 46 x 71 x 2442 | D96: 46 | E96: 71 | F96: 2442 | G96: =D96*E96*F96/1000000000 -> 0.007975572 | H96: =G96*$D$16 -> 4.4742959 | I96: =G96*$D$18*$D$20 -> 7.2072772 | J96: 5 | K96: Wall | L96: Batten | M96: =AD96*if(D96>45,$D$14,$D$15) -> 2.0164284 | N96: =J96*$D$19/(8*60) -> 0.15625 | O96: =M96+N96 -> 2.1726784 | P96: =A96*O96 -> 108.87948 | X96: ='Timber Order'!$C$16 -> Wall Beam 46 x 71 x 2450 | Y96: 1 | Z96: =A96*Y96 -> 50.113022 | AA96: {=1-(G96/Y96/index('Timber Order'!G:G,match($X96,'Timber Order'!C:C,0),1))} -> 0.0032653061 | AB96: =A96*G96 -> 0.39968002 | AC96: {=A96*Y96*index('Timber Order'!G:G,match($X96,'Timber Order'!C:C,0),1)} -> 0.40098937 | AD96: {=Y96*index('Timber Order'!G:G,match($X96,'Timber Order'!C:C,0),1)} -> 0.0080017 | AE96: =AC96-AB96 -> 0.001309353
A97: =sumif('Structures Database'!B:B,C97,'Structures Database'!W:W) -> 0 | B97: pcs | C97: =K97&" "&L97&" "&D97&" x "&E97&" x "&F97 -> Wall Batten 46 x 71 x 3053 | D97: 46 | E97: 71 | F97: 3053 | G97: =D97*E97*F97/1000000000 -> 0.009971098 | H97: =G97*$D$16 -> 5.593786 | I97: =G97*$D$18*$D$20 -> 9.0105722 | J97: 5 | K97: Wall | L97: Batten | M97: =AD97*if(D97>45,$D$14,$D$15) -> 2.5534568 | N97: =J97*$D$19/(8*60) -> 0.15625 | O97: =M97+N97 -> 2.7097068 | P97: =A97*O97 -> 0 | X97: ='Timber Order'!$C$17 -> Wall Beam 46 x 71 x 3650 | Y97: 0.85 | Z97: =A97*Y97 -> 0 | AA97: {=1-(G97/Y97/index('Timber Order'!G:G,match($X97,'Timber Order'!C:C,0),1))} -> 0.015954875 | AB97: =A97*G97 -> 0 | AC97: {=A97*Y97*index('Timber Order'!G:G,match($X97,'Timber Order'!C:C,0),1)} -> 0 | AD97: {=Y97*index('Timber Order'!G:G,match($X97,'Timber Order'!C:C,0),1)} -> 0.010132765 | AE97: =AC97-AB97 -> 0
A98: =sumif('Structures Database'!B:B,C98,'Structures Database'!W:W) -> 36 | B98: pcs | C98: =K98&" "&L98&" "&D98&" x "&E98&" x "&F98 -> Interior Door Beam 46 x 146 x 2415 | D98: 46 | E98: 146 | F98: 2415 | G98: =D98*E98*F98/1000000000 -> 0.01621914 | H98: =G98*$D$16 -> 9.0989375 | I98: =G98*$D$18*$D$20 -> 14.656734 | K98: Interior Door | L98: Beam | M98: =AD98*if(D98>45,$D$14,$D$15) -> 4.6305 | N98: =J98*$D$19/(8*60) -> 0 | O98: =M98+N98 -> 4.6305 | P98: =A98*O98 -> 166.698 | X98: ='Timber Order'!C33 -> Interior Door Beams 50 x 150 x 2450 | Y98: 1 | Z98: =A98*Y98 -> 36 | AA98: {=1-(G98/Y98/index('Timber Order'!G:G,match($X98,'Timber Order'!C:C,0),1))} -> 0.11732571 | AB98: =A98*G98 -> 0.58388904 | AC98: {=A98*Y98*index('Timber Order'!G:G,match($X98,'Timber Order'!C:C,0),1)} -> 0.6615 | AD98: {=Y98*index('Timber Order'!G:G,match($X98,'Timber Order'!C:C,0),1)} -> 0.018375 | AE98: =AC98-AB98 -> 0.07761096
A99: =sumif('Structures Database'!B:B,C99,'Structures Database'!W:W) -> 144 | B99: pcs | C99: =K99&" "&L99&" "&D99&" x "&E99&" x "&F99 -> Interior Door T&G Plank 22 x 96 x 550 | D99: 22 | E99: 96 | F99: 550 | G99: =D99*E99*F99/1000000000 -> 0.0011616 | H99: =G99*$D$16 -> 0.6516576 | I99: =G99*$D$18*$D$20 -> 1.0497019 | K99: Interior Door | L99: T&G Plank | M99: =AD99*if(D99>45,$D$14,$D$15) -> 0.336336 | N99: =J99*$D$19/(8*60) -> 0 | O99: =M99+N99 -> 0.336336 | P99: =A99*O99 -> 48.432384 | X99: ='Timber Order'!$C$27 -> Timber Floor Plank 22 x 96 x 2450 | Y99: 0.25 | Z99: =A99*Y99 -> 36 | AA99: {=1-(G99/Y99/index('Timber Order'!G:G,match($X99,'Timber Order'!C:C,0),1))} -> 0.10204082 | AB99: =A99*G99 -> 0.1672704 | AC99: {=A99*Y99*index('Timber Order'!G:G,match($X99,'Timber Order'!C:C,0),1)} -> 0.1862784 | AD99: {=Y99*index('Timber Order'!G:G,match($X99,'Timber Order'!C:C,0),1)} -> 0.0012936 | AE99: =AC99-AB99 -> 0.019008
A101: =sumif('Structures Database'!B:B,C101,'Structures Database'!W:W) -> 25 | B101: pcs | C101: =K101&" "&L101&" "&D101&" x "&E101&" x "&F101 -> Wall Stud 46 x 71 x 2554 | D101: 46 | E101: 71 | F101: 2554 | G101: =D101*E101*F101/1000000000 -> 0.008341364 | H101: =G101*$D$16 -> 4.6795052 | I101: =G101*$D$18*$D$20 -> 7.5378321 | J101: 5 | K101: Wall | L101: Stud | M101: =AD101*if(D101>45,$D$14,$D$15) -> 2.1028468 | N101: =J101*$D$19/(8*60) -> 0.15625 | O101: =M101+N101 -> 2.2590968 | P101: =A101*O101 -> 56.477419 | X101: ='Timber Order'!$C$17 -> Wall Beam 46 x 71 x 3650 | Y101: 0.7 | Z101: =A101*Y101 -> 17.5 | AA101: {=1-(G101/Y101/index('Timber Order'!G:G,match($X101,'Timber Order'!C:C,0),1))} -> 0.00039138943 | AB101: =A101*G101 -> 0.2085341 | AC101: {=A101*Y101*index('Timber Order'!G:G,match($X101,'Timber Order'!C:C,0),1)} -> 0.20861575 | AD101: {=Y101*index('Timber Order'!G:G,match($X101,'Timber Order'!C:C,0),1)} -> 0.00834463 | AE101: =AC101-AB101 -> 8.165e-05
A102: =sumif('Structures Database'!B:B,C102,'Structures Database'!W:W) -> 45 | B102: pcs | C102: =K102&" "&L102&" "&D102&" x "&E102&" x "&F102 -> Wall Stud 46 x 71 x 2899 | D102: 46 | E102: 71 | F102: 2899 | G102: =D102*E102*F102/1000000000 -> 0.009468134 | H102: =G102*$D$16 -> 5.3116232 | I102: =G102*$D$18*$D$20 -> 8.5560592 | J102: 5 | K102: Wall | L102: Stud | M102: =AD102*if(D102>45,$D$14,$D$15) -> 2.5534568 | N102: =J102*$D$19/(8*60) -> 0.15625 | O102: =M102+N102 -> 2.7097068 | P102: =A102*O102 -> 121.93681 | X102: ='Timber Order'!$C$17 -> Wall Beam 46 x 71 x 3650 | Y102: 0.85 | Z102: =A102*Y102 -> 38.25 | AA102: {=1-(G102/Y102/index('Timber Order'!G:G,match($X102,'Timber Order'!C:C,0),1))} -> 0.065592264 | AB102: =A102*G102 -> 0.42606603 | AC102: {=A102*Y102*index('Timber Order'!G:G,match($X102,'Timber Order'!C:C,0),1)} -> 0.45597443 | AD102: {=Y102*index('Timber Order'!G:G,match($X102,'Timber Order'!C:C,0),1)} -> 0.010132765 | AE102: =AC102-AB102 -> 0.029908395
A103: =sumif('Structures Database'!B:B,C103,'Structures Database'!W:W) -> 55.282555 | B103: pcs | C103: =K103&" "&L103&" "&D103&" x "&E103&" x "&F103 -> Wall Stud 46 x 71 x 2960 | D103: 46 | E103: 71 | F103: 2960 | G103: =D103*E103*F103/1000000000 -> 0.00966736 | H103: =G103*$D$16 -> 5.423389 | I103: =G103*$D$18*$D$20 -> 8.7360935 | J103: 5 | K103: Wall | L103: Stud | M103: =AD103*if(D103>45,$D$14,$D$15) -> 2.5534568 | N103: =J103*$D$19/(8*60) -> 0.15625 | O103: =M103+N103 -> 2.7097068 | P103: =A103*O103 -> 149.79951 | X103: ='Timber Order'!$C$17 -> Wall Beam 46 x 71 x 3650 | Y103: 0.85 | Z103: =A103*Y103 -> 46.990172 | AA103: {=1-(G103/Y103/index('Timber Order'!G:G,match($X103,'Timber Order'!C:C,0),1))} -> 0.045930701 | AB103: =A103*G103 -> 0.53443636 | AC103: {=A103*Y103*index('Timber Order'!G:G,match($X103,'Timber Order'!C:C,0),1)} -> 0.56016514 | AD103: {=Y103*index('Timber Order'!G:G,match($X103,'Timber Order'!C:C,0),1)} -> 0.010132765 | AE103: =AC103-AB103 -> 0.025728778
M104: =AD104*if(D104>45,$D$14,$D$15) -> 0 | P104: =A104*O104 -> 0
A105: =sumif('Structures Database'!B:B,C105,'Structures Database'!W:W) -> 14 | B105: pcs | C105: =K105&" "&L105&" "&D105&" x "&E105&" x "&F105 -> Wall Bracing 46 x 71 x 2416 | D105: 46 | E105: 71 | F105: 2416 | G105: =D105*E105*F105/1000000000 -> 0.007890656 | H105: =G105*$D$16 -> 4.426658 | I105: =G105*$D$18*$D$20 -> 7.1305412 | J105: 5 | K105: Wall | L105: Bracing | M105: =AD105*if(D105>45,$D$14,$D$15) -> 2.0164284 | N105: =J105*$D$19/(8*60) -> 0.15625 | O105: =M105+N105 -> 2.1726784 | P105: =A105*O105 -> 30.417498 | X105: ='Timber Order'!$C$16 -> Wall Beam 46 x 71 x 2450 | Y105: 1 | Z105: =A105*Y105 -> 14 | AA105: {=1-(G105/Y105/index('Timber Order'!G:G,match($X105,'Timber Order'!C:C,0),1))} -> 0.013877551 | AB105: =A105*G105 -> 0.11046918 | AC105: {=A105*Y105*index('Timber Order'!G:G,match($X105,'Timber Order'!C:C,0),1)} -> 0.1120238 | AD105: {=Y105*index('Timber Order'!G:G,match($X105,'Timber Order'!C:C,0),1)} -> 0.0080017 | AE105: =AC105-AB105 -> 0.001554616
A106: =sumif('Structures Database'!B:B,C106,'Structures Database'!W:W) -> 100.22604 | B106: pcs | C106: =K106&" "&L106&" "&D106&" x "&E106&" x "&F106 -> Wall Support Block 46 x 71 x 548 | D106: 46 | E106: 71 | F106: 548 | G106: =D106*E106*F106/1000000000 -> 0.001789768 | H106: =G106*$D$16 -> 1.0040598 | I106: =G106*$D$18*$D$20 -> 1.6173579 | J106: 5 | K106: Wall | L106: Support Block | M106: =AD106*if(D106>45,$D$14,$D$15) -> 0.5041071 | N106: =J106*$D$19/(8*60) -> 0.15625 | O106: =M106+N106 -> 0.6603571 | P106: =A106*O106 -> 66.18498 | X106: ='Timber Order'!$C$16 -> Wall Beam 46 x 71 x 2450 | Y106: 0.25 | Z106: =A106*Y106 -> 25.056511 | AA106: {=1-(G106/Y106/index('Timber Order'!G:G,match($X106,'Timber Order'!C:C,0),1))} -> 0.10530612 | AB106: =A106*G106 -> 0.17938137 | AC106: {=A106*Y106*index('Timber Order'!G:G,match($X106,'Timber Order'!C:C,0),1)} -> 0.20049468 | AD106: {=Y106*index('Timber Order'!G:G,match($X106,'Timber Order'!C:C,0),1)} -> 0.002000425 | AE106: =AC106-AB106 -> 0.021113318
M107: =AD107*if(D107>45,$D$14,$D$15) -> 0 | P107: =A107*O107 -> 0
A108: =sumif('Structures Database'!B:B,C108,'Structures Database'!W:W) -> 104 | B108: pcs | C108: =K108&" "&L108&" "&D108&" x "&E108&" x "&F108 -> Back Batten 22 x 46 x 1220 | D108: 22 | E108: 46 | F108: 1220 | G108: =D108*E108*F108/1000000000 -> 0.00123464 | H108: =G108*$D$16 -> 0.69263304 | I108: =G108*$D$18*$D$20 -> 1.1157059 | J108: 5 | K108: Back | L108: Batten | M108: =AD108*if(D108>45,$D$14,$D$15) -> 0.322322 | N108: =J108*$D$19/(8*60) -> 0.15625 | O108: =M108+N108 -> 0.478572 | P108: =A108*O108 -> 49.771488 | X108: ='Timber Order'!$C$25 -> Timber Back Batten 22 x 46 x 2450 | Y108: 0.5 | Z108: =A108*Y108 -> 52 | AA108: {=1-(G108/Y108/index('Timber Order'!G:G,match($X108,'Timber Order'!C:C,0),1))} -> 0.0040816327 | AB108: =A108*G108 -> 0.12840256 | AC108: {=A108*Y108*index('Timber Order'!G:G,match($X108,'Timber Order'!C:C,0),1)} -> 0.1289288 | AD108: {=Y108*index('Timber Order'!G:G,match($X108,'Timber Order'!C:C,0),1)} -> 0.0012397 | AE108: =AC108-AB108 -> 0.00052624
A109: =sumif('Structures Database'!B:B,C109,'Structures Database'!W:W) -> 26 | B109: pcs | C109: =K109&" "&L109&" "&D109&" x "&E109&" x "&F109 -> Back Batten 22 x 46 x 1598 | D109: 22 | E109: 46 | F109: 1598 | G109: =D109*E109*F109/1000000000 -> 0.001617176 | H109: =G109*$D$16 -> 0.90723574 | I109: =G109*$D$18*$D$20 -> 1.4613918 | J109: 5 | K109: Back | L109: Batten | M109: =AD109*if(D109>45,$D$14,$D$15) -> 0.42546504 | N109: =J109*$D$19/(8*60) -> 0.15625 | O109: =M109+N109 -> 0.58171504 | P109: =A109*O109 -> 15.124591 | X109: ='Timber Order'!$C$25 -> Timber Back Batten 22 x 46 x 2450 | Y109: 0.66 | Z109: =A109*Y109 -> 17.16 | AA109: {=1-(G109/Y109/index('Timber Order'!G:G,match($X109,'Timber Order'!C:C,0),1))} -> 0.011750155 | AB109: =A109*G109 -> 0.042046576 | AC109: {=A109*Y109*index('Timber Order'!G:G,match($X109,'Timber Order'!C:C,0),1)} -> 0.042546504 | AD109: {=Y109*index('Timber Order'!G:G,match($X109,'Timber Order'!C:C,0),1)} -> 0.001636404 | AE109: =AC109-AB109 -> 0.000499928
A110: =sumif('Structures Database'!B:B,C110,'Structures Database'!W:W) -> 0 | B110: pcs | C110: =K110&" "&L110&" "&D110&" x "&E110&" x "&F110 -> Back Batten 22 x 46 x 1689 | D110: 22 | E110: 46 | F110: 1689 | G110: =D110*E110*F110/1000000000 -> 0.001709268 | H110: =G110*$D$16 -> 0.95889935 | I110: =G110*$D$18*$D$20 -> 1.5446125 | J110: 5 | K110: Back | L110: Batten | M110: =AD110*if(D110>45,$D$14,$D$15) -> 0.42546504 | N110: =J110*$D$19/(8*60) -> 0.15625 | O110: =M110+N110 -> 0.58171504 | P110: =A110*O110 -> 0 | X110: ='Timber Order'!$C$25 -> Timber Back Batten 22 x 46 x 2450 | Y110: 0.66 | Z110: =A110*Y110 -> 0 | AA110: {=1-(G110/Y110/index('Timber Order'!G:G,match($X110,'Timber Order'!C:C,0),1))} -> -0.044526902 | AB110: =A110*G110 -> 0 | AC110: {=A110*Y110*index('Timber Order'!G:G,match($X110,'Timber Order'!C:C,0),1)} -> 0 | AD110: {=Y110*index('Timber Order'!G:G,match($X110,'Timber Order'!C:C,0),1)} -> 0.001636404 | AE110: =AC110-AB110 -> 0
A111: =sumif('Structures Database'!B:B,C111,'Structures Database'!W:W) -> 0 | B111: pcs | C111: =K111&" "&L111&" "&D111&" x "&E111&" x "&F111 -> Back Batten 22 x 46 x 1880 | D111: 22 | E111: 46 | F111: 1880 | G111: =D111*E111*F111/1000000000 -> 0.00190256 | H111: =G111*$D$16 -> 1.0673362 | I111: =G111*$D$18*$D$20 -> 1.7192845 | J111: 5 | K111: Back | L111: Batten | M111: =AD111*if(D111>45,$D$14,$D$15) -> 0.644644 | N111: =J111*$D$19/(8*60) -> 0.15625 | O111: =M111+N111 -> 0.800894 | P111: =A111*O111 -> 0 | X111: ='Timber Order'!$C$25 -> Timber Back Batten 22 x 46 x 2450 | Y111: 1 | Z111: =A111*Y111 -> 0 | AA111: {=1-(G111/Y111/index('Timber Order'!G:G,match($X111,'Timber Order'!C:C,0),1))} -> 0.23265306 | AB111: =A111*G111 -> 0 | AC111: {=A111*Y111*index('Timber Order'!G:G,match($X111,'Timber Order'!C:C,0),1)} -> 0 | AD111: {=Y111*index('Timber Order'!G:G,match($X111,'Timber Order'!C:C,0),1)} -> 0.0024794 | AE111: =AC111-AB111 -> 0
A112: =sumif('Structures Database'!B:B,C112,'Structures Database'!W:W) -> 179.31299 | B112: pcs | C112: =K112&" "&L112&" "&D112&" x "&E112&" x "&F112 -> Back Batten 22 x 46 x 2440 | D112: 22 | E112: 46 | F112: 2440 | G112: =D112*E112*F112/1000000000 -> 0.00246928 | H112: =G112*$D$16 -> 1.3852661 | I112: =G112*$D$18*$D$20 -> 2.2314118 | J112: 5 | K112: Back | L112: Batten | M112: =AD112*if(D112>45,$D$14,$D$15) -> 0.644644 | N112: =J112*$D$19/(8*60) -> 0.15625 | O112: =M112+N112 -> 0.800894 | P112: =A112*O112 -> 143.6107 | X112: ='Timber Order'!$C$25 -> Timber Back Batten 22 x 46 x 2450 | Y112: 1 | Z112: =A112*Y112 -> 179.31299 | AA112: {=1-(G112/Y112/index('Timber Order'!G:G,match($X112,'Timber Order'!C:C,0),1))} -> 0.0040816327 | AB112: =A112*G112 -> 0.44277398 | AC112: {=A112*Y112*index('Timber Order'!G:G,match($X112,'Timber Order'!C:C,0),1)} -> 0.44458863 | AD112: {=Y112*index('Timber Order'!G:G,match($X112,'Timber Order'!C:C,0),1)} -> 0.0024794 | AE112: =AC112-AB112 -> 0.0018146475
A113: =sumif('Structures Database'!B:B,C113,'Structures Database'!W:W) -> 0 | B113: pcs | C113: =K113&" "&L113&" "&D113&" x "&E113&" x "&F113 -> Back Batten 22 x 46 x 3053 | D113: 22 | E113: 46 | F113: 3053 | G113: =D113*E113*F113/1000000000 -> 0.003089636 | H113: =G113*$D$16 -> 1.7332858 | I113: =G113*$D$18*$D$20 -> 2.7920083 | J113: 5 | K113: Back | L113: Batten | M113: =AD113*if(D113>45,$D$14,$D$15) -> 0.802516 | N113: =J113*$D$19/(8*60) -> 0.15625 | O113: =M113+N113 -> 0.958766 | P113: =A113*O113 -> 0 | X113: ='Timber Order'!$C$26 -> Timber Back Batten 22 x 46 x 3050 | Y113: 1 | Z113: =A113*Y113 -> 0 | AA113: {=1-(G113/Y113/index('Timber Order'!G:G,match($X113,'Timber Order'!C:C,0),1))} -> -0.00098360656 | AB113: =A113*G113 -> 0 | AC113: {=A113*Y113*index('Timber Order'!G:G,match($X113,'Timber Order'!C:C,0),1)} -> 0 | AD113: {=Y113*index('Timber Order'!G:G,match($X113,'Timber Order'!C:C,0),1)} -> 0.0030866 | AE113: =AC113-AB113 -> 0
A114: =sumif('Structures Database'!B:B,C114,'Structures Database'!W:W) -> 92 | B114: pcs | C114: =K114&" "&L114&" "&D114&" x "&E114&" x "&F114 -> Facade Vertical Shiplap 22 x 96 x 1221 | D114: 22 | E114: 96 | F114: 1221 | G114: =D114*E114*F114/1000000000 -> 0.002578752 | H114: =G114*$D$16 -> 1.4466799 | I114: =G114*$D$18*$D$20 -> 2.3303382 | J114: 10 | K114: Facade | L114: Vertical Shiplap | M114: =AD114*if(D114>45,$D$14,$D$15) -> 0.837408 | N114: =J114*$D$19/(8*60) -> 0.3125 | O114: =M114+N114 -> 1.149908 | P114: =A114*O114 -> 105.79154 | X114: =X115 -> Timber Facade Plank 22 x 96 x 3050 | Y114: 0.5 | Z114: =A114*Y114 -> 46 | AA114: {=1-(G114/Y114/index('Timber Order'!G:G,match($X114,'Timber Order'!C:C,0),1))} -> 0.19934426 | AB114: =A114*G114 -> 0.23724518 | AC114: {=A114*Y114*index('Timber Order'!G:G,match($X114,'Timber Order'!C:C,0),1)} -> 0.2963136 | AD114: {=Y114*index('Timber Order'!G:G,match($X114,'Timber Order'!C:C,0),1)} -> 0.0032208 | AE114: =AC114-AB114 -> 0.059068416
A115: =sumif('Structures Database'!B:B,C115,'Structures Database'!W:W) -> 390.34274 | B115: pcs | C115: =K115&" "&L115&" "&D115&" x "&E115&" x "&F115 -> Facade Vertical Shiplap 22 x 96 x 2826 | D115: 22 | E115: 96 | F115: 2826 | G115: =D115*E115*F115/1000000000 -> 0.005968512 | H115: =G115*$D$16 -> 3.3483352 | I115: =G115*$D$18*$D$20 -> 5.3935593 | J115: 10 | K115: Facade | L115: Vertical Shiplap | M115: =AD115*if(D115>45,$D$14,$D$15) -> 1.674816 | N115: =J115*$D$19/(8*60) -> 0.3125 | O115: =M115+N115 -> 1.987316 | P115: =A115*O115 -> 775.73437 | X115: ='Timber Order'!$C$29 -> Timber Facade Plank 22 x 96 x 3050 | Y115: 1 | Z115: =A115*Y115 -> 390.34274 | AA115: {=1-(G115/Y115/index('Timber Order'!G:G,match($X115,'Timber Order'!C:C,0),1))} -> 0.073442623 | AB115: =A115*G115 -> 2.3297653 | AC115: {=A115*Y115*index('Timber Order'!G:G,match($X115,'Timber Order'!C:C,0),1)} -> 2.5144318 | AD115: {=Y115*index('Timber Order'!G:G,match($X115,'Timber Order'!C:C,0),1)} -> 0.0064416 | AE115: =AC115-AB115 -> 0.18466647
...

Sheet Timber Order
A3: Timber Procurement Order List
A4: Order date: | B4: Date
A5: By: | B5: Wolf Bierens - Easy Housing
A6: For: | B6: Contact Name - Company
A9: Timber quality and sustainability criteria
A10: Timber must be well seasoned, kiln dried, at specified dimensions within 2-3 mm tolerance and CCA treated. T&G, decking and shiplap planks must be planed and profiled properly.
A11: Timber must be sustainably sourced. This means with FSC (controlled) certification or under EUTR regulation.
A12: Easy Housing holds the legal claim to the construction stored carbon credits realised through its buildings. These credits do not conflict with any REDD+ or comparable forest conservation credits.
A14: Timber orderlist | D14: Specifications
A15: # | B15: Unit | C15: Item | D15: Width (mm) | E15: Height (mm) | F15: Length (mm) | G15: Volume (m3) | H15: Volume total | J15: Weight (kg) | K15: Carbon storage (kg CO2) | L15: Structure | M15: Type
A16: =roundup(sumif('Bill of Quantities'!X:X,C16,'Bill of Quantities'!Z:Z),0) -> 90 | B16: pcs | C16: =L16&" "&M16&" "&D16&" x "&E16&" x "&F16 -> Wall Beam 46 x 71 x 2450 | D16: 46 | E16: 71 | F16: 2450 | G16: =D16*E16*F16*0.000000001 -> 0.0080017 | H16: =A16*G16 -> 0.720153 | J16: =G16*'Bill of Quantities'!$D$16 -> 4.4889537 | K16: =G16*'Bill of Quantities'!$D$18*'Bill of Quantities'!$D$20 -> 7.2308882 | L16: Wall | M16: Beam
A17: =roundup(sumif('Bill of Quantities'!X:X,C17,'Bill of Quantities'!Z:Z),0) -> 103 | B17: pcs | C17: =L17&" "&M17&" "&D17&" x "&E17&" x "&F17 -> Wall Beam 46 x 71 x 3650 | D17: 46 | E17: 71 | F17: 3650 | G17: =D17*E17*F17*0.000000001 -> 0.0119209 | H17: =A17*G17 -> 1.2278527 | J17: =G17*'Bill of Quantities'!$D$16 -> 6.6876249 | K17: =G17*'Bill of Quantities'!$D$18*'Bill of Quantities'!$D$20 -> 10.772548 | L17: Wall | M17: Beam
A18: =roundup(sumif('Bill of Quantities'!X:X,C18,'Bill of Quantities'!Z:Z),0) -> 38 | B18: pcs | C18: =L18&" "&M18&" "&D18&" x "&E18&" x "&F18 -> Roof Beam 46 x 96 x 2450 | D18: 46 | E18: 96 | F18: 2450 | G18: =D18*E18*F18*0.000000001 -> 0.0108192 | H18: =A18*G18 -> 0.4111296 | J18: =G18*'Bill of Quantities'!$D$16 -> 6.0695712 | K18: =G18*'Bill of Quantities'!$D$18*'Bill of Quantities'!$D$20 -> 9.7769756 | L18: Roof | M18: Beam
A19: =roundup(sumif('Bill of Quantities'!X:X,C19,'Bill of Quantities'!Z:Z),0) -> 0 | B19: pcs | C19: =L19&" "&M19&" "&D19&" x "&E19&" x "&F19 -> Roof Beam 46 x 96 x 4250 | D19: 46 | E19: 96 | F19: 4250 | G19: =D19*E19*F19*0.000000001 -> 0.018768 | H19: =A19*G19 -> 0 | J19: =G19*'Bill of Quantities'!$D$16 -> 10.528848 | K19: =G19*'Bill of Quantities'!$D$18*'Bill of Quantities'!$D$20 -> 16.96006 | L19: Roof | M19: Beam
A20: =roundup(sumif('Bill of Quantities'!X:X,C20,'Bill of Quantities'!Z:Z),0) -> 34 | B20: pcs | C20: =L20&" "&M20&" "&D20&" x "&E20&" x "&F20 -> Roof Beam 46 x 96 x 5750 | D20: 46 | E20: 96 | F20: 5750 | G20: =D20*E20*F20*0.000000001 -> 0.025392 | H20: =A20*G20 -> 0.863328 | J20: =G20*'Bill of Quantities'!$D$16 -> 14.244912 | K20: =G20*'Bill of Quantities'!$D$18*'Bill of Quantities'!$D$20 -> 22.945963 | L20: Roof | M20: Beam
A21: =roundup(sumif('Bill of Quantities'!X:X,C21,'Bill of Quantities'!Z:Z),0) -> 86 | B21: pcs | C21: =L21&" "&M21&" "&D21&" x "&E21&" x "&F21 -> Floor Beam 46 x 146 x 2450 | D21: 46 | E21: 146 | F21: 2450 | G21: =D21*E21*F21*0.000000001 -> 0.0164542 | H21: =A21*G21 -> 1.4150612 | J21: =G21*'Bill of Quantities'!$D$16 -> 9.2308062 | K21: =G21*'Bill of Quantities'!$D$18*'Bill of Quantities'!$D$20 -> 14.86915 | L21: Floor | M21: Beam
A22: =roundup(sumif('Bill of Quantities'!X:X,C22,'Bill of Quantities'!Z:Z),0) -> 0 | B22: pcs | C22: =L22&" "&M22&" "&D22&" x "&E22&" x "&F22 -> Floor Beam 46 x 146 x 3050 | D22: 46 | E22: 146 | F22: 3050 | G22: =D22*E22*F22*0.000000001 -> 0.0204838 | H22: =A22*G22 -> 0 | J22: =G22*'Bill of Quantities'!$D$16 -> 11.491412 | K22: =G22*'Bill of Quantities'!$D$18*'Bill of Quantities'!$D$20 -> 18.510575 | L22: Floor | M22: Beam
A23: =roundup(sumif('Bill of Quantities'!X:X,C23,'Bill of Quantities'!Z:Z),0) -> 0 | B23: pcs | C23: =L23&" "&M23&" "&D23&" x "&E23&" x "&F23 -> Floor Beam 46 x 146 x 5450 | D23: 46 | E23: 146 | F23: 5450 | G23: =D23*E23*F23*0.000000001 -> 0.0366022 | H23: =A23*G23 -> 0 | J23: =G23*'Bill of Quantities'!$D$16 -> 20.533834 | K23: =G23*'Bill of Quantities'!$D$18*'Bill of Quantities'!$D$20 -> 33.076273 | L23: Floor | M23: Beam
A24: =roundup(sumif('Bill of Quantities'!X:X,C24,'Bill of Quantities'!Z:Z),0) -> 0 | B24: pcs | C24: =L24&" "&M24&" "&D24&" x "&E24&" x "&F24 -> Timber Column 100 x 100 x 3050 | D24: 100 | E24: 100 | F24: 3050 | G24: =D24*E24*F24*0.000000001 -> 0.0305 | H24: =A24*G24 -> 0 | J24: =G24*'Bill of Quantities'!$D$16 -> 17.1105 | K24: =G24*'Bill of Quantities'!$D$18*'Bill of Quantities'!$D$20 -> 27.561905 | L24: Timber | M24: Column
A25: =roundup(sumif('Bill of Quantities'!X:X,C25,'Bill of Quantities'!Z:Z),0) -> 249 | B25: pcs | C25: =L25&" "&M25&" "&D25&" x "&E25&" x "&F25 -> Timber Back Batten 22 x 46 x 2450 | D25: 22 | E25: 46 | F25: 2450 | G25: =D25*E25*F25*0.000000001 -> 0.0024794 | H25: =A25*G25 -> 0.6173706 | J25: =G25*'Bill of Quantities'!$D$16 -> 1.3909434 | K25: =G25*'Bill of Quantities'!$D$18*'Bill of Quantities'!$D$20 -> 2.2405569 | L25: Timber | M25: Back Batten
A26: =roundup(sumif('Bill of Quantities'!X:X,C26,'Bill of Quantities'!Z:Z),0) -> 0 | B26: pcs | C26: =L26&" "&M26&" "&D26&" x "&E26&" x "&F26 -> Timber Back Batten 22 x 46 x 3050 | D26: 22 | E26: 46 | F26: 3050 | G26: =D26*E26*F26*0.000000001 -> 0.0030866 | H26: =A26*G26 -> 0 | J26: =G26*'Bill of Quantities'!$D$16 -> 1.7315826 | K26: =G26*'Bill of Quantities'!$D$18*'Bill of Quantities'!$D$20 -> 2.7892647 | L26: Timber | M26: Back Batten
A27: =roundup(sumif('Bill of Quantities'!X:X,C27,'Bill of Quantities'!Z:Z),0) -> 328 | B27: pcs | C27: =L27&" "&M27&" "&D27&" x "&E27&" x "&F27 -> Timber Floor Plank 22 x 96 x 2450 | D27: 22 | E27: 96 | F27: 2450 | G27: =D27*E27*F27*0.000000001 -> 0.0051744 | H27: =A27*G27 -> 1.6972032 | J27: =G27*'Bill of Quantities'!$D$16 -> 2.9028384 | K27: =G27*'Bill of Quantities'!$D$18*'Bill of Quantities'!$D$20 -> 4.6759449 | L27: Timber | M27: Floor Plank
... A33: =roundup(sumif('Bill of Quantities'!X:X,C33,'Bill of Quantities'!Z:Z),0) -> 36 | B33: pcs | C33: =L33&" "&M33&" "&D33&" x "&E33&" x "&F33 -> Interior Door Beams 50 x 150 x 2450 | D33: 50 | E33: 150 | F33: 2450 | G33: =D33*E33*F33*0.000000001 -> 0.018375 | H33: =A33*G33 -> 0.6615 | J33: =G33*'Bill of Quantities'!$D$16 -> 10.308375 | K33: =G33*'Bill of Quantities'!$D$18*'Bill of Quantities'!$D$20 -> 16.604918 | L33: Interior Door | M33: Beams
A35: Total amounts | H35: =SUM(H16:H34) -> 10.780124 | I35: cbm
D44: Timber Standard Lengths
D45: Millimetre * | E45: Feet
D46: 2450 | E46: =round(D46/300,0) -> 8
D47: 2750 | E47: =round(D47/300,0) -> 9
D48: 3050 | E48: =round(D48/300,0) -> 10
D49: 3650 | E49: =round(D49/300,0) -> 12
D50: 3950 | E50: =round(D50/300,0) -> 13
D51: 4250 | E51: =round(D51/300,0) -> 14
D52: 5450 | E52: =round(D52/300,0) -> 18
D53: 5750 | E53: =round(D53/300,0) -> 19
D54: 6050 | E54: =round(D54/300,0) -> 20
D56: * default lengths at Busoga, but 6m not always available

Sheet Input Database
A1: Hier komt een database van inputs met behulp van een macro
A2: Macro knop die automatisch een PDF genereert van de project outputs en dan ook hier de inputs in opslaat
B4: Instructions: Copy Cells B20:B46 and paste special here as values only!
B5: Database
B6: Date
A8: Project input | B8: Project Input Database
A9: Client input
A10: ='Price Calc'!A13 -> Client Name | B10: One Bed Mono | C10: John's | D10: Alex Michael Thiaka | E10: Ziwa Rhino Sanctuary | F10: Tamsin Scurfield | G10: Jesse & Naomi | H10: Maureen | I10: Tamsin test | J10: Soul Agri Business Company Ltd | K10: Anwar
A11: ='Price Calc'!A14 -> Contact Details | B11: Example | C11: Test | D11: bolossatestates@gmail.com | E11: Captain Joe Roy | F11: tamsaway@gmail.com | G11: nduksk@gmail.com | H11: 254 722 808352 | I11: 0 | J11: +256 759 740888 | K11: +256 759 740888
A12: ='Price Calc'!A23 -> Project Location | B12: Greater Kampala | C12: Greater Kampala | D12: Olkalau | E12: Ziwa | F12: Jinja | G12: Nairobi | H12: Nairobi | I12: Kampala | J12: Kiryandongo | K12: Kiryandongo
A13: ='Price Calc'!A24 -> Distance from factory | B13: 50 | C13: 50 | D13: 150 | E13: 177 | F13: 89 | G13: 50 | H13: 180 | I13: 150 | J13: 213 | K13: 213
A14: Date of input
A15: ='Price Calc'!A15 -> Created by | B15: Wolf Bierens | C15: Wolf Bierens | D15: Monicah Migwi | E15: Wolf Bierens | F15: Brian Kulubya | G15: Wolf Bierens | H15: Branton | I15: Wolf | J15: Aaron | K15: Aaron
A17: Building input (structure parameters)
A18: ='Price Calc'!A18 -> Easy Housing Typology | B18: Mono Pitch | C18: Compact Gable | D18: Large Clerestory | E18: Compact Gable | F18: Large Clerestory | G18: Large Clerestory | H18: Mono Pitch | I18: Large Clerestory | J18: Large Clerestory | K18: Compact Gable
A19: Number of units (of exactly this type) | B19: 1 | C19: 1 | D19: 1 | E19: 4 | F19: 1 | G19: 1 | H19: 1 | I19: 1 | J19: 1 | K19: 1
A20: ='Price Calc'!A59 -> Columns A (1221) | B20: 0 | C20: 0 | D20: 2 | E20: 0 | F20: 2 | G20: 2 | H20: 0 | I20: 2 | J20: 3 | K20: 0
A21: ='Price Calc'!A60 -> Columns B (2442) | B21: 3 | C21: 4 | D21: 4 | E21: 4 | F21: 0 | G21: 2 | H21: 2 | I21: 2 | J21: 0 | K21: 4
A22: ='Price Calc'!A61 -> Columns C (3053) | B22: 0 | C22: 0 | D22: 0 | E22: 0 | F22: 2 | G22: 1 | H22: 3 | I22: 0 | J22: 3 | K22: 0
A23: ='Price Calc'!A64 -> Interior doors | B23: 2 | C23: 4 | D23: 6 | E23: 2 | F23: 3 | G23: 5 | H23: 4 | I23: 3 | J23: 1 | K23: 4
A24: ='Price Calc'!A65 -> Partitions (length) | B24: 6 | C24: 19.5 | D24: 37.7 | E24: 9 | F24: 15 | G24: 32 | H24: 6 | I24: 16 | J24: 39 | K24: 18.2
A25: ='Price Calc'!A66 -> Exterior doors & windows (area) | B25: 7.9 | C25: 15 | D25: 28.8 | E25: 22 | F25: 30.3 | G25: 27.2 | H25: 9.4 | I25: 23.3 | J25: 27 | K25: 14.7
A26: Bedrooms | B26: 1 | C26: 2 | D26: 3 | E26: 2 | F26: 2 | G26: 3 | H26: 3 | I26: 2 | J26: 4 | K26: 2
A27: Bathrooms | B27: 1 | C27: 2 | D27: 4 | E27: 1 | F27: 1 | G27: 2 | H27: 2 | I27: 1 | J27: 4 | K27: 2
A28: Kitchen areas | B28: 1 | C28: 1 | D28: 1 | E28: 0 | F28: 0 | G28: 1 | H28: 1 | I28: 1 | J28: 1 | K28: 1
A30: Additional options
A31: ='Price Calc'!A41 -> Terrace | B31: 0 | C31: 6 | D31: 18.5 | E31: 4 | F31: 27 | G31: 19 | H31: 4 | I31: 25.8 | J31: 11 | K31: 0
A32: ='Price Calc'!A42 -> Pergola | B32: 0 | C32: 6 | D32: 18.5 | E32: 0 | F32: 27 | G32: 17 | H32: 4 | I32: 25.8 | J32: 11 | K32: 0
A33: ='Price Calc'!A43 -> Railing open | B33: 0 | C33: 0 | D33: 11 | E33: 0 | F33: 14.7 | G33: 17 | H33: 0 | I33: 13 | J33: 0 | K33: 0
A34: ='Price Calc'!A44 -> Railing semi-closed | B34: 0 | C34: 0 | D34: 0 | E34: 10 | F34: 0 | G34: 0 | H34: 0 | I34: 0 | J34: 0 | K34: 0
A35: ='Price Calc'!A67 -> Extra staircase (beyond the first) | B35: 0 | C35: 0 | D35: 1 | E35: 0 | F35: 1 | G35: 1 | H35: 0 | I35: 0 | J35: 0 | K35: 0
A36: ='Price Calc'!A40 -> Burglar bars | B36: 0 | C36: 10 | D36: 0 | E36: 0 | F36: 0 | G36: 0 | H36: 0 | I36: 0 | J36: 0 | K36: 0
A37: ='Price Calc'!A45 -> Wheelchair ramp | B37: 0 | C37: 0 | D37: 0 | E37: 0 | F37: 0 | G37: 0 | H37: 0 | I37: 0 | J37: 0 | K37: 0
A38: ='Price Calc'!A46 -> Tiles | B38: 0 | C38: 0 | D38: 0 | E38: 1350000 | F38: 1500000 | G38: 0 | H38: 0 | I38: 2000000 | J38: 6400000 | K38: 0
A39: ='Price Calc'!A47 -> Sanitary wares | B39: 0 | C39: 0 | D39: 0 | E39: 2800000 | F39: 3500000 | G39: 0 | H39: 0 | I39: 3000000 | J39: 14000000 | K39: 0
A40: ='Price Calc'!A48 -> Biodigester | B40: 0 | C40: 0 | D40: 0 | E40: 0 | F40: 3100000 | G40: 0 | H40: 0 | I40: 3000000 | J40: 3200000 | K40: 0
A41: Other option(s) description | F41: Foundation extra height | G41: Foundation height at 1.2m | J41: Kitchen
A42: Other option(s) price | F42: 2500000 | G42: 150000 | J42: 5000000
K48: Amount
K49: 0
K50: 0
K51: 0
K52: 0
K53: 0
K54: 0
K55: 0
K56: 2
K57: 0
K58: 0
K59: 5
K60: 0
... K68: 0

Sheet Structures Database
A1: Structures database | C1: Per element | L1: Project cost item | O1: Totals per frame | V1: Calculation columns for building input
A2: # | B2: Element name | C2: ='Bill of Quantities'!D2 -> Width (mm) | D2: ='Bill of Quantities'!E2 -> Height (mm) | E2: ='Bill of Quantities'!F2 -> Length (mm) | F2: ='Bill of Quantities'!G2 -> Volume (m3) | G2: ='Bill of Quantities'!H2 -> Weight (kg) | H2: ='Bill of Quantities'!I2 -> Carbon storage (kg CO2) | I2: ='Bill of Quantities'!J2 -> Labour (min) | J2: ='Bill of Quantities'!K2 -> Structure | ... N2: ='Bill of Quantities'!O2 -> Total cost ($) | O2: Volume (m3) | P2: Weight (kg) | Q2: =H2 -> Carbon storage (kg CO2) | R2: =I2 -> Labour (min) | S2: =L2 -> Item cost ($) | T2: =M2 -> Labour cost ($) | U2: =N2 -> Total cost ($) | V2: Frame name | W2: Items in building | X2: Labour hours | Y2: Surface per frame
A4: Floor frames
A6: Foundation point | V6: =V7 -> Foundation point | Y6: =C6*E6*0.000001 -> 0
A7: 1 | B7: ='Bill of Quantities'!C35 -> Foundation block | C7: {=index('Bill of Quantities'!$D:$O,match($B7,'Bill of Quantities'!$C:$C,0),match(C$2,'Bill of Quantities'!$D$2:$O$2,0))} -> 300 | D7: {=index('Bill of Quantities'!$D:$O,match($B7,'Bill of Quantities'!$C:$C,0),match(D$2,'Bill of Quantities'!$D$2:$O$2,0))} -> 400 | E7: {=index('Bill of Quantities'!$D:$O,match($B7,'Bill of Quantities'!$C:$C,0),match(E$2,'Bill of Quantities'!$D$2:$O$2,0))} -> 300 | F7: {=index('Bill of Quantities'!$D:$O,match($B7,'Bill of Quantities'!$C:$C,0),match(F$2,'Bill of Quantities'!$D$2:$O$2,0))} -> 0.036 | G7: {=index('Bill of Quantities'!$D:$O,match($B7,'Bill of Quantities'!$C:$C,0),match(G$2,'Bill of Quantities'!$D$2:$O$2,0))} -> 86.4 | H7: {=index('Bill of Quantities'!$D:$O,match($B7,'Bill of Quantities'!$C:$C,0),match(H$2,'Bill of Quantities'!$D$2:$O$2,0))} -> 0 | I7: {=index('Bill of Quantities'!$D:$O,match($B7,'Bill of Quantities'!$C:$C,0),match(I$2,'Bill of Quantities'!$D$2:$O$2,0))} -> 180 | J7: {=index('Bill of Quantities'!$D:$O,match($B7,'Bill of Quantities'!$C:$C,0),match(J$2,'Bill of Quantities'!$D$2:$O$2,0))} -> Foundation | ... N7: {=index('Bill of Quantities'!$D:$O,match($B7,'Bill of Quantities'!$C:$C,0),match(N$2,'Bill of Quantities'!$D$2:$O$2,0))} -> 5.625 | O7: =$A7*F7 -> 0.036 | P7: =$A7*G7 -> 86.4 | Q7: =$A7*H7 -> 0 | R7: =$A7*I7 -> 180 | S7: =$A7*L7 -> 0 | T7: =$A7*M7 -> 5.625 | U7: =$A7*N7 -> 5.625 | V7: =$A$6 -> Foundation point | W7: {=A7*index('Project Costs'!A:A,match(V7,'Project Costs'!B:B,0),1)} -> 21 | X7: =W7*R7/60 -> 63
A8: 0.3 | B8: ='Bill of Quantities'!C36 -> Cement Bag 50 kg | C8: {=index('Bill of Quantities'!$D:$O,match($B8,'Bill of Quantities'!$C:$C,0),match(C$2,'Bill of Quantities'!$D$2:$O$2,0))} | D8: {=index('Bill of Quantities'!$D:$O,match($B8,'Bill of Quantities'!$C:$C,0),match(D$2,'Bill of Quantities'!$D$2:$O$2,0))} | E8: {=index('Bill of Quantities'!$D:$O,match($B8,'Bill of Quantities'!$C:$C,0),match(E$2,'Bill of Quantities'!$D$2:$O$2,0))} | F8: {=index('Bill of Quantities'!$D:$O,match($B8,'Bill of Quantities'!$C:$C,0),match(F$2,'Bill of Quantities'!$D$2:$O$2,0))} | G8: {=index('Bill of Quantities'!$D:$O,match($B8,'Bill of Quantities'!$C:$C,0),match(G$2,'Bill of Quantities'!$D$2:$O$2,0))} | H8: {=index('Bill of Quantities'!$D:$O,match($B8,'Bill of Quantities'!$C:$C,0),match(H$2,'Bill of Quantities'!$D$2:$O$2,0))} -> -0.6 | I8: {=index('Bill of Quantities'!$D:$O,match($B8,'Bill of Quantities'!$C:$C,0),match(I$2,'Bill of Quantities'!$D$2:$O$2,0))} | J8: {=index('Bill of Quantities'!$D:$O,match($B8,'Bill of Quantities'!$C:$C,0),match(J$2,'Bill of Quantities'!$D$2:$O$2,0))} -> Foundation | ... N8: {=index('Bill of Quantities'!$D:$O,match($B8,'Bill of Quantities'!$C:$C,0),match(N$2,'Bill of Quantities'!$D$2:$O$2,0))} -> 8.5890976 | O8: =$A8*F8 -> 0 | P8: =$A8*G8 -> 0 | Q8: =$A8*H8 -> -0.18 | R8: =$A8*I8 -> 0 | S8: =$A8*L8 -> 2.5767293 | T8: =$A8*M8 -> 0 | U8: =$A8*N8 -> 2.5767293 | V8: =$A$6 -> Foundation point | W8: {=A8*index('Project Costs'!A:A,match(V8,'Project Costs'!B:B,0),1)} -> 6.3 | X8: =W8*R8/60 -> 0
A9: =30/1000 -> 0.03 | B9: ='Bill of Quantities'!C37 -> Sand per tonne | C9: {=index('Bill of Quantities'!$D:$O,match($B9,'Bill of Quantities'!$C:$C,0),match(C$2,'Bill of Quantities'!$D$2:$O$2,0))} | D9: {=index('Bill of Quantities'!$D:$O,match($B9,'Bill of Quantities'!$C:$C,0),match(D$2,'Bill of Quantities'!$D$2:$O$2,0))} | E9: {=index('Bill of Quantities'!$D:$O,match($B9,'Bill of Quantities'!$C:$C,0),match(E$2,'Bill of Quantities'!$D$2:$O$2,0))} | F9: {=index('Bill of Quantities'!$D:$O,match($B9,'Bill of Quantities'!$C:$C,0),match(F$2,'Bill of Quantities'!$D$2:$O$2,0))} | G9: {=index('Bill of Quantities'!$D:$O,match($B9,'Bill of Quantities'!$C:$C,0),match(G$2,'Bill of Quantities'!$D$2:$O$2,0))} | H9: {=index('Bill of Quantities'!$D:$O,match($B9,'Bill of Quantities'!$C:$C,0),match(H$2,'Bill of Quantities'!$D$2:$O$2,0))} | I9: {=index('Bill of Quantities'!$D:$O,match($B9,'Bill of Quantities'!$C:$C,0),match(I$2,'Bill of Quantities'!$D$2:$O$2,0))} | J9: {=index('Bill of Quantities'!$D:$O,match($B9,'Bill of Quantities'!$C:$C,0),match(J$2,'Bill of Quantities'!$D$2:$O$2,0))} -> Foundation | ... N9: {=index('Bill of Quantities'!$D:$O,match($B9,'Bill of Quantities'!$C:$C,0),match(N$2,'Bill of Quantities'!$D$2:$O$2,0))} -> 12.162162 | O9: =$A9*F9 -> 0 | P9: =$A9*G9 -> 0 | Q9: =$A9*H9 -> 0 | R9: =$A9*I9 -> 0 | S9: =$A9*L9 -> 0.36486486 | T9: =$A9*M9 -> 0 | U9: =$A9*N9 -> 0.36486486 | V9: =$A$6 -> Foundation point | W9: {=A9*index('Project Costs'!A:A,match(V9,'Project Costs'!B:B,0),1)} -> 0.63 | X9: =W9*R9/60 -> 0
A10: =40/1000 -> 0.04 | B10: ='Bill of Quantities'!C38 -> Aggregates per tonne | C10: {=index('Bill of Quantities'!$D:$O,match($B10,'Bill of Quantities'!$C:$C,0),match(C$2,'Bill of Quantities'!$D$2:$O$2,0))} | D10: {=index('Bill of Quantities'!$D:$O,match($B10,'Bill of Quantities'!$C:$C,0),match(D$2,'Bill of Quantities'!$D$2:$O$2,0))} | E10: {=index('Bill of Quantities'!$D:$O,match($B10,'Bill of Quantities'!$C:$C,0),match(E$2,'Bill of Quantities'!$D$2:$O$2,0))} | F10: {=index('Bill of Quantities'!$D:$O,match($B10,'Bill of Quantities'!$C:$C,0),match(F$2,'Bill of Quantities'!$D$2:$O$2,0))} | G10: {=index('Bill of Quantities'!$D:$O,match($B10,'Bill of Quantities'!$C:$C,0),match(G$2,'Bill of Quantities'!$D$2:$O$2,0))} | H10: {=index('Bill of Quantities'!$D:$O,match($B10,'Bill of Quantities'!$C:$C,0),match(H$2,'Bill of Quantities'!$D$2:$O$2,0))} | I10: {=index('Bill of Quantities'!$D:$O,match($B10,'Bill of Quantities'!$C:$C,0),match(I$2,'Bill of Quantities'!$D$2:$O$2,0))} | J10: {=index('Bill of Quantities'!$D:$O,match($B10,'Bill of Quantities'!$C:$C,0),match(J$2,'Bill of Quantities'!$D$2:$O$2,0))} -> Foundation | ... N10: {=index('Bill of Quantities'!$D:$O,match($B10,'Bill of Quantities'!$C:$C,0),match(N$2,'Bill of Quantities'!$D$2:$O$2,0))} -> 62.162162 | O10: =$A10*F10 -> 0 | P10: =$A10*G10 -> 0 | Q10: =$A10*H10 -> 0 | R10: =$A10*I10 -> 0 | S10: =$A10*L10 -> 2.4864865 | T10: =$A10*M10 -> 0 | U10: =$A10*N10 -> 2.4864865 | V10: =$A$6 -> Foundation point | W10: {=A10*index('Project Costs'!A:A,match(V10,'Project Costs'!B:B,0),1)} -> 0.84 | X10: =W10*R10/60 -> 0
A11: 4 | B11: ='Bill of Quantities'!C39 -> M12 rod 200 mm (stainless steel) | C11: {=index('Bill of Quantities'!$D:$O,match($B11,'Bill of Quantities'!$C:$C,0),match(C$2,'Bill of Quantities'!$D$2:$O$2,0))} -> 16 | D11: {=index('Bill of Quantities'!$D:$O,match($B11,'Bill of Quantities'!$C:$C,0),match(D$2,'Bill of Quantities'!$D$2:$O$2,0))} | E11: {=index('Bill of Quantities'!$D:$O,match($B11,'Bill of Quantities'!$C:$C,0),match(E$2,'Bill of Quantities'!$D$2:$O$2,0))} -> 250 | F11: {=index('Bill of Quantities'!$D:$O,match($B11,'Bill of Quantities'!$C:$C,0),match(F$2,'Bill of Quantities'!$D$2:$O$2,0))} -> 5.0265482e-05 | G11: {=index('Bill of Quantities'!$D:$O,match($B11,'Bill of Quantities'!$C:$C,0),match(G$2,'Bill of Quantities'!$D$2:$O$2,0))} | H11: {=index('Bill of Quantities'!$D:$O,match($B11,'Bill of Quantities'!$C:$C,0),match(H$2,'Bill of Quantities'!$D$2:$O$2,0))} | I11: {=index('Bill of Quantities'!$D:$O,match($B11,'Bill of Quantities'!$C:$C,0),match(I$2,'Bill of Quantities'!$D$2:$O$2,0))} | J11: {=index('Bill of Quantities'!$D:$O,match($B11,'Bill of Quantities'!$C:$C,0),match(J$2,'Bill of Quantities'!$D$2:$O$2,0))} -> Foundation | ... N11: {=index('Bill of Quantities'!$D:$O,match($B11,'Bill of Quantities'!$C:$C,0),match(N$2,'Bill of Quantities'!$D$2:$O$2,0))} -> 3 | O11: =$A11*F11 -> 0.00020106193 | P11: =$A11*G11 -> 0 | Q11: =$A11*H11 -> 0 | R11: =$A11*I11 -> 0 | S11: =$A11*L11 -> 12 | T11: =$A11*M11 -> 0 | U11: =$A11*N11 -> 12 | V11: =$A$6 -> Foundation point | W11: {=A11*index('Project Costs'!A:A,match(V11,'Project Costs'!B:B,0),1)} -> 84 | X11: =W11*R11/60 -> 0
A12: 8 | B12: ='Bill of Quantities'!C40 -> M12 nut (stainless steel) | C12: {=index('Bill of Quantities'!$D:$O,match($B12,'Bill of Quantities'!$C:$C,0),match(C$2,'Bill of Quantities'!$D$2:$O$2,0))} -> 24 | D12: {=index('Bill of Quantities'!$D:$O,match($B12,'Bill of Quantities'!$C:$C,0),match(D$2,'Bill of Quantities'!$D$2:$O$2,0))} -> 24 | E12: {=index('Bill of Quantities'!$D:$O,match($B12,'Bill of Quantities'!$C:$C,0),match(E$2,'Bill of Quantities'!$D$2:$O$2,0))} -> 13 | F12: {=index('Bill of Quantities'!$D:$O,match($B12,'Bill of Quantities'!$C:$C,0),match(F$2,'Bill of Quantities'!$D$2:$O$2,0))} | G12: {=index('Bill of Quantities'!$D:$O,match($B12,'Bill of Quantities'!$C:$C,0),match(G$2,'Bill of Quantities'!$D$2:$O$2,0))} | H12: {=index('Bill of Quantities'!$D:$O,match($B12,'Bill of Quantities'!$C:$C,0),match(H$2,'Bill of Quantities'!$D$2:$O$2,0))} | I12: {=index('Bill of Quantities'!$D:$O,match($B12,'Bill of Quantities'!$C:$C,0),match(I$2,'Bill of Quantities'!$D$2:$O$2,0))} | J12: {=index('Bill of Quantities'!$D:$O,match($B12,'Bill of Quantities'!$C:$C,0),match(J$2,'Bill of Quantities'!$D$2:$O$2,0))} -> Foundation | ... N12: {=index('Bill of Quantities'!$D:$O,match($B12,'Bill of Quantities'!$C:$C,0),match(N$2,'Bill of Quantities'!$D$2:$O$2,0))} -> 0.4 | O12: =$A12*F12 -> 0 | P12: =$A12*G12 -> 0 | Q12: =$A12*H12 -> 0 | R12: =$A12*I12 -> 0 | S12: =$A12*L12 -> 3.2 | T12: =$A12*M12 -> 0 | U12: =$A12*N12 -> 3.2 | V12: =$A$6 -> Foundation point | W12: {=A12*index('Project Costs'!A:A,match(V12,'Project Costs'!B:B,0),1)} -> 168 | X12: =W12*R12/60 -> 0
A13: 8 | B13: ='Bill of Quantities'!C41 -> M12 washer (stainless steel) | C13: {=index('Bill of Quantities'!$D:$O,match($B13,'Bill of Quantities'!$C:$C,0),match(C$2,'Bill of Quantities'!$D$2:$O$2,0))} -> 30 | D13: {=index('Bill of Quantities'!$D:$O,match($B13,'Bill of Quantities'!$C:$C,0),match(D$2,'Bill of Quantities'!$D$2:$O$2,0))} | E13: {=index('Bill of Quantities'!$D:$O,match($B13,'Bill of Quantities'!$C:$C,0),match(E$2,'Bill of Quantities'!$D$2:$O$2,0))} -> 3 | F13: {=index('Bill of Quantities'!$D:$O,match($B13,'Bill of Quantities'!$C:$C,0),match(F$2,'Bill of Quantities'!$D$2:$O$2,0))} | G13: {=index('Bill of Quantities'!$D:$O,match($B13,'Bill of Quantities'!$C:$C,0),match(G$2,'Bill of Quantities'!$D$2:$O$2,0))} | H13: {=index('Bill of Quantities'!$D:$O,match($B13,'Bill of Quantities'!$C:$C,0),match(H$2,'Bill of Quantities'!$D$2:$O$2,0))} | I13: {=index('Bill of Quantities'!$D:$O,match($B13,'Bill of Quantities'!$C:$C,0),match(I$2,'Bill of Quantities'!$D$2:$O$2,0))} | J13: {=index('Bill of Quantities'!$D:$O,match($B13,'Bill of Quantities'!$C:$C,0),match(J$2,'Bill of Quantities'!$D$2:$O$2,0))} -> Foundation | ... N13: {=index('Bill of Quantities'!$D:$O,match($B13,'Bill of Quantities'!$C:$C,0),match(N$2,'Bill of Quantities'!$D$2:$O$2,0))} -> 0.2 | O13: =$A13*F13 -> 0 | P13: =$A13*G13 -> 0 | Q13: =$A13*H13 -> 0 | R13: =$A13*I13 -> 0 | S13: =$A13*L13 -> 1.6 | T13: =$A13*M13 -> 0 | U13: =$A13*N13 -> 1.6 | V13: =$A$6 -> Foundation point | W13: {=A13*index('Project Costs'!A:A,match(V13,'Project Costs'!B:B,0),1)} -> 168 | X13: =W13*R13/60 -> 0
A14: 4 | B14: ='Bill of Quantities'!C42 -> M12 drop anchor | C14: {=index('Bill of Quantities'!$D:$O,match($B14,'Bill of Quantities'!$C:$C,0),match(C$2,'Bill of Quantities'!$D$2:$O$2,0))} -> 20 | D14: {=index('Bill of Quantities'!$D:$O,match($B14,'Bill of Quantities'!$C:$C,0),match(D$2,'Bill of Quantities'!$D$2:$O$2,0))} | E14: {=index('Bill of Quantities'!$D:$O,match($B14,'Bill of Quantities'!$C:$C,0),match(E$2,'Bill of Quantities'!$D$2:$O$2,0))} -> 65 | F14: {=index('Bill of Quantities'!$D:$O,match($B14,'Bill of Quantities'!$C:$C,0),match(F$2,'Bill of Quantities'!$D$2:$O$2,0))} | G14: {=index('Bill of Quantities'!$D:$O,match($B14,'Bill of Quantities'!$C:$C,0),match(G$2,'Bill of Quantities'!$D$2:$O$2,0))} | H14: {=index('Bill of Quantities'!$D:$O,match($B14,'Bill of Quantities'!$C:$C,0),match(H$2,'Bill of Quantities'!$D$2:$O$2,0))} | I14: {=index('Bill of Quantities'!$D:$O,match($B14,'Bill of Quantities'!$C:$C,0),match(I$2,'Bill of Quantities'!$D$2:$O$2,0))} | J14: {=index('Bill of Quantities'!$D:$O,match($B14,'Bill of Quantities'!$C:$C,0),match(J$2,'Bill of Quantities'!$D$2:$O$2,0))} -> Foundation | ... N14: {=index('Bill of Quantities'!$D:$O,match($B14,'Bill of Quantities'!$C:$C,0),match(N$2,'Bill of Quantities'!$D$2:$O$2,0))} -> 1 | O14: =$A14*F14 -> 0 | P14: =$A14*G14 -> 0 | Q14: =$A14*H14 -> 0 | R14: =$A14*I14 -> 0 | S14: =$A14*L14 -> 4 | T14: =$A14*M14 -> 0 | U14: =$A14*N14 -> 4 | V14: =$A$6 -> Foundation point | W14: {=A14*index('Project Costs'!A:A,match(V14,'Project Costs'!B:B,0),1)} -> 84 | X14: =W14*R14/60 -> 0
A15: 0.1 | B15: ='Bill of Quantities'!C43 -> Y12 bar 12 metres | C15: {=index('Bill of Quantities'!$D:$O,match($B15,'Bill of Quantities'!$C:$C,0),match(C$2,'Bill of Quantities'!$D$2:$O$2,0))} -> 12 | D15: {=index('Bill of Quantities'!$D:$O,match($B15,'Bill of Quantities'!$C:$C,0),match(D$2,'Bill of Quantities'!$D$2:$O$2,0))} | E15: {=index('Bill of Quantities'!$D:$O,match($B15,'Bill of Quantities'!$C:$C,0),match(E$2,'Bill of Quantities'!$D$2:$O$2,0))} -> 12000 | F15: {=index('Bill of Quantities'!$D:$O,match($B15,'Bill of Quantities'!$C:$C,0),match(F$2,'Bill of Quantities'!$D$2:$O$2,0))} -> 0.001357168 | G15: {=index('Bill of Quantities'!$D:$O,match($B15,'Bill of Quantities'!$C:$C,0),match(G$2,'Bill of Quantities'!$D$2:$O$2,0))} | H15: {=index('Bill of Quantities'!$D:$O,match($B15,'Bill of Quantities'!$C:$C,0),match(H$2,'Bill of Quantities'!$D$2:$O$2,0))} | I15: {=index('Bill of Quantities'!$D:$O,match($B15,'Bill of Quantities'!$C:$C,0),match(I$2,'Bill of Quantities'!$D$2:$O$2,0))} | J15: {=index('Bill of Quantities'!$D:$O,match($B15,'Bill of Quantities'!$C:$C,0),match(J$2,'Bill of Quantities'!$D$2:$O$2,0))} -> Foundation | ... N15: {=index('Bill of Quantities'!$D:$O,match($B15,'Bill of Quantities'!$C:$C,0),match(N$2,'Bill of Quantities'!$D$2:$O$2,0))} -> 10.306917 | O15: =$A15*F15 -> 0.0001357168 | P15: =$A15*G15 -> 0 | Q15: =$A15*H15 -> 0 | R15: =$A15*I15 -> 0 | S15: =$A15*L15 -> 1.0306917 | T15: =$A15*M15 -> 0 | U15: =$A15*N15 -> 1.0306917 | V15: =$A$6 -> Foundation point | W15: {=A15*index('Project Costs'!A:A,match(V15,'Project Costs'!B:B,0),1)} -> 2.1 | X15: =W15*R15/60 -> 0
A16: 0.1 | B16: ='Bill of Quantities'!C44 -> 8 mm rebar 12 metres | C16: {=index('Bill of Quantities'!$D:$O,match($B16,'Bill of Quantities'!$C:$C,0),match(C$2,'Bill of Quantities'!$D$2:$O$2,0))} -> 8 | D16: {=index('Bill of Quantities'!$D:$O,match($B16,'Bill of Quantities'!$C:$C,0),match(D$2,'Bill of Quantities'!$D$2:$O$2,0))} | E16: {=index('Bill of Quantities'!$D:$O,match($B16,'Bill of Quantities'!$C:$C,0),match(E$2,'Bill of Quantities'!$D$2:$O$2,0))} -> 12000 | F16: {=index('Bill of Quantities'!$D:$O,match($B16,'Bill of Quantities'!$C:$C,0),match(F$2,'Bill of Quantities'!$D$2:$O$2,0))} -> 0.00060318579 | G16: {=index('Bill of Quantities'!$D:$O,match($B16,'Bill of Quantities'!$C:$C,0),match(G$2,'Bill of Quantities'!$D$2:$O$2,0))} | H16: {=index('Bill of Quantities'!$D:$O,match($B16,'Bill of Quantities'!$C:$C,0),match(H$2,'Bill of Quantities'!$D$2:$O$2,0))} | I16: {=index('Bill of Quantities'!$D:$O,match($B16,'Bill of Quantities'!$C:$C,0),match(I$2,'Bill of Quantities'!$D$2:$O$2,0))} | J16: {=index('Bill of Quantities'!$D:$O,match($B16,'Bill of Quantities'!$C:$C,0),match(J$2,'Bill of Quantities'!$D$2:$O$2,0))} -> Foundation | ... N16: {=index('Bill of Quantities'!$D:$O,match($B16,'Bill of Quantities'!$C:$C,0),match(N$2,'Bill of Quantities'!$D$2:$O$2,0))} -> 2.7485112 | O16: =$A16*F16 -> 6.0318579e-05 | P16: =$A16*G16 -> 0 | Q16: =$A16*H16 -> 0 | R16: =$A16*I16 -> 0 | S16: =$A16*L16 -> 0.27485112 | T16: =$A16*M16 -> 0 | U16: =$A16*N16 -> 0.27485112 | V16: =$A$6 -> Foundation point | W16: {=A16*index('Project Costs'!A:A,match(V16,'Project Costs'!B:B,0),1)} -> 2.1 | X16: =W16*R16/60 -> 0
A17: 0.2 | B17: ='Bill of Quantities'!C45 -> Binding wire per kg | C17: {=index('Bill of Quantities'!$D:$O,match($B17,'Bill of Quantities'!$C:$C,0),match(C$2,'Bill of Quantities'!$D$2:$O$2,0))} -> 12 | D17: {=index('Bill of Quantities'!$D:$O,match($B17,'Bill of Quantities'!$C:$C,0),match(D$2,'Bill of Quantities'!$D$2:$O$2,0))} | E17: {=index('Bill of Quantities'!$D:$O,match($B17,'Bill of Quantities'!$C:$C,0),match(E$2,'Bill of Quantities'!$D$2:$O$2,0))} -> 12000 | F17: {=index('Bill of Quantities'!$D:$O,match($B17,'Bill of Quantities'!$C:$C,0),match(F$2,'Bill of Quantities'!$D$2:$O$2,0))} -> 0.001357168 | G17: {=index('Bill of Quantities'!$D:$O,match($B17,'Bill of Quantities'!$C:$C,0),match(G$2,'Bill of Quantities'!$D$2:$O$2,0))} | H17: {=index('Bill of Quantities'!$D:$O,match($B17,'Bill of Quantities'!$C:$C,0),match(H$2,'Bill of Quantities'!$D$2:$O$2,0))} | I17: {=index('Bill of Quantities'!$D:$O,match($B17,'Bill of Quantities'!$C:$C,0),match(I$2,'Bill of Quantities'!$D$2:$O$2,0))} | J17: {=index('Bill of Quantities'!$D:$O,match($B17,'Bill of Quantities'!$C:$C,0),match(J$2,'Bill of Quantities'!$D$2:$O$2,0))} -> Foundation | ... N17: {=index('Bill of Quantities'!$D:$O,match($B17,'Bill of Quantities'!$C:$C,0),match(N$2,'Bill of Quantities'!$D$2:$O$2,0))} -> 1.6216216 | O17: =$A17*F17 -> 0.00027143361 | P17: =$A17*G17 -> 0 | Q17: =$A17*H17 -> 0 | R17: =$A17*I17 -> 0 | S17: =$A17*L17 -> 0.32432432 | T17: =$A17*M17 -> 0 | U17: =$A17*N17 -> 0.32432432 | V17: =$A$6 -> Foundation point | W17: {=A17*index('Project Costs'!A:A,match(V17,'Project Costs'!B:B,0),1)} -> 4.2 | X17: =W17*R17/60 -> 0
A18: 0.2 | B18: ='Bill of Quantities'!C46 -> Used engine oil per liter | C18: {=index('Bill of Quantities'!$D:$O,match($B18,'Bill of Quantities'!$C:$C,0),match(C$2,'Bill of Quantities'!$D$2:$O$2,0))} | D18: {=index('Bill of Quantities'!$D:$O,match($B18,'Bill of Quantities'!$C:$C,0),match(D$2,'Bill of Quantities'!$D$2:$O$2,0))} | E18: {=index('Bill of Quantities'!$D:$O,match($B18,'Bill of Quantities'!$C:$C,0),match(E$2,'Bill of Quantities'!$D$2:$O$2,0))} | F18: {=index('Bill of Quantities'!$D:$O,match($B18,'Bill of Quantities'!$C:$C,0),match(F$2,'Bill of Quantities'!$D$2:$O$2,0))} | G18: {=index('Bill of Quantities'!$D:$O,match($B18,'Bill of Quantities'!$C:$C,0),match(G$2,'Bill of Quantities'!$D$2:$O$2,0))} | H18: {=index('Bill of Quantities'!$D:$O,match($B18,'Bill of Quantities'!$C:$C,0),match(H$2,'Bill of Quantities'!$D$2:$O$2,0))} | I18: {=index('Bill of Quantities'!$D:$O,match($B18,'Bill of Quantities'!$C:$C,0),match(I$2,'Bill of Quantities'!$D$2:$O$2,0))} | J18: {=index('Bill of Quantities'!$D:$O,match($B18,'Bill of Quantities'!$C:$C,0),match(J$2,'Bill of Quantities'!$D$2:$O$2,0))} -> Foundation | ... N18: {=index('Bill of Quantities'!$D:$O,match($B18,'Bill of Quantities'!$C:$C,0),match(N$2,'Bill of Quantities'!$D$2:$O$2,0))} -> 0.68712781 | O18: =$A18*F18 -> 0 | P18: =$A18*G18 -> 0 | Q18: =$A18*H18 -> 0 | R18: =$A18*I18 -> 0 | S18: =$A18*L18 -> 0.13742556 | T18: =$A18*M18 -> 0 | U18: =$A18*N18 -> 0.13742556 | V18: =$A$6 -> Foundation point | W18: {=A18*index('Project Costs'!A:A,match(V18,'Project Costs'!B:B,0),1)} -> 4.2 | X18: =W18*R18/60 -> 0
A19: 6 | B19: ='Bill of Quantities'!C29 -> Screw 6x100 semi threaded HBS6100 | C19: {=index('Bill of Quantities'!$D:$O,match($B19,'Bill of Quantities'!$C:$C,0),match(C$2,'Bill of Quantities'!$D$2:$O$2,0))} -> 6 | D19: {=index('Bill of Quantities'!$D:$O,match($B19,'Bill of Quantities'!$C:$C,0),match(D$2,'Bill of Quantities'!$D$2:$O$2,0))} | E19: {=index('Bill of Quantities'!$D:$O,match($B19,'Bill of Quantities'!$C:$C,0),match(E$2,'Bill of Quantities'!$D$2:$O$2,0))} -> 100 | F19: {=index('Bill of Quantities'!$D:$O,match($B19,'Bill of Quantities'!$C:$C,0),match(F$2,'Bill of Quantities'!$D$2:$O$2,0))} -> 2.8274334e-06 | G19: {=index('Bill of Quantities'!$D:$O,match($B19,'Bill of Quantities'!$C:$C,0),match(G$2,'Bill of Quantities'!$D$2:$O$2,0))} -> 0.021771237 | H19: {=index('Bill of Quantities'!$D:$O,match($B19,'Bill of Quantities'!$C:$C,0),match(H$2,'Bill of Quantities'!$D$2:$O$2,0))} | I19: {=index('Bill of Quantities'!$D:$O,match($B19,'Bill of Quantities'!$C:$C,0),match(I$2,'Bill of Quantities'!$D$2:$O$2,0))} -> 1 | J19: {=index('Bill of Quantities'!$D:$O,match($B19,'Bill of Quantities'!$C:$C,0),match(J$2,'Bill of Quantities'!$D$2:$O$2,0))} -> Screw | ... N19: {=index('Bill of Quantities'!$D:$O,match($B19,'Bill of Quantities'!$C:$C,0),match(N$2,'Bill of Quantities'!$D$2:$O$2,0))} -> 0.09125 | O19: =$A19*F19 -> 1.69646e-05 | P19: =$A19*G19 -> 0.13062742 | Q19: =$A19*H19 -> 0 | R19: =$A19*I19 -> 6 | S19: =$A19*L19 -> 0.36 | T19: =$A19*M19 -> 0.1875 | U19: =$A19*N19 -> 0.5475 | V19: =$A$6 -> Foundation point | W19: {=A19*index('Project Costs'!A:A,match(V19,'Project Costs'!B:B,0),1)} -> 126 | X19: =W19*R19/60 -> 12.6
A20: 2 | B20: ='Bill of Quantities'!C47 -> Foundation plate 5 x 100 x 250 mm (redoxide coated) | C20: {=index('Bill of Quantities'!$D:$O,match($B20,'Bill of Quantities'!$C:$C,0),match(C$2,'Bill of Quantities'!$D$2:$O$2,0))} -> 100 | D20: {=index('Bill of Quantities'!$D:$O,match($B20,'Bill of Quantities'!$C:$C,0),match(D$2,'Bill of Quantities'!$D$2:$O$2,0))} -> 5 | E20: {=index('Bill of Quantities'!$D:$O,match($B20,'Bill of Quantities'!$C:$C,0),match(E$2,'Bill of Quantities'!$D$2:$O$2,0))} -> 250 | F20: {=index('Bill of Quantities'!$D:$O,match($B20,'Bill of Quantities'!$C:$C,0),match(F$2,'Bill of Quantities'!$D$2:$O$2,0))} -> 0.000125 | G20: {=index('Bill of Quantities'!$D:$O,match($B20,'Bill of Quantities'!$C:$C,0),match(G$2,'Bill of Quantities'!$D$2:$O$2,0))} | H20: {=index('Bill of Quantities'!$D:$O,match($B20,'Bill of Quantities'!$C:$C,0),match(H$2,'Bill of Quantities'!$D$2:$O$2,0))} | I20: {=index('Bill of Quantities'!$D:$O,match($B20,'Bill of Quantities'!$C:$C,0),match(I$2,'Bill of Quantities'!$D$2:$O$2,0))} -> 15 | J20: {=index('Bill of Quantities'!$D:$O,match($B20,'Bill of Quantities'!$C:$C,0),match(J$2,'Bill of Quantities'!$D$2:$O$2,0))} -> Foundation | ... N20: {=index('Bill of Quantities'!$D:$O,match($B20,'Bill of Quantities'!$C:$C,0),match(N$2,'Bill of Quantities'!$D$2:$O$2,0))} -> 4.5661293 | O20: =$A20*F20 -> 0.00025 | P20: =$A20*G20 -> 0 | Q20: =$A20*H20 -> 0 | R20: =$A20*I20 -> 30 | S20: =$A20*L20 -> 8.1947585 | T20: =$A20*M20 -> 0.9375 | U20: =$A20*N20 -> 9.1322585 | V20: =$A$6 -> Foundation point | W20: {=A20*index('Project Costs'!A:A,match(V20,'Project Costs'!B:B,0),1)} -> 42 | X20: =W20*R20/60 -> 21
A22: Floor frame 2442 x 1221 | C22: 2442 | D22: 172 | E22: 1221 | V22: =$A$22 -> Floor frame 2442 x 1221 | Y22: =C22*E22*0.000001 -> 2.981682
A23: 2 | B23: =B41 -> Floor Main Beam 46 x 146 x 2442 | C23: {=index('Bill of Quantities'!$D:$O,match($B23,'Bill of Quantities'!$C:$C,0),match(C$2,'Bill of Quantities'!$D$2:$O$2,0))} -> 46 | D23: {=index('Bill of Quantities'!$D:$O,match($B23,'Bill of Quantities'!$C:$C,0),match(D$2,'Bill of Quantities'!$D$2:$O$2,0))} -> 146 | E23: {=index('Bill of Quantities'!$D:$O,match($B23,'Bill of Quantities'!$C:$C,0),match(E$2,'Bill of Quantities'!$D$2:$O$2,0))} -> 2442 | F23: {=index('Bill of Quantities'!$D:$O,match($B23,'Bill of Quantities'!$C:$C,0),match(F$2,'Bill of Quantities'!$D$2:$O$2,0))} -> 0.016400472 | G23: {=index('Bill of Quantities'!$D:$O,match($B23,'Bill of Quantities'!$C:$C,0),match(G$2,'Bill of Quantities'!$D$2:$O$2,0))} -> 9.2006648 | H23: {=index('Bill of Quantities'!$D:$O,match($B23,'Bill of Quantities'!$C:$C,0),match(H$2,'Bill of Quantities'!$D$2:$O$2,0))} -> 14.820598 | I23: {=index('Bill of Quantities'!$D:$O,match($B23,'Bill of Quantities'!$C:$C,0),match(I$2,'Bill of Quantities'!$D$2:$O$2,0))} -> 5 | J23: {=index('Bill of Quantities'!$D:$O,match($B23,'Bill of Quantities'!$C:$C,0),match(J$2,'Bill of Quantities'!$D$2:$O$2,0))} -> Floor | ... N23: {=index('Bill of Quantities'!$D:$O,match($B23,'Bill of Quantities'!$C:$C,0),match(N$2,'Bill of Quantities'!$D$2:$O$2,0))} -> 4.3027084 | O23: =$A23*F23 -> 0.032800944 | P23: =$A23*G23 -> 18.40133 | Q23: =$A23*H23 -> 29.641196 | R23: =$A23*I23 -> 10 | S23: =$A23*L23 -> 8.2929168 | T23: =$A23*M23 -> 0.3125 | U23: =$A23*N23 -> 8.6054168 | V23: =$A$22 -> Floor frame 2442 x 1221 | W23: {=A23*index('Project Costs'!A:A,match(V23,'Project Costs'!B:B,0),1)} -> 8 | X23: =W23*R23/60 -> 1.3333333
A24: 5 | B24: ='Bill of Quantities'!C91 -> Floor Sub Beam 46 x 146 x 1121 | C24: {=index('Bill of Quantities'!$D:$O,match($B24,'Bill of Quantities'!$C:$C,0),match(C$2,'Bill of Quantities'!$D$2:$O$2,0))} -> 46 | D24: {=index('Bill of Quantities'!$D:$O,match($B24,'Bill of Quantities'!$C:$C,0),match(D$2,'Bill of Quantities'!$D$2:$O$2,0))} -> 146 | E24: {=index('Bill of Quantities'!$D:$O,match($B24,'Bill of Quantities'!$C:$C,0),match(E$2,'Bill of Quantities'!$D$2:$O$2,0))} -> 1121 | F24: {=index('Bill of Quantities'!$D:$O,match($B24,'Bill of Quantities'!$C:$C,0),match(F$2,'Bill of Quantities'!$D$2:$O$2,0))} -> 0.007528636 | G24: {=index('Bill of Quantities'!$D:$O,match($B24,'Bill of Quantities'!$C:$C,0),match(G$2,'Bill of Quantities'!$D$2:$O$2,0))} -> 4.2235648 | H24: {=index('Bill of Quantities'!$D:$O,match($B24,'Bill of Quantities'!$C:$C,0),match(H$2,'Bill of Quantities'!$D$2:$O$2,0))} -> 6.803395 | I24: {=index('Bill of Quantities'!$D:$O,match($B24,'Bill of Quantities'!$C:$C,0),match(I$2,'Bill of Quantities'!$D$2:$O$2,0))} -> 5 | J24: {=index('Bill of Quantities'!$D:$O,match($B24,'Bill of Quantities'!$C:$C,0),match(J$2,'Bill of Quantities'!$D$2:$O$2,0))} -> Floor | ... N24: {=index('Bill of Quantities'!$D:$O,match($B24,'Bill of Quantities'!$C:$C,0),match(N$2,'Bill of Quantities'!$D$2:$O$2,0))} -> 2.2294792 | O24: =$A24*F24 -> 0.03764318 | P24: =$A24*G24 -> 21.117824 | Q24: =$A24*H24 -> 34.016975 | R24: =$A24*I24 -> 25 | S24: =$A24*L24 -> 10.366146 | T24: =$A24*M24 -> 0.78125 | U24: =$A24*N24 -> 11.147396 | V24: =$A$22 -> Floor frame 2442 x 1221 | W24: {=A24*index('Project Costs'!A:A,match(V24,'Project Costs'!B:B,0),1)} -> 20 | X24: =W24*R24/60 -> 8.3333333
A25: 4 | B25: =B43 -> Floor Support Block 46 x 146 x 548 | C25: {=index('Bill of Quantities'!$D:$O,match($B25,'Bill of Quantities'!$C:$C,0),match(C$2,'Bill of Quantities'!$D$2:$O$2,0))} -> 46 | D25: {=index('Bill of Quantities'!$D:$O,match($B25,'Bill of Quantities'!$C:$C,0),match(D$2,'Bill of Quantities'!$D$2:$O$2,0))} -> 146 | E25: {=index('Bill of Quantities'!$D:$O,match($B25,'Bill of Quantities'!$C:$C,0),match(E$2,'Bill of Quantities'!$D$2:$O$2,0))} -> 548 | F25: {=index('Bill of Quantities'!$D:$O,match($B25,'Bill of Quantities'!$C:$C,0),match(F$2,'Bill of Quantities'!$D$2:$O$2,0))} -> 0.003680368 | G25: {=index('Bill of Quantities'!$D:$O,match($B25,'Bill of Quantities'!$C:$C,0),match(G$2,'Bill of Quantities'!$D$2:$O$2,0))} -> 2.0646864 | H25: {=index('Bill of Quantities'!$D:$O,match($B25,'Bill of Quantities'!$C:$C,0),match(H$2,'Bill of Quantities'!$D$2:$O$2,0))} -> 3.3258345 | I25: {=index('Bill of Quantities'!$D:$O,match($B25,'Bill of Quantities'!$C:$C,0),match(I$2,'Bill of Quantities'!$D$2:$O$2,0))} -> 5 | J25: {=index('Bill of Quantities'!$D:$O,match($B25,'Bill of Quantities'!$C:$C,0),match(J$2,'Bill of Quantities'!$D$2:$O$2,0))} -> Floor | ... N25: {=index('Bill of Quantities'!$D:$O,match($B25,'Bill of Quantities'!$C:$C,0),match(N$2,'Bill of Quantities'!$D$2:$O$2,0))} -> 1.1928646 | O25: =$A25*F25 -> 0.014721472 | P25: =$A25*G25 -> 8.2587458 | Q25: =$A25*H25 -> 13.303338 | R25: =$A25*I25 -> 20 | S25: =$A25*L25 -> 4.1464584 | T25: =$A25*M25 -> 0.625 | U25: =$A25*N25 -> 4.7714584 | V25: =$A$22 -> Floor frame 2442 x 1221 | W25: {=A25*index('Project Costs'!A:A,match(V25,'Project Costs'!B:B,0),1)} -> 16 | X25: =W25*R25/60 -> 5.3333333
A26: 15 | B26: =B44 -> Floor Plank Tongue Groove 22 x 96 x 2440 | C26: {=index('Bill of Quantities'!$D:$O,match($B26,'Bill of Quantities'!$C:$C,0),match(C$2,'Bill of Quantities'!$D$2:$O$2,0))} -> 22 | D26: {=index('Bill of Quantities'!$D:$O,match($B26,'Bill of Quantities'!$C:$C,0),match(D$2,'Bill of Quantities'!$D$2:$O$2,0))} -> 96 | E26: {=index('Bill of Quantities'!$D:$O,match($B26,'Bill of Quantities'!$C:$C,0),match(E$2,'Bill of Quantities'!$D$2:$O$2,0))} -> 2440 | F26: {=index('Bill of Quantities'!$D:$O,match($B26,'Bill of Quantities'!$C:$C,0),match(F$2,'Bill of Quantities'!$D$2:$O$2,0))} -> 0.00515328 | G26: {=index('Bill of Quantities'!$D:$O,match($B26,'Bill of Quantities'!$C:$C,0),match(G$2,'Bill of Quantities'!$D$2:$O$2,0))} -> 2.8909901 | H26: {=index('Bill of Quantities'!$D:$O,match($B26,'Bill of Quantities'!$C:$C,0),match(H$2,'Bill of Quantities'!$D$2:$O$2,0))} -> 4.6568594 | I26: {=index('Bill of Quantities'!$D:$O,match($B26,'Bill of Quantities'!$C:$C,0),match(I$2,'Bill of Quantities'!$D$2:$O$2,0))} -> 5 | J26: {=index('Bill of Quantities'!$D:$O,match($B26,'Bill of Quantities'!$C:$C,0),match(J$2,'Bill of Quantities'!$D$2:$O$2,0))} -> Floor | ... N26: {=index('Bill of Quantities'!$D:$O,match($B26,'Bill of Quantities'!$C:$C,0),match(N$2,'Bill of Quantities'!$D$2:$O$2,0))} -> 1.501594 | O26: =$A26*F26 -> 0.0772992 | P26: =$A26*G26 -> 43.364851 | Q26: =$A26*H26 -> 69.852891 | R26: =$A26*I26 -> 75 | S26: =$A26*L26 -> 20.18016 | T26: =$A26*M26 -> 2.34375 | U26: =$A26*N26 -> 22.52391 | V26: =$A$22 -> Floor frame 2442 x 1221 | W26: {=A26*index('Project Costs'!A:A,match(V26,'Project Costs'!B:B,0),1)} -> 60 | X26: =W26*R26/60 -> 75
A27: =A26*5 -> 75 | B27: =B45 -> Screw 3.5x40 small head screw SHS3540 | C27: {=index('Bill of Quantities'!$D:$O,match($B27,'Bill of Quantities'!$C:$C,0),match(C$2,'Bill of Quantities'!$D$2:$O$2,0))} -> 3.5 | D27: {=index('Bill of Quantities'!$D:$O,match($B27,'Bill of Quantities'!$C:$C,0),match(D$2,'Bill of Quantities'!$D$2:$O$2,0))} | E27: {=index('Bill of Quantities'!$D:$O,match($B27,'Bill of Quantities'!$C:$C,0),match(E$2,'Bill of Quantities'!$D$2:$O$2,0))} -> 40 | F27: {=index('Bill of Quantities'!$D:$O,match($B27,'Bill of Quantities'!$C:$C,0),match(F$2,'Bill of Quantities'!$D$2:$O$2,0))} -> 3.848451e-07 | G27: {=index('Bill of Quantities'!$D:$O,match($B27,'Bill of Quantities'!$C:$C,0),match(G$2,'Bill of Quantities'!$D$2:$O$2,0))} -> 0.0029633073 | H27: {=index('Bill of Quantities'!$D:$O,match($B27,'Bill of Quantities'!$C:$C,0),match(H$2,'Bill of Quantities'!$D$2:$O$2,0))} | I27: {=index('Bill of Quantities'!$D:$O,match($B27,'Bill of Quantities'!$C:$C,0),match(I$2,'Bill of Quantities'!$D$2:$O$2,0))} -> 1 | J27: {=index('Bill of Quantities'!$D:$O,match($B27,'Bill of Quantities'!$C:$C,0),match(J$2,'Bill of Quantities'!$D$2:$O$2,0))} -> Screw | ... N27: {=index('Bill of Quantities'!$D:$O,match($B27,'Bill of Quantities'!$C:$C,0),match(N$2,'Bill of Quantities'!$D$2:$O$2,0))} -> 0.077547556 | O27: =$A27*F27 -> 2.8863383e-05 | P27: =$A27*G27 -> 0.22224805 | Q27: =$A27*H27 -> 0 | R27: =$A27*I27 -> 75 | S27: =$A27*L27 -> 3.4723167 | T27: =$A27*M27 -> 2.34375 | U27: =$A27*N27 -> 5.8160667 | V27: =$A$22 -> Floor frame 2442 x 1221 | W27: {=A27*index('Project Costs'!A:A,match(V27,'Project Costs'!B:B,0),1)} -> 300 | X27: =W27*R27/60 -> 375
A28: 10 | B28: =B46 -> Screw 6x100 semi threaded HBS6100 | C28: {=index('Bill of Quantities'!$D:$O,match($B28,'Bill of Quantities'!$C:$C,0),match(C$2,'Bill of Quantities'!$D$2:$O$2,0))} -> 6 | D28: {=index('Bill of Quantities'!$D:$O,match($B28,'Bill of Quantities'!$C:$C,0),match(D$2,'Bill of Quantities'!$D$2:$O$2,0))} | E28: {=index('Bill of Quantities'!$D:$O,match($B28,'Bill of Quantities'!$C:$C,0),match(E$2,'Bill of Quantities'!$D$2:$O$2,0))} -> 100 | F28: {=index('Bill of Quantities'!$D:$O,match($B28,'Bill of Quantities'!$C:$C,0),match(F$2,'Bill of Quantities'!$D$2:$O$2,0))} -> 2.8274334e-06 | G28: {=index('Bill of Quantities'!$D:$O,match($B28,'Bill of Quantities'!$C:$C,0),match(G$2,'Bill of Quantities'!$D$2:$O$2,0))} -> 0.021771237 | H28: {=index('Bill of Quantities'!$D:$O,match($B28,'Bill of Quantities'!$C:$C,0),match(H$2,'Bill of Quantities'!$D$2:$O$2,0))} | I28: {=index('Bill of Quantities'!$D:$O,match($B28,'Bill of Quantities'!$C:$C,0),match(I$2,'Bill of Quantities'!$D$2:$O$2,0))} -> 1 | J28: {=index('Bill of Quantities'!$D:$O,match($B28,'Bill of Quantities'!$C:$C,0),match(J$2,'Bill of Quantities'!$D$2:$O$2,0))} -> Screw | ... N28: {=index('Bill of Quantities'!$D:$O,match($B28,'Bill of Quantities'!$C:$C,0),match(N$2,'Bill of Quantities'!$D$2:$O$2,0))} -> 0.09125 | O28: =$A28*F28 -> 2.8274334e-05 | P28: =$A28*G28 -> 0.21771237 | Q28: =$A28*H28 -> 0 | R28: =$A28*I28 -> 10 | S28: =$A28*L28 -> 0.6 | T28: =$A28*M28 -> 0.3125 | U28: =$A28*N28 -> 0.9125 | V28: =$A$22 -> Floor frame 2442 x 1221 | W28: {=A28*index('Project Costs'!A:A,match(V28,'Project Costs'!B:B,0),1)} -> 40 | X28: =W28*R28/60 -> 6.6666667
A29: =A24*4+A25*4 -> 36 | B29: =B47 -> Screw 6x120 semi threaded HBS6120 | C29: {=index('Bill of Quantities'!$D:$O,match($B29,'Bill of Quantities'!$C:$C,0),match(C$2,'Bill of Quantities'!$D$2:$O$2,0))} -> 6 | D29: {=index('Bill of Quantities'!$D:$O,match($B29,'Bill of Quantities'!$C:$C,0),match(D$2,'Bill of Quantities'!$D$2:$O$2,0))} | E29: {=index('Bill of Quantities'!$D:$O,match($B29,'Bill of Quantities'!$C:$C,0),match(E$2,'Bill of Quantities'!$D$2:$O$2,0))} -> 120 | F29: {=index('Bill of Quantities'!$D:$O,match($B29,'Bill of Quantities'!$C:$C,0),match(F$2,'Bill of Quantities'!$D$2:$O$2,0))} -> 3.3929201e-06 | G29: {=index('Bill of Quantities'!$D:$O,match($B29,'Bill of Quantities'!$C:$C,0),match(G$2,'Bill of Quantities'!$D$2:$O$2,0))} -> 0.026125485 | H29: {=index('Bill of Quantities'!$D:$O,match($B29,'Bill of Quantities'!$C:$C,0),match(H$2,'Bill of Quantities'!$D$2:$O$2,0))} | I29: {=index('Bill of Quantities'!$D:$O,match($B29,'Bill of Quantities'!$C:$C,0),match(I$2,'Bill of Quantities'!$D$2:$O$2,0))} -> 1 | J29: {=index('Bill of Quantities'!$D:$O,match($B29,'Bill of Quantities'!$C:$C,0),match(J$2,'Bill of Quantities'!$D$2:$O$2,0))} -> Screw | ... N29: {=index('Bill of Quantities'!$D:$O,match($B29,'Bill of Quantities'!$C:$C,0),match(N$2,'Bill of Quantities'!$D$2:$O$2,0))} -> 0.09125 | O29: =$A29*F29 -> 0.00012214512 | P29: =$A29*G29 -> 0.94051744 | Q29: =$A29*H29 -> 0 | R29: =$A29*I29 -> 36 | S29: =$A29*L29 -> 2.16 | T29: =$A29*M29 -> 1.125 | U29: =$A29*N29 -> 3.285 | V29: =$A$22 -> Floor frame 2442 x 1221 | W29: {=A29*index('Project Costs'!A:A,match(V29,'Project Costs'!B:B,0),1)} -> 144 | X29: =W29*R29/60 -> 86.4
A31: Floor frame 2442 x 2442 | C31: 2442 | D31: 172 | E31: 2442 | V31: =V32 -> Floor frame 2442 x 2442 | Y31: =C31*E31*0.000001 -> 5.963364
A32: 2 | B32: ='Bill of Quantities'!C88 -> Floor Main Beam 46 x 146 x 2442 | C32: {=index('Bill of Quantities'!$D:$O,match($B32,'Bill of Quantities'!$C:$C,0),match(C$2,'Bill of Quantities'!$D$2:$O$2,0))} -> 46 | D32: {=index('Bill of Quantities'!$D:$O,match($B32,'Bill of Quantities'!$C:$C,0),match(D$2,'Bill of Quantities'!$D$2:$O$2,0))} -> 146 | E32: {=index('Bill of Quantities'!$D:$O,match($B32,'Bill of Quantities'!$C:$C,0),match(E$2,'Bill of Quantities'!$D$2:$O$2,0))} -> 2442 | F32: {=index('Bill of Quantities'!$D:$O,match($B32,'Bill of Quantities'!$C:$C,0),match(F$2,'Bill of Quantities'!$D$2:$O$2,0))} -> 0.016400472 | G32: {=index('Bill of Quantities'!$D:$O,match($B32,'Bill of Quantities'!$C:$C,0),match(G$2,'Bill of Quantities'!$D$2:$O$2,0))} -> 9.2006648 | H32: {=index('Bill of Quantities'!$D:$O,match($B32,'Bill of Quantities'!$C:$C,0),match(H$2,'Bill of Quantities'!$D$2:$O$2,0))} -> 14.820598 | I32: {=index('Bill of Quantities'!$D:$O,match($B32,'Bill of Quantities'!$C:$C,0),match(I$2,'Bill of Quantities'!$D$2:$O$2,0))} -> 5 | J32: {=index('Bill of Quantities'!$D:$O,match($B32,'Bill of Quantities'!$C:$C,0),match(J$2,'Bill of Quantities'!$D$2:$O$2,0))} -> Floor | ... N32: {=index('Bill of Quantities'!$D:$O,match($B32,'Bill of Quantities'!$C:$C,0),match(N$2,'Bill of Quantities'!$D$2:$O$2,0))} -> 4.3027084 | O32: =$A32*F32 -> 0.032800944 | P32: =$A32*G32 -> 18.40133 | Q32: =$A32*H32 -> 29.641196 | R32: =$A32*I32 -> 10 | S32: =$A32*L32 -> 8.2929168 | T32: =$A32*M32 -> 0.3125 | U32: =$A32*N32 -> 8.6054168 | V32: =$A$31 -> Floor frame 2442 x 2442 | W32: {=A32*index('Project Costs'!A:A,match(V32,'Project Costs'!B:B,0),1)} -> 16 | X32: =W32*R32/60 -> 2.6666667
A33: 5 | B33: ='Bill of Quantities'!C89 -> Floor Sub Beam 46 x 146 x 2342 | C33: {=index('Bill of Quantities'!$D:$O,match($B33,'Bill of Quantities'!$C:$C,0),match(C$2,'Bill of Quantities'!$D$2:$O$2,0))} -> 46 | D33: {=index('Bill of Quantities'!$D:$O,match($B33,'Bill of Quantities'!$C:$C,0),match(D$2,'Bill of Quantities'!$D$2:$O$2,0))} -> 146 | E33: {=index('Bill of Quantities'!$D:$O,match($B33,'Bill of Quantities'!$C:$C,0),match(E$2,'Bill of Quantities'!$D$2:$O$2,0))} -> 2342 | F33: {=index('Bill of Quantities'!$D:$O,match($B33,'Bill of Quantities'!$C:$C,0),match(F$2,'Bill of Quantities'!$D$2:$O$2,0))} -> 0.015728872 | G33: {=index('Bill of Quantities'!$D:$O,match($B33,'Bill of Quantities'!$C:$C,0),match(G$2,'Bill of Quantities'!$D$2:$O$2,0))} -> 8.8238972 | H33: {=index('Bill of Quantities'!$D:$O,match($B33,'Bill of Quantities'!$C:$C,0),match(H$2,'Bill of Quantities'!$D$2:$O$2,0))} -> 14.213694 | I33: {=index('Bill of Quantities'!$D:$O,match($B33,'Bill of Quantities'!$C:$C,0),match(I$2,'Bill of Quantities'!$D$2:$O$2,0))} -> 5 | J33: {=index('Bill of Quantities'!$D:$O,match($B33,'Bill of Quantities'!$C:$C,0),match(J$2,'Bill of Quantities'!$D$2:$O$2,0))} -> Floor | ... N33: {=index('Bill of Quantities'!$D:$O,match($B33,'Bill of Quantities'!$C:$C,0),match(N$2,'Bill of Quantities'!$D$2:$O$2,0))} -> 4.3027084 | O33: =$A33*F33 -> 0.07864436 | P33: =$A33*G33 -> 44.119486 | Q33: =$A33*H33 -> 71.06847 | R33: =$A33*I33 -> 25 | S33: =$A33*L33 -> 20.732292 | T33: =$A33*M33 -> 0.78125 | U33: =$A33*N33 -> 21.513542 | V33: =$A$31 -> Floor frame 2442 x 2442 | W33: {=A33*index('Project Costs'!A:A,match(V33,'Project Costs'!B:B,0),1)} -> 40 | X33: =W33*R33/60 -> 16.666667
A34: 4 | B34: ='Bill of Quantities'!C92 -> Floor Support Block 46 x 146 x 548 | C34: {=index('Bill of Quantities'!$D:$O,match($B34,'Bill of Quantities'!$C:$C,0),match(C$2,'Bill of Quantities'!$D$2:$O$2,0))} -> 46 | D34: {=index('Bill of Quantities'!$D:$O,match($B34,'Bill of Quantities'!$C:$C,0),match(D$2,'Bill of Quantities'!$D$2:$O$2,0))} -> 146 | E34: {=index('Bill of Quantities'!$D:$O,match($B34,'Bill of Quantities'!$C:$C,0),match(E$2,'Bill of Quantities'!$D$2:$O$2,0))} -> 548 | F34: {=index('Bill of Quantities'!$D:$O,match($B34,'Bill of Quantities'!$C:$C,0),match(F$2,'Bill of Quantities'!$D$2:$O$2,0))} -> 0.003680368 | G34: {=index('Bill of Quantities'!$D:$O,match($B34,'Bill of Quantities'!$C:$C,0),match(G$2,'Bill of Quantities'!$D$2:$O$2,0))} -> 2.0646864 | H34: {=index('Bill of Quantities'!$D:$O,match($B34,'Bill of Quantities'!$C:$C,0),match(H$2,'Bill of Quantities'!$D$2:$O$2,0))} -> 3.3258345 | I34: {=index('Bill of Quantities'!$D:$O,match($B34,'Bill of Quantities'!$C:$C,0),match(I$2,'Bill of Quantities'!$D$2:$O$2,0))} -> 5 | J34: {=index('Bill of Quantities'!$D:$O,match($B34,'Bill of Quantities'!$C:$C,0),match(J$2,'Bill of Quantities'!$D$2:$O$2,0))} -> Floor | ... N34: {=index('Bill of Quantities'!$D:$O,match($B34,'Bill of Quantities'!$C:$C,0),match(N$2,'Bill of Quantities'!$D$2:$O$2,0))} -> 1.1928646 | O34: =$A34*F34 -> 0.014721472 | P34: =$A34*G34 -> 8.2587458 | Q34: =$A34*H34 -> 13.303338 | R34: =$A34*I34 -> 20 | S34: =$A34*L34 -> 4.1464584 | T34: =$A34*M34 -> 0.625 | U34: =$A34*N34 -> 4.7714584 | V34: =$A$31 -> Floor frame 2442 x 2442 | W34: {=A34*index('Project Costs'!A:A,match(V34,'Project Costs'!B:B,0),1)} -> 32 | X34: =W34*R34/60 -> 10.666667
A35: 29 | B35: ='Bill of Quantities'!C93 -> Floor Plank Tongue Groove 22 x 96 x 2440 | C35: {=index('Bill of Quantities'!$D:$O,match($B35,'Bill of Quantities'!$C:$C,0),match(C$2,'Bill of Quantities'!$D$2:$O$2,0))} -> 22 | D35: {=index('Bill of Quantities'!$D:$O,match($B35,'Bill of Quantities'!$C:$C,0),match(D$2,'Bill of Quantities'!$D$2:$O$2,0))} -> 96 | E35: {=index('Bill of Quantities'!$D:$O,match($B35,'Bill of Quantities'!$C:$C,0),match(E$2,'Bill of Quantities'!$D$2:$O$2,0))} -> 2440 | F35: {=index('Bill of Quantities'!$D:$O,match($B35,'Bill of Quantities'!$C:$C,0),match(F$2,'Bill of Quantities'!$D$2:$O$2,0))} -> 0.00515328 | G35: {=index('Bill of Quantities'!$D:$O,match($B35,'Bill of Quantities'!$C:$C,0),match(G$2,'Bill of Quantities'!$D$2:$O$2,0))} -> 2.8909901 | H35: {=index('Bill of Quantities'!$D:$O,match($B35,'Bill of Quantities'!$C:$C,0),match(H$2,'Bill of Quantities'!$D$2:$O$2,0))} -> 4.6568594 | I35: {=index('Bill of Quantities'!$D:$O,match($B35,'Bill of Quantities'!$C:$C,0),match(I$2,'Bill of Quantities'!$D$2:$O$2,0))} -> 5 | J35: {=index('Bill of Quantities'!$D:$O,match($B35,'Bill of Quantities'!$C:$C,0),match(J$2,'Bill of Quantities'!$D$2:$O$2,0))} -> Floor | ... N35: {=index('Bill of Quantities'!$D:$O,match($B35,'Bill of Quantities'!$C:$C,0),match(N$2,'Bill of Quantities'!$D$2:$O$2,0))} -> 1.501594 | O35: =$A35*F35 -> 0.14944512 | P35: =$A35*G35 -> 83.838712 | Q35: =$A35*H35 -> 135.04892 | R35: =$A35*I35 -> 145 | S35: =$A35*L35 -> 39.014976 | T35: =$A35*M35 -> 4.53125 | U35: =$A35*N35 -> 43.546226 | V35: =$A$31 -> Floor frame 2442 x 2442 | W35: {=A35*index('Project Costs'!A:A,match(V35,'Project Costs'!B:B,0),1)} -> 232 | X35: =W35*R35/60 -> 560.66667
A36: =A35*5 -> 145 | B36: ='Bill of Quantities'!$C$23 -> Screw 3.5x40 small head screw SHS3540 | C36: {=index('Bill of Quantities'!$D:$O,match($B36,'Bill of Quantities'!$C:$C,0),match(C$2,'Bill of Quantities'!$D$2:$O$2,0))} -> 3.5 | D36: {=index('Bill of Quantities'!$D:$O,match($B36,'Bill of Quantities'!$C:$C,0),match(D$2,'Bill of Quantities'!$D$2:$O$2,0))} | E36: {=index('Bill of Quantities'!$D:$O,match($B36,'Bill of Quantities'!$C:$C,0),match(E$2,'Bill of Quantities'!$D$2:$O$2,0))} -> 40 | F36: {=index('Bill of Quantities'!$D:$O,match($B36,'Bill of Quantities'!$C:$C,0),match(F$2,'Bill of Quantities'!$D$2:$O$2,0))} -> 3.848451e-07 | G36: {=index('Bill of Quantities'!$D:$O,match($B36,'Bill of Quantities'!$C:$C,0),match(G$2,'Bill of Quantities'!$D$2:$O$2,0))} -> 0.0029633073 | H36: {=index('Bill of Quantities'!$D:$O,match($B36,'Bill of Quantities'!$C:$C,0),match(H$2,'Bill of Quantities'!$D$2:$O$2,0))} | I36: {=index('Bill of Quantities'!$D:$O,match($B36,'Bill of Quantities'!$C:$C,0),match(I$2,'Bill of Quantities'!$D$2:$O$2,0))} -> 1 | J36: {=index('Bill of Quantities'!$D:$O,match($B36,'Bill of Quantities'!$C:$C,0),match(J$2,'Bill of Quantities'!$D$2:$O$2,0))} -> Screw | ... N36: {=index('Bill of Quantities'!$D:$O,match($B36,'Bill of Quantities'!$C:$C,0),match(N$2,'Bill of Quantities'!$D$2:$O$2,0))} -> 0.077547556 | O36: =$A36*F36 -> 5.580254e-05 | P36: =$A36*G36 -> 0.42967955 | Q36: =$A36*H36 -> 0 | R36: =$A36*I36 -> 145 | S36: =$A36*L36 -> 6.7131457 | T36: =$A36*M36 -> 4.53125 | U36: =$A36*N36 -> 11.244396 | V36: =$A$31 -> Floor frame 2442 x 2442 | W36: {=A36*index('Project Costs'!A:A,match(V36,'Project Costs'!B:B,0),1)} -> 1160 | X36: =W36*R36/60 -> 2803.3333
A37: 10 | B37: ='Bill of Quantities'!C29 -> Screw 6x100 semi threaded HBS6100 | C37: {=index('Bill of Quantities'!$D:$O,match($B37,'Bill of Quantities'!$C:$C,0),match(C$2,'Bill of Quantities'!$D$2:$O$2,0))} -> 6 | D37: {=index('Bill of Quantities'!$D:$O,match($B37,'Bill of Quantities'!$C:$C,0),match(D$2,'Bill of Quantities'!$D$2:$O$2,0))} | E37: {=index('Bill of Quantities'!$D:$O,match($B37,'Bill of Quantities'!$C:$C,0),match(E$2,'Bill of Quantities'!$D$2:$O$2,0))} -> 100 | F37: {=index('Bill of Quantities'!$D:$O,match($B37,'Bill of Quantities'!$C:$C,0),match(F$2,'Bill of Quantities'!$D$2:$O$2,0))} -> 2.8274334e-06 | G37: {=index('Bill of Quantities'!$D:$O,match($B37,'Bill of Quantities'!$C:$C,0),match(G$2,'Bill of Quantities'!$D$2:$O$2,0))} -> 0.021771237 | H37: {=index('Bill of Quantities'!$D:$O,match($B37,'Bill of Quantities'!$C:$C,0),match(H$2,'Bill of Quantities'!$D$2:$O$2,0))} | I37: {=index('Bill of Quantities'!$D:$O,match($B37,'Bill of Quantities'!$C:$C,0),match(I$2,'Bill of Quantities'!$D$2:$O$2,0))} -> 1 | J37: {=index('Bill of Quantities'!$D:$O,match($B37,'Bill of Quantities'!$C:$C,0),match(J$2,'Bill of Quantities'!$D$2:$O$2,0))} -> Screw | ... N37: {=index('Bill of Quantities'!$D:$O,match($B37,'Bill of Quantities'!$C:$C,0),match(N$2,'Bill of Quantities'!$D$2:$O$2,0))} -> 0.09125 | O37: =$A37*F37 -> 2.8274334e-05 | P37: =$A37*G37 -> 0.21771237 | Q37: =$A37*H37 -> 0 | R37: =$A37*I37 -> 10 | S37: =$A37*L37 -> 0.6 | T37: =$A37*M37 -> 0.3125 | U37: =$A37*N37 -> 0.9125 | V37: =$A$31 -> Floor frame 2442 x 2442 | W37: {=A37*index('Project Costs'!A:A,match(V37,'Project Costs'!B:B,0),1)} -> 80 | X37: =W37*R37/60 -> 13.333333
A38: =A33*4+A34*4 -> 36 | B38: ='Bill of Quantities'!C30 -> Screw 6x120 semi threaded HBS6120 | C38: {=index('Bill of Quantities'!$D:$O,match($B38,'Bill of Quantities'!$C:$C,0),match(C$2,'Bill of Quantities'!$D$2:$O$2,0))} -> 6 | D38: {=index('Bill of Quantities'!$D:$O,match($B38,'Bill of Quantities'!$C:$C,0),match(D$2,'Bill of Quantities'!$D$2:$O$2,0))} | E38: {=index('Bill of Quantities'!$D:$O,match($B38,'Bill of Quantities'!$C:$C,0),match(E$2,'Bill of Quantities'!$D$2:$O$2,0))} -> 120 | F38: {=index('Bill of Quantities'!$D:$O,match($B38,'Bill of Quantities'!$C:$C,0),match(F$2,'Bill of Quantities'!$D$2:$O$2,0))} -> 3.3929201e-06 | G38: {=index('Bill of Quantities'!$D:$O,match($B38,'Bill of Quantities'!$C:$C,0),match(G$2,'Bill of Quantities'!$D$2:$O$2,0))} -> 0.026125485 | H38: {=index('Bill of Quantities'!$D:$O,match($B38,'Bill of Quantities'!$C:$C,0),match(H$2,'Bill of Quantities'!$D$2:$O$2,0))} | I38: {=index('Bill of Quantities'!$D:$O,match($B38,'Bill of Quantities'!$C:$C,0),match(I$2,'Bill of Quantities'!$D$2:$O$2,0))} -> 1 | J38: {=index('Bill of Quantities'!$D:$O,match($B38,'Bill of Quantities'!$C:$C,0),match(J$2,'Bill of Quantities'!$D$2:$O$2,0))} -> Screw | ... N38: {=index('Bill of Quantities'!$D:$O,match($B38,'Bill of Quantities'!$C:$C,0),match(N$2,'Bill of Quantities'!$D$2:$O$2,0))} -> 0.09125 | O38: =$A38*F38 -> 0.00012214512 | P38: =$A38*G38 -> 0.94051744 | Q38: =$A38*H38 -> 0 | R38: =$A38*I38 -> 36 | S38: =$A38*L38 -> 2.16 | T38: =$A38*M38 -> 1.125 | U38: =$A38*N38 -> 3.285 | V38: =$A$31 -> Floor frame 2442 x 2442 | W38: {=A38*index('Project Costs'!A:A,match(V38,'Project Costs'!B:B,0),1)} -> 288 | X38: =W38*R38/60 -> 172.8
A40: Floor frame 2442 x 3053 | C40: 2442 | D40: 172 | E40: 3053 | V40: =V41 -> Floor frame 2442 x 3053 | Y40: =C40*E40*0.000001 -> 7.455426
A41: 2 | B41: ='Bill of Quantities'!C88 -> Floor Main Beam 46 x 146 x 2442 | C41: {=index('Bill of Quantities'!$D:$O,match($B41,'Bill of Quantities'!$C:$C,0),match(C$2,'Bill of Quantities'!$D$2:$O$2,0))} -> 46 | D41: {=index('Bill of Quantities'!$D:$O,match($B41,'Bill of Quantities'!$C:$C,0),match(D$2,'Bill of Quantities'!$D$2:$O$2,0))} -> 146 | E41: {=index('Bill of Quantities'!$D:$O,match($B41,'Bill of Quantities'!$C:$C,0),match(E$2,'Bill of Quantities'!$D$2:$O$2,0))} -> 2442 | F41: {=index('Bill of Quantities'!$D:$O,match($B41,'Bill of Quantities'!$C:$C,0),match(F$2,'Bill of Quantities'!$D$2:$O$2,0))} -> 0.016400472 | G41: {=index('Bill of Quantities'!$D:$O,match($B41,'Bill of Quantities'!$C:$C,0),match(G$2,'Bill of Quantities'!$D$2:$O$2,0))} -> 9.2006648 | H41: {=index('Bill of Quantities'!$D:$O,match($B41,'Bill of Quantities'!$C:$C,0),match(H$2,'Bill of Quantities'!$D$2:$O$2,0))} -> 14.820598 | I41: {=index('Bill of Quantities'!$D:$O,match($B41,'Bill of Quantities'!$C:$C,0),match(I$2,'Bill of Quantities'!$D$2:$O$2,0))} -> 5 | J41: {=index('Bill of Quantities'!$D:$O,match($B41,'Bill of Quantities'!$C:$C,0),match(J$2,'Bill of Quantities'!$D$2:$O$2,0))} -> Floor | ... N41: {=index('Bill of Quantities'!$D:$O,match($B41,'Bill of Quantities'!$C:$C,0),match(N$2,'Bill of Quantities'!$D$2:$O$2,0))} -> 4.3027084 | O41: =$A41*F41 -> 0.032800944 | P41: =$A41*G41 -> 18.40133 | Q41: =$A41*H41 -> 29.641196 | R41: =$A41*I41 -> 10 | S41: =$A41*L41 -> 8.2929168 | T41: =$A41*M41 -> 0.3125 | U41: =$A41*N41 -> 8.6054168 | V41: =$A$40 -> Floor frame 2442 x 3053 | W41: {=A41*index('Project Costs'!A:A,match(V41,'Project Costs'!B:B,0),1)} -> 0 | X41: =W41*R41/60 -> 0
A42: 5 | B42: ='Bill of Quantities'!C90 -> Floor Sub Beam 46 x 146 x 2952 | C42: {=index('Bill of Quantities'!$D:$O,match($B42,'Bill of Quantities'!$C:$C,0),match(C$2,'Bill of Quantities'!$D$2:$O$2,0))} -> 46 | D42: {=index('Bill of Quantities'!$D:$O,match($B42,'Bill of Quantities'!$C:$C,0),match(D$2,'Bill of Quantities'!$D$2:$O$2,0))} -> 146 | E42: {=index('Bill of Quantities'!$D:$O,match($B42,'Bill of Quantities'!$C:$C,0),match(E$2,'Bill of Quantities'!$D$2:$O$2,0))} -> 2952 | F42: {=index('Bill of Quantities'!$D:$O,match($B42,'Bill of Quantities'!$C:$C,0),match(F$2,'Bill of Quantities'!$D$2:$O$2,0))} -> 0.019825632 | G42: {=index('Bill of Quantities'!$D:$O,match($B42,'Bill of Quantities'!$C:$C,0),match(G$2,'Bill of Quantities'!$D$2:$O$2,0))} -> 11.12218 | H42: {=index('Bill of Quantities'!$D:$O,match($B42,'Bill of Quantities'!$C:$C,0),match(H$2,'Bill of Quantities'!$D$2:$O$2,0))} -> 17.915809 | I42: {=index('Bill of Quantities'!$D:$O,match($B42,'Bill of Quantities'!$C:$C,0),match(I$2,'Bill of Quantities'!$D$2:$O$2,0))} -> 5 | J42: {=index('Bill of Quantities'!$D:$O,match($B42,'Bill of Quantities'!$C:$C,0),match(J$2,'Bill of Quantities'!$D$2:$O$2,0))} -> Floor | ... N42: {=index('Bill of Quantities'!$D:$O,match($B42,'Bill of Quantities'!$C:$C,0),match(N$2,'Bill of Quantities'!$D$2:$O$2,0))} -> 5.3181676 | O42: =$A42*F42 -> 0.09912816 | P42: =$A42*G42 -> 55.610898 | Q42: =$A42*H42 -> 89.579045 | R42: =$A42*I42 -> 25 | S42: =$A42*L42 -> 25.809588 | T42: =$A42*M42 -> 0.78125 | U42: =$A42*N42 -> 26.590838 | V42: =$A$40 -> Floor frame 2442 x 3053 | W42: {=A42*index('Project Costs'!A:A,match(V42,'Project Costs'!B:B,0),1)} -> 0 | X42: =W42*R42/60 -> 0
A43: 8 | B43: ='Bill of Quantities'!C92 -> Floor Support Block 46 x 146 x 548 | C43: {=index('Bill of Quantities'!$D:$O,match($B43,'Bill of Quantities'!$C:$C,0),match(C$2,'Bill of Quantities'!$D$2:$O$2,0))} -> 46 | D43: {=index('Bill of Quantities'!$D:$O,match($B43,'Bill of Quantities'!$C:$C,0),match(D$2,'Bill of Quantities'!$D$2:$O$2,0))} -> 146 | E43: {=index('Bill of Quantities'!$D:$O,match($B43,'Bill of Quantities'!$C:$C,0),match(E$2,'Bill of Quantities'!$D$2:$O$2,0))} -> 548 | F43: {=index('Bill of Quantities'!$D:$O,match($B43,'Bill of Quantities'!$C:$C,0),match(F$2,'Bill of Quantities'!$D$2:$O$2,0))} -> 0.003680368 | G43: {=index('Bill of Quantities'!$D:$O,match($B43,'Bill of Quantities'!$C:$C,0),match(G$2,'Bill of Quantities'!$D$2:$O$2,0))} -> 2.0646864 | H43: {=index('Bill of Quantities'!$D:$O,match($B43,'Bill of Quantities'!$C:$C,0),match(H$2,'Bill of Quantities'!$D$2:$O$2,0))} -> 3.3258345 | I43: {=index('Bill of Quantities'!$D:$O,match($B43,'Bill of Quantities'!$C:$C,0),match(I$2,'Bill of Quantities'!$D$2:$O$2,0))} -> 5 | J43: {=index('Bill of Quantities'!$D:$O,match($B43,'Bill of Quantities'!$C:$C,0),match(J$2,'Bill of Quantities'!$D$2:$O$2,0))} -> Floor | ... N43: {=index('Bill of Quantities'!$D:$O,match($B43,'Bill of Quantities'!$C:$C,0),match(N$2,'Bill of Quantities'!$D$2:$O$2,0))} -> 1.1928646 | O43: =$A43*F43 -> 0.029442944 | P43: =$A43*G43 -> 16.517492 | Q43: =$A43*H43 -> 26.606676 | R43: =$A43*I43 -> 40 | S43: =$A43*L43 -> 8.2929168 | T43: =$A43*M43 -> 1.25 | U43: =$A43*N43 -> 9.5429168 | V43: =$A$40 -> Floor frame 2442 x 3053 | W43: {=A43*index('Project Costs'!A:A,match(V43,'Project Costs'!B:B,0),1)} -> 0 | X43: =W43*R43/60 -> 0
A44: 36 | B44: ='Bill of Quantities'!C93 -> Floor Plank Tongue Groove 22 x 96 x 2440 | C44: {=index('Bill of Quantities'!$D:$O,match($B44,'Bill of Quantities'!$C:$C,0),match(C$2,'Bill of Quantities'!$D$2:$O$2,0))} -> 22 | D44: {=index('Bill of Quantities'!$D:$O,match($B44,'Bill of Quantities'!$C:$C,0),match(D$2,'Bill of Quantities'!$D$2:$O$2,0))} -> 96 | E44: {=index('Bill of Quantities'!$D:$O,match($B44,'Bill of Quantities'!$C:$C,0),match(E$2,'Bill of Quantities'!$D$2:$O$2,0))} -> 2440 | F44: {=index('Bill of Quantities'!$D:$O,match($B44,'Bill of Quantities'!$C:$C,0),match(F$2,'Bill of Quantities'!$D$2:$O$2,0))} -> 0.00515328 | G44: {=index('Bill of Quantities'!$D:$O,match($B44,'Bill of Quantities'!$C:$C,0),match(G$2,'Bill of Quantities'!$D$2:$O$2,0))} -> 2.8909901 | H44: {=index('Bill of Quantities'!$D:$O,match($B44,'Bill of Quantities'!$C:$C,0),match(H$2,'Bill of Quantities'!$D$2:$O$2,0))} -> 4.6568594 | I44: {=index('Bill of Quantities'!$D:$O,match($B44,'Bill of Quantities'!$C:$C,0),match(I$2,'Bill of Quantities'!$D$2:$O$2,0))} -> 5 | J44: {=index('Bill of Quantities'!$D:$O,match($B44,'Bill of Quantities'!$C:$C,0),match(J$2,'Bill of Quantities'!$D$2:$O$2,0))} -> Floor | ... N44: {=index('Bill of Quantities'!$D:$O,match($B44,'Bill of Quantities'!$C:$C,0),match(N$2,'Bill of Quantities'!$D$2:$O$2,0))} -> 1.501594 | O44: =$A44*F44 -> 0.18551808 | P44: =$A44*G44 -> 104.07564 | Q44: =$A44*H44 -> 167.64694 | R44: =$A44*I44 -> 180 | S44: =$A44*L44 -> 48.432384 | T44: =$A44*M44 -> 5.625 | U44: =$A44*N44 -> 54.057384 | V44: =$A$40 -> Floor frame 2442 x 3053 | W44: {=A44*index('Project Costs'!A:A,match(V44,'Project Costs'!B:B,0),1)} -> 0 | X44: =W44*R44/60 -> 0
A45: =A44*5 -> 180 | B45: ='Bill of Quantities'!$C$23 -> Screw 3.5x40 small head screw SHS3540 | C45: {=index('Bill of Quantities'!$D:$O,match($B45,'Bill of Quantities'!$C:$C,0),match(C$2,'Bill of Quantities'!$D$2:$O$2,0))} -> 3.5 | D45: {=index('Bill of Quantities'!$D:$O,match($B45,'Bill of Quantities'!$C:$C,0),match(D$2,'Bill of Quantities'!$D$2:$O$2,0))} | E45: {=index('Bill of Quantities'!$D:$O,match($B45,'Bill of Quantities'!$C:$C,0),match(E$2,'Bill of Quantities'!$D$2:$O$2,0))} -> 40 | F45: {=index('Bill of Quantities'!$D:$O,match($B45,'Bill of Quantities'!$C:$C,0),match(F$2,'Bill of Quantities'!$D$2:$O$2,0))} -> 3.848451e-07 | G45: {=index('Bill of Quantities'!$D:$O,match($B45,'Bill of Quantities'!$C:$C,0),match(G$2,'Bill of Quantities'!$D$2:$O$2,0))} -> 0.0029633073 | H45: {=index('Bill of Quantities'!$D:$O,match($B45,'Bill of Quantities'!$C:$C,0),match(H$2,'Bill of Quantities'!$D$2:$O$2,0))} | I45: {=index('Bill of Quantities'!$D:$O,match($B45,'Bill of Quantities'!$C:$C,0),match(I$2,'Bill of Quantities'!$D$2:$O$2,0))} -> 1 | J45: {=index('Bill of Quantities'!$D:$O,match($B45,'Bill of Quantities'!$C:$C,0),match(J$2,'Bill of Quantities'!$D$2:$O$2,0))} -> Screw | ... N45: {=index('Bill of Quantities'!$D:$O,match($B45,'Bill of Quantities'!$C:$C,0),match(N$2,'Bill of Quantities'!$D$2:$O$2,0))} -> 0.077547556 | O45: =$A45*F45 -> 6.9272118e-05 | P45: =$A45*G45 -> 0.53339531 | Q45: =$A45*H45 -> 0 | R45: =$A45*I45 -> 180 | S45: =$A45*L45 -> 8.3335602 | T45: =$A45*M45 -> 5.625 | U45: =$A45*N45 -> 13.95856 | V45: =$A$40 -> Floor frame 2442 x 3053 | W45: {=A45*index('Project Costs'!A:A,match(V45,'Project Costs'!B:B,0),1)} -> 0 | X45: =W45*R45/60 -> 0
A46: 10 | B46: ='Bill of Quantities'!C29 -> Screw 6x100 semi threaded HBS6100 | C46: {=index('Bill of Quantities'!$D:$O,match($B46,'Bill of Quantities'!$C:$C,0),match(C$2,'Bill of Quantities'!$D$2:$O$2,0))} -> 6 | D46: {=index('Bill of Quantities'!$D:$O,match($B46,'Bill of Quantities'!$C:$C,0),match(D$2,'Bill of Quantities'!$D$2:$O$2,0))} | E46: {=index('Bill of Quantities'!$D:$O,match($B46,'Bill of Quantities'!$C:$C,0),match(E$2,'Bill of Quantities'!$D$2:$O$2,0))} -> 100 | F46: {=index('Bill of Quantities'!$D:$O,match($B46,'Bill of Quantities'!$C:$C,0),match(F$2,'Bill of Quantities'!$D$2:$O$2,0))} -> 2.8274334e-06 | G46: {=index('Bill of Quantities'!$D:$O,match($B46,'Bill of Quantities'!$C:$C,0),match(G$2,'Bill of Quantities'!$D$2:$O$2,0))} -> 0.021771237 | H46: {=index('Bill of Quantities'!$D:$O,match($B46,'Bill of Quantities'!$C:$C,0),match(H$2,'Bill of Quantities'!$D$2:$O$2,0))} | I46: {=index('Bill of Quantities'!$D:$O,match($B46,'Bill of Quantities'!$C:$C,0),match(I$2,'Bill of Quantities'!$D$2:$O$2,0))} -> 1 | J46: {=index('Bill of Quantities'!$D:$O,match($B46,'Bill of Quantities'!$C:$C,0),match(J$2,'Bill of Quantities'!$D$2:$O$2,0))} -> Screw | ... N46: {=index('Bill of Quantities'!$D:$O,match($B46,'Bill of Quantities'!$C:$C,0),match(N$2,'Bill of Quantities'!$D$2:$O$2,0))} -> 0.09125 | O46: =$A46*F46 -> 2.8274334e-05 | P46: =$A46*G46 -> 0.21771237 | Q46: =$A46*H46 -> 0 | R46: =$A46*I46 -> 10 | S46: =$A46*L46 -> 0.6 | T46: =$A46*M46 -> 0.3125 | U46: =$A46*N46 -> 0.9125 | V46: =$A$40 -> Floor frame 2442 x 3053 | W46: {=A46*index('Project Costs'!A:A,match(V46,'Project Costs'!B:B,0),1)} -> 0 | X46: =W46*R46/60 -> 0
A47: =A42*4+A43*4 -> 52 | B47: ='Bill of Quantities'!C30 -> Screw 6x120 semi threaded HBS6120 | C47: {=index('Bill of Quantities'!$D:$O,match($B47,'Bill of Quantities'!$C:$C,0),match(C$2,'Bill of Quantities'!$D$2:$O$2,0))} -> 6 | D47: {=index('Bill of Quantities'!$D:$O,match($B47,'Bill of Quantities'!$C:$C,0),match(D$2,'Bill of Quantities'!$D$2:$O$2,0))} | E47: {=index('Bill of Quantities'!$D:$O,match($B47,'Bill of Quantities'!$C:$C,0),match(E$2,'Bill of Quantities'!$D$2:$O$2,0))} -> 120 | F47: {=index('Bill of Quantities'!$D:$O,match($B47,'Bill of Quantities'!$C:$C,0),match(F$2,'Bill of Quantities'!$D$2:$O$2,0))} -> 3.3929201e-06 | G47: {=index('Bill of Quantities'!$D:$O,match($B47,'Bill of Quantities'!$C:$C,0),match(G$2,'Bill of Quantities'!$D$2:$O$2,0))} -> 0.026125485 | H47: {=index('Bill of Quantities'!$D:$O,match($B47,'Bill of Quantities'!$C:$C,0),match(H$2,'Bill of Quantities'!$D$2:$O$2,0))} | I47: {=index('Bill of Quantities'!$D:$O,match($B47,'Bill of Quantities'!$C:$C,0),match(I$2,'Bill of Quantities'!$D$2:$O$2,0))} -> 1 | J47: {=index('Bill of Quantities'!$D:$O,match($B47,'Bill of Quantities'!$C:$C,0),match(J$2,'Bill of Quantities'!$D$2:$O$2,0))} -> Screw | ... N47: {=index('Bill of Quantities'!$D:$O,match($B47,'Bill of Quantities'!$C:$C,0),match(N$2,'Bill of Quantities'!$D$2:$O$2,0))} -> 0.09125 | O47: =$A47*F47 -> 0.00017643184 | P47: =$A47*G47 -> 1.3585252 | Q47: =$A47*H47 -> 0 | R47: =$A47*I47 -> 52 | S47: =$A47*L47 -> 3.12 | T47: =$A47*M47 -> 1.625 | U47: =$A47*N47 -> 4.745 | V47: =$A$40 -> Floor frame 2442 x 3053 | W47: {=A47*index('Project Costs'!A:A,match(V47,'Project Costs'!B:B,0),1)} -> 0 | X47: =W47*R47/60 -> 0
A49: Floor frame 2442 x 3663 | C49: 2442 | D49: 172 | E49: 3053 | V49: =A49 -> Floor frame 2442 x 3663 | Y49: =C49*E49*0.000001 -> 7.455426
A50: 2 | B50: =B41 -> Floor Main Beam 46 x 146 x 2442 | C50: {=index('Bill of Quantities'!$D:$O,match($B50,'Bill of Quantities'!$C:$C,0),match(C$2,'Bill of Quantities'!$D$2:$O$2,0))} -> 46 | D50: {=index('Bill of Quantities'!$D:$O,match($B50,'Bill of Quantities'!$C:$C,0),match(D$2,'Bill of Quantities'!$D$2:$O$2,0))} -> 146 | E50: {=index('Bill of Quantities'!$D:$O,match($B50,'Bill of Quantities'!$C:$C,0),match(E$2,'Bill of Quantities'!$D$2:$O$2,0))} -> 2442 | F50: {=index('Bill of Quantities'!$D:$O,match($B50,'Bill of Quantities'!$C:$C,0),match(F$2,'Bill of Quantities'!$D$2:$O$2,0))} -> 0.016400472 | G50: {=index('Bill of Quantities'!$D:$O,match($B50,'Bill of Quantities'!$C:$C,0),match(G$2,'Bill of Quantities'!$D$2:$O$2,0))} -> 9.2006648 | H50: {=index('Bill of Quantities'!$D:$O,match($B50,'Bill of Quantities'!$C:$C,0),match(H$2,'Bill of Quantities'!$D$2:$O$2,0))} -> 14.820598 | I50: {=index('Bill of Quantities'!$D:$O,match($B50,'Bill of Quantities'!$C:$C,0),match(I$2,'Bill of Quantities'!$D$2:$O$2,0))} -> 5 | J50: {=index('Bill of Quantities'!$D:$O,match($B50,'Bill of Quantities'!$C:$C,0),match(J$2,'Bill of Quantities'!$D$2:$O$2,0))} -> Floor | ... N50: {=index('Bill of Quantities'!$D:$O,match($B50,'Bill of Quantities'!$C:$C,0),match(N$2,'Bill of Quantities'!$D$2:$O$2,0))} -> 4.3027084 | O50: =$A50*F50 -> 0.032800944 | P50: =$A50*G50 -> 18.40133 | Q50: =$A50*H50 -> 29.641196 | R50: =$A50*I50 -> 10 | S50: =$A50*L50 -> 8.2929168 | T50: =$A50*M50 -> 0.3125 | U50: =$A50*N50 -> 8.6054168 | V50: =$A$49 -> Floor frame 2442 x 3663 | W50: {=A50*index('Project Costs'!A:A,match(V50,'Project Costs'!B:B,0),1)} -> 0 | X50: =W50*R50/60 -> 0
A51: 5 | B51: =B42 -> Floor Sub Beam 46 x 146 x 2952 | C51: {=index('Bill of Quantities'!$D:$O,match($B51,'Bill of Quantities'!$C:$C,0),match(C$2,'Bill of Quantities'!$D$2:$O$2,0))} -> 46 | D51: {=index('Bill of Quantities'!$D:$O,match($B51,'Bill of Quantities'!$C:$C,0),match(D$2,'Bill of Quantities'!$D$2:$O$2,0))} -> 146 | E51: {=index('Bill of Quantities'!$D:$O,match($B51,'Bill of Quantities'!$C:$C,0),match(E$2,'Bill of Quantities'!$D$2:$O$2,0))} -> 2952 | F51: {=index('Bill of Quantities'!$D:$O,match($B51,'Bill of Quantities'!$C:$C,0),match(F$2,'Bill of Quantities'!$D$2:$O$2,0))} -> 0.019825632 | G51: {=index('Bill of Quantities'!$D:$O,match($B51,'Bill of Quantities'!$C:$C,0),match(G$2,'Bill of Quantities'!$D$2:$O$2,0))} -> 11.12218 | H51: {=index('Bill of Quantities'!$D:$O,match($B51,'Bill of Quantities'!$C:$C,0),match(H$2,'Bill of Quantities'!$D$2:$O$2,0))} -> 17.915809 | I51: {=index('Bill of Quantities'!$D:$O,match($B51,'Bill of Quantities'!$C:$C,0),match(I$2,'Bill of Quantities'!$D$2:$O$2,0))} -> 5 | J51: {=index('Bill of Quantities'!$D:$O,match($B51,'Bill of Quantities'!$C:$C,0),match(J$2,'Bill of Quantities'!$D$2:$O$2,0))} -> Floor | ... N51: {=index('Bill of Quantities'!$D:$O,match($B51,'Bill of Quantities'!$C:$C,0),match(N$2,'Bill of Quantities'!$D$2:$O$2,0))} -> 5.3181676 | O51: =$A51*F51 -> 0.09912816 | P51: =$A51*G51 -> 55.610898 | Q51: =$A51*H51 -> 89.579045 | R51: =$A51*I51 -> 25 | S51: =$A51*L51 -> 25.809588 | T51: =$A51*M51 -> 0.78125 | U51: =$A51*N51 -> 26.590838 | V51: =$A$49 -> Floor frame 2442 x 3663 | W51: {=A51*index('Project Costs'!A:A,match(V51,'Project Costs'!B:B,0),1)} -> 0 | X51: =W51*R51/60 -> 0
A52: 8 | B52: =B43 -> Floor Support Block 46 x 146 x 548 | C52: {=index('Bill of Quantities'!$D:$O,match($B52,'Bill of Quantities'!$C:$C,0),match(C$2,'Bill of Quantities'!$D$2:$O$2,0))} -> 46 | D52: {=index('Bill of Quantities'!$D:$O,match($B52,'Bill of Quantities'!$C:$C,0),match(D$2,'Bill of Quantities'!$D$2:$O$2,0))} -> 146 | E52: {=index('Bill of Quantities'!$D:$O,match($B52,'Bill of Quantities'!$C:$C,0),match(E$2,'Bill of Quantities'!$D$2:$O$2,0))} -> 548 | F52: {=index('Bill of Quantities'!$D:$O,match($B52,'Bill of Quantities'!$C:$C,0),match(F$2,'Bill of Quantities'!$D$2:$O$2,0))} -> 0.003680368 | G52: {=index('Bill of Quantities'!$D:$O,match($B52,'Bill of Quantities'!$C:$C,0),match(G$2,'Bill of Quantities'!$D$2:$O$2,0))} -> 2.0646864 | H52: {=index('Bill of Quantities'!$D:$O,match($B52,'Bill of Quantities'!$C:$C,0),match(H$2,'Bill of Quantities'!$D$2:$O$2,0))} -> 3.3258345 | I52: {=index('Bill of Quantities'!$D:$O,match($B52,'Bill of Quantities'!$C:$C,0),match(I$2,'Bill of Quantities'!$D$2:$O$2,0))} -> 5 | J52: {=index('Bill of Quantities'!$D:$O,match($B52,'Bill of Quantities'!$C:$C,0),match(J$2,'Bill of Quantities'!$D$2:$O$2,0))} -> Floor | ... N52: {=index('Bill of Quantities'!$D:$O,match($B52,'Bill of Quantities'!$C:$C,0),match(N$2,'Bill of Quantities'!$D$2:$O$2,0))} -> 1.1928646 | O52: =$A52*F52 -> 0.029442944 | P52: =$A52*G52 -> 16.517492 | Q52: =$A52*H52 -> 26.606676 | R52: =$A52*I52 -> 40 | S52: =$A52*L52 -> 8.2929168 | T52: =$A52*M52 -> 1.25 | U52: =$A52*N52 -> 9.5429168 | V52: =$A$49 -> Floor frame 2442 x 3663 | W52: {=A52*index('Project Costs'!A:A,match(V52,'Project Costs'!B:B,0),1)} -> 0 | X52: =W52*R52/60 -> 0
A53: 36 | B53: =B44 -> Floor Plank Tongue Groove 22 x 96 x 2440 | C53: {=index('Bill of Quantities'!$D:$O,match($B53,'Bill of Quantities'!$C:$C,0),match(C$2,'Bill of Quantities'!$D$2:$O$2,0))} -> 22 | D53: {=index('Bill of Quantities'!$D:$O,match($B53,'Bill of Quantities'!$C:$C,0),match(D$2,'Bill of Quantities'!$D$2:$O$2,0))} -> 96 | E53: {=index('Bill of Quantities'!$D:$O,match($B53,'Bill of Quantities'!$C:$C,0),match(E$2,'Bill of Quantities'!$D$2:$O$2,0))} -> 2440 | F53: {=index('Bill of Quantities'!$D:$O,match($B53,'Bill of Quantities'!$C:$C,0),match(F$2,'Bill of Quantities'!$D$2:$O$2,0))} -> 0.00515328 | G53: {=index('Bill of Quantities'!$D:$O,match($B53,'Bill of Quantities'!$C:$C,0),match(G$2,'Bill of Quantities'!$D$2:$O$2,0))} -> 2.8909901 | H53: {=index('Bill of Quantities'!$D:$O,match($B53,'Bill of Quantities'!$C:$C,0),match(H$2,'Bill of Quantities'!$D$2:$O$2,0))} -> 4.6568594 | I53: {=index('Bill of Quantities'!$D:$O,match($B53,'Bill of Quantities'!$C:$C,0),match(I$2,'Bill of Quantities'!$D$2:$O$2,0))} -> 5 | J53: {=index('Bill of Quantities'!$D:$O,match($B53,'Bill of Quantities'!$C:$C,0),match(J$2,'Bill of Quantities'!$D$2:$O$2,0))} -> Floor | ... N53: {=index('Bill of Quantities'!$D:$O,match($B53,'Bill of Quantities'!$C:$C,0),match(N$2,'Bill of Quantities'!$D$2:$O$2,0))} -> 1.501594 | O53: =$A53*F53 -> 0.18551808 | P53: =$A53*G53 -> 104.07564 | Q53: =$A53*H53 -> 167.64694 | R53: =$A53*I53 -> 180 | S53: =$A53*L53 -> 48.432384 | T53: =$A53*M53 -> 5.625 | U53: =$A53*N53 -> 54.057384 | V53: =$A$49 -> Floor frame 2442 x 3663 | W53: {=A53*index('Project Costs'!A:A,match(V53,'Project Costs'!B:B,0),1)} -> 0 | X53: =W53*R53/60 -> 0
