Workbook

Sheet Project Input
A1: Easy Housing - Calculation Template - 2026 | B1: Last update: 22-06-2026 by Wolf
A3: Instructions
A4: Open floor plan (.pdf) for which quote has to be made
A5: Fill out the input fields below
A6: Check if parameters like floor area correspond with plan
A7: Open Google Slide: "Easy Housing - Quotation Template Uganda - July 2025"
A8: Update the two tables in the slide
A9: Check if quotation values are properly linked to the template
A10: Do not adjust text or fields in slide template
A11: Create a copy of Google slide doc quote template (from the right country)
A12: Copy the input column in this spreadsheet to the Input Database from column K onwards (for future reference)
A13: Download Google Slide as .pdf and save in the shared quotation folder on the drive
A14: File name format: "YYMMDD - Easy Housing Quotation - Client Name in Location"
... A17: Sign the contract! :)
A20: Project input | B20: Input values | C20: Unit | D20: Comment
A21: Client input
A22: ='Price Calc'!A13 -> Client Name | B22: One Bedroom Compact Gable | C22: name | D22: Full name
A23: ='Price Calc'!A14 -> Contact Details | B23: +256 712 345 678 | C23: phone/mail | D23: Add phone or email
A24: ='Price Calc'!A23 -> Project Location | B24: Sagala | C24: location | D24: Add name municipality (village/town/city)
A25: ='Price Calc'!A24 -> Distance from factory | B25: 50 | C25: km | D25: With Google maps
A26: Date of input | B26: 46023 | C26: date | D26: DD/MM/YYYY
A27: ='Price Calc'!A15 -> Created by | B27: Wolf Bierens | C27: name | D27: Add your full name
A29: Building input (structure parameters)
A30: ='Price Calc'!A18 -> Easy Housing Typology | B30: Large Gable (9768) | D30: Select right typology (mm depth of building between brackets to check if not sure)
A31: Number of units (of exactly this type) | B31: 1 | C31: home(s) | D31: Make separate quotes for different models / plans
A32: ='Price Calc'!A60 -> Columns A (1221) | B32: 0 | C32: columns
A33: ='Price Calc'!A61 -> Columns B (2442) | B33: 2 | C33: columns
A34: ='Price Calc'!A62 -> Columns C (3053) | B34: 2 | C34: columns | D34: Do not use for Large A-Frames and Compact Gable | F34: Total GFA | G34: ='Price Calc'!H19 -> 109.2 | H34: sqm (without extra terraces)
A35: ='Price Calc'!A66 -> Partitions (length) | B35: 33 | C35: linear metres | F35: Estimate | G35: =0.3*G34 -> 32.76 | H35: Can be used for quick estimates
A36: ='Price Calc'!A65 -> Interior doors | B36: 5 | C36: pcs | F36: Estimate | G36: =sum(B38:B40) -> 5 | H36: Default estimations
A37: ='Price Calc'!A67 -> External doors & windows (area) | B37: 23.7 | C37: sqm | D37: Total alu - fill tool below - cell linked to D81 | F37: Estimate | G37: =0.2*'Project Costs'!B27 -> 24.812827
A38: Bedrooms | B38: 3 | C38: number
A39: Bathrooms | B39: 2 | C39: number | D39: Count for plumbing
A40: Other rooms | B40: 0 | C40: number
A41: Kitchen areas | B41: 1 | C41: number | D41: Count for plumbing. Kitchen islands count separately.
A43: Additional options
A44: ='Price Calc'!A41 -> Terrace | B44: 0 | C44: sqm | D44: Inside verandas under roof section are not counted (as they are within typology GFA)
A45: ='Price Calc'!A42 -> Pergola | B45: 0 | C45: sqm | D45: Price for open pergola without sheets
A46: ='Price Calc'!A43 -> Railing open | B46: 0 | C46: linear metres
A47: ='Price Calc'!A44 -> Railing semi-closed | B47: 0 | C47: linear metres
A48: ='Price Calc'!A68 -> Extra staircase (beyond the first) | B48: 0 | C48: pcs | D48: First staircase included - not counted
A49: ='Price Calc'!A40 -> Burglar bars | B49: 0 | C49: sqm | D49: Pro tip: use window tool below
A50: ='Price Calc'!A45 -> Wheelchair ramp | B50: 0 | C50: pcs
A51: ='Price Calc'!A46 -> Tiles | B51: 0 | C51: quote price | D51: case by case
A52: ='Price Calc'!A47 -> Sanitary wares | B52: 0 | C52: quote price | D52: case by case
A53: ='Price Calc'!A48 -> Biodigester | B53: 0 | C53: quote price | D53: Default 3M for normal home and 3.5M for large home (>90sqm)
A54: Other option(s) description | C54: text input | D54: Leave empty if no other options
A55: Other option(s) price | C55: price | D55: Leave empty if no other options
A59: Calculation Tool for Surface Of Windows and Exterior Doors
A60: Instructions: First put all orange cells below to zero and then fill out the amounts of standard windows/doors and in the last orange cell extra surface area of non-standard doors/windows
A61: Standard type | B61: Amount | C61: Surface per item | D61: Total area sqm per line | E61: Default name
A62: Entrance door 950 x 2388 | B62: 0 | C62: 2.2686 | D62: =B62*C62 -> 0
A63: Terrace swing doors 1700 x 2388 | B63: 0 | C63: 4.0596 | D63: =B63*C63 -> 0
A64: Sliding doors 1700 x 2388 | B64: 0 | C64: 4.0596 | D64: =B64*C64 -> 0
A65: Sliding doors 2100 x 2388 | B65: 0 | C65: =2.1*2.388 -> 5.0148 | D65: =B65*C65 -> 0
A66: Sliding doors 2300 x 2388 | B66: 0 | C66: 5.4924 | D66: =B66*C66 -> 0
A67: Sliding doors 2900 x 2388 | B67: 0 | C67: 6.9252 | D67: =B67*C67 -> 0
A68: Sliding doors 3510 x 2388 | B68: 0 | C68: 8.38188 | D68: =B68*C68 -> 0
A69: Bathroom window 500 x 1316 | B69: 2 | C69: 0.658 | D69: =B69*C69 -> 1.316
A70: Bathroom window 900 x 1316 | B70: 0 | C70: 1.1844 | D70: =B70*C70 -> 0
A71: Sliding window 1100 x 1316 | B71: 0 | C71: 1.4476 | D71: =B71*C71 -> 0
A72: Sliding window 1400 x 1316 | B72: 5 | C72: 1.8424 | D72: =B72*C72 -> 9.212 | E72: WS3
A73: Sliding window 1700 x 1316 | B73: 0 | C73: =1.7*1.316 -> 2.2372 | D73: =B73*C73 -> 0 | E73: WS4
A74: High window (fixed) 1100 x 1766 | B74: 0 | C74: 1.9426 | D74: =B74*C74 -> 0
A75: High window (fixed) 1700 x 1766 | B75: 0 | C75: 3.0022 | D75: =B75*C75 -> 0
A76: Full height window (fixed) 500 x 2366 | B76: 0 | C76: 1.183 | D76: =B76*C76 -> 0
A77: Full height window (fixed) 1100 x 2366 | B77: 0 | C77: 2.6026 | D77: =B77*C77 -> 0
A78: Panorama window (fixed) 1400 x 846 | B78: 0 | C78: =1.4*0.846 -> 1.1844 | D78: =B78*C78 -> 0
A79: Panorama window (fixed) 1700 x 846 | B79: 0 | C79: 1.4382 | D79: =B79*C79 -> 0
A80: Panorama window (fixed) 2300 x 846 | B80: 0 | C80: 1.9458 | D80: =B80*C80 -> 0 | E80: =SUM(B62:B80) -> 7 | F80: Sum count standard size windows
A81: Other windows and doors in sqm | B81: 0 | C81: sqm | D81: =B81 -> 0
A82: Total windows and doors area (sqm) | C82: Surface: | D82: =ROUND(SUM(D62:D81),1) -> 10.5 | E82: sqm - use this as input for aluminium surface area

Sheet Project Output
J2: HOW TO USE THIS QUOTATION (this column is not printed)
B3: Quotation | J3: 1. Enter the quote details on the Project Input tab — they flow here automatically via Price Calc.
J4: 2. Pick the country in the yellow cell C5 (Uganda = UGX, Kenya = KES). All prices and the currency switch instantly.
B5: Country (select): | C5: Uganda | E5: Quotation date: | F5: =TODAY() -> 46195 | H5: =IF($C$5="Kenya","KES","UGX") -> UGX | J5: 3. Review the client info, building specification and price breakdown.
B6: Quotation ref: | C6: ="EH-"&TEXT(TODAY(),"YYMMDD") -> EH-260622 | E6: Valid until: | F6: =TODAY()+30 -> 46225 | J6: 4. Optional: hide any additional-option rows showing “–” before sending, so the client only sees the included options.
J7: 5. Export to PDF: File ▸ Export As / Save As ▸ PDF (or Ctrl/Cmd+P ▸ Save as PDF). The print area and A4 page setup are preset to fit ~2 pages.
B8: CLIENT INFORMATION | J8: 6. Save with the file name: “YYMMDD - Easy Housing Quotation - Client in Location”, then send it with the floor-plan PDF.
B9: Client name | C9: ='Price Calc'!B13 -> One Bedroom Compact Gable
B10: Contact details | C10: ='Price Calc'!B14 -> +256 712 345 678 | J10: Note on macro buttons: one-click “Save to database” and “Export PDF” buttons need a macro-enabled workbook (.xlsm). This file is a standard .xlsx, so those run as the manual steps above. Ask if you would like an .xlsm version with the buttons wired up.
B11: Project location | C11: ='Price Calc'!B23 -> Sagala
B12: Distance from factory (km) | C12: ='Price Calc'!B24 -> 50
B13: Prepared by | C13: ='Price Calc'!B15 -> Wolf Bierens
B15: BUILDING SPECIFICATION
B16: Easy Housing typology | C16: ='Price Calc'!B18 -> Large Gable (9768)
B17: Gross floor area (per home) | C17: ='Price Calc'!B19 -> 109.2
B18: Terrace | C18: ='Price Calc'!B20 -> 0
B19: Bedrooms | C19: ='Price Calc'!B21 -> 3
B20: Bathrooms | C20: ='Price Calc'!B22 -> 2
B21: Exterior doors & windows | C21: ='Project Input'!B37 -> 23.7
B22: Number of units | C22: ='Project Input'!B31 -> 1
B24: PRICE BREAKDOWN (all amounts include VAT)
B25: Item | C25: Size | D25: Unit | E25: ="Unit price ("&$H$5&")" -> Unit price (UGX) | F25: ="Amount ("&$H$5&")" -> Amount (UGX)
B26: Complete Easy Home (per unit) | F26: =IF($C$5="Kenya",'Price Calc'!K30,'Price Calc'!E30) -> 177216000
B27: Includes: all labour & overhead · full structure · paintworks · electrical installation · plumbing (where applicable). See price list for full inclusions.
B28: Additional options
B29: Burglar bars | C29: ='Price Calc'!B40 -> 0 | D29: ='Price Calc'!C40 -> sqm | E29: =IF($C$5="Kenya",'Price Calc'!J40,'Price Calc'!D40) -> 250000 | F29: =IF($C$5="Kenya",'Price Calc'!K40,'Price Calc'!E40) -> 0
B30: Terrace | C30: ='Price Calc'!B41 -> 0 | D30: ='Price Calc'!C41 -> sqm | E30: =IF($C$5="Kenya",'Price Calc'!J41,'Price Calc'!D41) -> 300000 | F30: =IF($C$5="Kenya",'Price Calc'!K41,'Price Calc'!E41) -> 0
B31: Pergola | C31: ='Price Calc'!B42 -> 0 | D31: ='Price Calc'!C42 -> sqm | E31: =IF($C$5="Kenya",'Price Calc'!J42,'Price Calc'!D42) -> 100000 | F31: =IF($C$5="Kenya",'Price Calc'!K42,'Price Calc'!E42) -> 0
B32: Railing (open) | C32: ='Price Calc'!B43 -> 0 | D32: ='Price Calc'!C43 -> m1 | E32: =IF($C$5="Kenya",'Price Calc'!J43,'Price Calc'!D43) -> 90000 | F32: =IF($C$5="Kenya",'Price Calc'!K43,'Price Calc'!E43) -> 0
B33: Railing (semi-closed) | C33: ='Price Calc'!B44 -> 0 | D33: ='Price Calc'!C44 -> m1 | E33: =IF($C$5="Kenya",'Price Calc'!J44,'Price Calc'!D44) -> 180000 | F33: =IF($C$5="Kenya",'Price Calc'!K44,'Price Calc'!E44) -> 0
B34: Wheelchair ramp | C34: ='Price Calc'!B45 -> 0 | D34: ='Price Calc'!C45 -> pcs | E34: =IF($C$5="Kenya",'Price Calc'!J45,'Price Calc'!D45) -> 1500000 | F34: =IF($C$5="Kenya",'Price Calc'!K45,'Price Calc'!E45) -> 0
B35: Tiles | D35: total | F35: =IF($C$5="Kenya",'Price Calc'!K46,'Price Calc'!E46) -> 0
B36: Sanitary wares | D36: total | F36: =IF($C$5="Kenya",'Price Calc'!K47,'Price Calc'!E47) -> 0
B37: Biodigester | D37: total | F37: =IF($C$5="Kenya",'Price Calc'!K48,'Price Calc'!E48) -> 0
B38: ='Price Calc'!A49 -> Other options: | F38: =IF($C$5="Kenya",'Price Calc'!K49,'Price Calc'!E49)
B39: Total additional options | F39: =IF($C$5="Kenya",'Price Calc'!K50,'Price Calc'!E50) -> 0
B40: Total price per home (incl. options) | F40: =IF($C$5="Kenya",'Price Calc'!K52,'Price Calc'!E52) -> 177216000
B41: Number of homes | C41: ='Price Calc'!B54 -> 1
B42: ="GRAND TOTAL · incl. VAT · "&$H$5 -> GRAND TOTAL · incl. VAT · UGX | E42: =IF($C$5="Kenya",'Price Calc'!K54,'Price Calc'!E54) -> 177216000
B45: WHAT'S INCLUDED
B46: • Full prefabricated timber structure, delivered and assembled on your prepared foundation.
B47: • All interior and exterior paintworks and standard finishings.
B48: • Electrical installation (wiring, points, distribution board) ready for grid or solar connection.
B49: • Plumbing rough-in and fixtures for the bathrooms and kitchen areas quoted.
B50: • Standard aluminium windows and exterior doors as per the building specification.
B51: • Project management, transport to site and aftercare warranty.
B52: TIMELINE & SITE REQUIREMENTS
B53: Production lead time | C53: Approx. 6–10 weeks from signed contract and deposit, depending on typology and current workshop load.
B54: On-site assembly | C54: Approx. 2–6 weeks after delivery, subject to typology, weather and site access.
B55: Site preparation (by client) | C55: Level, accessible plot; foundation set-out per our drawings; secure storage for materials.
B56: Access | C56: Road access for a delivery truck to within reasonable distance of the build location.
B57: TERMS & DISCLAIMERS
B58: • This quotation is valid for 30 days from the quotation date. Prices thereafter may be subject to revision.
B59: • All amounts are inclusive of VAT and stated in the selected country currency (UGX or KES).
B60: • Transport to site is included for the stated distance.
B61: • This quotation is indicative and based on the information provided.
B62: • No rights can be derived from this quotation. It does not constitute a binding contract until a construction agreement is signed by both parties.
B64: Easy Housing · Sustainable, Social, Scalable · www.easyhousing.org

Sheet Project Budget
B2: EASY HOUSING — PROJECT BUDGET OVERVIEW
B3: Internal PM budget & procurement tracker · cost basis, ex VAT · use together with the Bill of Quantities tab
B5: Client / project | C5: ='Project Costs'!E24 -> One Bedroom Compact Gable | E5: Typology | F5: ='Project Costs'!E23 -> Large Gable (9768)
B6: Project code | C6: ='Project Costs'!B12 -> EH-000 | E6: GFA (per home) | F6: ='Project Costs'!B24 -> 109.17702
B7: Location | C7: ='Project Input'!B24 -> Sagala | E7: Number of units | F7: ='Project Input'!B31 -> 1
B9: All amounts below are per single home, in the project currency, excluding VAT. Enter actuals as the project progresses; variance updates automatically. Multiply by the number of units (above) for the project total.
B11: 1. MATERIALS & SUPPLIES
B12: Budget line | C12: ="Budget ("&'Project Costs'!$B$38&")" -> Budget (UGX) | D12: ="Actual ("&'Project Costs'!$B$38&")" -> Actual (UGX) | E12: Variance | F12: Source / note
B13: Timber (beams & planks) | C13: ='Project Costs'!M35 -> 14118331 | D13: 0 | E13: =C13-D13 -> 14118331 | F13: Project Costs M34
B14: Plywood | C14: ='Project Costs'!M34 -> 5860761.7 | D14: 0 | E14: =C14-D14 -> 5860761.7 | F14: Project Costs M33
B15: Roof sheets, screws, ridges, gutters | C15: ='Project Costs'!M28 -> 5912462 | D15: 0 | E15: =C15-D15 -> 5912462 | F15: Project Costs M27
B16: Roof insulation | C16: ='Project Costs'!M36 -> 714285 | D16: 0 | E16: =C16-D16 -> 714285 | F16: Project Costs M35
B17: Wall insulation | C17: ='Project Costs'!M37 -> 1200668 | D17: 0 | E17: =C17-D17 -> 1200668 | F17: Project Costs M36
B18: Foundation blocks | C18: ='Project Costs'!M25 -> 4005262.2 | D18: 0 | E18: =C18-D18 -> 4005262.2 | F18: Project Costs M24
B19: Cement boards (bathrooms) | C19: ='Project Costs'!M33 -> 2640698.3 | D19: 0 | E19: =C19-D19 -> 2640698.3 | F19: Project Costs M32
B20: Interior doors | C20: ='Project Costs'!M27 -> 3700000 | D20: 0 | E20: =C20-D20 -> 3700000 | F20: Project Costs M26
B21: Subtotal | C21: =SUM(C13:C20) -> 38152468 | D21: =SUM(D13:D20) -> 0 | E21: =SUM(E13:E20) -> 38152468
B23: 2. SUBCONTRACTORS (specialist trades)
B24: Budget line | C24: ="Budget ("&'Project Costs'!$B$38&")" -> Budget (UGX) | D24: ="Actual ("&'Project Costs'!$B$38&")" -> Actual (UGX) | E24: Variance | F24: Source / note
B25: Aluminium doors & windows (fabrication + install) | C25: =SUM('Project Costs'!J100:J116) -> 14030400 | D25: 0 | E25: =C25-D25 -> 14030400 | F25: Project Costs J99:J115 — incl. bulk-area input
B26: Paintworks (interior & exterior) | C26: ='Project Costs'!M29 -> 10974959 | D26: 0 | E26: =C26-D26 -> 10974959 | F26: Project Costs M28
B27: Electrical installation (MEP) | C27: ='Project Costs'!M31 -> 9188276.8 | D27: 0 | E27: =C27-D27 -> 9188276.8 | F27: Project Costs M30
B28: Plumbing (MEP) | C28: ='Project Costs'!M32 -> 3729425.6 | D28: 0 | E28: =C28-D28 -> 3729425.6 | F28: Project Costs M31
B29: Subtotal | C29: =SUM(C25:C28) -> 37923062 | D29: =SUM(D25:D28) -> 0 | E29: =SUM(E25:E28) -> 37923062
B31: 3. LOGISTICS & TRANSPORT
B32: Budget line | C32: ="Budget ("&'Project Costs'!$B$38&")" -> Budget (UGX) | D32: ="Actual ("&'Project Costs'!$B$38&")" -> Actual (UGX) | E32: Variance | F32: Source / note
B33: Transport of frames to site (within 100 km) | C33: ='Project Costs'!M30 -> 2019774.9 | D33: 0 | E33: =C33-D33 -> 2019774.9 | F33: Project Costs M29
B34: Subtotal | C34: =SUM(C33) -> 2019774.9 | D34: =SUM(D33) -> 0 | E34: =SUM(E33) -> 2019774.9
B36: PROCUREMENT BUDGET — per home | C36: =C21+C29+C34 -> 78095305 | D36: =D21+D29+D34 -> 0 | E36: =E21+E29+E34 -> 78095305
B37: Project total — procurement (× number of units) | C37: =C36*'Project Input'!B31 -> 78095305
B39: 4. LABOUR OVERVIEW (own crew — for scheduling)
B40: Labour activity | C40: Budget (days) | D40: Actual (days) | E40: Variance | F40: Source / note
B41: Prefabrication labour | C41: ='Project Costs'!R25 -> 70 | D41: 0 | E41: =C41-D41 -> 70
B42: Foundation casting & placement | C42: ='Project Costs'!R26 -> 11 | D42: 0 | E42: =C42-D42 -> 11
B43: Site placement labour | C43: ='Project Costs'!R27 -> 55 | D43: 0 | E43: =C43-D43 -> 55
B44: Site finishings | C44: ='Project Costs'!R28 -> 30 | D44: 0 | E44: =C44-D44 -> 30
B45: Paintworks (on site) | C45: ='Project Costs'!R29 -> 43 | D45: 0 | E45: =C45-D45 -> 43
B46: Project manager | C46: ='Project Costs'!R30 -> 13 | D46: 0 | E46: =C46-D46 -> 13
B47: Total labour | C47: =SUM(C41:C46) -> 222 | D47: =SUM(D41:D46) -> 0 | E47: =SUM(E41:E46) -> 222
B48: Day rate (carpenter, ex VAT) — assumption | C48: {=INDEX('Location Data'!N:N,MATCH('Project Costs'!B11,'Location Data'!A:A,0))} -> 15 | E48: Source: Location Data
B49: Indicative labour cost (total days × day rate × FX) | C49: =C47*C48*'Project Costs'!B39 -> 12321000 | E49: Indicative only — largely already inside the packages above; do not add to procurement total.
B51: 5. EXTRA OPTIONS — cost vs. price (per home)
B52: Option | C52: Qty | D52: Est. cost | E52: Client price | F52: Margin
B53: Burglar bars | C53: ='Project Input'!B49 -> 0 | D53: 0 | E53: =IF('Project Costs'!$B$38="UGX",'Price Calc'!E40,IF('Project Costs'!$B$38="KSH",'Price Calc'!K40,"")) -> 0 | F53: =IF(AND(ISNUMBER(E53),ISNUMBER(D53)),E53-D53,"") -> 0
B54: Terrace | C54: ='Project Input'!B44 -> 0 | D54: 0 | E54: =IF('Project Costs'!$B$38="UGX",'Price Calc'!E41,IF('Project Costs'!$B$38="KSH",'Price Calc'!K41,"")) -> 0 | F54: =IF(AND(ISNUMBER(E54),ISNUMBER(D54)),E54-D54,"") -> 0
B55: Pergola | C55: ='Project Input'!B45 -> 0 | D55: 0 | E55: =IF('Project Costs'!$B$38="UGX",'Price Calc'!E42,IF('Project Costs'!$B$38="KSH",'Price Calc'!K42,"")) -> 0 | F55: =IF(AND(ISNUMBER(E55),ISNUMBER(D55)),E55-D55,"") -> 0
B56: Railing (open) | C56: ='Project Input'!B46 -> 0 | D56: 0 | E56: =IF('Project Costs'!$B$38="UGX",'Price Calc'!E43,IF('Project Costs'!$B$38="KSH",'Price Calc'!K43,"")) -> 0 | F56: =IF(AND(ISNUMBER(E56),ISNUMBER(D56)),E56-D56,"") -> 0
B57: Railing (semi-closed) | C57: ='Project Input'!B47 -> 0 | D57: 0 | E57: =IF('Project Costs'!$B$38="UGX",'Price Calc'!E44,IF('Project Costs'!$B$38="KSH",'Price Calc'!K44,"")) -> 0 | F57: =IF(AND(ISNUMBER(E57),ISNUMBER(D57)),E57-D57,"") -> 0
B58: Wheelchair ramp | C58: ='Project Input'!B50 -> 0 | D58: 0 | E58: =IF('Project Costs'!$B$38="UGX",'Price Calc'!E45,IF('Project Costs'!$B$38="KSH",'Price Calc'!K45,"")) -> 0 | F58: =IF(AND(ISNUMBER(E58),ISNUMBER(D58)),E58-D58,"") -> 0
B59: Extra staircase | C59: ='Project Input'!B48 -> 0 | D59: 0 | E59: =IF('Project Costs'!$B$38="UGX",'Price Calc'!E68,IF('Project Costs'!$B$38="KSH",'Price Calc'!G68,"")) -> 0 | F59: =IF(AND(ISNUMBER(E59),ISNUMBER(D59)),E59-D59,"") -> 0
B60: Tiles | C60: ="total" -> total | D60: 0 | E60: =IF('Project Costs'!$B$38="UGX",'Price Calc'!E46,IF('Project Costs'!$B$38="KSH",'Price Calc'!K46,"")) -> 0 | F60: =IF(AND(ISNUMBER(E60),ISNUMBER(D60)),E60-D60,"") -> 0
B61: Sanitary wares | C61: ="total" -> total | D61: 0 | E61: =IF('Project Costs'!$B$38="UGX",'Price Calc'!E47,IF('Project Costs'!$B$38="KSH",'Price Calc'!K47,"")) -> 0 | F61: =IF(AND(ISNUMBER(E61),ISNUMBER(D61)),E61-D61,"") -> 0
B62: Biodigester | C62: ="total" -> total | D62: 0 | E62: =IF('Project Costs'!$B$38="UGX",'Price Calc'!E48,IF('Project Costs'!$B$38="KSH",'Price Calc'!K48,"")) -> 0 | F62: =IF(AND(ISNUMBER(E62),ISNUMBER(D62)),E62-D62,"") -> 0
B63: Total options | D63: =SUM(D53:D62) -> 0 | E63: =SUM(E53:E62) -> 0 | F63: =SUM(F53:F62) -> 0
B64: Client price links automatically for Uganda/Kenya projects (incl. VAT, from Price Calc); enter the estimated cost (ex VAT) to see margin. For other countries, enter both manually.
B66: RECONCILIATION TO FULL PROJECT COST
B67: Line | C67: ="Per home ("&'Project Costs'!$B$38&")" -> Per home (UGX) | F67: Note
B68: Direct procurement budget (per home, ex VAT) | C68: =C36 -> 78095305 | F68: Materials + subcontractors + logistics
B69: Balance: own labour, overhead, finishings, contingency | C69: ='Project Costs'!B49-C36 -> 45013382 | F69: Difference vs. total cost
B70: Total project cost (per home, ex VAT) | C70: ='Project Costs'!B49 -> 123108687 | F70: Project Costs B48
B71: Total project cost (per home, incl. VAT) | C71: ='Project Costs'!B52 -> 1.5979508e+08 | F71: Project Costs B51

Sheet Project Costs
A5: Easy Housing - Calculation Template 2026
A6: ! Do not share sheets or extracts externally unless authorised !
A8: Project parameters | I8: Calculations | J8: Typologies | L8: Floor frame A | M8: Floor frame B | N8: Floor frame C | O8: Floor frame D (3363) | P8: Foundation | Q8: Wall B low | R8: Wall C low | S8: Wall B high | T8: Wall C high | U8: Roof frame 1221 x 5685 (mono pitch) | V8: Roof frame 1598x 5685 (mono pitch edge) | W8: Roof frame 1221 x 3574 (compact gable) | X8: Roof frame 1689 x 3574 (compact gable edge) | Y8: Roof frame 1221 x 4194 (standard gable) | Z8: Roof frame 1689 x 4194 (standard gable edge) | AA8: Roof frame 1221 x 5435 (large gable) | AB8: Roof frame 1689 x 5435 (large gable edge) | AC8: Roof frame 1221 x 5780 (clerestory upper) | AD8: Roof frame 1689 x 5780 (clerestory upper edge) | AE8: Roof frame 1221 x 4194 (clerestory lower) | AF8: Roof frame 1689 x 4194 (clerestory lower edge)
J9: ='Price Calc'!A88 -> Mono Pitch (4884) | L9: =2*$E$25 -> 0 | M9: =2*$E$26 -> 4 | N9: =2*$E$27 -> 4 | O9: =2*$E$27 -> 4 | P9: =3*(SUM($E$25:$E$27)+1) -> 15 | Q9: =E26+0.5*E25 -> 2 | R9: =E27 -> 2 | S9: =4+E26+0.5*E25 -> 6 | T9: =E27 -> 2 | U9: =E25+2*E26+2.5*E27-2 -> 7 | V9: 2
J10: ='Price Calc'!A89 -> Small Gable (4884) | L10: =L9 -> 0 | M10: =M9 -> 4 | N10: =N9 -> 4 | O10: =O9 -> 4 | P10: =P9 -> 15 | Q10: =Q9 -> 2 | R10: =R9 -> 2 | S10: =S9 -> 6 | T10: =T9 -> 2 | Y10: =Y12 -> 14 | Z10: =Z12 -> 4
A11: Project location parameters | B11: Kampala, Uganda | J11: ='Price Calc'!A90 -> Compact Gable (6106) | L11: 0 | M11: 0 | N11: =E26*2+E25 -> 4 | O11: =2*$E$27 -> 4 | P11: =3*(SUM($E$25:$E$27)+1) -> 15 | Q11: =E26*2+E25 -> 4 | R11: 0 | S11: 0 | T11: 4 | W11: =(E25+2*E26+2.5*E27-2)*2 -> 14 | X11: 4
A12: Project code | B12: EH-000 | J12: ='Price Calc'!A91 -> Standard Gable (7326) | L12: =3*$E$25 -> 0 | M12: =3*$E$26 -> 6 | N12: =3*$E$27 -> 6 | O12: =2*$E$27 -> 4 | P12: =4*(SUM($E$25:$E$27)+1) -> 20 | Q12: =E26*2+E25 -> 4 | R12: =E27*2 -> 4 | S12: 6 | T12: 0 | Y12: =(E25+2*E26+2.5*E27-2)*2 -> 14 | Z12: 4
A13: Project name | J13: ='Price Calc'!A92 -> Large Gable (9768) | L13: =4*$E$25 -> 0 | M13: =4*$E$26 -> 8 | N13: =4*$E$27 -> 8 | O13: =2*$E$27 -> 4 | P13: =5*(SUM($E$25:$E$27)+1) -> 25 | Q13: =E26*2+E25 -> 4 | R13: =E27*2 -> 4 | S13: 8 | T13: 0 | AA13: =Y12 -> 14 | AB13: =Z12 -> 4
A14: Project Location | B14: Greater Kampala (<100km from factory) | J14: ='Price Calc'!A93 -> Standard Clerestory (7326) | L14: =3*$E$25 -> 0 | M14: =3*$E$26 -> 6 | N14: =3*$E$27 -> 6 | O14: =2*$E$27 -> 4 | P14: =4*(SUM($E$25:$E$27)+1) -> 20 | Q14: =E26+0.5*E25 -> 2 | R14: =E27 -> 2 | S14: =6+E26+0.5*E25 -> 8 | T14: =E27 -> 2 | AC14: =U9 -> 7 | AD14: 2 | AE14: =AC14 -> 7 | AF14: 2
A15: Client name | B15: Example calculation | J15: ='Price Calc'!A94 -> Large Clerestory (8547) | L15: =3.5*$E$25 -> 0 | M15: =3.5*$E$26 -> 7 | N15: =3.5*$E$27 -> 7 | O15: =2*$E$27 -> 4 | P15: =5*(SUM($E$25:$E$27)+1) -> 25 | Q15: =Q14 -> 2 | R15: =R14 -> 2 | S15: =S14+1 -> 9 | T15: =T14 -> 2 | AC15: =AC14 -> 7 | AD15: 2 | AE15: =AC14 -> 7 | AF15: 2
J16: ='Price Calc'!A95 -> A Frame Compact (3663) | O16: =E26+0.5*E25 -> 2 | P16: =2*(SUM($E$25:$E$27)+1) -> 10 | T16: 2 | U16: =2*(E25+2*E26+2.5*E27-2) -> 14 | V16: 4
J17: ='Price Calc'!A96 -> A Frame Standard (4884) | M17: =2*E26+E25 -> 4 | O17: =2*$E$27 -> 4 | P17: =3*(SUM($E$25:$E$27)+1) -> 15 | S17: 4 | U17: =2*(E25+2*E26+2.5*E27-2) -> 14 | V17: 4
J18: ='Price Calc'!A97 -> A Frame Large (6106) | N18: =2*E26 -> 4 | O18: =2*$E$27 -> 4 | P18: =3*(SUM($E$25:$E$27)+1) -> 15 | T18: 4 | U18: =2*(E25+2*E26+2.5*E27-2) -> 14 | V18: 4
A19: Date created | B19: =TODAY() -> 46195 | I19: Selected: | J19: =E23 -> Large Gable (9768) | L19: =INDEX(L9:L18,MATCH($J$19,$J$9:$J$18,0),1) -> 0 | M19: =INDEX(M9:M18,MATCH($J$19,$J$9:$J$18,0),1) -> 8 | N19: =INDEX(N9:N18,MATCH($J$19,$J$9:$J$18,0),1) -> 8 | O19: =INDEX(O9:O18,MATCH($J$19,$J$9:$J$18,0),1) -> 4 | P19: =INDEX(P9:P18,MATCH($J$19,$J$9:$J$18,0),1) -> 25 | Q19: =INDEX(Q9:Q18,MATCH($J$19,$J$9:$J$18,0),1) -> 4 | R19: =INDEX(R9:R18,MATCH($J$19,$J$9:$J$18,0),1) -> 4 | S19: =INDEX(S9:S18,MATCH($J$19,$J$9:$J$18,0),1) -> 8 | ... AF19: =INDEX(AF9:AF18,MATCH($J$19,$J$9:$J$18,0),1)
A22: Building parameters | D22: Quick Input Tool - now linked to input tab, do not overwrite | J22: Subcontractor / supplier budget overview * | O22: Labour time overview
A23: Building typology | B23: =E23 -> Large Gable (9768) | D23: Typology | E23: ='Project Input'!B30 -> Large Gable (9768)
A24: Gross floor surface (sqm) | B24: =SUM(V69:V71)+0.044*(A76*2.442+A77*3.053+A78*2.442+A79*3.053) -> 109.17702 | D24: Name | E24: ='Project Input'!B22 -> One Bedroom Compact Gable | J24: Description | M24: =B38&" ex VAT **" -> UGX ex VAT ** | O24: Description | R24: Labour days
A25: Decking surface area (sqm) | B25: =SUM(V73:V75) -> 0 | D25: Floor A - 1221 | E25: ='Project Input'!B32 -> 0 | F25: columns | J25: Foundation blocks | M25: =J122 -> 4005262.2 | O25: Prefabrication labour | R25: =ROUNDUP(SUM(T69:T95)/8,0) -> 70
A26: Net floor surface without decking/walls | B26: =SUM(V69:V71)-0.099*(A76*2.442+A77*3.053+A78*2.442+A79*3.053) -> 103.24024 | D26: Floor B - 2442 | E26: ='Project Input'!B33 -> 2 | F26: columns | G26: use for compact gable | J26: Aluminium doors and windows | M26: =SUM(J100:J115) -> 0 | O26: Foundation casting and placement | R26: =ROUND(T122/8,0) -> 11
A27: Exterior wall surface (sqm) | B27: =SUM(V76:V79) -> 124.06414 | D27: Floor C - 3053 | E27: ='Project Input'!B34 -> 2 | F27: columns | J27: Interior doors | M27: =J123 -> 3700000 | O27: Site placement labour | R27: =ROUNDUP(0.5*$B$24,0) -> 55
A28: Outer windows and doors (sqm) | B28: =SUM(V100:V115)+A116 -> 23.7 | D28: Partitions | E28: ='Project Input'!B35 -> 33 | F28: m1 / default at 30% of GFA | G28: 0.3 | H28: =G23*B19 | J28: Roof sheets, inc screws, ridges, gutters, labour | M28: =J124 -> 5912462 | O28: Site finishings (steps, fascia, skirts, substrate) | R28: =ROUNDUP(B24*0.2+2+A126*0.2+A127,0) -> 30
A29: Net facade surface (sqm) | B29: =B27-B28 -> 100.36414 | D29: Interior doors | E29: ='Project Input'!B36 -> 5 | F29: pcs | J29: Paint works interior and exterior | M29: =J125 -> 10974959 | O29: Paint works (on site) | R29: =ROUND(T125/8,0) -> 43
A30: Partition wall surface (sqm) | B30: =V80*2 -> 198 | D30: Aluminium | E30: ='Project Input'!B37 -> 23.7 | F30: sqm / default at 20% of ext wall surface | G30: 0.2 | H30: =G25*B22 | J30: Truck frames transport to sites <100 km | M30: =J138 -> 2019774.9 | O30: Project manager | R30: =ROUND(2+0.1*B24,0) -> 13
A31: Roof surface (sqm) | B31: =SUM(V83:V94) -> 130.62967 | D31: Extra ext. wall | E31: 0 | F31: grid steps 61cm (indents etc) | J31: Electricity | M31: =J156 -> 9188276.8 | O31: Total | R31: =SUM(R25:R30) -> 222 | S31: days
A32: Number ext doors and windows (if filled) | B32: =SUM(A100:A115) -> 0 | D32: Veranda A | E32: 0 | F32: frames | J32: Plumbing | M32: =J157 -> 3729425.6 | R32: =R31*8 -> 1776 | S32: hours
A33: Foundation type | B33: ='Bill of Quantities'!C35 -> Foundation block | D33: Veranda B | E33: 0 | F33: frames | J33: Cement boards bathrooms | M33: =J127 -> 2640698.3
A34: Foundation average height (mm) | B34: 400 | D34: Veranda C | E34: =ROUNDUP('Project Input'!B44/(3.05*2.44),0) -> 0 | F34: frames | J34: Plywood | M34: =SUM('Bill of Quantities'!P52:P55)*B39 -> 5860761.7
A35: Distance from workshop (km) | B35: ='Project Input'!B25 -> 50 | D35: Bathrooms | E35: ='Project Input'!B39 -> 2 | F35: bathroom(s) | J35: Timber | M35: ='Timber Order'!H35*'Bill of Quantities'!D14*B39 -> 14118331
J36: Roof insulation | M36: ='Bill of Quantities'!P83*B39 -> 714285
A37: Price information (outdated) | J37: Wall insulation | M37: ='Bill of Quantities'!P84*B39 -> 1200668
A38: ='Location Data'!C5 -> Currency | B38: {=INDEX('Location Data'!C:C,MATCH($B$11,'Location Data'!A:A,0),1)} -> UGX | J38: Total | M38: =SUM(M24:M37) -> 64064905
A39: ='Location Data'!D5 -> Conversion rate from USD | B39: {=INDEX('Location Data'!D:D,MATCH($B$11,'Location Data'!A:A,0),1)} -> 3700
A40: Margin | B40: 0.1
A41: ='Location Data'!E5 -> Value added tax (VAT) | B41: {=INDEX('Location Data'!E:E,MATCH($B$11,'Location Data'!A:A,0),1)} -> 0.18 | J41: * subcontractor budgets are exclusive of VAT
A42: Cost price in USD ex VAT | B42: =D64 -> 33272.618 | J42: ** budgets incl all material, labour,transportation costs
A43: Margin | B43: =B42*B40 -> 3327.2618 | D43: Standard models
A44: Licence Fee Easy Building | B44: =C135 -> 4367.081
A45: Sales price in USD ex VAT | B45: =B42+B43 -> 36599.88 | D45: Typology | E45: =J9 -> Mono Pitch (4884) | F45: =E45 -> Mono Pitch (4884) | G45: =F45 -> Mono Pitch (4884) | H45: =G45 -> Mono Pitch (4884) | I45: Compact Gable 6106 | J45: Compact Gable 6106 | K45: Compact Gable 6106 | L45: Compact Gable 6106 | M45: Compact Gable 6106 | N45: Standard Gable 7326 | O45: Standard Gable 7326 | P45: Standard Gable 7326 | Q45: Large Gable 9768 | R45: Clerestory 8547 | S45: Clerestory 8547 | T45: Clerestory 8547 | U45: Compact Gable 6106 | V45: Clerestory 7326 | W45: Clerestory 8547 | X45: Compact Gable 6106 | Y45: Mono Pitch 4884 | Z45: Clerestory 8547 | AA45: Mono Pitch 4884 | AB45: Clerestory 8547 | AC45: A Frame Large | AD45: A Frame Compact | AE45: A Frame Standard
A46: Price in USD in VAT | B46: =B45*B41+B45 -> 43187.858 | D46: Building width | E46: Studio | F46: 1BR Mono | G46: 2BR Mono | H46: 3BR Mono | I46: 1BR Compact Gable | J46: 2BR Compact Gable | K46: 3BR Compact Gable | L46: 4BR Compact Gable | M46: 2BR Comfort Compact Gable | N46: 2BR Gable | O46: 3BR Gable | P46: 4BR Gable | Q46: 3BR Large Gable | R46: 2BR Clerestory | S46: 4BR Clerestory | T46: Nisha's | U46: John's | V46: Sarah's | W46: Naomi & Jesse | X46: Mlango Farm | Y46: Milly | Z46: Naomi & Jesse | AA46: Janet | AB46: Pius O | AC46: Zziwa test | AD46: Compact A Frame | AE46: Standard A Frame
A47: Price per sqm GFA in USD in VAT | B47: =B46/B24 -> 395.57644 | D47: Floor A - 1221 | E47: 0 | F47: 0 | G47: 0 | H47: 0 | I47: 0 | J47: 0 | K47: 1 | L47: 0 | M47: 0 | N47: 0 | O47: 0 | P47: 0 | Q47: 0 | R47: 1 | S47: 1 | T47: 2 | U47: 0 | V47: 0 | W47: 2 | X47: 0 | Y47: 0 | Z47: 2 | AA47: 0 | AB47: 2 | AC47: 0 | AD47: 0 | AE47: 0
D48: Floor B - 2442 | E48: 2 | F48: 0 | G48: 1 | H48: 0 | I48: 3 | J48: 4 | K48: 4 | L48: 5 | M48: 5 | N48: 1 | O48: 4 | P48: 2 | Q48: 2 | R48: 0 | S48: 0 | T48: 0 | U48: 4 | V48: 2 | W48: 2 | X48: 4 | Y48: 1 | Z48: 2 | AA48: 0 | AB48: 4 | AC48: 4 | AD48: 3 | AE48: 3
A49: ="Price in "&B38&" ex VAT" -> Price in UGX ex VAT | B49: =ROUND(B42*B39,0) -> 123108687 | D49: Floor C - 3053 | E49: 0 | F49: 2 | G49: 2 | H49: 3 | I49: 0 | J49: 0 | K49: 0 | L49: 0 | M49: 0 | N49: 3 | O49: 1 | P49: 3 | Q49: 2 | R49: 2 | S49: 3 | T49: 3 | U49: 0 | V49: 3 | W49: 1 | X49: 0 | Y49: 2 | Z49: 1 | AA49: 3 | AB49: 0 | AC49: 0 | AD49: 0 | AE49: 0
A50: Margin | B50: =B49*B40 -> 12310869 | D50: Partitions | E50: 4.5 | F50: 6 | G50: 12.5 | H50: 14 | I50: 10 | J50: 22 | K50: 24 | L50: 29 | M50: 24 | N50: 20 | O50: 38 | P50: 42.5 | Q50: 33 | R50: 15.5 | S50: 28.5 | T50: 29 | U50: 19.5 | V50: 35 | W50: 35 | X50: 17 | Y50: 12 | Z50: 35 | AA50: 14.5 | AB50: 32 | AC50: 9 | AD50: 5 | AE50: 6
A51: VAT | B51: =(B49+B50)*B41 -> 24375520 | D51: Interior doors | E51: 1 | F51: 2 | G51: 3 | H51: 4 | I51: 2 | J51: 4 | K51: 5 | L51: 6 | M51: 4 | N51: 4 | O51: 6 | P51: 7 | Q51: 5 | R51: 3 | S51: 6 | T51: 6 | U51: 4 | V51: 7 | W51: 5 | X51: 4 | Y51: 3 | Z51: 5 | AA51: 4 | AB51: 7 | AC51: 2 | AD51: 1 | AE51: 1
A52: ="Price in "&B38&" inclusive VAT" -> Price in UGX inclusive VAT | B52: =B49+B50+B51 -> 1.5979508e+08 | D52: Aluminium | E52: 7.2 | F52: 7.9 | G52: 10.2 | H52: 9.4 | I52: 16 | J52: 18.5 | K52: 20 | L52: 26 | M52: 26 | N52: 21 | O52: 19 | P52: 20.8 | Q52: 23.7 | R52: 18.9 | S52: 27.5 | T52: 34 | U52: 15 | V52: ? | W52: 27.6 | X52: 22 | Y52: 10.2 | Z52: 27.6 | AA52: 13.2 | AB52: 23 | AC52: 16 | AD52: 9 | AE52: 11
A53: ="Price per GFA sqm in "&B38&" inclusive VAT" -> Price per GFA sqm in UGX inclusive VAT | B53: =B52/B24 -> 1463632.8 | D53: Extra ext. wall | E53: 0 | F53: 0 | G53: 0 | H53: 4 | I53: 2 | J53: 2 | K53: 2 | L53: 2 | M53: 6 | N53: 0 | O53: 4 | P53: 4 | Q53: 0 | R53: 0 | S53: 4 | T53: 4 | U53: 0 | V53: 4 | W53: 0 | X53: 2 | Y53: 0 | Z53: 0 | AA53: 2 | AB53: 4 | AC53: 0 | AD53: 0 | AE53: 0
D54: Veranda A | E54: 0 | F54: 0 | G54: 0 | H54: 0 | I54: 0 | J54: 0 | K54: 0 | L54: 0 | M54: 0 | N54: 0 | O54: 0 | P54: 0 | Q54: 0 | R54: 0 | S54: 0 | T54: 2 | U54: 2 | V54: 0 | W54: 3 | X54: 0 | Y54: 0 | Z54: 3 | AA54: 0 | AB54: 1 | AC54: 2 | AD54: 0 | AE54: 2
D55: Veranda B | E55: 0 | F55: 0 | G55: 0 | H55: 0 | I55: 0 | J55: 0 | K55: 0 | L55: 0 | M55: 0 | N55: 0 | O55: 0 | P55: 0 | Q55: 0 | R55: 0 | S55: 0 | T55: 0 | U55: 0 | V55: 0 | W55: 1 | X55: 4 | Y55: 1 | Z55: 1 | AA55: 0 | AB55: 3 | AC55: 0 | AD55: 0 | AE55: 0
D56: Veranda C | E56: 0 | F56: 0 | G56: 0 | H56: 0 | I56: 0 | J56: 0 | K56: 0 | L56: 0 | M56: 0 | N56: 0 | O56: 0 | P56: 0 | Q56: 0 | R56: 0 | S56: 0 | T56: 3 | U56: 0 | V56: 2 | W56: 1 | X56: 0 | Y56: 2 | Z56: 1 | AA56: 0 | AB56: 0 | AC56: 2 | AD56: 0 | AE56: 0
D57: Bathrooms | E57: 1 | F57: 1 | G57: 1 | H57: 1 | I57: 1 | J57: 2 | K57: 2 | L57: 2 | M57: 2 | N57: 2 | O57: 3 | P57: 3 | Q57: 2 | R57: 1 | S57: 2 | T57: 2 | U57: 2 | V57: 3 | W57: 2 | X57: 2 | Y57: 1 | Z57: 2 | AA57: 1 | AB57: 2 | AC57: 1 | AD57: 1 | AE57: 1
C62: USD | I62: =B38 -> UGX | O62: Specs
A64: Building parameters (all prices below ex vat) | D64: =SUM(D65:D1090) -> 33272.618 | F64: =SUM(F68:F1090) -> 3312.2618 | H64: =SUM(H65:H1090) -> 36434.88 | I64: Totals | J64: =SUM(J65:J1090) -> 1.2255369e+08 | L64: =SUM(L65:L1090) -> 12255369 | N64: =SUM(N65:N1090) -> 1.3480906e+08 | P64: =SUM(P65:P1090) -> 13162.676 | R64: =SUM(R65:R1090) -> 16925.567 | T64: =SUM(T65:T1090) -> 1064.7487
AG65: Input Database
A66: Frames | C66: ! All costs and prices below are exclusive of VAT ! | AF66: Name | AG66: One Bedroom Urban | AH66: Two Bed Space | AI66: Three Bed Urban Test | AJ66: Studio BB Mono | AK66: 1BR CC Mono | AL66: 2BR CBC Mono | AM66: 3BR CCC Mono | AN66: 2BR Gable CBCC | AO66: 3BR Gable CBBBB | AP66: 4BR Gable CBBCC | AQ66: 2BR Clerestory CAC | AR66: 4BR Clerestory CCAC | AS66: 4BR Large Gable CBBC | AU66: Combined order for Busoga
A67: Amount | B67: Description | C67: Cost item ($) | D67: Cost total | E67: Margin item | F67: Margin total | G67: Price item | H67: Price total | I67: Cost item | J67: Cost total | K67: Margin item | L67: Margin total | M67: Price item | N67: Price total | O67: Weight item | P67: Weight total | Q67: Carbon item | R67: Carbon total | S67: Labour item | T67: Labour total | U67: Surface item | V67: Surface total | W67: Facade surface | X67: Facade total
A68: # | B68: Name | C68: USD | D68: USD | E68: USD | F68: USD | G68: USD | H68: USD | I68: =$B$38 -> UGX | J68: =$B$38 -> UGX | K68: =$B$38 -> UGX | L68: =$B$38 -> UGX | M68: =$B$38 -> UGX | N68: =$B$38 -> UGX | O68: kg | P68: kg | Q68: kg CO2 stored | R68: kg CO2 stored | S68: hours | T68: hours | U68: sqm | V68: sqm
A69: =L19 -> 0 | B69: ='Structures Database'!A22 -> Floor frame 2442 x 1221 | C69: =SUMIF('Structures Database'!$V:$V,$B69,'Structures Database'!U:U) -> 57.061748 | D69: =$A69*C69 -> 0 | E69: =C69*$B$40 -> 5.7061748 | F69: =A69*E69 -> 0 | G69: =C69+E69 -> 62.767923 | H69: =A69*G69 -> 0 | I69: =C69*$B$39 -> 211128.47 | J69: =I69*A69 -> 0 | K69: =E69*$B$39 -> 21112.847 | L69: =K69*A69 -> 0 | M69: =G69*$B$39 -> 232241.31 | N69: =M69*A69 -> 0 | O69: =SUMIF('Structures Database'!$V:$V,$B69,'Structures Database'!P:P) -> 92.523228 | P69: =$A69*O69 -> 0 | Q69: =SUMIF('Structures Database'!$V:$V,$B69,'Structures Database'!Q:Q) -> 146.8144 | R69: =$A69*Q69 -> 0 | S69: =SUMIF('Structures Database'!$V:$V,$B69,'Structures Database'!R:R)/60 -> 4.1833333 | T69: =A69*S69 -> 0 | U69: =SUMIF('Structures Database'!$V:$V,$B69,'Structures Database'!Y:Y) -> 2.981682 | V69: =A69*U69 -> 0 | AG69: 0 | AH69: 3.5 | AI69: 0 | AJ69: 0 | AK69: 0 | AL69: 0 | AM69: 0 | AN69: 0 | AO69: 0 | AP69: 0 | AQ69: 3.5 | AR69: 0.5 | AS69: 0 | AU69: =AJ69+AK69+AL69+AM69+AN69+AO69+AP69+AQ69+AR69+AS69 -> 4
A70: =M19 -> 8 | B70: ='Structures Database'!A31 -> Floor frame 2442 x 2442 | C70: =SUMIF('Structures Database'!$V:$V,$B70,'Structures Database'!U:U) -> 93.878539 | D70: =$A70*C70 -> 751.02831 | E70: =C70*$B$40 -> 9.3878539 | F70: =A70*E70 -> 75.102831 | G70: =C70+E70 -> 103.26639 | H70: =A70*G70 -> 826.13114 | I70: =C70*$B$39 -> 347350.59 | J70: =I70*A70 -> 2778804.8 | K70: =E70*$B$39 -> 34735.059 | L70: =K70*A70 -> 277880.48 | M70: =G70*$B$39 -> 382085.65 | N70: =M70*A70 -> 3056685.2 | O70: =SUMIF('Structures Database'!$V:$V,$B70,'Structures Database'!P:P) -> 156.20618 | P70: =$A70*O70 -> 1249.6495 | Q70: =SUMIF('Structures Database'!$V:$V,$B70,'Structures Database'!Q:Q) -> 249.06193 | R70: =$A70*Q70 -> 1992.4954 | S70: =SUMIF('Structures Database'!$V:$V,$B70,'Structures Database'!R:R)/60 -> 6.5166667 | T70: =A70*S70 -> 52.133333 | U70: =SUMIF('Structures Database'!$V:$V,$B70,'Structures Database'!Y:Y) -> 5.963364 | V70: =A70*U70 -> 47.706912 | AG70: 6 | AH70: 0 | AI70: 8 | AJ70: 4 | AK70: 0 | AL70: 2 | AM70: 0 | AN70: 3 | AO70: 12 | AP70: 6 | AQ70: 0 | AR70: 1.5 | AS70: 8 | AU70: =AJ70+AK70+AL70+AM70+AN70+AO70+AP70+AQ70+AR70+AS70 -> 36.5
A71: =N19 -> 8 | B71: ='Structures Database'!A40 -> Floor frame 2442 x 3053 | C71: =SUMIF('Structures Database'!$V:$V,$B71,'Structures Database'!U:U) -> 118.41262 | D71: =$A71*C71 -> 947.30093 | E71: =C71*$B$40 -> 11.841262 | F71: =A71*E71 -> 94.730093 | G71: =C71+E71 -> 130.25388 | H71: =A71*G71 -> 1042.031 | I71: =C71*$B$39 -> 438126.68 | J71: =I71*A71 -> 3505013.4 | K71: =E71*$B$39 -> 43812.668 | L71: =K71*A71 -> 350501.34 | M71: =G71*$B$39 -> 481939.35 | N71: =M71*A71 -> 3855514.8 | O71: =SUMIF('Structures Database'!$V:$V,$B71,'Structures Database'!P:P) -> 196.71499 | P71: =$A71*O71 -> 1573.72 | Q71: =SUMIF('Structures Database'!$V:$V,$B71,'Structures Database'!Q:Q) -> 313.47386 | R71: =$A71*Q71 -> 2507.7908 | S71: =SUMIF('Structures Database'!$V:$V,$B71,'Structures Database'!R:R)/60 -> 8.2833333 | T71: =A71*S71 -> 66.266667 | U71: =SUMIF('Structures Database'!$V:$V,$B71,'Structures Database'!Y:Y) -> 7.455426 | V71: =A71*U71 -> 59.643408 | AG71: 0 | AH71: 7.5 | AI71: 0 | AJ71: 0 | AK71: 4 | AL71: 4 | AM71: 6 | AN71: 9 | AO71: 3 | AP71: 9 | AQ71: 7 | AR71: 10.5 | AS71: 8 | AU71: =AJ71+AK71+AL71+AM71+AN71+AO71+AP71+AQ71+AR71+AS71 -> 60.5
A72: =N20 | B72: ='Structures Database'!A49 -> Floor frame 2442 x 3663 | C72: =SUMIF('Structures Database'!$V:$V,$B72,'Structures Database'!U:U) -> 118.41262 | D72: =$A72*C72 -> 0 | E72: =C72*$B$40 -> 11.841262 | F72: =A72*E72 -> 0 | G72: =C72+E72 -> 130.25388 | H72: =A72*G72 -> 0 | I72: =C72*$B$39 -> 438126.68 | J72: =I72*A72 -> 0 | K72: =E72*$B$39 -> 43812.668 | L72: =K72*A72 -> 0 | M72: =G72*$B$39 -> 481939.35 | N72: =M72*A72 -> 0 | O72: =SUMIF('Structures Database'!$V:$V,$B72,'Structures Database'!P:P) -> 196.71499 | P72: =$A72*O72 -> 0 | Q72: =SUMIF('Structures Database'!$V:$V,$B72,'Structures Database'!Q:Q) -> 313.47386 | R72: =$A72*Q72 -> 0 | S72: =SUMIF('Structures Database'!$V:$V,$B72,'Structures Database'!R:R)/60 -> 8.2833333 | T72: =A72*S72 -> 0 | U72: =SUMIF('Structures Database'!$V:$V,$B72,'Structures Database'!Y:Y) -> 7.455426 | V72: =A72*U72 -> 0 | AG72: 0 | AH72: 7.5 | AI72: 0 | AJ72: 0 | AK72: 4 | AL72: 4 | AM72: 6 | AN72: 9 | AO72: 3 | AP72: 9 | AQ72: 7 | AR72: 10.5 | AS72: 8 | AU72: =AJ72+AK72+AL72+AM72+AN72+AO72+AP72+AQ72+AR72+AS72 -> 60.5
A73: =E32 -> 0 | B73: ='Structures Database'!A58 -> Decking frame 2442 x 1221 | C73: =SUMIF('Structures Database'!$V:$V,$B73,'Structures Database'!U:U) -> 52.821108 | D73: =$A73*C73 -> 0 | E73: =C73*$B$40 -> 5.2821108 | F73: =A73*E73 -> 0 | G73: =C73+E73 -> 58.103219 | H73: =A73*G73 -> 0 | I73: =C73*$B$39 -> 195438.1 | J73: =I73*A73 -> 0 | K73: =E73*$B$39 -> 19543.81 | L73: =K73*A73 -> 0 | M73: =G73*$B$39 -> 214981.91 | N73: =M73*A73 -> 0 | O73: =SUMIF('Structures Database'!$V:$V,$B73,'Structures Database'!P:P) -> 83.850258 | P73: =$A73*O73 -> 0 | Q73: =SUMIF('Structures Database'!$V:$V,$B73,'Structures Database'!Q:Q) -> 132.84382 | R73: =$A73*Q73 -> 0 | S73: =SUMIF('Structures Database'!$V:$V,$B73,'Structures Database'!R:R)/60 -> 3.6833333 | T73: =A73*S73 -> 0 | U73: =SUMIF('Structures Database'!$V:$V,$B73,'Structures Database'!Y:Y) -> 2.981682 | V73: =A73*U73 -> 0 | AG73: 0 | AH73: 0 | AI73: 0 | AJ73: 0 | AK73: 0 | AL73: 0 | AM73: 0 | AN73: 0 | AO73: 0 | AP73: 0 | AQ73: 0 | AR73: 0 | AS73: 0 | AU73: =AJ73+AK73+AL73+AM73+AN73+AO73+AP73+AQ73+AR73+AS73 -> 0
A74: =E33 -> 0 | B74: ='Structures Database'!A67 -> Decking frame 2442 x 2442 | C74: =SUMIF('Structures Database'!$V:$V,$B74,'Structures Database'!U:U) -> 87.286591 | D74: =$A74*C74 -> 0 | E74: =C74*$B$40 -> 8.7286591 | F74: =A74*E74 -> 0 | G74: =C74+E74 -> 96.01525 | H74: =A74*G74 -> 0 | I74: =C74*$B$39 -> 322960.39 | J74: =I74*A74 -> 0 | K74: =E74*$B$39 -> 32296.039 | L74: =K74*A74 -> 0 | M74: =G74*$B$39 -> 355256.43 | N74: =M74*A74 -> 0 | O74: =SUMIF('Structures Database'!$V:$V,$B74,'Structures Database'!P:P) -> 141.76605 | P74: =$A74*O74 -> 0 | Q74: =SUMIF('Structures Database'!$V:$V,$B74,'Structures Database'!Q:Q) -> 225.77763 | R74: =$A74*Q74 -> 0 | S74: =SUMIF('Structures Database'!$V:$V,$B74,'Structures Database'!R:R)/60 -> 5.6833333 | T74: =A74*S74 -> 0 | U74: =SUMIF('Structures Database'!$V:$V,$B74,'Structures Database'!Y:Y) -> 5.963364 | V74: =A74*U74 -> 0 | AG74: 0 | AH74: 0 | AI74: 0 | AJ74: 0 | AK74: 0 | AL74: 0 | AM74: 0 | AN74: 0 | AO74: 0 | AP74: 0 | AQ74: 0 | AR74: 0 | AS74: 0 | AU74: =AJ74+AK74+AL74+AM74+AN74+AO74+AP74+AQ74+AR74+AS74 -> 0
A75: =E34 -> 0 | B75: ='Structures Database'!A76 -> Decking frame 2442 x 3053 | C75: =SUMIF('Structures Database'!$V:$V,$B75,'Structures Database'!U:U) -> 104.41356 | D75: =$A75*C75 -> 0 | E75: =C75*$B$40 -> 10.441356 | F75: =A75*E75 -> 0 | G75: =C75+E75 -> 114.85491 | H75: =A75*G75 -> 0 | I75: =C75*$B$39 -> 386330.16 | J75: =I75*A75 -> 0 | K75: =E75*$B$39 -> 38633.016 | L75: =K75*A75 -> 0 | M75: =G75*$B$39 -> 424963.17 | N75: =M75*A75 -> 0 | O75: =SUMIF('Structures Database'!$V:$V,$B75,'Structures Database'!P:P) -> 170.71453 | P75: =$A75*O75 -> 0 | Q75: =SUMIF('Structures Database'!$V:$V,$B75,'Structures Database'!Q:Q) -> 272.22936 | R75: =$A75*Q75 -> 0 | S75: =SUMIF('Structures Database'!$V:$V,$B75,'Structures Database'!R:R)/60 -> 6.6833333 | T75: =A75*S75 -> 0 | U75: =SUMIF('Structures Database'!$V:$V,$B75,'Structures Database'!Y:Y) -> 7.455426 | V75: =A75*U75 -> 0 | AG75: 0 | AH75: 0 | AI75: 0 | AJ75: 0 | AK75: 0 | AL75: 0 | AM75: 0 | AN75: 0 | AO75: 0 | AP75: 0 | AQ75: 0 | AR75: 0 | AS75: 0 | AU75: =AJ75+AK75+AL75+AM75+AN75+AO75+AP75+AQ75+AR75+AS75 -> 0
A76: =Q19 -> 4 | B76: ='Structures Database'!A87 -> Wall frame 2442 x 2654 | C76: =SUMIF('Structures Database'!$V:$V,$B76,'Structures Database'!U:U) -> 61.862474 | D76: =$A76*C76 -> 247.4499 | E76: =C76*$B$40 -> 6.1862474 | F76: =A76*E76 -> 24.74499 | G76: =C76+E76 -> 68.048722 | H76: =A76*G76 -> 272.19489 | I76: =C76*$B$39 -> 228891.16 | J76: =I76*A76 -> 915564.62 | K76: =E76*$B$39 -> 22889.116 | L76: =K76*A76 -> 91556.462 | M76: =G76*$B$39 -> 251780.27 | N76: =M76*A76 -> 1007121.1 | O76: =SUMIF('Structures Database'!$V:$V,$B76,'Structures Database'!P:P) -> 92.330016 | P76: =$A76*O76 -> 369.32006 | Q76: =SUMIF('Structures Database'!$V:$V,$B76,'Structures Database'!Q:Q) -> 146.0858 | R76: =$A76*Q76 -> 584.3432 | S76: =SUMIF('Structures Database'!$V:$V,$B76,'Structures Database'!R:R)/60 -> 4.0166667 | T76: =A76*S76 -> 16.066667 | U76: =SUMIF('Structures Database'!$V:$V,$B76,'Structures Database'!Y:Y) -> 6.901092 | V76: =A76*U76 -> 27.604368 | AG76: 3 | AH76: 1 | AI76: 6 | AJ76: 4 | AK76: 0 | AL76: 1 | AM76: 2 | AN76: 3 | AO76: 11 | AP76: 8 | AQ76: 0 | AR76: 1.5 | AS76: 4 | AU76: =AJ76+AK76+AL76+AM76+AN76+AO76+AP76+AQ76+AR76+AS76 -> 34.5
A77: =R19 -> 4 | B77: ='Structures Database'!A101 -> Wall frame 3053 x 2654 | C77: =SUMIF('Structures Database'!$V:$V,$B77,'Structures Database'!U:U) -> 75.256547 | D77: =$A77*C77 -> 301.02619 | E77: =C77*$B$40 -> 7.5256547 | F77: =A77*E77 -> 30.102619 | G77: =C77+E77 -> 82.782202 | H77: =A77*G77 -> 331.12881 | I77: =C77*$B$39 -> 278449.22 | J77: =I77*A77 -> 1113796.9 | K77: =E77*$B$39 -> 27844.922 | L77: =K77*A77 -> 111379.69 | M77: =G77*$B$39 -> 306294.15 | N77: =M77*A77 -> 1225176.6 | O77: =SUMIF('Structures Database'!$V:$V,$B77,'Structures Database'!P:P) -> 112.99274 | P77: =$A77*O77 -> 451.97095 | Q77: =SUMIF('Structures Database'!$V:$V,$B77,'Structures Database'!Q:Q) -> 178.95608 | R77: =$A77*Q77 -> 715.82432 | S77: =SUMIF('Structures Database'!$V:$V,$B77,'Structures Database'!R:R)/60 -> 4.6666667 | T77: =A77*S77 -> 18.666667 | U77: =SUMIF('Structures Database'!$V:$V,$B77,'Structures Database'!Y:Y) -> 8.627778 | V77: =A77*U77 -> 34.511112 | AG77: 0 | AH77: 4 | AI77: 0 | AJ77: 0 | AK77: 2 | AL77: 2 | AM77: 3 | AN77: 3 | AO77: 4 | AP77: 6 | AQ77: 2 | AR77: 3 | AS77: 4 | AU77: =AJ77+AK77+AL77+AM77+AN77+AO77+AP77+AQ77+AR77+AS77 -> 29
A78: =S19+E31/4 -> 8 | B78: ='Structures Database'!A115 -> Wall frame 2442 x 2999 | C78: =SUMIF('Structures Database'!$V:$V,$B78,'Structures Database'!U:U) -> 66.177913 | D78: =$A78*C78 -> 529.42331 | E78: =C78*$B$40 -> 6.6177913 | F78: =A78*E78 -> 52.942331 | G78: =C78+E78 -> 72.795705 | H78: =A78*G78 -> 582.36564 | I78: =C78*$B$39 -> 244858.28 | J78: =I78*A78 -> 1958866.2 | K78: =E78*$B$39 -> 24485.828 | L78: =K78*A78 -> 195886.62 | M78: =G78*$B$39 -> 269344.11 | N78: =M78*A78 -> 2154752.9 | O78: =SUMIF('Structures Database'!$V:$V,$B78,'Structures Database'!P:P) -> 98.240725 | P78: =$A78*O78 -> 785.9258 | Q78: =SUMIF('Structures Database'!$V:$V,$B78,'Structures Database'!Q:Q) -> 155.5849 | R78: =$A78*Q78 -> 1244.6792 | S78: =SUMIF('Structures Database'!$V:$V,$B78,'Structures Database'!R:R)/60 -> 4.1166667 | T78: =A78*S78 -> 32.933333 | U78: =SUMIF('Structures Database'!$V:$V,$B78,'Structures Database'!Y:Y) -> 7.743582 | V78: =A78*U78 -> 61.948656 | AG78: 7 | AH78: 7 | AI78: 7 | AJ78: 4 | AK78: 4 | AL78: 5 | AM78: 2 | AN78: 5 | AO78: 2 | AP78: 2 | AQ78: 8 | AR78: 7.5 | AS78: 8 | AU78: =AJ78+AK78+AL78+AM78+AN78+AO78+AP78+AQ78+AR78+AS78 -> 47.5
A79: =T19 -> 0 | B79: ='Structures Database'!A129 -> Wall frame 3053 x 2999 | C79: =SUMIF('Structures Database'!$V:$V,$B79,'Structures Database'!U:U) -> 80.538193 | D79: =$A79*C79 -> 0 | E79: =C79*$B$40 -> 8.0538193 | F79: =A79*E79 -> 0 | G79: =C79+E79 -> 88.592012 | H79: =A79*G79 -> 0 | I79: =C79*$B$39 -> 297991.31 | J79: =I79*A79 -> 0 | K79: =E79*$B$39 -> 29799.131 | L79: =K79*A79 -> 0 | M79: =G79*$B$39 -> 327790.45 | N79: =M79*A79 -> 0 | O79: =SUMIF('Structures Database'!$V:$V,$B79,'Structures Database'!P:P) -> 120.2231 | P79: =$A79*O79 -> 0 | Q79: =SUMIF('Structures Database'!$V:$V,$B79,'Structures Database'!Q:Q) -> 190.57539 | R79: =$A79*Q79 -> 0 | S79: =SUMIF('Structures Database'!$V:$V,$B79,'Structures Database'!R:R)/60 -> 4.7916667 | T79: =A79*S79 -> 0 | U79: =SUMIF('Structures Database'!$V:$V,$B79,'Structures Database'!Y:Y) -> 9.681063 | V79: =A79*U79 -> 0 | AG79: 0 | AH79: 0 | AI79: 0 | AJ79: 0 | AK79: 2 | AL79: 2 | AM79: 3 | AN79: 3 | AO79: 0 | AP79: 0 | AQ79: 2 | AR79: 3 | AS79: 0 | AU79: =AJ79+AK79+AL79+AM79+AN79+AO79+AP79+AQ79+AR79+AS79 -> 15
A80: =E28 -> 33 | B80: ='Structures Database'!A154 -> Partition wall frame per m1 | C80: =SUMIF('Structures Database'!$V:$V,$B80,'Structures Database'!U:U) -> 48.248533 | D80: =$A80*C80 -> 1592.2016 | E80: =C80*$B$40 -> 4.8248533 | F80: =A80*E80 -> 159.22016 | G80: =C80+E80 -> 53.073387 | H80: =A80*G80 -> 1751.4218 | I80: =C80*$B$39 -> 178519.57 | J80: =I80*A80 -> 5891145.9 | K80: =E80*$B$39 -> 17851.957 | L80: =K80*A80 -> 589114.59 | M80: =G80*$B$39 -> 196371.53 | N80: =M80*A80 -> 6480260.5 | O80: =SUMIF('Structures Database'!$V:$V,$B80,'Structures Database'!P:P) -> 60.191411 | P80: =$A80*O80 -> 1986.3166 | Q80: =SUMIF('Structures Database'!$V:$V,$B80,'Structures Database'!Q:Q) -> 97.047642 | R80: =$A80*Q80 -> 3202.5722 | S80: =SUMIF('Structures Database'!$V:$V,$B80,'Structures Database'!R:R)/60 -> 2.4356811 | T80: =A80*S80 -> 80.377477 | U80: =SUMIF('Structures Database'!$V:$V,$B80,'Structures Database'!Y:Y) -> 3 | V80: =A80*U80 -> 99 | AG80: 6.5 | AH80: 6.5 | AI80: 13 | AJ80: 4.5 | AK80: 6 | AL80: 12.5 | AM80: 14 | AN80: 20 | AO80: 38 | AP80: 42.5 | AQ80: 16.5 | AR80: 29 | AS80: 33 | AU80: =AJ80+AK80+AL80+AM80+AN80+AO80+AP80+AQ80+AR80+AS80 -> 216
A81: =B29 -> 100.36414 | B81: ='Structures Database'!A181 -> Facade per m2 - vertical cladding | C81: =SUMIF('Structures Database'!$V:$V,$B81,'Structures Database'!U:U) -> 10.583216 | D81: =$A81*C81 -> 1062.1753 | E81: =C81*$B$40 -> 1.0583216 | F81: =A81*E81 -> 106.21753 | G81: =C81+E81 -> 11.641537 | H81: =A81*G81 -> 1168.3928 | I81: =C81*$B$39 -> 39157.898 | J81: =I81*A81 -> 3930048.6 | K81: =E81*$B$39 -> 3915.7898 | L81: =K81*A81 -> 393004.86 | M81: =G81*$B$39 -> 43073.688 | N81: =M81*A81 -> 4323053.4 | O81: =SUMIF('Structures Database'!$V:$V,$B81,'Structures Database'!P:P) -> 15.602939 | P81: =$A81*O81 -> 1565.9755 | Q81: =SUMIF('Structures Database'!$V:$V,$B81,'Structures Database'!Q:Q) -> 24.879539 | R81: =$A81*Q81 -> 2497.0134 | S81: =SUMIF('Structures Database'!$V:$V,$B81,'Structures Database'!R:R)/60 -> 1.2960827 | T81: =A81*S81 -> 130.08022 | U81: =SUMIF('Structures Database'!$V:$V,$B81,'Structures Database'!Y:Y) -> 1 | V81: =A81*U81 -> 100.36414 | AG81: =AH29 | AH81: =AI29 | AI81: 84.01785 | AJ81: 51.319824 | AK81: 60.333138 | AL81: 72.087876 | AM81: 73.530135 | AN81: 90.822273 | AO81: 104.41429 | AP81: 99.214176 | AQ81: 79.63851 | AR81: 95.871882 | AS81: 100.40078 | AU81: =AJ81+AK81+AL81+AM81+AN81+AO81+AP81+AQ81+AR81+AS81 -> 827.63289
A82: 0 | B82: ='Structures Database'!A174 -> Facade frame 2442 x 2654 (vertical cladding) | C82: =SUMIF('Structures Database'!$V:$V,$B82,'Structures Database'!U:U) -> 69.89179 | D82: =$A82*C82 -> 0 | E82: =C82*$B$40 -> 6.989179 | F82: =A82*E82 -> 0 | G82: =C82+E82 -> 76.880969 | H82: =A82*G82 -> 0 | I82: =C82*$B$39 -> 258599.62 | J82: =I82*A82 -> 0 | K82: =E82*$B$39 -> 25859.962 | L82: =K82*A82 -> 0 | M82: =G82*$B$39 -> 284459.59 | N82: =M82*A82 -> 0 | O82: =SUMIF('Structures Database'!$V:$V,$B82,'Structures Database'!P:P) -> 101.2108 | P82: =$A82*O82 -> 0 | Q82: =SUMIF('Structures Database'!$V:$V,$B82,'Structures Database'!Q:Q) -> 161.24598 | R82: =$A82*Q82 -> 0 | S82: =SUMIF('Structures Database'!$V:$V,$B82,'Structures Database'!R:R)/60 -> 8.95 | T82: =A82*S82 -> 0 | U82: =SUMIF('Structures Database'!$V:$V,$B82,'Structures Database'!Y:Y) -> 6.481068 | V82: =A82*U82 -> 0 | AG82: 0 | AH82: 0 | AI82: 0 | AJ82: 0 | AK82: 0 | AL82: 0 | AM82: 0 | AN82: 0 | AO82: 0 | AP82: 0 | AQ82: 0 | AR82: 0 | AS82: 0 | AU82: =AJ82+AK82+AL82+AM82+AN82+AO82+AP82+AQ82+AR82+AS82 -> 0
A83: =U19 | B83: ='Structures Database'!A191 -> Roof frame 1221 x 5685 (mono pitch) | C83: =SUMIF('Structures Database'!$V:$V,$B83,'Structures Database'!U:U) -> 81.838415 | D83: =$A83*C83 -> 0 | E83: =C83*$B$40 -> 8.1838415 | F83: =A83*E83 -> 0 | G83: =C83+E83 -> 90.022257 | H83: =A83*G83 -> 0 | I83: =C83*$B$39 -> 302802.14 | J83: =I83*A83 -> 0 | K83: =E83*$B$39 -> 30280.214 | L83: =K83*A83 -> 0 | M83: =G83*$B$39 -> 333082.35 | N83: =M83*A83 -> 0 | O83: =SUMIF('Structures Database'!$V:$V,$B83,'Structures Database'!P:P) -> 106.59204 | P83: =$A83*O83 -> 0 | Q83: =SUMIF('Structures Database'!$V:$V,$B83,'Structures Database'!Q:Q) -> 167.05226 | R83: =$A83*Q83 -> 0 | S83: =SUMIF('Structures Database'!$V:$V,$B83,'Structures Database'!R:R)/60 -> 7.1 | T83: =A83*S83 -> 0 | U83: =SUMIF('Structures Database'!$V:$V,$B83,'Structures Database'!Y:Y) -> 6.995109 | V83: =A83*U83 -> 0 | AG83: 4 | AH83: 0 | AI83: 6 | AJ83: 2 | AK83: 3 | AL83: 5 | AM83: 5.5 | AN83: 0 | AO83: 0 | AP83: 0 | AQ83: 0 | AR83: 0 | AS83: 0 | AU83: =AJ83+AK83+AL83+AM83+AN83+AO83+AP83+AQ83+AR83+AS83 -> 15.5
A84: =V19 | B84: ='Structures Database'!A207 -> Roof frame 1598x 5685 (mono pitch edge) | C84: =SUMIF('Structures Database'!$V:$V,$B84,'Structures Database'!U:U) -> 133.59487 | D84: =$A84*C84 -> 0 | E84: =C84*$B$40 -> 13.359487 | F84: =A84*E84 -> 0 | G84: =C84+E84 -> 146.95436 | H84: =A84*G84 -> 0 | I84: =C84*$B$39 -> 494301.02 | J84: =I84*A84 -> 0 | K84: =E84*$B$39 -> 49430.102 | L84: =K84*A84 -> 0 | M84: =G84*$B$39 -> 543731.12 | N84: =M84*A84 -> 0 | O84: =SUMIF('Structures Database'!$V:$V,$B84,'Structures Database'!P:P) -> 170.36873 | P84: =$A84*O84 -> 0 | Q84: =SUMIF('Structures Database'!$V:$V,$B84,'Structures Database'!Q:Q) -> 267.39082 | R84: =$A84*Q84 -> 0 | S84: =SUMIF('Structures Database'!$V:$V,$B84,'Structures Database'!R:R)/60 -> 14.475 | T84: =A84*S84 -> 0 | U84: =SUMIF('Structures Database'!$V:$V,$B84,'Structures Database'!Y:Y) -> 9.28098 | V84: =A84*U84 -> 0 | AG84: 2 | AH84: 0 | AI84: 2 | AJ84: 2 | AK84: 2 | AL84: 2 | AM84: 2 | AN84: 0 | AO84: 0 | AP84: 0 | AQ84: 0 | AR84: 0 | AS84: 0 | AU84: =AJ84+AK84+AL84+AM84+AN84+AO84+AP84+AQ84+AR84+AS84 -> 8
A85: =W19 | B85: ='Structures Database'!A223 -> Roof frame 1221 x 3574 (compact gable) | C85: =SUMIF('Structures Database'!$V:$V,$B85,'Structures Database'!U:U) -> 64.202047 | D85: =$A85*C85 -> 0 | E85: =C85*$B$40 -> 6.4202047 | F85: =A85*E85 -> 0 | G85: =C85+E85 -> 70.622251 | H85: =A85*G85 -> 0 | I85: =C85*$B$39 -> 237547.57 | J85: =I85*A85 -> 0 | K85: =E85*$B$39 -> 23754.757 | L85: =K85*A85 -> 0 | M85: =G85*$B$39 -> 261302.33 | N85: =M85*A85 -> 0 | O85: =SUMIF('Structures Database'!$V:$V,$B85,'Structures Database'!P:P) -> 78.19967 | P85: =$A85*O85 -> 0 | Q85: =SUMIF('Structures Database'!$V:$V,$B85,'Structures Database'!Q:Q) -> 121.98428 | R85: =$A85*Q85 -> 0 | S85: =SUMIF('Structures Database'!$V:$V,$B85,'Structures Database'!R:R)/60 -> 5.7833333 | T85: =A85*S85 -> 0 | U85: =SUMIF('Structures Database'!$V:$V,$B85,'Structures Database'!Y:Y) -> 4.390716 | V85: =A85*U85 -> 0 | AG85: 0 | AH85: 0 | AI85: 0 | AJ85: 0 | AK85: 0 | AL85: 0 | AM85: 0 | AN85: 15 | AO85: 18 | AP85: 19 | AQ85: 0 | AR85: 0 | AS85: 0 | AU85: =AJ85+AK85+AL85+AM85+AN85+AO85+AP85+AQ85+AR85+AS85 -> 52
A86: =X19 | B86: ='Structures Database'!A239 -> Roof frame 1689 x 3574 (compact gable edge) | C86: =SUMIF('Structures Database'!$V:$V,$B86,'Structures Database'!U:U) -> 101.31906 | D86: =$A86*C86 -> 0 | E86: =C86*$B$40 -> 10.131906 | F86: =A86*E86 -> 0 | G86: =C86+E86 -> 111.45097 | H86: =A86*G86 -> 0 | I86: =C86*$B$39 -> 374880.53 | J86: =I86*A86 -> 0 | K86: =E86*$B$39 -> 37488.053 | L86: =K86*A86 -> 0 | M86: =G86*$B$39 -> 412368.58 | N86: =M86*A86 -> 0 | O86: =SUMIF('Structures Database'!$V:$V,$B86,'Structures Database'!P:P) -> 122.04981 | P86: =$A86*O86 -> 0 | Q86: =SUMIF('Structures Database'!$V:$V,$B86,'Structures Database'!Q:Q) -> 190.6737 | R86: =$A86*Q86 -> 0 | S86: =SUMIF('Structures Database'!$V:$V,$B86,'Structures Database'!R:R)/60 -> 11.15 | T86: =A86*S86 -> 0 | U86: =SUMIF('Structures Database'!$V:$V,$B86,'Structures Database'!Y:Y) -> 6.152756 | V86: =A86*U86 -> 0 | AG86: 0 | AH86: 0 | AI86: 0 | AJ86: 0 | AK86: 0 | AL86: 0 | AM86: 0 | AN86: 4 | AO86: 4 | AP86: 4 | AQ86: 0 | AR86: 0 | AS86: 0 | AU86: =AJ86+AK86+AL86+AM86+AN86+AO86+AP86+AQ86+AR86+AS86 -> 12
A87: =Y19 | B87: ='Structures Database'!A255 -> Roof frame 1221 x 4194 (standard gable) | C87: =SUMIF('Structures Database'!$V:$V,$B87,'Structures Database'!U:U) -> 67.445159 | D87: =$A87*C87 -> 0 | E87: =C87*$B$40 -> 6.7445159 | F87: =A87*E87 -> 0 | G87: =C87+E87 -> 74.189675 | H87: =A87*G87 -> 0 | I87: =C87*$B$39 -> 249547.09 | J87: =I87*A87 -> 0 | K87: =E87*$B$39 -> 24954.709 | L87: =K87*A87 -> 0 | M87: =G87*$B$39 -> 274501.8 | N87: =M87*A87 -> 0 | O87: =SUMIF('Structures Database'!$V:$V,$B87,'Structures Database'!P:P) -> 85.584283 | P87: =$A87*O87 -> 0 | Q87: =SUMIF('Structures Database'!$V:$V,$B87,'Structures Database'!Q:Q) -> 133.71957 | R87: =$A87*Q87 -> 0 | S87: =SUMIF('Structures Database'!$V:$V,$B87,'Structures Database'!R:R)/60 -> 6 | T87: =A87*S87 -> 0 | U87: =SUMIF('Structures Database'!$V:$V,$B87,'Structures Database'!Y:Y) -> 5.147736 | V87: =A87*U87 -> 0 | AG87: 0 | AH87: 0 | AI87: 0 | AJ87: 0 | AK87: 0 | AL87: 0 | AM87: 0 | AN87: 15 | AO87: 18 | AP87: 19 | AQ87: 0 | AR87: 0 | AS87: 0 | AU87: =AJ87+AK87+AL87+AM87+AN87+AO87+AP87+AQ87+AR87+AS87 -> 52
A88: =Z19 | B88: ='Structures Database'!A271 -> Roof frame 1689 x 4194 (standard gable edge) | C88: =SUMIF('Structures Database'!$V:$V,$B88,'Structures Database'!U:U) -> 108.47197 | D88: =$A88*C88 -> 0 | E88: =C88*$B$40 -> 10.847197 | F88: =A88*E88 -> 0 | G88: =C88+E88 -> 119.31916 | H88: =A88*G88 -> 0 | I88: =C88*$B$39 -> 401346.27 | J88: =I88*A88 -> 0 | K88: =E88*$B$39 -> 40134.627 | L88: =K88*A88 -> 0 | M88: =G88*$B$39 -> 441480.9 | N88: =M88*A88 -> 0 | O88: =SUMIF('Structures Database'!$V:$V,$B88,'Structures Database'!P:P) -> 135.86262 | P88: =$A88*O88 -> 0 | Q88: =SUMIF('Structures Database'!$V:$V,$B88,'Structures Database'!Q:Q) -> 212.68883 | R88: =$A88*Q88 -> 0 | S88: =SUMIF('Structures Database'!$V:$V,$B88,'Structures Database'!R:R)/60 -> 11.875 | T88: =A88*S88 -> 0 | U88: =SUMIF('Structures Database'!$V:$V,$B88,'Structures Database'!Y:Y) -> 7.213576 | V88: =A88*U88 -> 0 | AG88: 0 | AH88: 0 | AI88: 0 | AJ88: 0 | AK88: 0 | AL88: 0 | AM88: 0 | AN88: 4 | AO88: 4 | AP88: 4 | AQ88: 0 | AR88: 0 | AS88: 0 | AU88: =AJ88+AK88+AL88+AM88+AN88+AO88+AP88+AQ88+AR88+AS88 -> 12
A89: =AA19 -> 14 | B89: ='Structures Database'!A287 -> Roof frame 1221 x 5435 (large gable) | C89: =SUMIF('Structures Database'!$V:$V,$B89,'Structures Database'!U:U) -> 83.185323 | D89: =$A89*C89 -> 1164.5945 | E89: =C89*$B$40 -> 8.3185323 | F89: =A89*E89 -> 116.45945 | G89: =C89+E89 -> 91.503855 | H89: =A89*G89 -> 1281.054 | I89: =C89*$B$39 -> 307785.7 | J89: =I89*A89 -> 4308999.7 | K89: =E89*$B$39 -> 30778.57 | L89: =K89*A89 -> 430899.97 | M89: =G89*$B$39 -> 338564.27 | N89: =M89*A89 -> 4739899.7 | O89: =SUMIF('Structures Database'!$V:$V,$B89,'Structures Database'!P:P) -> 106.20391 | P89: =$A89*O89 -> 1486.8548 | Q89: =SUMIF('Structures Database'!$V:$V,$B89,'Structures Database'!Q:Q) -> 166.38964 | R89: =$A89*Q89 -> 2329.455 | S89: =SUMIF('Structures Database'!$V:$V,$B89,'Structures Database'!R:R)/60 -> 7.3333333 | T89: =A89*S89 -> 102.66667 | U89: =SUMIF('Structures Database'!$V:$V,$B89,'Structures Database'!Y:Y) -> 6.662997 | V89: =A89*U89 -> 93.281958 | AG89: 0 | AH89: 0 | AI89: 0 | AJ89: 0 | AK89: 0 | AL89: 0 | AM89: 0 | AN89: 0 | AO89: 0 | AP89: 0 | AQ89: 0 | AR89: 0 | AS89: 14 | AU89: =AJ89+AK89+AL89+AM89+AN89+AO89+AP89+AQ89+AR89+AS89 -> 14
A90: =AB19 -> 4 | B90: ='Structures Database'!A303 -> Roof frame 1689 x 5435 (large gable edge) | C90: =SUMIF('Structures Database'!$V:$V,$B90,'Structures Database'!U:U) -> 133.59487 | D90: =$A90*C90 -> 534.37948 | E90: =C90*$B$40 -> 13.359487 | F90: =A90*E90 -> 53.437948 | G90: =C90+E90 -> 146.95436 | H90: =A90*G90 -> 587.81743 | I90: =C90*$B$39 -> 494301.02 | J90: =I90*A90 -> 1977204.1 | K90: =E90*$B$39 -> 49430.102 | L90: =K90*A90 -> 197720.41 | M90: =G90*$B$39 -> 543731.12 | N90: =M90*A90 -> 2174924.5 | O90: =SUMIF('Structures Database'!$V:$V,$B90,'Structures Database'!P:P) -> 169.01386 | P90: =$A90*O90 -> 676.05545 | Q90: =SUMIF('Structures Database'!$V:$V,$B90,'Structures Database'!Q:Q) -> 265.20838 | R90: =$A90*Q90 -> 1060.8335 | S90: =SUMIF('Structures Database'!$V:$V,$B90,'Structures Database'!R:R)/60 -> 14.475 | T90: =A90*S90 -> 57.9 | U90: =SUMIF('Structures Database'!$V:$V,$B90,'Structures Database'!Y:Y) -> 9.336927 | V90: =A90*U90 -> 37.347708 | AG90: 0 | AH90: 0 | AI90: 0 | AJ90: 0 | AK90: 0 | AL90: 0 | AM90: 0 | AN90: 0 | AO90: 0 | AP90: 0 | AQ90: 0 | AR90: 0 | AS90: 4 | AU90: =AJ90+AK90+AL90+AM90+AN90+AO90+AP90+AQ90+AR90+AS90 -> 4
A91: =AC19 | B91: ='Structures Database'!A319 -> Roof frame 1221 x 5780 (clerestory upper) | C91: =SUMIF('Structures Database'!$V:$V,$B91,'Structures Database'!U:U) -> 88.572955 | D91: =$A91*C91 -> 0 | E91: =C91*$B$40 -> 8.8572955 | F91: =A91*E91 -> 0 | G91: =C91+E91 -> 97.430251 | H91: =A91*G91 -> 0 | I91: =C91*$B$39 -> 327719.93 | J91: =I91*A91 -> 0 | K91: =E91*$B$39 -> 32771.993 | L91: =K91*A91 -> 0 | M91: =G91*$B$39 -> 360491.93 | N91: =M91*A91 -> 0 | O91: =SUMIF('Structures Database'!$V:$V,$B91,'Structures Database'!P:P) -> 114.64761 | P91: =$A91*O91 -> 0 | Q91: =SUMIF('Structures Database'!$V:$V,$B91,'Structures Database'!Q:Q) -> 179.84127 | R91: =$A91*Q91 -> 0 | S91: =SUMIF('Structures Database'!$V:$V,$B91,'Structures Database'!R:R)/60 -> 8.2666667 | T91: =A91*S91 -> 0 | U91: =SUMIF('Structures Database'!$V:$V,$B91,'Structures Database'!Y:Y) -> 7.111104 | V91: =A91*U91 -> 0 | AG91: 0 | AH91: 4 | AI91: 0 | AJ91: 0 | AK91: 0 | AL91: 0 | AM91: 0 | AN91: 0 | AO91: 0 | AP91: 0 | AQ91: 4 | AR91: 6.5 | AS91: 0 | AU91: =AJ91+AK91+AL91+AM91+AN91+AO91+AP91+AQ91+AR91+AS91 -> 10.5
A92: =AD19 | B92: ='Structures Database'!A335 -> Roof frame 1689 x 5780 (clerestory upper edge) | C92: =SUMIF('Structures Database'!$V:$V,$B92,'Structures Database'!U:U) -> 143.92618 | D92: =$A92*C92 -> 0 | E92: =C92*$B$40 -> 14.392618 | F92: =A92*E92 -> 0 | G92: =C92+E92 -> 158.31879 | H92: =A92*G92 -> 0 | I92: =C92*$B$39 -> 532526.86 | J92: =I92*A92 -> 0 | K92: =E92*$B$39 -> 53252.686 | L92: =K92*A92 -> 0 | M92: =G92*$B$39 -> 585779.54 | N92: =M92*A92 -> 0 | O92: =SUMIF('Structures Database'!$V:$V,$B92,'Structures Database'!P:P) -> 183.63161 | P92: =$A92*O92 -> 0 | Q92: =SUMIF('Structures Database'!$V:$V,$B92,'Structures Database'!Q:Q) -> 288.32472 | R92: =$A92*Q92 -> 0 | S92: =SUMIF('Structures Database'!$V:$V,$B92,'Structures Database'!R:R)/60 -> 16.258333 | T92: =A92*S92 -> 0 | U92: =SUMIF('Structures Database'!$V:$V,$B92,'Structures Database'!Y:Y) -> 9.964864 | V92: =A92*U92 -> 0 | AG92: 0 | AH92: 2 | AI92: 0 | AJ92: 0 | AK92: 0 | AL92: 0 | AM92: 0 | AN92: 0 | AO92: 0 | AP92: 0 | AQ92: 2 | AR92: 2 | AS92: 0 | AU92: =AJ92+AK92+AL92+AM92+AN92+AO92+AP92+AQ92+AR92+AS92 -> 4
A93: =AE19 | B93: ='Structures Database'!A351 -> Roof frame 1221 x 4194 (clerestory lower) | C93: =SUMIF('Structures Database'!$V:$V,$B93,'Structures Database'!U:U) -> 67.276231 | D93: =$A93*C93 -> 0 | E93: =C93*$B$40 -> 6.7276231 | F93: =A93*E93 -> 0 | G93: =C93+E93 -> 74.003854 | H93: =A93*G93 -> 0 | I93: =C93*$B$39 -> 248922.05 | J93: =I93*A93 -> 0 | K93: =E93*$B$39 -> 24892.205 | L93: =K93*A93 -> 0 | M93: =G93*$B$39 -> 273814.26 | N93: =M93*A93 -> 0 | O93: =SUMIF('Structures Database'!$V:$V,$B93,'Structures Database'!P:P) -> 86.230944 | P93: =$A93*O93 -> 0 | Q93: =SUMIF('Structures Database'!$V:$V,$B93,'Structures Database'!Q:Q) -> 134.83528 | R93: =$A93*Q93 -> 0 | S93: =SUMIF('Structures Database'!$V:$V,$B93,'Structures Database'!R:R)/60 -> 6.1166667 | T93: =A93*S93 -> 0 | U93: =SUMIF('Structures Database'!$V:$V,$B93,'Structures Database'!Y:Y) -> 5.147736 | V93: =A93*U93 -> 0 | AG93: 0 | AH93: 4 | AI93: 0 | AJ93: 0 | AK93: 0 | AL93: 0 | AM93: 0 | AN93: 0 | AO93: 0 | AP93: 0 | AQ93: 4 | AR93: 6.5 | AS93: 0 | AU93: =AJ93+AK93+AL93+AM93+AN93+AO93+AP93+AQ93+AR93+AS93 -> 10.5
A94: =AF19 | B94: ='Structures Database'!A367 -> Roof frame 1689 x 4194 (clerestory lower edge) | C94: =SUMIF('Structures Database'!$V:$V,$B94,'Structures Database'!U:U) -> 110.31947 | D94: =$A94*C94 -> 0 | E94: =C94*$B$40 -> 11.031947 | F94: =A94*E94 -> 0 | G94: =C94+E94 -> 121.35142 | H94: =A94*G94 -> 0 | I94: =C94*$B$39 -> 408182.03 | J94: =I94*A94 -> 0 | K94: =E94*$B$39 -> 40818.203 | L94: =K94*A94 -> 0 | M94: =G94*$B$39 -> 449000.24 | N94: =M94*A94 -> 0 | O94: =SUMIF('Structures Database'!$V:$V,$B94,'Structures Database'!P:P) -> 139.28806 | P94: =$A94*O94 -> 0 | Q94: =SUMIF('Structures Database'!$V:$V,$B94,'Structures Database'!Q:Q) -> 218.0936 | R94: =$A94*Q94 -> 0 | S94: =SUMIF('Structures Database'!$V:$V,$B94,'Structures Database'!R:R)/60 -> 12.325 | T94: =A94*S94 -> 0 | U94: =SUMIF('Structures Database'!$V:$V,$B94,'Structures Database'!Y:Y) -> 7.213576 | V94: =A94*U94 -> 0 | AG94: 0 | AH94: 2 | AI94: 0 | AJ94: 0 | AK94: 0 | AL94: 0 | AM94: 0 | AN94: 0 | AO94: 0 | AP94: 0 | AQ94: 2 | AR94: 2 | AS94: 0 | AU94: =AJ94+AK94+AL94+AM94+AN94+AO94+AP94+AQ94+AR94+AS94 -> 4
A95: =A91*0.5+A92*0.5 -> 0 | B95: ='Structures Database'!A383 -> Clerestory frame 2442 x 420 | C95: =SUMIF('Structures Database'!$V:$V,$B95,'Structures Database'!U:U) -> 40.334662 | D95: =$A95*C95 -> 0 | E95: =C95*$B$40 -> 4.0334662 | F95: =A95*E95 -> 0 | G95: =C95+E95 -> 44.368129 | H95: =A95*G95 -> 0 | I95: =C95*$B$39 -> 149238.25 | J95: =I95*A95 -> 0 | K95: =E95*$B$39 -> 14923.825 | L95: =K95*A95 -> 0 | M95: =G95*$B$39 -> 164162.08 | N95: =M95*A95 -> 0 | O95: =SUMIF('Structures Database'!$V:$V,$B95,'Structures Database'!P:P) -> 16.585816 | P95: =$A95*O95 -> 0 | Q95: =SUMIF('Structures Database'!$V:$V,$B95,'Structures Database'!Q:Q) -> 25.875065 | R95: =$A95*Q95 -> 0 | S95: =SUMIF('Structures Database'!$V:$V,$B95,'Structures Database'!R:R)/60 -> 2.9166667 | T95: =A95*S95 -> 0 | U95: =SUMIF('Structures Database'!$V:$V,$B95,'Structures Database'!Y:Y) -> 1.02564 | V95: =A95*U95 -> 0 | AG95: =AG91*0.5+AG92*0.5 -> 0 | AH95: =AH91*0.5+AH92*0.5 -> 3 | AI95: 0 | AJ95: 0 | AK95: 0 | AL95: 0 | AM95: 0 | AN95: 0 | AO95: 0 | AP95: 0 | AQ95: 3 | AR95: 4.25 | AS95: 0 | AU95: =AJ95+AK95+AL95+AM95+AN95+AO95+AP95+AQ95+AR95+AS95 -> 7.25
AU96: =AJ96+AK96+AL96+AM96+AN96+AO96+AP96+AQ96+AR96+AS96 -> 0
A97: Windows and exterior door table | AG97: Windows and exterior door table | AH97: Windows and exterior door table | AI97: Windows and exterior door table | AJ97: Windows and exterior door table | AK97: Windows and exterior door table | AL97: Windows and exterior door table | AM97: Windows and exterior door table | AN97: Windows and exterior door table | AO97: Windows and exterior door table | AP97: Windows and exterior door table | AQ97: Windows and exterior door table | AR97: Windows and exterior door table | AS97: Windows and exterior door table
A98: ='Structures Database'!U393 -> 160 | B98: price per sqm alu windows doors | C98: Cost item ($) | D98: Cost total | E98: Margin item | F98: Margin total | G98: Price item | H98: Price total | I98: Cost item | J98: Cost total | K98: Margin item | L98: Margin total | M98: Price item | N98: Price total | AG98: ='Structures Database'!AW393 | AH98: ='Structures Database'!AX393 | AI98: 130 | AJ98: 130 | AK98: 130 | AL98: 130 | AM98: 130 | AN98: 130 | AO98: 130 | AP98: 130 | AQ98: 130 | AR98: 130 | AS98: 130
B99: Net standard window and door dimensions | C99: USD | D99: USD | E99: USD | F99: USD | G99: USD | H99: USD | I99: =$B$38 -> UGX | J99: =$B$38 -> UGX | K99: =$B$38 -> UGX | L99: =$B$38 -> UGX | M99: =$B$38 -> UGX | N99: =$B$38 -> UGX | U99: Surface | V99: Surface total | W99: Width | X99: Height | AU99: =AJ99+AK99+AL99+AM99+AN99+AO99+AP99+AQ99+AR99+AS99 -> 0
A100: 0 | B100: =Y100&" "&W100&" x "&X100 -> Entrance door 950 x 2388 | C100: =U100*$A$98 -> 362.976 | D100: =A100*C100 -> 0 | E100: =C100*$B$40 -> 36.2976 | F100: =A100*E100 -> 0 | G100: =C100+E100 -> 399.2736 | H100: =A100*G100 -> 0 | I100: =C100*$B$39 -> 1343011.2 | J100: =I100*A100 -> 0 | K100: =E100*$B$39 -> 134301.12 | L100: =K100*A100 -> 0 | M100: =G100*$B$39 -> 1477312.3 | N100: =M100*A100 -> 0 | U100: =W100*X100/1000000 -> 2.2686 | V100: =U100*A100 -> 0 | W100: 950 | X100: 2388 | Y100: Entrance door | AG100: 1 | AH100: 2 | AI100: 1 | AJ100: 1 | AK100: 1 | AL100: 1 | AM100: 1 | AN100: 2 | AO100: 1 | AP100: 1 | AQ100: 2 | AR100: 2 | AS100: 1 | AU100: =AJ100+AK100+AL100+AM100+AN100+AO100+AP100+AQ100+AR100+AS100 -> 13
A101: 0 | B101: =Y101&" "&W101&" x "&X101 -> Terrace swing doors 1700 x 2388 | C101: =U101*$A$98 -> 649.536 | D101: =A101*C101 -> 0 | E101: =C101*$B$40 -> 64.9536 | F101: =A101*E101 -> 0 | G101: =C101+E101 -> 714.4896 | H101: =A101*G101 -> 0 | I101: =C101*$B$39 -> 2403283.2 | J101: =I101*A101 -> 0 | K101: =E101*$B$39 -> 240328.32 | L101: =K101*A101 -> 0 | M101: =G101*$B$39 -> 2643611.5 | N101: =M101*A101 -> 0 | U101: =W101*X101/1000000 -> 4.0596 | V101: =U101*A101 -> 0 | W101: 1700 | X101: 2388 | Y101: Terrace swing doors | AG101: 0 | AH101: 0 | AI101: 0 | AJ101: 0 | AK101: 0 | AL101: 0 | AM101: 0 | AN101: 0 | AO101: 1 | AP101: 0 | AQ101: 0 | AR101: 0 | AS101: 0 | AU101: =AJ101+AK101+AL101+AM101+AN101+AO101+AP101+AQ101+AR101+AS101 -> 1
A102: 0 | B102: =Y102&" "&W102&" x "&X102 -> Sliding doors 1700 x 2388 | C102: =U102*$A$98 -> 649.536 | D102: =A102*C102 -> 0 | E102: =C102*$B$40 -> 64.9536 | F102: =A102*E102 -> 0 | G102: =C102+E102 -> 714.4896 | H102: =A102*G102 -> 0 | I102: =C102*$B$39 -> 2403283.2 | J102: =I102*A102 -> 0 | K102: =E102*$B$39 -> 240328.32 | L102: =K102*A102 -> 0 | M102: =G102*$B$39 -> 2643611.5 | N102: =M102*A102 -> 0 | U102: =W102*X102/1000000 -> 4.0596 | V102: =U102*A102 -> 0 | W102: 1700 | X102: 2388 | Y102: Sliding doors | AG102: 0 | AH102: 0 | AI102: 0 | AJ102: 0 | AK102: 0 | AL102: 0 | AM102: 0 | AN102: 0 | AO102: 0 | AP102: 0 | AQ102: 0 | AR102: 0 | AS102: 0 | AU102: =AJ102+AK102+AL102+AM102+AN102+AO102+AP102+AQ102+AR102+AS102 -> 0
A103: 0 | B103: =Y103&" "&W103&" x "&X103 -> Sliding doors 2300 x 2388 | C103: =U103*$A$98 -> 878.784 | D103: =A103*C103 -> 0 | E103: =C103*$B$40 -> 87.8784 | F103: =A103*E103 -> 0 | G103: =C103+E103 -> 966.6624 | H103: =A103*G103 -> 0 | I103: =C103*$B$39 -> 3251500.8 | J103: =I103*A103 -> 0 | K103: =E103*$B$39 -> 325150.08 | L103: =K103*A103 -> 0 | M103: =G103*$B$39 -> 3576650.9 | N103: =M103*A103 -> 0 | U103: =W103*X103/1000000 -> 5.4924 | V103: =U103*A103 -> 0 | W103: 2300 | X103: 2388 | Y103: Sliding doors | AG103: 0 | AH103: 0 | AI103: 0 | AJ103: 0 | AK103: 0 | AL103: 0 | AM103: 0 | AN103: 1 | AO103: 0 | AP103: 1 | AQ103: 0 | AR103: 0 | AS103: 1 | AU103: =AJ103+AK103+AL103+AM103+AN103+AO103+AP103+AQ103+AR103+AS103 -> 3
A104: 0 | B104: =Y104&" "&W104&" x "&X104 -> Sliding doors 2900 x 2388 | C104: =U104*$A$98 -> 1108.032 | D104: =A104*C104 -> 0 | E104: =C104*$B$40 -> 110.8032 | F104: =A104*E104 -> 0 | G104: =C104+E104 -> 1218.8352 | H104: =A104*G104 -> 0 | I104: =C104*$B$39 -> 4099718.4 | J104: =I104*A104 -> 0 | K104: =E104*$B$39 -> 409971.84 | L104: =K104*A104 -> 0 | M104: =G104*$B$39 -> 4509690.2 | N104: =M104*A104 -> 0 | U104: =W104*X104/1000000 -> 6.9252 | V104: =U104*A104 -> 0 | W104: 2900 | X104: 2388 | Y104: Sliding doors | AG104: 0 | AH104: 0 | AI104: 0 | AJ104: 0 | AK104: 0 | AL104: 0 | AM104: 0 | AN104: 0 | AO104: 0 | AP104: 0 | AQ104: 0 | AR104: 0 | AS104: 0 | AU104: =AJ104+AK104+AL104+AM104+AN104+AO104+AP104+AQ104+AR104+AS104 -> 0
A105: 0 | B105: =Y105&" "&W105&" x "&X105 -> Sliding doors 3510 x 2388 | C105: =U105*$A$98 -> 1341.1008 | D105: =A105*C105 -> 0 | E105: =C105*$B$40 -> 134.11008 | F105: =A105*E105 -> 0 | G105: =C105+E105 -> 1475.2109 | H105: =A105*G105 -> 0 | I105: =C105*$B$39 -> 4962073 | J105: =I105*A105 -> 0 | K105: =E105*$B$39 -> 496207.3 | L105: =K105*A105 -> 0 | M105: =G105*$B$39 -> 5458280.3 | N105: =M105*A105 -> 0 | U105: =W105*X105/1000000 -> 8.38188 | V105: =U105*A105 -> 0 | W105: 3510 | X105: 2388 | Y105: Sliding doors | AG105: 0 | AH105: 0 | AI105: 0 | AJ105: 0 | AK105: 0 | AL105: 0 | AM105: 0 | AN105: 0 | AO105: 0 | AP105: 0 | AQ105: 0 | AR105: 0 | AS105: 0 | AU105: =AJ105+AK105+AL105+AM105+AN105+AO105+AP105+AQ105+AR105+AS105 -> 0
A106: 0 | B106: =Y106&" "&W106&" x "&X106 -> Bathroom window 500 x 1316 | C106: =U106*$A$98 -> 105.28 | D106: =A106*C106 -> 0 | E106: =C106*$B$40 -> 10.528 | F106: =A106*E106 -> 0 | G106: =C106+E106 -> 115.808 | H106: =A106*G106 -> 0 | I106: =C106*$B$39 -> 389536 | J106: =I106*A106 -> 0 | K106: =E106*$B$39 -> 38953.6 | L106: =K106*A106 -> 0 | M106: =G106*$B$39 -> 428489.6 | N106: =M106*A106 -> 0 | U106: =W106*X106/1000000 -> 0.658 | V106: =U106*A106 -> 0 | W106: 500 | X106: 1316 | Y106: Bathroom window | AG106: 1 | AH106: 1 | AI106: 1 | AJ106: 3 | AK106: 2 | AL106: 1 | AM106: 2 | AN106: 0 | AO106: 2 | AP106: 2 | AQ106: 1 | AR106: 2 | AS106: 2 | AU106: =AJ106+AK106+AL106+AM106+AN106+AO106+AP106+AQ106+AR106+AS106 -> 17
A107: 0 | B107: =Y107&" "&W107&" x "&X107 -> Bathroom window 900 x 1316 | C107: =U107*$A$98 -> 189.504 | D107: =A107*C107 -> 0 | E107: =C107*$B$40 -> 18.9504 | F107: =A107*E107 -> 0 | G107: =C107+E107 -> 208.4544 | H107: =A107*G107 -> 0 | I107: =C107*$B$39 -> 701164.8 | J107: =I107*A107 -> 0 | K107: =E107*$B$39 -> 70116.48 | L107: =K107*A107 -> 0 | M107: =G107*$B$39 -> 771281.28 | N107: =M107*A107 -> 0 | U107: =W107*X107/1000000 -> 1.1844 | V107: =U107*A107 -> 0 | W107: 900 | X107: 1316 | Y107: Bathroom window | AG107: 0 | AH107: 0 | AI107: 0 | AJ107: 0 | AK107: 0 | AL107: 0 | AM107: 0 | AN107: 2 | AO107: 1 | AP107: 1 | AQ107: 0 | AR107: 0 | AS107: 0 | AU107: =AJ107+AK107+AL107+AM107+AN107+AO107+AP107+AQ107+AR107+AS107 -> 4
A108: 0 | B108: =Y108&" "&W108&" x "&X108 -> Sliding window 1100 x 1316 | C108: =U108*$A$98 -> 231.616 | D108: =A108*C108 -> 0 | E108: =C108*$B$40 -> 23.1616 | F108: =A108*E108 -> 0 | G108: =C108+E108 -> 254.7776 | H108: =A108*G108 -> 0 | I108: =C108*$B$39 -> 856979.2 | J108: =I108*A108 -> 0 | K108: =E108*$B$39 -> 85697.92 | L108: =K108*A108 -> 0 | M108: =G108*$B$39 -> 942677.12 | N108: =M108*A108 -> 0 | U108: =W108*X108/1000000 -> 1.4476 | V108: =U108*A108 -> 0 | W108: 1100 | X108: 1316 | Y108: Sliding window | AG108: 4 | AH108: 8 | AI108: 6 | AJ108: 2 | AK108: 3 | AL108: 5 | AM108: 4 | AN108: 0 | AO108: 0 | AP108: 0 | AQ108: 0 | AR108: 4 | AS108: 0 | AU108: =AJ108+AK108+AL108+AM108+AN108+AO108+AP108+AQ108+AR108+AS108 -> 18
A109: 0 | B109: =Y109&" "&W109&" x "&X109 -> Sliding window 1400 x 1316 | C109: =U109*$A$98 -> 294.784 | D109: =A109*C109 -> 0 | E109: =C109*$B$40 -> 29.4784 | F109: =A109*E109 -> 0 | G109: =C109+E109 -> 324.2624 | H109: =A109*G109 -> 0 | I109: =C109*$B$39 -> 1090700.8 | J109: =I109*A109 -> 0 | K109: =E109*$B$39 -> 109070.08 | L109: =K109*A109 -> 0 | M109: =G109*$B$39 -> 1199770.9 | N109: =M109*A109 -> 0 | U109: =W109*X109/1000000 -> 1.8424 | V109: =U109*A109 -> 0 | W109: 1400 | X109: 1316 | Y109: Sliding window | AG109: 0 | AH109: 0 | AI109: 0 | AJ109: 0 | AK109: 0 | AL109: 0 | AM109: 0 | AN109: 4 | AO109: 5 | AP109: 6 | AQ109: 4 | AR109: 6 | AS109: 5 | AU109: =AJ109+AK109+AL109+AM109+AN109+AO109+AP109+AQ109+AR109+AS109 -> 30
A110: 0 | B110: =Y110&" "&W110&" x "&X110 -> High window (fixed) 1100 x 1766 | C110: =U110*$A$98 -> 310.816 | D110: =A110*C110 -> 0 | E110: =C110*$B$40 -> 31.0816 | F110: =A110*E110 -> 0 | G110: =C110+E110 -> 341.8976 | H110: =A110*G110 -> 0 | I110: =C110*$B$39 -> 1150019.2 | J110: =I110*A110 -> 0 | K110: =E110*$B$39 -> 115001.92 | L110: =K110*A110 -> 0 | M110: =G110*$B$39 -> 1265021.1 | N110: =M110*A110 -> 0 | U110: =W110*X110/1000000 -> 1.9426 | V110: =U110*A110 -> 0 | W110: 1100 | X110: 1766 | Y110: High window (fixed) | AG110: 0 | AH110: 0 | AI110: 0 | AJ110: 0 | AK110: 0 | AL110: 0 | AM110: 0 | AN110: 0 | AO110: 0 | AP110: 0 | AQ110: 0 | AR110: 0 | AS110: 0 | AU110: =AJ110+AK110+AL110+AM110+AN110+AO110+AP110+AQ110+AR110+AS110 -> 0
A111: 0 | B111: =Y111&" "&W111&" x "&X111 -> High window (fixed) 1700 x 1766 | C111: =U111*$A$98 -> 480.352 | D111: =A111*C111 -> 0 | E111: =C111*$B$40 -> 48.0352 | F111: =A111*E111 -> 0 | G111: =C111+E111 -> 528.3872 | H111: =A111*G111 -> 0 | I111: =C111*$B$39 -> 1777302.4 | J111: =I111*A111 -> 0 | K111: =E111*$B$39 -> 177730.24 | L111: =K111*A111 -> 0 | M111: =G111*$B$39 -> 1955032.6 | N111: =M111*A111 -> 0 | U111: =W111*X111/1000000 -> 3.0022 | V111: =U111*A111 -> 0 | W111: 1700 | X111: 1766 | Y111: High window (fixed) | AG111: 0 | AH111: 0 | AI111: 0 | AJ111: 0 | AK111: 0 | AL111: 0 | AM111: 0 | AN111: 0 | AO111: 0 | AP111: 0 | AQ111: 0 | AR111: 0 | AS111: 0 | AU111: =AJ111+AK111+AL111+AM111+AN111+AO111+AP111+AQ111+AR111+AS111 -> 0
... A115: 0 | B115: =Y115&" "&W115&" x "&X115 -> Panorama window (fixed) 2300 x 846 | C115: =U115*$A$98 -> 311.328 | D115: =A115*C115 -> 0 | E115: =C115*$B$40 -> 31.1328 | F115: =A115*E115 -> 0 | G115: =C115+E115 -> 342.4608 | H115: =A115*G115 -> 0 | I115: =C115*$B$39 -> 1151913.6 | J115: =I115*A115 -> 0 | K115: =E115*$B$39 -> 115191.36 | L115: =K115*A115 -> 0 | M115: =G115*$B$39 -> 1267105 | N115: =M115*A115 -> 0 | U115: =W115*X115/1000000 -> 1.9458 | V115: =U115*A115 -> 0 | W115: 2300 | X115: 846 | Y115: Panorama window (fixed) | AG115: 0 | AH115: 0 | AI115: 0 | AJ115: 0 | AK115: 0 | AL115: 0 | AM115: 0 | AN115: 0 | AO115: 0 | AP115: 0 | AQ115: 0 | AR115: 0 | AS115: 0 | AU115: =AJ115+AK115+AL115+AM115+AN115+AO115+AP115+AQ115+AR115+AS115 -> 0
...

Sheet Price Calc
A1: EASY HOUSING — PRICE CALCULATION
A2: Internal sales-price engine — Uganda (UGX) & Kenya (KES). Inputs flow in from the Project Input tab. Edit only the highlighted rate cells.
A3: UGANDA · UGX | G3: KENYA · KES
A4: General Information | G4: General Information
A5: Quotation Date | B5: =TODAY() -> 46195 | G5: Quotation Date | H5: =TODAY() -> 46195
A6: Validity | B6: One month | G6: Validity | H6: One month
A8: All prices are inclusive of VAT | G8: All prices are inclusive of VAT
A9: All prices are in Ugandan Shillings (UGX) | G9: All prices are in Kenyan Shillings (KES)
A10: No rights can be derived from this quote | G10: No rights can be derived from this quote
A12: Client Information | G12: Client Information
A13: Client Name | B13: ='Project Input'!B22 -> One Bedroom Compact Gable | G13: Client Name | H13: =B13 -> One Bedroom Compact Gable
A14: Contact Details | B14: ='Project Input'!B23 -> +256 712 345 678 | G14: Contact Details | H14: =B14 -> +256 712 345 678
A15: Created by | B15: ='Project Input'!B27 -> Wolf Bierens | G15: Quotation Made By | H15: =B15 -> Wolf Bierens
A17: Project information | G17: Project information
A18: Easy Housing Typology | B18: =B59 -> Large Gable (9768) | G18: Easy Housing Typology | H18: =B18 -> Large Gable (9768)
A19: Gross Floor Area (sqm) | B19: =B63 -> 109.2 | G19: Gross Floor Area (sqm) | H19: =B19 -> 109.2
A20: Terrace (sqm) | B20: =B41 -> 0 | G20: Terrace (sqm) | H20: =B20 -> 0
A21: Bedrooms | B21: =B70 -> 3 | G21: Bedrooms | H21: =B21 -> 3
A22: Bathrooms | B22: =B71 -> 2 | G22: Bathrooms | H22: =B22 -> 2
A23: Project Location | B23: ='Project Input'!B24 -> Sagala | G23: Project Location | H23: =B23 -> Sagala
A24: Distance from factory | B24: ='Project Input'!B25 -> 50 | G24: Distance from factory | H24: =B24 -> 50
A26: Quotation Price Breakdown | G26: Quotation Price Breakdown
A28: Price Breakdown | E28: Price (UGX) | G28: Price Breakdown | K28: Price (KES)
A30: Complete Easy Home | E30: =E82 -> 177216000 | G30: Complete Easy Home | K30: =G82 -> 6793780
A31: Includes: | G31: Includes:
A32: All labour and overhead | G32: All labour and overhead
A33: Full structure | G33: Full structure
A34: Paintworks | G34: Paintworks
A35: Electrical installations | G35: Electrical installations
A36: Plumbing (if any) | G36: Plumbing (if any)
A37: See price list for more details | G37: See price list for more details
A39: Additional options | B39: Size | C39: Unit | D39: Unit price | E39: Price (UGX) | G39: Additional options | H39: Size | I39: Unit | J39: Unit price | K39: Price (KES)
A40: Burglar bars | B40: ='Project Input'!B49 -> 0 | C40: sqm | D40: 250000 | E40: =B40*D40 -> 0 | F40: For standard design burglar bars of steel | G40: Burglar bars | H40: =B40 -> 0 | I40: =C40 -> sqm | J40: 7500 | K40: =H40*J40 -> 0
A41: Terrace | B41: ='Project Input'!B44 -> 0 | C41: sqm | D41: 300000 | E41: =B41*D41 -> 0 | F41: In standard size frames, including linseed oil finishing and foundation work | G41: Terrace | H41: =B41 -> 0 | I41: =C41 -> sqm | J41: 12000 | K41: =H41*J41 -> 0
A42: Pergola | B42: ='Project Input'!B45 -> 0 | C42: sqm | D42: 100000 | E42: =B42*D42 -> 0 | F42: For an open structure pergola with beams every 60 cm | G42: Pergola | H42: =B42 -> 0 | I42: =C42 -> sqm | J42: 4000 | K42: =H42*J42 -> 0
A43: Railing open | B43: ='Project Input'!B46 -> 0 | C43: m1 | D43: 90000 | E43: =B43*D43 -> 0 | F43: With studs every 1.2m | G43: Railing open | H43: =B43 -> 0 | I43: =C43 -> m1 | J43: 3500 | K43: =H43*J43 -> 0
A44: Railing semi-closed | B44: ='Project Input'!B47 -> 0 | C44: m1 | D44: 180000 | E44: =B44*D44 -> 0 | F44: With studs every 20 cm so that kids and animals cannot fall through | G44: Railing semi-closed | H44: =B44 -> 0 | I44: =C44 -> m1 | J44: 7000 | K44: =H44*J44 -> 0
A45: Wheelchair ramp | B45: ='Project Input'!B50 -> 0 | C45: pcs | D45: 1500000 | E45: =B45*D45 -> 0 | F45: For an average ramp of around 5m long (low inclination) | G45: Wheelchair ramp | H45: =B45 -> 0 | I45: =C45 -> pcs | J45: 6500 | K45: =H45*J45 -> 0
A46: Tiles | C46: total | E46: ='Project Input'!B51 -> 0 | G46: Tiles | I46: =C46 -> total | K46: ='Project Input'!B51 -> 0
A47: Sanitary wares | C47: total | E47: ='Project Input'!B52 -> 0 | G47: Sanitary wares | I47: =C47 -> total | K47: ='Project Input'!B52 -> 0
A48: Biodigester | C48: total | E48: ='Project Input'!B53 -> 0 | G48: Biodigester | I48: =C48 -> total | K48: ='Project Input'!B53 -> 0
A49: ="Other options: "&'Project Input'!B54 -> Other options: | E49: ='Project Input'!B55 | G49: ='Project Input'!A55 -> Other option(s) price | I49: =C49 | K49: ='Project Input'!B55
A50: Total Additional Options | E50: =SUM(E40:E49) -> 0 | G50: Total Additional Options | H50: =B50 | I50: =C50 | K50: =SUM(K40:K49) -> 0
A52: Total Price Per Home Including Options | D52: UGX | E52: =E30+E50 -> 177216000 | G52: Total Price Per Home Including Options | K52: =K30+K50 -> 6793780
F53: Per GFA | L53: Per GFA
A54: Number of Homes | B54: ='Project Input'!B31 -> 1 | C54: home(s) | D54: =E52 -> 177216000 | E54: =B54*D54 -> 177216000 | F54: =E54/$B$55 -> 1622857.1 | G54: Number of Homes | H54: =B54 -> 1 | J54: =K52 -> 6793780 | K54: =H54*J54 -> 6793780 | L54: =K54/$B$55 -> 62214.103
B55: =B19*B54 -> 109.2 | C55: GFA | E55: =E54/'Location Data'!$D$6 -> 47896.216 | F55: =E55/$B$55 -> 438.61004 | K55: =K54/'Location Data'!D12 -> 52259.846 | L55: =K55/$B$55 -> 478.57002
A56: CALCULATION ENGINE — internal logic. Edit only the yellow rate cells (annual price update). Do not move rows: the Project Input, Project Costs & Project Output tabs link here.
D57: Uganda (UGX) | F57: Kenya (KES)
A58: Basic structure parameters | B58: Amount | C58: Unit | D58: Unit price | E58: Total price | F58: Unit price | G58: Total price
A59: Building typology | B59: ='Project Input'!B30 -> Large Gable (9768)
A60: Columns A (1221) | B60: ='Project Input'!B32 -> 0 | C60: pcs
A61: Columns B (2442) | B61: ='Project Input'!B33 -> 2 | C61: pcs
A62: Columns C (3053) | B62: ='Project Input'!B34 -> 2 | C62: pcs
A63: Floor area | B63: =H98 -> 109.2 | C63: sqm
A64: Core and shell price | D64: =I98 -> 1145000 | E64: =J98 -> 125034000 | F64: =K98 -> 43500 | G64: =L98 -> 4750200
A65: Interior doors | B65: ='Project Input'!B36 -> 5 | C65: pcs | D65: 850000 | E65: =B65*D65 -> 4250000 | F65: 30000 | G65: =B65*F65 -> 150000
A66: Partitions (length) | B66: ='Project Input'!B35 -> 33 | C66: linear metres | D66: 500000 | E66: =B66*D66 -> 16500000 | F66: 20000 | G66: =B66*F66 -> 660000
A67: External doors & windows (area) | B67: ='Project Input'!B37 -> 23.7 | C67: sqm | D67: 600000 | E67: =B67*D67 -> 14220000 | F67: 23000 | G67: =B67*F67 -> 545100
A68: Extra staircase (beyond the first) | B68: ='Project Input'!B48 -> 0 | C68: pcs | D68: 600000 | E68: =B68*D68 -> 0 | F68: 32000 | G68: =B68*F68 -> 0
A69: Living rooms | B69: 0 | C69: #
A70: Bedrooms | B70: ='Project Input'!B38 -> 3 | C70: #
A71: Bathrooms | B71: ='Project Input'!B39 -> 2 | C71: #
A72: Kitchen areas | B72: ='Project Input'!B41 -> 1 | C72: #
A73: Corridors | B73: 0 | C73: #
A74: Other rooms | B74: 0 | C74: #
A75: Total sqm bathrooms | B75: 0 | C75: sqm
A76: Total circumference bathrooms | B76: 0 | C76: linear metres
A77: Distance from factory | B77: ='Project Input'!B25 -> 50 | C77: km | D77: 400 | E77: =IF((B77-100)>0,(B77-100)*B63*D77,0) -> 0 | F77: 15 | G77: =IF((B77-100)>0,(B77-100)*B63*F77,0) -> 0
A78: Electricity | B78: =B80 -> 109.2 | C78: sqm | E78: =2000000+B78*80000 -> 10736000 | G78: =80000+3200*B78 -> 429440
A79: Plumbing | B79: =B72+B71 -> 3 | C79: plumbing areas | E79: =IF(B79>0,1500000+500000*B79,0) -> 3000000 | G79: =IF(B79>0,60000+20000*B79,0) -> 120000
A80: Architecture costs | B80: =B63 -> 109.2 | C80: sqm | E80: =15000*B80 -> 1638000 | G80: =600*B80 -> 65520
A81: Engineering costs | B81: =B80 -> 109.2 | C81: sqm | E81: =200000+B81*15000 -> 1838000 | G81: =8000+600*B81 -> 73520
A82: Full Easy Home Price | C82: Total | E82: =SUM(E59:E81) -> 177216000 | G82: =SUM(G59:G81) -> 6793780
A83: Colour key: | C83: Yellow fill = editable rate cell (update at annual price changes)
A84: Linked from Project Input / databases
A86: TYPOLOGY CALCULATOR — GFA & basic-structure price by typology (yellow = per-sqm rate)
A87: Typology Calculator | B87: Gross Depth | C87: Column A | D87: Column B | E87: Column C | F87: Flanks | G87: Width Total | H87: GFA | I87: Sqm Price (UGX) | J87: Basic Price (UGX) | K87: Sqm Price (KES) | L87: Basic Price (KES)
A88: Mono Pitch (4884) | B88: 4972 | C88: =1221*$B$60 -> 0 | D88: =2442*$B$61 -> 4884 | E88: =3053*$B$62 -> 6106 | F88: 88 | G88: =SUM(C88:F88) -> 11078 | H88: =ROUNDUP(B88*G88/1000000,1) -> 55.1 | I88: 1145000 | J88: =H88*I88 -> 63089500 | K88: 43500 | L88: =K88*H88 -> 2396850
A89: Small Gable (4884) | B89: =B88 -> 4972 | C89: =1221*$B$60 -> 0 | D89: =2442*$B$61 -> 4884 | E89: =3053*$B$62 -> 6106 | F89: 88 | G89: =SUM(C89:F89) -> 11078 | H89: =ROUNDUP(B89*G89/1000000,1) -> 55.1 | I89: 1255000 | K89: 45000
A90: Compact Gable (6106) | B90: 6194 | C90: =1221*$B$60 -> 0 | D90: =2442*$B$61 -> 4884 | E90: =3053*$B$62 -> 6106 | F90: 88 | G90: =SUM(C90:F90) -> 11078 | H90: =ROUNDUP(B90*G90/1000000,1) -> 68.7 | I90: 1145000 | J90: =H90*I90 -> 78661500 | K90: 43500 | L90: =K90*H90 -> 2988450
A91: Standard Gable (7326) | B91: 7414 | C91: =1221*$B$60 -> 0 | D91: =2442*$B$61 -> 4884 | E91: =3053*$B$62 -> 6106 | F91: 88 | G91: =SUM(C91:F91) -> 11078 | H91: =ROUNDUP(B91*G91/1000000,1) -> 82.2 | I91: 1145000 | J91: =H91*I91 -> 94119000 | K91: 43500 | L91: =K91*H91 -> 3575700
A92: Large Gable (9768) | B92: 9856 | C92: =1221*$B$60 -> 0 | D92: =2442*$B$61 -> 4884 | E92: =3053*$B$62 -> 6106 | F92: 88 | G92: =SUM(C92:F92) -> 11078 | H92: =ROUNDUP(B92*G92/1000000,1) -> 109.2 | I92: 1145000 | J92: =H92*I92 -> 125034000 | K92: 43500 | L92: =K92*H92 -> 4750200
A93: Standard Clerestory (7326) | B93: 7414 | C93: =1221*$B$60 -> 0 | D93: =2442*$B$61 -> 4884 | E93: =3053*$B$62 -> 6106 | F93: 88 | G93: =SUM(C93:F93) -> 11078 | H93: =ROUNDUP(B93*G93/1000000,1) -> 82.2 | I93: 1255000 | J93: =H93*I93 -> 103161000 | K93: 45000 | L93: =K93*H93 -> 3699000
A94: Large Clerestory (8547) | B94: 8635 | C94: =1221*$B$60 -> 0 | D94: =2442*$B$61 -> 4884 | E94: =3053*$B$62 -> 6106 | F94: 88 | G94: =SUM(C94:F94) -> 11078 | H94: =ROUNDUP(B94*G94/1000000,1) -> 95.7 | I94: 1255000 | J94: =H94*I94 -> 120103500 | K94: 45000 | L94: =K94*H94 -> 4306500
A95: A Frame Compact (3663) | B95: 3663 | C95: =1221*$B$60 -> 0 | D95: =2442*$B$61 -> 4884 | E95: =3053*$B$62 -> 6106 | F95: 44 | G95: =SUM(C95:F95) -> 11034 | H95: =ROUNDUP(B95*G95/1000000,1) -> 40.5 | I95: 1145000 | J95: =H95*I95 -> 46372500 | K95: 43500 | L95: =K95*H95 -> 1761750
A96: A Frame Standard (4884) | B96: 4884 | C96: =1221*$B$60 -> 0 | D96: =2442*$B$61 -> 4884 | E96: =3053*$B$62 -> 6106 | F96: 44 | G96: =SUM(C96:F96) -> 11034 | H96: =ROUNDUP(B96*G96/1000000,1) -> 53.9 | I96: 1145000 | J96: =H96*I96 -> 61715500 | K96: 43500 | L96: =K96*H96 -> 2344650
A97: A Frame Large (6106) | B97: 6106 | C97: =1221*$B$60 -> 0 | D97: =2442*$B$61 -> 4884 | E97: =3053*$B$62 -> 6106 | F97: 44 | G97: =SUM(C97:F97) -> 11034 | H97: =ROUNDUP(B97*G97/1000000,1) -> 67.4 | I97: 1145000 | J97: =H97*I97 -> 77173000 | K97: 43500 | L97: =K97*H97 -> 2931900
A98: =B59 -> Large Gable (9768) | H98: =INDEX(H88:H97,MATCH($A$98,$A$88:$A$97,0)) -> 109.2 | I98: =INDEX(I88:I97,MATCH($A$98,$A$88:$A$97,0)) -> 1145000 | J98: =INDEX(J88:J97,MATCH($A$98,$A$88:$A$97,0)) -> 125034000 | K98: =INDEX(K88:K97,MATCH($A$98,$A$88:$A$97,0)) -> 43500 | L98: =INDEX(L88:L97,MATCH($A$98,$A$88:$A$97,0)) -> 4750200

Sheet Catalogue Prices 2026
A1: Prices including VAT per Q1 2025
A3: Uganda | B3: GFA | C3: Basic home | E3: Tier 1 finishings | H3: Total inc tier 1 finishings | K3: Price ex finishing per GFA | L3: Price inc finishing per GFA | M3: Licence fee | O3: Bathrooms | P3: Kitchen blocks
A4: Model | C4: USD | D4: UGX | E4: USD | G4: UGX | H4: USD | I4: UGX
A5: Studio | B5: 25 | C5: =D5/3700 -> 9121.6216 | D5: =B5*1350000 -> 33750000 | E5: =G5/3700 -> 1689.1892 | G5: =B5*250000 -> 6250000 | H5: =I5/3700 -> 10810.811 | I5: =D5+G5 -> 40000000 | K5: =C5/B5 -> 364.86486 | L5: =H5/B5 -> 432.43243 | M5: =B5*25 -> 625 | N5: =K5*3700 -> 1350000 | O5: 1 | P5: 5
A6: One Bedroom Mono | B6: 37 | C6: =D6/3700 -> 13500 | D6: =B6*1350000 -> 49950000 | E6: =G6/3700 -> 2500 | G6: =B6*250000 -> 9250000 | H6: =I6/3700 -> 16000 | I6: =D6+G6 -> 59200000 | K6: =C6/B6 -> 364.86486 | L6: =H6/B6 -> 432.43243 | M6: =B6*25 -> 925 | N6: =K6*3700 -> 1350000 | O6: 1 | P6: 4
A7: Two Bedroom Mono | B7: 43 | C7: =D7/3700 -> 15689.189 | D7: =B7*1350000 -> 58050000 | E7: =G7/3700 -> 2905.4054 | G7: =B7*250000 -> 10750000 | H7: =I7/3700 -> 18594.595 | I7: =D7+G7 -> 68800000 | K7: =C7/B7 -> 364.86486 | L7: =H7/B7 -> 432.43243 | M7: =B7*25 -> 1075 | N7: =K7*3700 -> 1350000 | O7: 1 | P7: 5
A8: Three Bedroom Mono | B8: 46 | C8: =D8/3700 -> 16783.784 | D8: =B8*1350000 -> 62100000 | E8: =G8/3700 -> 3108.1081 | G8: =B8*250000 -> 11500000 | H8: =I8/3700 -> 19891.892 | I8: =D8+G8 -> 73600000 | K8: =C8/B8 -> 364.86486 | L8: =H8/B8 -> 432.43243 | M8: =B8*25 -> 1150 | N8: =K8*3700 -> 1350000 | O8: 1 | P8: 4
A9: One Bedroom Compact Gable | B9: 46 | O9: 1 | P9: 6
A10: Two Bedroom Compact Gable | B10: 61 | O10: 2 | P10: 6
A11: Three Bedroom Compact Gable | B11: 69 | O11: 2 | P11: 6
A12: Four Bedroom Compact Gable | B12: 76 | O12: 2 | P12: 6
A13: Two Bedroom Comfort Compact Gable | B13: 76 | O13: 2 | P13: 6
A14: Two Bedroom Gable | B14: 87 | C14: =D14/3700 -> 31743.243 | D14: =B14*1350000 -> 117450000 | E14: =G14/3700 -> 5878.3784 | G14: =B14*250000 -> 21750000 | H14: =I14/3700 -> 37621.622 | I14: =D14+G14 -> 139200000 | K14: =C14/B14 -> 364.86486 | L14: =H14/B14 -> 432.43243 | M14: =B14*25 -> 2175 | N14: =K14*3700 -> 1350000 | O14: 2 | P14: 7
A15: Three Bedroom Gable | B15: 96 | C15: =D15/3700 -> 35027.027 | D15: =B15*1350000 -> 129600000 | E15: =G15/3700 -> 6486.4865 | G15: =B15*250000 -> 24000000 | H15: =I15/3700 -> 41513.514 | I15: =D15+G15 -> 153600000 | K15: =C15/B15 -> 364.86486 | L15: =H15/B15 -> 432.43243 | M15: =B15*25 -> 2400 | N15: =K15*3700 -> 1350000 | O15: 3 | P15: 7
A16: Four Bedroom Gable | B16: 105 | C16: =D16/3700 -> 38310.811 | D16: =B16*1350000 -> 141750000 | E16: =G16/3700 -> 7094.5946 | G16: =B16*250000 -> 26250000 | H16: =I16/3700 -> 45405.405 | I16: =D16+G16 -> 168000000 | K16: =C16/B16 -> 364.86486 | L16: =H16/B16 -> 432.43243 | M16: =B16*25 -> 2625 | N16: =K16*3700 -> 1350000 | O16: 3 | P16: 7
A17: Three Bedroom Large Gable | B17: 109 | C17: =D17/3700 -> 39770.27 | D17: =B17*1350000 -> 147150000 | E17: =G17/3700 -> 7364.8649 | G17: =B17*250000 -> 27250000 | H17: =I17/3700 -> 47135.135 | I17: =D17+G17 -> 174400000 | K17: =C17/B17 -> 364.86486 | L17: =H17/B17 -> 432.43243 | M17: =B17*25 -> 2725 | N17: =K17*3700 -> 1350000 | O17: 2 | P17: 8
A18: Two Bedroom Clerestory | B18: 64 | C18: =D18/3700 -> 24562.162 | D18: =B18*1420000 -> 90880000 | E18: =G18/3700 -> 4324.3243 | G18: =B18*250000 -> 16000000 | H18: =I18/3700 -> 28886.486 | I18: =D18+G18 -> 106880000 | K18: =C18/B18 -> 383.78378 | L18: =H18/B18 -> 451.35135 | M18: =B18*25 -> 1600 | N18: =K18*3700 -> 1420000 | O18: 1 | P18: 7
A19: Four Bedroom Clerestory | B19: 106 | C19: =D19/3700 -> 40681.081 | D19: =B19*1420000 -> 150520000 | E19: =G19/3700 -> 7162.1622 | G19: =B19*250000 -> 26500000 | H19: =I19/3700 -> 47843.243 | I19: =D19+G19 -> 177020000 | K19: =C19/B19 -> 383.78378 | L19: =H19/B19 -> 451.35135 | M19: =B19*25 -> 2650 | N19: =K19*3700 -> 1420000 | O19: 2 | P19: 7
A22: All models except clerestory at 1.35M per sqm. Clerestory at 1.42M per sqm.
A23: Uganda | C23: UGX | M23: Transposed for brochure
A24: Model | B24: Floor area | C24: Basic structure | D24: Electricals | E24: Plumbing | F24: Total | G24: Tiling | H24: Sanitary wares | I24: Kitchen block | J24: Grand total | K24: Basic in USD | L24: Full in USD | N24: Studio | O24: One Bedroom Mono | P24: Two Bedroom Mono | Q24: Three Bedroom Mono | R24: Two Bedroom Gable | S24: Three Bedroom Gable | T24: Four Bedroom Gable | U24: Three Bedroom Large Gable | V24: Two Bedroom Clerestory | W24: Four Bedroom Clerestory
A25: Studio | B25: =B5 -> 25 | C25: =B25*1350000 -> 33750000 | D25: =1500000+50000*B25 -> 2750000 | E25: =500000+O5*1000000+B5*20000 -> 2000000 | F25: =C25+D25+E25 -> 38500000 | G25: =80000*12*O5 -> 960000 | H25: =2300000*O5 -> 2300000 | I25: =2000000+500000*P5 -> 4500000 | J25: =SUM(C25:I25) -> 84760000 | K25: =C25/'Location Data'!$D$6 -> 9121.6216 | L25: =J25/'Location Data'!$D$6 -> 22908.108 | M25: Basic structure | N25: 33750000 | O25: 41850000 | P25: 58050000 | Q25: 62100000 | R25: 117450000 | S25: 129600000 | T25: 141750000 | U25: 147150000 | V25: 86400000 | W25: 122850000
A26: One Bedroom Mono | B26: 37 | C26: =B26*1350000 -> 49950000 | D26: =1500000+50000*B26 -> 3350000 | E26: =500000+O6*1000000+B6*20000 -> 2240000 | F26: =C26+D26+E26 -> 55540000 | G26: =80000*12*O6 -> 960000 | H26: =2300000*O6 -> 2300000 | I26: =I25 -> 4500000 | J26: =SUM(C26:I26) -> 118840000 | K26: =C26/'Location Data'!$D$6 -> 13500 | L26: =J26/'Location Data'!$D$6 -> 32118.919 | M26: Electricals | N26: 2750000 | O26: 3050000 | P26: 3650000 | Q26: 3800000 | R26: 5850000 | S26: 6300000 | T26: 6750000 | U26: 6950000 | V26: 4700000 | W26: 6050000
A27: Two Bedroom Mono | B27: =B7 -> 43 | C27: =B27*1350000 -> 58050000 | D27: =1500000+50000*B27 -> 3650000 | E27: =500000+O7*1000000+B7*20000 -> 2360000 | F27: =C27+D27+E27 -> 64060000 | G27: =80000*12*O7 -> 960000 | H27: =2300000*O7 -> 2300000 | I27: =2000000+500000*P7 -> 4500000 | J27: =SUM(C27:I27) -> 135880000 | K27: =C27/'Location Data'!$D$6 -> 15689.189 | L27: =J27/'Location Data'!$D$6 -> 36724.324 | M27: Plumbing | N27: 2000000 | O27: 2120000 | P27: 2360000 | Q27: 2420000 | R27: 4240000 | S27: 5420000 | T27: 5600000 | U27: 4680000 | V27: 2780000 | W27: 4320000
A28: Three Bedroom Mono | B28: =B8 -> 46 | C28: =B28*1350000 -> 62100000 | D28: =1500000+50000*B28 -> 3800000 | E28: =500000+O8*1000000+B8*20000 -> 2420000 | F28: =C28+D28+E28 -> 68320000 | G28: =80000*12*O8 -> 960000 | H28: =2300000*O8 -> 2300000 | I28: =2000000+500000*P8 -> 4000000 | J28: =SUM(C28:I28) -> 143900000 | K28: =C28/'Location Data'!$D$6 -> 16783.784 | L28: =J28/'Location Data'!$D$6 -> 38891.892 | M28: Tiling | N28: 960000 | O28: 960000 | P28: 960000 | Q28: 960000 | R28: 1920000 | S28: 2880000 | T28: 2880000 | U28: 1920000 | V28: 960000 | W28: 1920000
A29: One Bedroom Compact Gable | B29: 46 | C29: =B29*1350000 -> 62100000 | D29: =1500000+50000*B29 -> 3800000 | E29: =500000+O9*1000000+B9*20000 -> 2420000 | F29: =C29+D29+E29 -> 68320000 | G29: =80000*12*O9 -> 960000 | H29: =2300000*O9 -> 2300000 | I29: =2000000+500000*P9 -> 5000000 | J29: =SUM(C29:I29) -> 144900000 | K29: =C29/'Location Data'!$D$6 -> 16783.784 | L29: =J29/'Location Data'!$D$6 -> 39162.162 | M29: Sanitary wares | N29: 2300000 | O29: 2300000 | P29: 2300000 | Q29: 2300000 | R29: 4600000 | S29: 6900000 | T29: 6900000 | U29: 4600000 | V29: 2300000 | W29: 4600000
A30: Two Bedroom Compact Gable | B30: 61 | C30: =B30*1350000 -> 82350000 | D30: =1500000+50000*B30 -> 4550000 | E30: =500000+O10*1000000+B10*20000 -> 3720000 | F30: =C30+D30+E30 -> 90620000 | G30: =80000*12*O10 -> 1920000 | H30: =2300000*O10 -> 4600000 | I30: =2000000+500000*P10 -> 5000000 | J30: =SUM(C30:I30) -> 192760000 | K30: =C30/'Location Data'!$D$6 -> 22256.757 | L30: =J30/'Location Data'!$D$6 -> 52097.297 | M30: Kitchen block | N30: 4500000 | O30: 4500000 | P30: 4500000 | Q30: 4000000 | R30: 5500000 | S30: 5500000 | T30: 5500000 | U30: 6000000 | V30: 5500000 | W30: 5500000
A31: Three Bedroom Compact Gable | B31: 69 | C31: =B31*1350000 -> 93150000 | D31: =1500000+50000*B31 -> 4950000 | E31: =500000+O11*1000000+B11*20000 -> 3880000 | F31: =C31+D31+E31 -> 101980000 | G31: =80000*12*O11 -> 1920000 | H31: =2300000*O11 -> 4600000 | I31: =2000000+500000*P11 -> 5000000 | J31: =SUM(C31:I31) -> 215480000 | K31: =C31/'Location Data'!$D$6 -> 25175.676 | L31: =J31/'Location Data'!$D$6 -> 58237.838 | M31: Grand total | N31: 46260000 | O31: 54780000 | P31: 71820000 | Q31: 75580000 | R31: 139560000 | S31: 156600000 | T31: 169380000 | U31: 171300000 | V31: 102640000 | W31: 145240000
A32: Four Bedroom Compact Gable | B32: 76 | C32: =B32*1350000 -> 102600000 | D32: =1500000+50000*B32 -> 5300000 | E32: =500000+O12*1000000+B12*20000 -> 4020000 | F32: =C32+D32+E32 -> 111920000 | G32: =80000*12*O12 -> 1920000 | H32: =2300000*O12 -> 4600000 | I32: =2000000+500000*P12 -> 5000000 | J32: =SUM(C32:I32) -> 235360000 | K32: =C32/'Location Data'!$D$6 -> 27729.73 | L32: =J32/'Location Data'!$D$6 -> 63610.811
A33: Two Bedroom Comfort Compact Gable | B33: 76 | C33: =B33*1350000 -> 102600000 | D33: =1500000+50000*B33 -> 5300000 | E33: =500000+O13*1000000+B13*20000 -> 4020000 | F33: =C33+D33+E33 -> 111920000 | G33: =80000*12*O13 -> 1920000 | H33: =2300000*O13 -> 4600000 | I33: =2000000+500000*P13 -> 5000000 | J33: =SUM(C33:I33) -> 235360000 | K33: =C33/'Location Data'!$D$6 -> 27729.73 | L33: =J33/'Location Data'!$D$6 -> 63610.811
A34: Two Bedroom Gable | B34: =B14 -> 87 | C34: =B34*1350000 -> 117450000 | D34: =1500000+50000*B34 -> 5850000 | E34: =500000+O14*1000000+B14*20000 -> 4240000 | F34: =C34+D34+E34 -> 127540000 | G34: =80000*12*O14 -> 1920000 | H34: =2300000*O14 -> 4600000 | I34: =2000000+500000*P14 -> 5500000 | J34: =SUM(C34:I34) -> 267100000 | K34: =C34/'Location Data'!$D$6 -> 31743.243 | L34: =J34/'Location Data'!$D$6 -> 72189.189
A35: Three Bedroom Gable | B35: =B15 -> 96 | C35: =B35*1350000 -> 129600000 | D35: =1500000+50000*B35 -> 6300000 | E35: =500000+O15*1000000+B15*20000 -> 5420000 | F35: =C35+D35+E35 -> 141320000 | G35: =80000*12*O15 -> 2880000 | H35: =2300000*O15 -> 6900000 | I35: =2000000+500000*P15 -> 5500000 | J35: =SUM(C35:I35) -> 297920000 | K35: =C35/'Location Data'!$D$6 -> 35027.027 | L35: =J35/'Location Data'!$D$6 -> 80518.919
A36: Four Bedroom Gable | B36: =B16 -> 105 | C36: =B36*1350000 -> 141750000 | D36: =1500000+50000*B36 -> 6750000 | E36: =500000+O16*1000000+B16*20000 -> 5600000 | F36: =C36+D36+E36 -> 154100000 | G36: =80000*12*O16 -> 2880000 | H36: =2300000*O16 -> 6900000 | I36: =2000000+500000*P16 -> 5500000 | J36: =SUM(C36:I36) -> 323480000 | K36: =C36/'Location Data'!$D$6 -> 38310.811 | L36: =J36/'Location Data'!$D$6 -> 87427.027
A37: Three Bedroom Large Gable | B37: =B17 -> 109 | C37: =B37*1350000 -> 147150000 | D37: =1500000+50000*B37 -> 6950000 | E37: =500000+O17*1000000+B17*20000 -> 4680000 | F37: =C37+D37+E37 -> 158780000 | G37: =80000*12*O17 -> 1920000 | H37: =2300000*O17 -> 4600000 | I37: =2000000+500000*P17 -> 6000000 | J37: =SUM(C37:I37) -> 330080000 | K37: =C37/'Location Data'!$D$6 -> 39770.27 | L37: =J37/'Location Data'!$D$6 -> 89210.811
A38: Two Bedroom Large Clerestory | B38: =B18 -> 64 | C38: =D18 -> 90880000 | D38: =1500000+50000*B38 -> 4700000 | E38: =500000+O18*1000000+B18*20000 -> 2780000 | F38: =C38+D38+E38 -> 98360000 | G38: =80000*12*O18 -> 960000 | H38: =2300000*O18 -> 2300000 | I38: =2000000+500000*P18 -> 5500000 | J38: =SUM(C38:I38) -> 205480000 | K38: =C38/'Location Data'!$D$6 -> 24562.162 | L38: =J38/'Location Data'!$D$6 -> 55535.135 | N38: UGX | O38: 1350000 | P38: per sqm gfa all types | R38: =O38/'Location Data'!$D$6 -> 364.86486
A39: Four Bedroom Large Clerestory | B39: 106 | C39: =D19 -> 150520000 | D39: =1500000+50000*B39 -> 6800000 | E39: =500000+O19*1000000+B19*20000 -> 4620000 | F39: =C39+D39+E39 -> 161940000 | G39: =80000*12*O19 -> 1920000 | H39: =2300000*O19 -> 4600000 | I39: =2000000+500000*P19 -> 5500000 | J39: =SUM(C39:I39) -> 335900000 | K39: =C39/'Location Data'!$D$6 -> 40681.081 | L39: =J39/'Location Data'!$D$6 -> 90783.784 | O39: 1420000 | P39: per sqm gfa for clerestory | R39: =O39/'Location Data'!$D$6 -> 383.78378
A41: Kenya | C41: KES
A42: Model | B42: Floor area | C42: Basic structure | D42: Electricals | E42: Plumbing | F42: Total | G42: Tiling | H42: Sanitary wares | I42: Kitchen block | J42: Grand total | K42: Basic in USD | L42: Full in USD | N42: KES | O42: 52000 | P42: per sqm gfa all types | R42: =O42/'Location Data'!$D$12 -> 400 | S42: =R42/R38 -> 1.0962963
A43: Studio | B43: 25 | C43: =B43*$O$42 -> 1300000 | D43: =D25*($S$43+0.05)/'Location Data'!$D$6*'Location Data'!$D$12 -> 111345.17 | E43: =E25*($S$43+0.05)/'Location Data'!$D$6*'Location Data'!$D$12 -> 80978.302 | F43: =C43+D43+E43 -> 1492323.5 | G43: =G25*($S$43+0.05)/'Location Data'!$D$6*'Location Data'!$D$12 -> 38869.585 | H43: =H25*($S$43+0.05)/'Location Data'!$D$6*'Location Data'!$D$12 -> 93125.048 | I43: =I25*($S$43+0.05)/'Location Data'!$D$6*'Location Data'!$D$12 -> 182201.18 | J43: =SUM(C43:I43) -> 3298842.7 | K43: =C43/'Location Data'!$D$12 -> 10000 | L43: =J43/'Location Data'!$D$12 -> 25375.713 | O43: 55000 | P43: per sqm gfa for clerestory | R43: =O43/'Location Data'!$D$12 -> 423.07692 | S43: =R43/R39 -> 1.1023835
A44: One Bedroom Mono | B44: 37 | C44: =B44*$O$42 -> 1924000 | D44: =D26*($S$43+0.05)/'Location Data'!$D$6*'Location Data'!$D$12 -> 135638.66 | E44: =E26*($S$43+0.05)/'Location Data'!$D$6*'Location Data'!$D$12 -> 90695.699 | F44: =C44+D44+E44 -> 2150334.4 | G44: =G26*($S$43+0.05)/'Location Data'!$D$6*'Location Data'!$D$12 -> 38869.585 | H44: =H26*($S$43+0.05)/'Location Data'!$D$6*'Location Data'!$D$12 -> 93125.048 | I44: =I26*($S$43+0.05)/'Location Data'!$D$6*'Location Data'!$D$12 -> 182201.18 | J44: =SUM(C44:I44) -> 4614864.5 | K44: =C44/'Location Data'!$D$12 -> 14800 | L44: =J44/'Location Data'!$D$12 -> 35498.958
A45: Two Bedroom Mono | B45: 43 | C45: =B45*$O$42 -> 2236000 | D45: =D27*($S$43+0.05)/'Location Data'!$D$6*'Location Data'!$D$12 -> 147785.4 | E45: =E27*($S$43+0.05)/'Location Data'!$D$6*'Location Data'!$D$12 -> 95554.397 | F45: =C45+D45+E45 -> 2479339.8 | G45: =G27*($S$43+0.05)/'Location Data'!$D$6*'Location Data'!$D$12 -> 38869.585 | H45: =H27*($S$43+0.05)/'Location Data'!$D$6*'Location Data'!$D$12 -> 93125.048 | I45: =I27*($S$43+0.05)/'Location Data'!$D$6*'Location Data'!$D$12 -> 182201.18 | J45: =SUM(C45:I45) -> 5272875.4 | K45: =C45/'Location Data'!$D$12 -> 17200 | L45: =J45/'Location Data'!$D$12 -> 40560.58
A46: Three Bedroom Mono | B46: 46 | C46: =B46*$O$42 -> 2392000 | D46: =D28*($S$43+0.05)/'Location Data'!$D$6*'Location Data'!$D$12 -> 153858.77 | E46: =E28*($S$43+0.05)/'Location Data'!$D$6*'Location Data'!$D$12 -> 97983.746 | F46: =C46+D46+E46 -> 2643842.5 | G46: =G28*($S$43+0.05)/'Location Data'!$D$6*'Location Data'!$D$12 -> 38869.585 | H46: =H28*($S$43+0.05)/'Location Data'!$D$6*'Location Data'!$D$12 -> 93125.048 | I46: =I28*($S$43+0.05)/'Location Data'!$D$6*'Location Data'!$D$12 -> 161956.6 | J46: =SUM(C46:I46) -> 5581636.3 | K46: =C46/'Location Data'!$D$12 -> 18400 | L46: =J46/'Location Data'!$D$12 -> 42935.664
A47: One Bedroom Compact Gable | B47: 46 | C47: =B47*$O$42 -> 2392000 | D47: =D29*($S$43+0.05)/'Location Data'!$D$6*'Location Data'!$D$12 -> 153858.77 | E47: =E29*($S$43+0.05)/'Location Data'!$D$6*'Location Data'!$D$12 -> 97983.746 | F47: =C47+D47+E47 -> 2643842.5 | G47: =G29*($S$43+0.05)/'Location Data'!$D$6*'Location Data'!$D$12 -> 38869.585 | H47: =H29*($S$43+0.05)/'Location Data'!$D$6*'Location Data'!$D$12 -> 93125.048 | I47: =I29*($S$43+0.05)/'Location Data'!$D$6*'Location Data'!$D$12 -> 202445.76 | J47: =SUM(C47:I47) -> 5622125.4 | K47: =C47/'Location Data'!$D$12 -> 18400 | L47: =J47/'Location Data'!$D$12 -> 43247.119
A48: Two Bedroom Compact Gable | B48: 61 | C48: =B48*$O$42 -> 3172000 | D48: =D30*($S$43+0.05)/'Location Data'!$D$6*'Location Data'!$D$12 -> 184225.64 | E48: =E30*($S$43+0.05)/'Location Data'!$D$6*'Location Data'!$D$12 -> 150619.64 | F48: =C48+D48+E48 -> 3506845.3 | G48: =G30*($S$43+0.05)/'Location Data'!$D$6*'Location Data'!$D$12 -> 77739.17 | H48: =H30*($S$43+0.05)/'Location Data'!$D$6*'Location Data'!$D$12 -> 186250.1 | I48: =I30*($S$43+0.05)/'Location Data'!$D$6*'Location Data'!$D$12 -> 202445.76 | J48: =SUM(C48:I48) -> 7480125.6 | K48: =C48/'Location Data'!$D$12 -> 24400 | L48: =J48/'Location Data'!$D$12 -> 57539.428
A49: Three Bedroom Compact Gable | B49: 69 | C49: =B49*$O$42 -> 3588000 | D49: =D31*($S$43+0.05)/'Location Data'!$D$6*'Location Data'!$D$12 -> 200421.3 | E49: =E31*($S$43+0.05)/'Location Data'!$D$6*'Location Data'!$D$12 -> 157097.91 | F49: =C49+D49+E49 -> 3945519.2 | G49: =G31*($S$43+0.05)/'Location Data'!$D$6*'Location Data'!$D$12 -> 77739.17 | H49: =H31*($S$43+0.05)/'Location Data'!$D$6*'Location Data'!$D$12 -> 186250.1 | I49: =I31*($S$43+0.05)/'Location Data'!$D$6*'Location Data'!$D$12 -> 202445.76 | J49: =SUM(C49:I49) -> 8357473.4 | K49: =C49/'Location Data'!$D$12 -> 27600 | L49: =J49/'Location Data'!$D$12 -> 64288.257
A50: Four Bedroom Compact Gable | B50: 76 | C50: =B50*$O$42 -> 3952000 | D50: =D32*($S$43+0.05)/'Location Data'!$D$6*'Location Data'!$D$12 -> 214592.5 | E50: =E32*($S$43+0.05)/'Location Data'!$D$6*'Location Data'!$D$12 -> 162766.39 | F50: =C50+D50+E50 -> 4329358.9 | G50: =G32*($S$43+0.05)/'Location Data'!$D$6*'Location Data'!$D$12 -> 77739.17 | H50: =H32*($S$43+0.05)/'Location Data'!$D$6*'Location Data'!$D$12 -> 186250.1 | I50: =I32*($S$43+0.05)/'Location Data'!$D$6*'Location Data'!$D$12 -> 202445.76 | J50: =SUM(C50:I50) -> 9125152.8 | K50: =C50/'Location Data'!$D$12 -> 30400 | L50: =J50/'Location Data'!$D$12 -> 70193.483
A51: Two Bedroom Comfort Compact Gable | B51: 76 | C51: =B51*$O$42 -> 3952000 | D51: =D33*($S$43+0.05)/'Location Data'!$D$6*'Location Data'!$D$12 -> 214592.5 | E51: =E33*($S$43+0.05)/'Location Data'!$D$6*'Location Data'!$D$12 -> 162766.39 | F51: =C51+D51+E51 -> 4329358.9 | G51: =G33*($S$43+0.05)/'Location Data'!$D$6*'Location Data'!$D$12 -> 77739.17 | H51: =H33*($S$43+0.05)/'Location Data'!$D$6*'Location Data'!$D$12 -> 186250.1 | I51: =I33*($S$43+0.05)/'Location Data'!$D$6*'Location Data'!$D$12 -> 202445.76 | J51: =SUM(C51:I51) -> 9125152.8 | K51: =C51/'Location Data'!$D$12 -> 30400 | L51: =J51/'Location Data'!$D$12 -> 70193.483
A52: Two Bedroom Gable | B52: 87 | C52: =B52*$O$42 -> 4524000 | D52: =D34*($S$43+0.05)/'Location Data'!$D$6*'Location Data'!$D$12 -> 236861.53 | E52: =E34*($S$43+0.05)/'Location Data'!$D$6*'Location Data'!$D$12 -> 171674 | F52: =C52+D52+E52 -> 4932535.5 | G52: =G34*($S$43+0.05)/'Location Data'!$D$6*'Location Data'!$D$12 -> 77739.17 | H52: =H34*($S$43+0.05)/'Location Data'!$D$6*'Location Data'!$D$12 -> 186250.1 | I52: =I34*($S$43+0.05)/'Location Data'!$D$6*'Location Data'!$D$12 -> 222690.33 | J52: =SUM(C52:I52) -> 10351751 | K52: =C52/'Location Data'!$D$12 -> 34800 | L52: =J52/'Location Data'!$D$12 -> 79628.851
A53: Three Bedroom Gable | B53: 96 | C53: =B53*$O$42 -> 4992000 | D53: =D35*($S$43+0.05)/'Location Data'!$D$6*'Location Data'!$D$12 -> 255081.65 | E53: =E35*($S$43+0.05)/'Location Data'!$D$6*'Location Data'!$D$12 -> 219451.2 | F53: =C53+D53+E53 -> 5466532.9 | G53: =G35*($S$43+0.05)/'Location Data'!$D$6*'Location Data'!$D$12 -> 116608.76 | H53: =H35*($S$43+0.05)/'Location Data'!$D$6*'Location Data'!$D$12 -> 279375.14 | I53: =I35*($S$43+0.05)/'Location Data'!$D$6*'Location Data'!$D$12 -> 222690.33 | J53: =SUM(C53:I53) -> 11551740 | K53: =C53/'Location Data'!$D$12 -> 38400 | L53: =J53/'Location Data'!$D$12 -> 88859.538
A54: Four Bedroom Gable | B54: 105 | C54: =B54*$O$42 -> 5460000 | D54: =D36*($S$43+0.05)/'Location Data'!$D$6*'Location Data'!$D$12 -> 273301.77 | E54: =E36*($S$43+0.05)/'Location Data'!$D$6*'Location Data'!$D$12 -> 226739.25 | F54: =C54+D54+E54 -> 5960041 | G54: =G36*($S$43+0.05)/'Location Data'!$D$6*'Location Data'!$D$12 -> 116608.76 | H54: =H36*($S$43+0.05)/'Location Data'!$D$6*'Location Data'!$D$12 -> 279375.14 | I54: =I36*($S$43+0.05)/'Location Data'!$D$6*'Location Data'!$D$12 -> 222690.33 | J54: =SUM(C54:I54) -> 12538756 | K54: =C54/'Location Data'!$D$12 -> 42000 | L54: =J54/'Location Data'!$D$12 -> 96451.971
A55: Three Bedroom Large Gable | B55: 109 | C55: =B55*$O$42 -> 5668000 | D55: =D37*($S$43+0.05)/'Location Data'!$D$6*'Location Data'!$D$12 -> 281399.6 | E55: =E37*($S$43+0.05)/'Location Data'!$D$6*'Location Data'!$D$12 -> 189489.23 | F55: =C55+D55+E55 -> 6138888.8 | G55: =G37*($S$43+0.05)/'Location Data'!$D$6*'Location Data'!$D$12 -> 77739.17 | H55: =H37*($S$43+0.05)/'Location Data'!$D$6*'Location Data'!$D$12 -> 186250.1 | I55: =I37*($S$43+0.05)/'Location Data'!$D$6*'Location Data'!$D$12 -> 242934.91 | J55: =SUM(C55:I55) -> 12784702 | K55: =C55/'Location Data'!$D$12 -> 43600 | L55: =J55/'Location Data'!$D$12 -> 98343.86
A56: Two Bedroom Large Clerestory | B56: 64 | C56: =B56*$O$43 -> 3520000 | D56: =D38*($S$43+0.05)/'Location Data'!$D$6*'Location Data'!$D$12 -> 190299.01 | E56: =E38*($S$43+0.05)/'Location Data'!$D$6*'Location Data'!$D$12 -> 112559.84 | F56: =C56+D56+E56 -> 3822858.9 | G56: =G38*($S$43+0.05)/'Location Data'!$D$6*'Location Data'!$D$12 -> 38869.585 | H56: =H38*($S$43+0.05)/'Location Data'!$D$6*'Location Data'!$D$12 -> 93125.048 | I56: =I38*($S$43+0.05)/'Location Data'!$D$6*'Location Data'!$D$12 -> 222690.33 | J56: =SUM(C56:I56) -> 8000402.7 | K56: =C56/'Location Data'!$D$12 -> 27076.923 | L56: =J56/'Location Data'!$D$12 -> 61541.559
A57: Four Bedroom Large Clerestory | B57: 106 | C57: =B57*$O$43 -> 5830000 | D57: =D39*($S$43+0.05)/'Location Data'!$D$6*'Location Data'!$D$12 -> 275326.23 | E57: =E39*($S$43+0.05)/'Location Data'!$D$6*'Location Data'!$D$12 -> 187059.88 | F57: =C57+D57+E57 -> 6292386.1 | G57: =G39*($S$43+0.05)/'Location Data'!$D$6*'Location Data'!$D$12 -> 77739.17 | H57: =H39*($S$43+0.05)/'Location Data'!$D$6*'Location Data'!$D$12 -> 186250.1 | I57: =I39*($S$43+0.05)/'Location Data'!$D$6*'Location Data'!$D$12 -> 222690.33 | J57: =SUM(C57:I57) -> 13071452 | K57: =C57/'Location Data'!$D$12 -> 44846.154 | L57: =J57/'Location Data'!$D$12 -> 100549.63
A59: Ghana | C59: GHS | N59: GSH | O59: 6400 | P59: per sqm gfa all types | R59: =O59/'Location Data'!$D$10 -> 441.37931 | S59: =R59/R38 -> 1.2097063
A60: Model | B60: Floor area | C60: Basic structure | D60: Electricals | E60: Plumbing | F60: Total | G60: Tiling | H60: Sanitary wares | I60: Kitchen block | J60: Grand total | K60: Basic in USD | L60: Full in USD | O60: 6700 | P60: per sqm gfa for clerestory | R60: =O60/'Location Data'!$D$10 -> 462.06897 | S60: =R60/R39 -> 1.2039825
A61: Studio | B61: 25 | C61: =B61*$O$59 -> 160000 | D61: =D25*($S$60+0.05)/'Location Data'!$D$6*'Location Data'!$D$10 -> 13514.203 | E61: =E25*($S$60+0.05)/'Location Data'!$D$6*'Location Data'!$D$10 -> 9828.5116 | F61: =C61+D61+E61 -> 183342.72 | G61: =G25*($S$60+0.05)/'Location Data'!$D$6*'Location Data'!$D$10 -> 4717.6856 | H61: =H25*($S$60+0.05)/'Location Data'!$D$6*'Location Data'!$D$10 -> 11302.788 | I61: =I25*($S$60+0.05)/'Location Data'!$D$6*'Location Data'!$D$10 -> 22114.151 | J61: =SUM(C61:I61) -> 404820.06 | K61: =C61/'Location Data'!$D$10 -> 11034.483 | L61: =J61/'Location Data'!$D$10 -> 27918.625
A62: One Bedroom Mono | B62: 37 | C62: =B62*$O$59 -> 236800 | D62: =D26*($S$60+0.05)/'Location Data'!$D$6*'Location Data'!$D$10 -> 16462.757 | E62: =E26*($S$60+0.05)/'Location Data'!$D$6*'Location Data'!$D$10 -> 11007.933 | F62: =C62+D62+E62 -> 264270.69 | G62: =G26*($S$60+0.05)/'Location Data'!$D$6*'Location Data'!$D$10 -> 4717.6856 | H62: =H26*($S$60+0.05)/'Location Data'!$D$6*'Location Data'!$D$10 -> 11302.788 | I62: =I26*($S$60+0.05)/'Location Data'!$D$6*'Location Data'!$D$10 -> 22114.151 | J62: =SUM(C62:I62) -> 566676 | K62: =C62/'Location Data'!$D$10 -> 16331.034 | L62: =J62/'Location Data'!$D$10 -> 39081.104
A63: Two Bedroom Mono | B63: 43 | C63: =B63*$O$59 -> 275200 | D63: =D27*($S$60+0.05)/'Location Data'!$D$6*'Location Data'!$D$10 -> 17937.034 | E63: =E27*($S$60+0.05)/'Location Data'!$D$6*'Location Data'!$D$10 -> 11597.644 | F63: =C63+D63+E63 -> 304734.68 | G63: =G27*($S$60+0.05)/'Location Data'!$D$6*'Location Data'!$D$10 -> 4717.6856 | H63: =H27*($S$60+0.05)/'Location Data'!$D$6*'Location Data'!$D$10 -> 11302.788 | I63: =I27*($S$60+0.05)/'Location Data'!$D$6*'Location Data'!$D$10 -> 22114.151 | J63: =SUM(C63:I63) -> 647603.98 | K63: =C63/'Location Data'!$D$10 -> 18979.31 | L63: =J63/'Location Data'!$D$10 -> 44662.343
A64: Three Bedroom Mono | B64: 46 | C64: =B64*$O$59 -> 294400 | D64: =D28*($S$60+0.05)/'Location Data'!$D$6*'Location Data'!$D$10 -> 18674.172 | E64: =E28*($S$60+0.05)/'Location Data'!$D$6*'Location Data'!$D$10 -> 11892.499 | F64: =C64+D64+E64 -> 324966.67 | G64: =G28*($S$60+0.05)/'Location Data'!$D$6*'Location Data'!$D$10 -> 4717.6856 | H64: =H28*($S$60+0.05)/'Location Data'!$D$6*'Location Data'!$D$10 -> 11302.788 | I64: =I28*($S$60+0.05)/'Location Data'!$D$6*'Location Data'!$D$10 -> 19657.023 | J64: =SUM(C64:I64) -> 685610.84 | K64: =C64/'Location Data'!$D$10 -> 20303.448 | L64: =J64/'Location Data'!$D$10 -> 47283.506
A65: One Bedroom Compact Gable | B65: 46 | C65: =B65*$O$59 -> 294400 | D65: =D29*($S$60+0.05)/'Location Data'!$D$6*'Location Data'!$D$10 -> 18674.172 | E65: =E29*($S$60+0.05)/'Location Data'!$D$6*'Location Data'!$D$10 -> 11892.499 | F65: =C65+D65+E65 -> 324966.67 | G65: =G29*($S$60+0.05)/'Location Data'!$D$6*'Location Data'!$D$10 -> 4717.6856 | H65: =H29*($S$60+0.05)/'Location Data'!$D$6*'Location Data'!$D$10 -> 11302.788 | I65: =I29*($S$60+0.05)/'Location Data'!$D$6*'Location Data'!$D$10 -> 24571.279 | J65: =SUM(C65:I65) -> 690525.1 | K65: =C65/'Location Data'!$D$10 -> 20303.448 | L65: =J65/'Location Data'!$D$10 -> 47622.42
A66: Two Bedroom Compact Gable | B66: 61 | C66: =B66*$O$59 -> 390400 | D66: =D30*($S$60+0.05)/'Location Data'!$D$6*'Location Data'!$D$10 -> 22359.864 | E66: =E30*($S$60+0.05)/'Location Data'!$D$6*'Location Data'!$D$10 -> 18281.032 | F66: =C66+D66+E66 -> 431040.9 | G66: =G30*($S$60+0.05)/'Location Data'!$D$6*'Location Data'!$D$10 -> 9435.3711 | H66: =H30*($S$60+0.05)/'Location Data'!$D$6*'Location Data'!$D$10 -> 22605.577 | I66: =I30*($S$60+0.05)/'Location Data'!$D$6*'Location Data'!$D$10 -> 24571.279 | J66: =SUM(C66:I66) -> 918694.02 | K66: =C66/'Location Data'!$D$10 -> 26924.138 | L66: =J66/'Location Data'!$D$10 -> 63358.208
A67: Three Bedroom Compact Gable | B67: 69 | C67: =B67*$O$59 -> 441600 | D67: =D31*($S$60+0.05)/'Location Data'!$D$6*'Location Data'!$D$10 -> 24325.566 | E67: =E31*($S$60+0.05)/'Location Data'!$D$6*'Location Data'!$D$10 -> 19067.313 | F67: =C67+D67+E67 -> 484992.88 | G67: =G31*($S$60+0.05)/'Location Data'!$D$6*'Location Data'!$D$10 -> 9435.3711 | H67: =H31*($S$60+0.05)/'Location Data'!$D$6*'Location Data'!$D$10 -> 22605.577 | I67: =I31*($S$60+0.05)/'Location Data'!$D$6*'Location Data'!$D$10 -> 24571.279 | J67: =SUM(C67:I67) -> 1026598 | K67: =C67/'Location Data'!$D$10 -> 30455.172 | L67: =J67/'Location Data'!$D$10 -> 70799.861
A68: Four Bedroom Compact Gable | B68: 76 | C68: =B68*$O$59 -> 486400 | D68: =D32*($S$60+0.05)/'Location Data'!$D$6*'Location Data'!$D$10 -> 26045.556 | E68: =E32*($S$60+0.05)/'Location Data'!$D$6*'Location Data'!$D$10 -> 19755.308 | F68: =C68+D68+E68 -> 532200.86 | G68: =G32*($S$60+0.05)/'Location Data'!$D$6*'Location Data'!$D$10 -> 9435.3711 | H68: =H32*($S$60+0.05)/'Location Data'!$D$6*'Location Data'!$D$10 -> 22605.577 | I68: =I32*($S$60+0.05)/'Location Data'!$D$6*'Location Data'!$D$10 -> 24571.279 | J68: =SUM(C68:I68) -> 1121014 | K68: =C68/'Location Data'!$D$10 -> 33544.828 | L68: =J68/'Location Data'!$D$10 -> 77311.307
A69: Two Bedroom Comfort Compact Gable | B69: 76 | C69: =B69*$O$59 -> 486400 | D69: =D33*($S$60+0.05)/'Location Data'!$D$6*'Location Data'!$D$10 -> 26045.556 | E69: =E33*($S$60+0.05)/'Location Data'!$D$6*'Location Data'!$D$10 -> 19755.308 | F69: =C69+D69+E69 -> 532200.86 | G69: =G33*($S$60+0.05)/'Location Data'!$D$6*'Location Data'!$D$10 -> 9435.3711 | H69: =H33*($S$60+0.05)/'Location Data'!$D$6*'Location Data'!$D$10 -> 22605.577 | I69: =I33*($S$60+0.05)/'Location Data'!$D$6*'Location Data'!$D$10 -> 24571.279 | J69: =SUM(C69:I69) -> 1121014 | K69: =C69/'Location Data'!$D$10 -> 33544.828 | L69: =J69/'Location Data'!$D$10 -> 77311.307
A70: Two Bedroom Gable | B70: 87 | C70: =B70*$O$59 -> 556800 | D70: =D34*($S$60+0.05)/'Location Data'!$D$6*'Location Data'!$D$10 -> 28748.396 | E70: =E34*($S$60+0.05)/'Location Data'!$D$6*'Location Data'!$D$10 -> 20836.445 | F70: =C70+D70+E70 -> 606384.84 | G70: =G34*($S$60+0.05)/'Location Data'!$D$6*'Location Data'!$D$10 -> 9435.3711 | H70: =H34*($S$60+0.05)/'Location Data'!$D$6*'Location Data'!$D$10 -> 22605.577 | I70: =I34*($S$60+0.05)/'Location Data'!$D$6*'Location Data'!$D$10 -> 27028.407 | J70: =SUM(C70:I70) -> 1271839 | K70: =C70/'Location Data'!$D$10 -> 38400 | L70: =J70/'Location Data'!$D$10 -> 87713.037
A71: Three Bedroom Gable | B71: 96 | C71: =B71*$O$59 -> 614400 | D71: =D35*($S$60+0.05)/'Location Data'!$D$6*'Location Data'!$D$10 -> 30959.812 | E71: =E35*($S$60+0.05)/'Location Data'!$D$6*'Location Data'!$D$10 -> 26635.266 | F71: =C71+D71+E71 -> 671995.08 | G71: =G35*($S$60+0.05)/'Location Data'!$D$6*'Location Data'!$D$10 -> 14153.057 | H71: =H35*($S$60+0.05)/'Location Data'!$D$6*'Location Data'!$D$10 -> 33908.365 | I71: =I35*($S$60+0.05)/'Location Data'!$D$6*'Location Data'!$D$10 -> 27028.407 | J71: =SUM(C71:I71) -> 1419080 | K71: =C71/'Location Data'!$D$10 -> 42372.414 | L71: =J71/'Location Data'!$D$10 -> 97867.585
A72: Four Bedroom Gable | B72: 105 | C72: =B72*$O$59 -> 672000 | D72: =D36*($S$60+0.05)/'Location Data'!$D$6*'Location Data'!$D$10 -> 33171.227 | E72: =E36*($S$60+0.05)/'Location Data'!$D$6*'Location Data'!$D$10 -> 27519.833 | F72: =C72+D72+E72 -> 732691.06 | G72: =G36*($S$60+0.05)/'Location Data'!$D$6*'Location Data'!$D$10 -> 14153.057 | H72: =H36*($S$60+0.05)/'Location Data'!$D$6*'Location Data'!$D$10 -> 33908.365 | I72: =I36*($S$60+0.05)/'Location Data'!$D$6*'Location Data'!$D$10 -> 27028.407 | J72: =SUM(C72:I72) -> 1540471.9 | K72: =C72/'Location Data'!$D$10 -> 46344.828 | L72: =J72/'Location Data'!$D$10 -> 106239.44
... A75: Four Bedroom Large Clerestory | B75: 106 | C75: =B75*$O$59 -> 678400 | D75: =D39*($S$60+0.05)/'Location Data'!$D$6*'Location Data'!$D$10 -> 33416.939 | E75: =E39*($S$60+0.05)/'Location Data'!$D$6*'Location Data'!$D$10 -> 22703.862 | F75: =C75+D75+E75 -> 734520.8 | G75: =G39*($S$60+0.05)/'Location Data'!$D$6*'Location Data'!$D$10 -> 9435.3711 | H75: =H39*($S$60+0.05)/'Location Data'!$D$6*'Location Data'!$D$10 -> 22605.577 | I75: =I39*($S$60+0.05)/'Location Data'!$D$6*'Location Data'!$D$10 -> 27028.407 | J75: =SUM(C75:I75) -> 1528111 | K75: =C75/'Location Data'!$D$10 -> 46786.207 | L75: =J75/'Location Data'!$D$10 -> 105386.96
B79: Uganda | C79: Kenya | D79: Ghana | G79: USD (UG)
A80: Custom plan with mono pitch roof | B80: 1000000 | C80: =ROUND(B80*1.1/'Location Data'!$D$6*'Location Data'!$D$12,-2) -> 38600 | D80: =ROUND(B80*1.1/'Location Data'!$D$6*'Location Data'!$D$10,-2) -> 4300 | E80: per floor plan | G80: =B80/3700 -> 270.27027 | J80: per floor plan
A81: Custom plan for other types | B81: 1500000 | C81: =ROUND(B81*1.1/'Location Data'!$D$6*'Location Data'!$D$12,-2) -> 58000 | D81: =ROUND(B81*1.1/'Location Data'!$D$6*'Location Data'!$D$10,-2) -> 6500 | E81: per floor plan | G81: =B81/3700 -> 405.40541 | J81: per floor plan
A82: Extra revisions beyond first round | B82: 500000 | C82: =ROUND(B82*1.1/'Location Data'!$D$6*'Location Data'!$D$12,-2) -> 19300 | D82: =ROUND(B82*1.1/'Location Data'!$D$6*'Location Data'!$D$10,-2) -> 2200 | E82: per extra revision | G82: =B82/3700 -> 135.13514 | J82: per extra revision
A83: Stamped and printed permit drawings | B83: 1000000 | C83: =ROUND(B83*1.1/'Location Data'!$D$6*'Location Data'!$D$12,-2) -> 38600 | D83: =ROUND(B83*1.1/'Location Data'!$D$6*'Location Data'!$D$10,-2) -> 4300 | E83: per floor plan | G83: =B83/3700 -> 270.27027 | J83: per floor plan
A84: Site visit rate per day | B84: 400000 | C84: =ROUND(B84*1.1/'Location Data'!$D$6*'Location Data'!$D$12,-2) -> 15500 | D84: =ROUND(B84*1.1/'Location Data'!$D$6*'Location Data'!$D$10,-2) -> 1700 | E84: per day excluding transport (and accommodation) | G84: =B84/3700 -> 108.10811 | J84: per day excluding transport (and accommodation)
A85: Site plan with one unit | B85: 200000 | C85: =ROUND(B85*1.1/'Location Data'!$D$6*'Location Data'!$D$12,-2) -> 7700 | D85: =ROUND(B85*1.1/'Location Data'!$D$6*'Location Data'!$D$10,-2) -> 900 | E85: per site plan (excludes site visit if applicable) | G85: =B85/3700 -> 54.054054 | J85: per site plan (excludes site visit if applicable)
A86: Master plan 2-5 units | B86: 1500000 | C86: =ROUND(B86*1.1/'Location Data'!$D$6*'Location Data'!$D$12,-2) -> 58000 | D86: =ROUND(B86*1.1/'Location Data'!$D$6*'Location Data'!$D$10,-2) -> 6500 | E86: per master plan | G86: =B86/3700 -> 405.40541 | J86: per master plan
A87: Master plan 6-10 units | B87: 2500000 | C87: =ROUND(B87*1.1/'Location Data'!$D$6*'Location Data'!$D$12,-2) -> 96600 | D87: =ROUND(B87*1.1/'Location Data'!$D$6*'Location Data'!$D$10,-2) -> 10800 | E87: per master plan | G87: =B87/3700 -> 675.67568 | J87: per master plan
A88: Master plan 11-25 units | B88: 3500000 | C88: =ROUND(B88*1.1/'Location Data'!$D$6*'Location Data'!$D$12,-2) -> 135300 | D88: =ROUND(B88*1.1/'Location Data'!$D$6*'Location Data'!$D$10,-2) -> 15100 | E88: per master plan | G88: =B88/3700 -> 945.94595 | J88: per master plan
A89: Master plan revision | B89: 500000 | C89: =ROUND(B89*1.1/'Location Data'!$D$6*'Location Data'!$D$12,-2) -> 19300 | D89: =ROUND(B89*1.1/'Location Data'!$D$6*'Location Data'!$D$10,-2) -> 2200 | E89: per revision | G89: =B89/3700 -> 135.13514 | J89: per revision
A90: Rendering | B90: 1000000 | C90: =ROUND(B90*1.1/'Location Data'!$D$6*'Location Data'!$D$12,-2) -> 38600 | D90: =ROUND(B90*1.1/'Location Data'!$D$6*'Location Data'!$D$10,-2) -> 4300 | E90: per rendered image | G90: =B90/3700 -> 270.27027 | J90: per rendered image
B92: Uganda | C92: Kenya | D92: Ghana
A93: Name | B93: Price per unit | C93: Price per unit | D93: Price per unit | E93: Unit
A94: Basic structure | B94: 1350000 | C94: =ROUND(B94*1.1/'Location Data'!$D$6*'Location Data'!$D$12,-1) -> 52180 | D94: =ROUND(B94*1.1/'Location Data'!$D$6*'Location Data'!$D$10,-1) -> 5820 | E94: sqm
A95: Clerestory basic structure | B95: 1420000 | C95: =ROUND(B95*1.1/'Location Data'!$D$6*'Location Data'!$D$12,-1) -> 54880 | D95: =ROUND(B95*1.1/'Location Data'!$D$6*'Location Data'!$D$10,-1) -> 6120 | E95: sqm
A96: Extra interior door | B96: 850000 | C96: =ROUND(B96*1.1/'Location Data'!$D$6*'Location Data'!$D$12,-1) -> 32850 | D96: =ROUND(B96*1.1/'Location Data'!$D$6*'Location Data'!$D$10,-1) -> 3660 | E96: pcs
A97: Extra partition wall | B97: 450000 | C97: =ROUND(B97*1.1/'Location Data'!$D$6*'Location Data'!$D$12,-1) -> 17390 | D97: =ROUND(B97*1.1/'Location Data'!$D$6*'Location Data'!$D$10,-1) -> 1940 | E97: linear metre
A98: Extra windows/doors (alu) | B98: 500000 | C98: =ROUND(B98*1.1/'Location Data'!$D$6*'Location Data'!$D$12,-1) -> 19320 | D98: =ROUND(B98*1.1/'Location Data'!$D$6*'Location Data'!$D$10,-1) -> 2160 | E98: sqm
A99: Burglar bars | B99: 200000 | C99: =ROUND(B99*1.1/'Location Data'!$D$6*'Location Data'!$D$12,-1) -> 7730 | D99: =ROUND(B99*1.1/'Location Data'!$D$6*'Location Data'!$D$10,-1) -> 860 | E99: sqm
A100: Terrace | B100: 285000 | C100: =ROUND(B100*1.1/'Location Data'!$D$6*'Location Data'!$D$12,-1) -> 11010 | D100: =ROUND(B100*1.1/'Location Data'!$D$6*'Location Data'!$D$10,-1) -> 1230 | E100: sqm
A101: Pergola | B101: 100000 | C101: =ROUND(B101*1.1/'Location Data'!$D$6*'Location Data'!$D$12,-1) -> 3860 | D101: =ROUND(B101*1.1/'Location Data'!$D$6*'Location Data'!$D$10,-1) -> 430 | E101: sqm
A102: Sheets on pergola | B102: 185000 | C102: =ROUND(B102*1.1/'Location Data'!$D$6*'Location Data'!$D$12,-1) -> 7150 | D102: =ROUND(B102*1.1/'Location Data'!$D$6*'Location Data'!$D$10,-1) -> 800 | E102: sqm
A103: Railing open | B103: 85000 | C103: =ROUND(B103*1.1/'Location Data'!$D$6*'Location Data'!$D$12,-1) -> 3290 | D103: =ROUND(B103*1.1/'Location Data'!$D$6*'Location Data'!$D$10,-1) -> 370 | E103: linear metre
A104: Railing semi-closed | B104: 185000 | C104: =ROUND(B104*1.1/'Location Data'!$D$6*'Location Data'!$D$12,-1) -> 7150 | D104: =ROUND(B104*1.1/'Location Data'!$D$6*'Location Data'!$D$10,-1) -> 800 | E104: linear metre
A105: Extra step | B105: 250000 | C105: =ROUND(B105*1.1/'Location Data'!$D$6*'Location Data'!$D$12,-1) -> 9660 | D105: =ROUND(B105*1.1/'Location Data'!$D$6*'Location Data'!$D$10,-1) -> 1080 | E105: pcs
... A113: Biodigester | B113: 2500000 | C113: =ROUND(B113*1.1/'Location Data'!$D$6*'Location Data'!$D$12,-1) -> 96620 | D113: =ROUND(B113*1.1/'Location Data'!$D$6*'Location Data'!$D$10,-1) -> 10780 | E113: piece
A114: Remote location charge | B114: 400 | C114: =ROUND(B114*1.1/'Location Data'!$D$6*'Location Data'!$D$12,0) -> 15 | D114: =ROUND(B114*1.1/'Location Data'!$D$6*'Location Data'!$D$10,0) -> 2 | E114: per km > 100
A115: Rainwater harvesting system
B119: * inclusive of vat and all costs
A120: New price formula for bespoke plans | B120: Uganda | F120: Kenya
A121: Basic structure per sqm | B121: 1200000 | C121: 1.2M | D121: per gfa without int doors or partitions | F121: =B121*0.036*1.1 -> 47520
...

Sheet Bill of Quantities
A1: Bill of Quantities | D1: Specifications | M1: Item costs | P1: Project costs | Q1: Cost database | X1: Orderlist | AB1: =SUM(AB88:AB148) -> 14.33684 | AC1: =SUM(AC88:AC148) -> 15.106843 | AE1: =SUM(AE88:AE148) -> 0.7700037 | AF1: =AE1/AC1 -> 0.050970523
A2: # | B2: Unit | C2: Item | D2: Width (mm) | E2: Height (mm) | F2: Length (mm) | G2: Volume (m3) | H2: Weight (kg) | I2: Carbon storage (kg CO2) | J2: Labour (min) | K2: Structure | L2: Type | M2: Item cost ($) | N2: Labour cost ($) | O2: Total cost ($) | Q2: ='Location Data'!A6 -> Kampala, Uganda | R2: ='Location Data'!A7 -> West Nile, Uganda | S2: ='Location Data'!A8 -> Beira, Mozambique | T2: ='Location Data'!A9 -> Maputo, Mozambique | U2: ='Location Data'!A10 -> Accra, Ghana | V2: ='Location Data'!A11 -> Arusha, Tanzania | W2: ='Location Data'!A12 -> Nairobi, Kenya | X2: Sawn from | Y2: Gross fraction | Z2: Sum | AA2: Loss | AB2: Net vol | AC2: Gross vol | AD2: Gross vol / item | AE2: Project loss | AF2: Loss percentage
A4: Project name | C4: ='Project Costs'!B13
A5: ='Project Costs'!A14 -> Project Location | C5: ='Project Costs'!B14 -> Greater Kampala (<100km from factory)
A6: ='Project Costs'!A15 -> Client name | C6: ='Project Costs'!B15 -> Example calculation
A8: Country parameters | C8: Description | D8: Value
C9: Selected location | D9: ='Project Costs'!B11 -> Kampala, Uganda
C10: ='Location Data'!B5 -> Country | D10: {=INDEX('Location Data'!B:B,MATCH($D$9,'Location Data'!A:A,0),1)} -> Uganda
C11: ='Location Data'!G5 -> Distance from sawmill | D11: {=INDEX('Location Data'!G:G,MATCH($D$9,'Location Data'!A:A,0),1)} -> 100
C12: ='Location Data'!F5 -> Forestry partner | D12: {=INDEX('Location Data'!F:F,MATCH($D$9,'Location Data'!A:A,0),1)} -> Green Resources, Jinja
C13: ='Location Data'!H5 -> Timber species | D13: {=INDEX('Location Data'!H:H,MATCH($D$9,'Location Data'!A:A,0),1)} -> Pinus caribaea
C14: ='Location Data'!I5 -> Price per m3 (normal - ex vat, ex mill) | D14: =I14*G14 -> 252 | F14: Offcut loss | G14: 1 | H14: Bulk price | I14: {=INDEX('Location Data'!I:I,MATCH($D$9,'Location Data'!A:A,0),1)} -> 252
C15: ='Location Data'!J5 -> Price per m3 (profiled) | D15: =I15*G15 -> 260 | F15: Offcut loss | G15: 1 | H15: Bulk price | I15: {=INDEX('Location Data'!J:J,MATCH($D$9,'Location Data'!A:A,0),1)} -> 260
C16: ='Location Data'!K5 -> Timber density (wet) | D16: {=INDEX('Location Data'!K:K,MATCH($D$9,'Location Data'!A:A,0),1)} -> 561
C17: ='Location Data'!L5 -> Moisture content | D17: {=INDEX('Location Data'!L:L,MATCH($D$9,'Location Data'!A:A,0),1)} -> 0.12
C18: ='Location Data'!M5 -> Timber density (dry) | D18: {=INDEX('Location Data'!M:M,MATCH($D$9,'Location Data'!A:A,0),1)} -> 493
C19: ='Location Data'!N5 -> Carpenter cost (day) | D19: {=INDEX('Location Data'!N:N,MATCH($D$9,'Location Data'!A:A,0),1)} -> 15
C20: Carbon storage in CO2 per kg dry timber | D20: 1.833
A22: Screws and fasteners | Q22: Now calculating with mostly local prices
A23: =SUMIF('Structures Database'!B:B,C23,'Structures Database'!W:W) -> 2600 | B23: pcs | C23: Screw 3.5x40 small head screw SHS3540 | D23: 3.5 | F23: 40 | G23: =(D23/2)^2*PI()*F23/1000000000 -> 3.848451e-07 | H23: =G23*7700 -> 0.0029633073 | J23: 1 | K23: Screw | L23: Flooring | M23: =INDEX(23:23,1,MATCH($D$9,$2:$2,0)) -> 0.046297556 | N23: =J23*$D$19/(8*60) -> 0.03125 | O23: =M23+N23 -> 0.077547556 | P23: =A23*O23 -> 201.62365 | Q23: =0.0253*$X$26 -> 0.046297556 | R23: =$Q23 -> 0.046297556 | S23: =$Q23 -> 0.046297556 | T23: =$Q23 -> 0.046297556 | U23: =$Q23 -> 0.046297556 | V23: =$Q23 -> 0.046297556 | W23: =Q23 -> 0.046297556 | X23: Screw specs from Rotho Blaas now assumed with 25% import tax, 15% withholding tax, and 25% freight costs (USD 500 on USD 2500 order) across markets. VAT is added separately per country.
A24: =SUMIF('Structures Database'!B:B,C24,'Structures Database'!W:W) -> 0 | B24: pcs | C24: Screw 3.5x50 stainless small head screw SHS3550AS | D24: 3.5 | F24: 50 | G24: =(D24/2)^2*PI()*F24/1000000000 -> 4.8105638e-07 | H24: =G24*7700 -> 0.0037041341 | J24: 1 | K24: Screw | L24: Decking / Facade | M24: =INDEX(24:24,1,MATCH($D$9,$2:$2,0)) -> 0.070086815 | N24: =J24*$D$19/(8*60) -> 0.03125 | O24: =M24+N24 -> 0.10133681 | P24: =A24*O24 -> 0 | Q24: =0.0383*$X$26 -> 0.070086815 | R24: =$Q24 -> 0.070086815 | S24: =$Q24 -> 0.070086815 | T24: =$Q24 -> 0.070086815 | U24: =$Q24 -> 0.070086815 | V24: =$Q24 -> 0.070086815 | W24: =Q24 -> 0.070086815 | X24: Screw specs from Rotho Blaas now assumed with 25% import tax, 15% withholding tax, and 25% freight costs (USD 500 on USD 2500 order) across markets. VAT is added separately per country.
A25: =SUMIF('Structures Database'!B:B,C25,'Structures Database'!W:W) -> 0 | B25: pcs | C25: Screw 4 x 50 Stainless A2 SCA450 | D25: 4 | F25: 50 | G25: =(D25/2)^2*PI()*F25/1000000000 -> 6.2831853e-07 | H25: =G25*7700 -> 0.0048380527 | J25: 1 | K25: Screw | L25: Outdoor | M25: =INDEX(25:25,1,MATCH($D$9,$2:$2,0)) -> 0.1024768 | N25: =J25*$D$19/(8*60) -> 0.03125 | O25: =M25+N25 -> 0.1337268 | P25: =A25*O25 -> 0 | Q25: =0.056*$X$26 -> 0.1024768 | R25: =$Q25 -> 0.1024768 | S25: =$Q25 -> 0.1024768 | T25: =$Q25 -> 0.1024768 | U25: =$Q25 -> 0.1024768 | V25: =$Q25 -> 0.1024768 | W25: =Q25 -> 0.1024768 | X25: Import factor
A26: =SUMIF('Structures Database'!B:B,C26,'Structures Database'!W:W) -> 6101.8993 | B26: pcs | C26: Screw 4x40 semi threaded HBS440 | D26: 4 | F26: 40 | G26: =(D26/2)^2*PI()*F26/1000000000 -> 5.0265482e-07 | H26: =G26*7700 -> 0.0038704421 | J26: 1 | K26: Screw | L26: Boards | M26: =INDEX(26:26,1,MATCH($D$9,$2:$2,0)) -> 0.012 | N26: =J26*$D$19/(8*60) -> 0.03125 | O26: =M26+N26 -> 0.04325 | P26: =A26*O26 -> 263.90714 | Q26: 0.012 | R26: =$Q26 -> 0.012 | S26: =$Q26 -> 0.012 | T26: =$Q26 -> 0.012 | U26: =$Q26 -> 0.012 | V26: =$Q26 -> 0.012 | W26: =Q26 -> 0.012 | X26: =(2475+600+(0.35+0.06+0.015)*2475+680000/3700+218.45)/2475 -> 1.8299429
A27: =SUMIF('Structures Database'!B:B,C27,'Structures Database'!W:W) -> 3509.2015 | B27: pcs | C27: Screw 4x60 semi threaded HBS460 | D27: 4 | F27: 60 | G27: =(D27/2)^2*PI()*F27/1000000000 -> 7.5398224e-07 | H27: =G27*7700 -> 0.0058056632 | J27: 1 | K27: Screw | L27: Back Battens | M27: =INDEX(27:27,1,MATCH($D$9,$2:$2,0)) -> 0.018 | N27: =J27*$D$19/(8*60) -> 0.03125 | O27: =M27+N27 -> 0.04925 | P27: =A27*O27 -> 172.82817 | Q27: 0.018 | R27: =$Q27 -> 0.018 | S27: =$Q27 -> 0.018 | T27: =$Q27 -> 0.018 | U27: =$Q27 -> 0.018 | V27: =$Q27 -> 0.018 | W27: =Q27 -> 0.018
A28: =SUMIF('Structures Database'!B:B,C28,'Structures Database'!W:W) -> 0 | B28: pcs | C28: Screw 5x80 semi threaded HBS580 | D28: 5 | F28: 80 | G28: =(D28/2)^2*PI()*F28/1000000000 -> 1.5707963e-06 | H28: =G28*7700 -> 0.012095132 | J28: 1 | K28: Screw | L28: Frames | M28: =INDEX(28:28,1,MATCH($D$9,$2:$2,0)) -> 0.146 | N28: =J28*$D$19/(8*60) -> 0.03125 | O28: =M28+N28 -> 0.17725 | P28: =A28*O28 -> 0 | Q28: 0.146 | R28: =$Q28 -> 0.146 | S28: =$Q28 -> 0.146 | T28: =$Q28 -> 0.146 | U28: =$Q28 -> 0.146 | V28: =$Q28 -> 0.146 | W28: =Q28 -> 0.146
A29: =SUMIF('Structures Database'!B:B,C29,'Structures Database'!W:W) -> 949.02106 | B29: pcs | C29: Screw 6x100 semi threaded HBS6100 | D29: 6 | F29: 100 | G29: =(D29/2)^2*PI()*F29/1000000000 -> 2.8274334e-06 | H29: =G29*7700 -> 0.021771237 | J29: 1 | K29: Screw | L29: Frames | M29: =INDEX(29:29,1,MATCH($D$9,$2:$2,0)) -> 0.06 | N29: =J29*$D$19/(8*60) -> 0.03125 | O29: =M29+N29 -> 0.09125 | P29: =A29*O29 -> 86.598172 | Q29: 0.06 | R29: =$Q29 -> 0.06 | S29: =$Q29 -> 0.06 | T29: =$Q29 -> 0.06 | U29: =$Q29 -> 0.06 | V29: =$Q29 -> 0.06 | W29: =Q29 -> 0.06
A30: =SUMIF('Structures Database'!B:B,C30,'Structures Database'!W:W) -> 2574.4865 | B30: pcs | C30: Screw 6x120 semi threaded HBS6120 | D30: 6 | F30: 120 | G30: =(D30/2)^2*PI()*F30/1000000000 -> 3.3929201e-06 | H30: =G30*7700 -> 0.026125485 | J30: 1 | K30: Screw | L30: Frames | M30: =INDEX(30:30,1,MATCH($D$9,$2:$2,0)) -> 0.06 | N30: =J30*$D$19/(8*60) -> 0.03125 | O30: =M30+N30 -> 0.09125 | P30: =A30*O30 -> 234.92189 | Q30: 0.06 | R30: =$Q30 -> 0.06 | S30: =$Q30 -> 0.06 | T30: =$Q30 -> 0.06 | U30: =$Q30 -> 0.06 | V30: =$Q30 -> 0.06 | W30: =Q30 -> 0.06
A31: =SUMIF('Structures Database'!B:B,C31,'Structures Database'!W:W) -> 104 | B31: pcs | C31: Screw 6x160 semi threaded HBS6160 | D31: 6 | F31: 160 | G31: =(D31/2)^2*PI()*F31/1000000000 -> 4.5238934e-06 | H31: =G31*7700 -> 0.034833979 | J31: 1 | K31: Screw | L31: Frames | M31: =INDEX(31:31,1,MATCH($D$9,$2:$2,0)) -> 0.41891054 | N31: =J31*$D$19/(8*60) -> 0.03125 | O31: =M31+N31 -> 0.45016054 | P31: =A31*O31 -> 46.816696 | Q31: =0.22892*$X$26 -> 0.41891054 | R31: =$Q31 -> 0.41891054 | S31: =$Q31 -> 0.41891054 | T31: =$Q31 -> 0.41891054 | U31: =$Q31 -> 0.41891054 | V31: =$Q31 -> 0.41891054 | W31: =Q31 -> 0.41891054
A32: =SUMIF('Structures Database'!B:B,C32,'Structures Database'!W:W) -> 522.51866 | B32: pcs | C32: Corrugated roof screw 67 mm | D32: 6 | F32: 67 | G32: =(D32/2)^2*PI()*F32/1000000000 -> 1.8943804e-06 | H32: =G32*7700 -> 0.014586729 | J32: 1 | K32: Screw | L32: Roofing | M32: =INDEX(32:32,1,MATCH($D$9,$2:$2,0)) -> 0.11756757 | N32: =J32*$D$19/(8*60) -> 0.03125 | O32: =M32+N32 -> 0.14881757 | P32: =A32*O32 -> 77.759957 | Q32: =435/'Location Data'!$D$6 -> 0.11756757 | R32: =$Q32 -> 0.11756757 | S32: =$Q32 -> 0.11756757 | T32: =$Q32 -> 0.11756757 | U32: =$Q32 -> 0.11756757 | V32: =$Q32 -> 0.11756757 | W32: =Q32 -> 0.11756757
A34: Foundation materials
A35: =SUMIF('Structures Database'!B:B,C35,'Structures Database'!W:W) -> 25 | B35: pcs | C35: Foundation block | D35: 300 | E35: 400 | F35: 300 | G35: =D35*E35*F35/1000000000 -> 0.036 | H35: =G35*2400 -> 86.4 | I35: 0 | J35: 180 | K35: Foundation | L35: Point | M35: {=INDEX(35:35,1,MATCH($D$9,$2:$2,0))} -> 0 | N35: =J35*$D$19/(8*60) -> 5.625 | O35: =M35+N35 -> 5.625 | P35: =A35*O35 -> 140.625 | Q35: 0 | R35: 0 | S35: 0 | T35: 0 | U35: 0 | V35: 0 | W35: 0
A36: =SUMIF('Structures Database'!B:B,C36,'Structures Database'!W:W) -> 7.5 | B36: pcs | C36: Cement Bag 50 kg | I36: -0.6 | K36: Foundation | L36: Cement | M36: =37500/3700/1.18 -> 8.5890976 | N36: =J36*$D$19/(8*60) -> 0 | O36: =M36+N36 -> 8.5890976 | P36: =A36*O36 -> 64.418232
A37: =SUMIF('Structures Database'!B:B,C37,'Structures Database'!W:W) -> 0.75 | B37: tonnes | C37: Sand per tonne | K37: Foundation | L37: Anchor | M37: =135000/3/3700 -> 12.162162 | N37: =J37*$D$19/(8*60) -> 0 | O37: =M37+N37 -> 12.162162 | P37: =A37*O37 -> 9.1216216
A38: =SUMIF('Structures Database'!B:B,C38,'Structures Database'!W:W) -> 1 | B38: tonnes | C38: Aggregates per tonne | K38: Foundation | L38: Anchor | M38: =230000/3700 -> 62.162162 | N38: =J38*$D$19/(8*60) -> 0 | O38: =M38+N38 -> 62.162162 | P38: =A38*O38 -> 62.162162
A39: =SUMIF('Structures Database'!B:B,C39,'Structures Database'!W:W) -> 100 | B39: pcs | C39: M12 rod 200 mm (stainless steel) | D39: 16 | F39: 250 | G39: =(D39/2)^2*PI()*F39/1000000000 -> 5.0265482e-05 | K39: Foundation | L39: Rod | M39: 3 | N39: =J39*$D$19/(8*60) -> 0 | O39: =M39+N39 -> 3 | P39: =A39*O39 -> 300
A40: =SUMIF('Structures Database'!B:B,C40,'Structures Database'!W:W) -> 200 | B40: pcs | C40: M12 nut (stainless steel) | D40: 24 | E40: 24 | F40: 13 | K40: Foundation | L40: Nut | M40: 0.4 | N40: =J40*$D$19/(8*60) -> 0 | O40: =M40+N40 -> 0.4 | P40: =A40*O40 -> 80
A41: =SUMIF('Structures Database'!B:B,C41,'Structures Database'!W:W) -> 200 | B41: pcs | C41: M12 washer (stainless steel) | D41: 30 | F41: 3 | K41: Foundation | L41: Washer | M41: 0.2 | N41: =J41*$D$19/(8*60) -> 0 | O41: =M41+N41 -> 0.2 | P41: =A41*O41 -> 40
A42: =SUMIF('Structures Database'!B:B,C42,'Structures Database'!W:W) -> 100 | B42: pcs | C42: M12 drop anchor | D42: 20 | F42: 65 | K42: Foundation | L42: Anchor | M42: 1 | N42: =J42*$D$19/(8*60) -> 0 | O42: =M42+N42 -> 1 | P42: =A42*O42 -> 100
A43: =SUMIF('Structures Database'!B:B,C43,'Structures Database'!W:W) -> 2.5 | B43: pcs | C43: Y12 bar 12 metres | D43: 12 | F43: 12000 | G43: =(D43/2)^2*PI()*F43/1000000000 -> 0.001357168 | K43: Foundation | L43: Rebar | M43: =45000/1.18/3700 -> 10.306917 | N43: =J43*$D$19/(8*60) -> 0 | O43: =M43+N43 -> 10.306917 | P43: =A43*O43 -> 25.767293
A44: =SUMIF('Structures Database'!B:B,C44,'Structures Database'!W:W) -> 2.5 | B44: pcs | C44: 8 mm rebar 12 metres | D44: 8 | F44: 12000 | G44: =(D44/2)^2*PI()*F44/1000000000 -> 0.00060318579 | K44: Foundation | L44: Rebar | M44: =12000/1.18/3700 -> 2.7485112 | N44: =J44*$D$19/(8*60) -> 0 | O44: =M44+N44 -> 2.7485112 | P44: =A44*O44 -> 6.8712781
A45: =SUMIF('Structures Database'!B:B,C45,'Structures Database'!W:W) -> 5 | B45: pcs | C45: Binding wire per kg | D45: 12 | F45: 12000 | G45: =(D45/2)^2*PI()*F45/1000000000 -> 0.001357168 | K45: Foundation | L45: Wire | M45: =6000/3700 -> 1.6216216 | N45: =J45*$D$19/(8*60) -> 0 | O45: =M45+N45 -> 1.6216216 | P45: =A45*O45 -> 8.1081081
A46: =SUMIF('Structures Database'!B:B,C46,'Structures Database'!W:W) -> 5 | B46: liter | C46: Used engine oil per liter | K46: Foundation | L46: Oil | M46: =3000/3700/1.18 -> 0.68712781 | N46: =J46*$D$19/(8*60) -> 0 | O46: =M46+N46 -> 0.68712781 | P46: =A46*O46 -> 3.435639
A47: =SUMIF('Structures Database'!B:B,C47,'Structures Database'!W:W) -> 50 | B47: pcs | C47: Foundation plate 5 x 100 x 250 mm (redoxide coated) | D47: 100 | E47: 5 | F47: 250 | G47: =D47*E47*F47/1000000000 -> 0.000125 | J47: 15 | K47: Foundation | L47: Plate | M47: =600000/114/1.18/3700+7000/3700+1 -> 4.0973793 | N47: =J47*$D$19/(8*60) -> 0.46875 | O47: =M47+N47 -> 4.5661293 | P47: =A47*O47 -> 228.30646
A49: Timber and boards
A50: =SUMIF('Structures Database'!B:B,C50,'Structures Database'!W:W) -> 0 | B50: pcs | C50: Gypsum board 10 x 1220 x 2440 | D50: 10 | E50: 1220 | F50: 2440 | G50: =D50*E50*F50/1000000000 -> 0.029768 | H50: =G50*800 -> 23.8144 | J50: 10 | K50: Board | L50: Gypsum | M50: 8 | Q50: 10 | R50: 10
A51: =5.5*'Project Costs'!A127 -> 11 | B51: pcs | C51: Cement fibre board 10 x 1220 x 2440 | D51: 10 | E51: 1220 | F51: 2440 | G51: =D51*E51*F51/1000000000 -> 0.029768 | H51: =G51*1350 -> 40.1868 | J51: 20 | K51: Board | L51: Cement Fibre | M51: 16 | P51: =A51*M51 -> 176
A52: =SUMIF('Structures Database'!B:B,C52,'Structures Database'!W:W) -> 0 | B52: pcs | C52: Plywood 6 x 1220 x 2440 | D52: 6 | E52: 1220 | F52: 2440 | G52: =D52*E52*F52/1000000000 -> 0.0178608 | H52: =G52*510 -> 9.109008 | I52: =H52*0.88*$D$20 -> 14.693194 | J52: 10 | K52: Board | L52: Plywood | M52: =INDEX(52:52,1,MATCH($D$9,$2:$2,0)) -> 8 | N52: =J52*$D$19/(8*60) -> 0.3125 | O52: =M52+N52 -> 8.3125 | P52: =A52*O52 -> 0 | Q52: =Q55/18*6*1.2 -> 8 | R52: =R55/18*6*1.2 -> 8 | S52: =S55/18*6*1.2 -> 10 | T52: =T55/18*6*1.2 -> 10 | U52: =475*0.009*1.22*2.44+2 -> 14.72582 | V52: =V55/18*6*1.2 -> 8.3
A53: =SUMIF('Structures Database'!B:B,C53,'Structures Database'!W:W) -> 36 | B53: pcs | C53: Plywood 9 x 1220 x 2440 | D53: 9 | E53: 1220 | F53: 2440 | G53: =D53*E53*F53/1000000000 -> 0.0267912 | H53: =G53*510 -> 13.663512 | I53: =H53*0.88*$D$20 -> 22.039791 | J53: 10 | K53: Board | L53: Plywood | M53: =INDEX(53:53,1,MATCH($D$9,$2:$2,0)) -> 7.7874485 | N53: =J53*$D$19/(8*60) -> 0.3125 | O53: =M53+N53 -> 8.0999485 | P53: =A53*O53 -> 291.59814 | Q53: =34000/1.18/3700 -> 7.7874485 | R53: 7.8 | S53: =S55/18*9*1.2 -> 15 | T53: =T55/18*9*1.2 -> 15 | U53: =475*0.009*1.22*2.44+2 -> 14.72582 | V53: =V55/18*9*1.2 -> 12.45 | W53: =Q53*1.2 -> 9.3449382
A54: =SUMIF('Structures Database'!B:B,C54,'Structures Database'!W:W) -> 103.79189 | B54: pcs | C54: Plywood 12 x 1220 x 2440 | D54: 12 | E54: 1220 | F54: 2440 | G54: =D54*E54*F54/1000000000 -> 0.0357216 | H54: =G54*510 -> 18.218016 | I54: =H54*0.88*$D$20 -> 29.386389 | J54: 10 | K54: Board | L54: Plywood | M54: =INDEX(54:54,1,MATCH($D$9,$2:$2,0)) -> 12.139258 | N54: =J54*$D$19/(8*60) -> 0.3125 | O54: =M54+N54 -> 12.451758 | P54: =A54*O54 -> 1292.3915 | Q54: =53000/1.18/3700 -> 12.139258 | R54: 12.15 | S54: =S55/18*12*1.1 -> 18.333333 | T54: =T55/18*12*1.1 -> 18.333333 | U54: =425*0.012*1.22*2.44+2 -> 17.18168 | V54: =V55/18*12*1.1 -> 15.216667 | W54: =Q54*1.2 -> 14.567109
A55: =SUMIF('Structures Database'!B:B,C55,'Structures Database'!W:W) -> 0 | B55: pcs | C55: Plywood 18 x 1220 x 2440 | D55: 18 | E55: 1220 | F55: 2440 | G55: =D55*E55*F55/1000000000 -> 0.0535824 | H55: =G55*510 -> 27.327024 | I55: =H55*0.88*$D$20 -> 44.079583 | J55: 10 | K55: Board | L55: Plywood | M55: =INDEX(55:55,1,MATCH($D$9,$2:$2,0)) -> 20 | N55: =J55*$D$19/(8*60) -> 0.3125 | O55: =M55+N55 -> 20.3125 | P55: =A55*O55 -> 0 | Q55: 20 | R55: 20 | S55: 25 | T55: 25 | U55: =400*0.018*1.22*2.44+2 -> 23.43296 | V55: =45000/2400 + 2 -> 20.75
A57: ='Timber Order'!H35 -> 15.141925 | B57: cbm | C57: Timber - dried, treated and planed | D57: 1000 | E57: 1000 | F57: 1000 | G57: 1 | H57: =D16 -> 561
A58: ='Timber Order'!A16 -> 98 | B58: ='Timber Order'!B16 -> pcs | C58: ='Timber Order'!C16 -> Wall Beam 46 x 71 x 2450 | D58: ='Timber Order'!D16 -> 46 | E58: ='Timber Order'!E16 -> 71 | F58: ='Timber Order'!F16 -> 2450 | G58: ='Timber Order'!G16 -> 0.0080017 | H58: ='Timber Order'!J16 -> 4.4889537 | I58: ='Timber Order'!K16 -> 7.2308882 | K58: ='Timber Order'!L16 -> Wall | L58: ='Timber Order'!M16 -> Beam
A59: ='Timber Order'!A17 -> 130 | B59: ='Timber Order'!B17 -> pcs | C59: ='Timber Order'!C17 -> Wall Beam 46 x 71 x 3650 | D59: ='Timber Order'!D17 -> 46 | E59: ='Timber Order'!E17 -> 71 | F59: ='Timber Order'!F17 -> 3650 | G59: ='Timber Order'!G17 -> 0.0119209 | H59: ='Timber Order'!J17 -> 6.6876249 | I59: ='Timber Order'!K17 -> 10.772548 | K59: ='Timber Order'!L17 -> Wall | L59: ='Timber Order'!M17 -> Beam
A60: ='Timber Order'!A18 -> 55 | B60: ='Timber Order'!B18 -> pcs | C60: ='Timber Order'!C18 -> Roof Beam 46 x 96 x 2450 | D60: ='Timber Order'!D18 -> 46 | E60: ='Timber Order'!E18 -> 96 | F60: ='Timber Order'!F18 -> 2450 | G60: ='Timber Order'!G18 -> 0.0108192 | H60: ='Timber Order'!J18 -> 6.0695712 | I60: ='Timber Order'!K18 -> 9.7769756 | K60: ='Timber Order'!L18 -> Roof | L60: ='Timber Order'!M18 -> Beam
A61: ='Timber Order'!A19 -> 3 | B61: ='Timber Order'!B19 -> pcs | C61: ='Timber Order'!C19 -> Roof Beam 46 x 96 x 4250 | D61: ='Timber Order'!D19 -> 46 | E61: ='Timber Order'!E19 -> 96 | F61: ='Timber Order'!F19 -> 4250 | G61: ='Timber Order'!G19 -> 0.018768 | H61: ='Timber Order'!J19 -> 10.528848 | I61: ='Timber Order'!K19 -> 16.96006 | K61: ='Timber Order'!L19 -> Roof | L61: ='Timber Order'!M19 -> Beam
A62: ='Timber Order'!A20 -> 61 | B62: ='Timber Order'!B20 -> pcs | C62: ='Timber Order'!C20 -> Roof Beam 46 x 96 x 5750 | D62: ='Timber Order'!D20 -> 46 | E62: ='Timber Order'!E20 -> 96 | F62: ='Timber Order'!F20 -> 5750 | G62: ='Timber Order'!G20 -> 0.025392 | H62: ='Timber Order'!J20 -> 14.244912 | I62: ='Timber Order'!K20 -> 22.945963 | K62: ='Timber Order'!L20 -> Roof | L62: ='Timber Order'!M20 -> Beam
A63: ='Timber Order'!A21 -> 96 | B63: ='Timber Order'!B21 -> pcs | C63: ='Timber Order'!C21 -> Floor Beam 46 x 146 x 2450 | D63: ='Timber Order'!D21 -> 46 | E63: ='Timber Order'!E21 -> 146 | F63: ='Timber Order'!F21 -> 2450 | G63: ='Timber Order'!G21 -> 0.0164542 | H63: ='Timber Order'!J21 -> 9.2308062 | I63: ='Timber Order'!K21 -> 14.86915 | K63: ='Timber Order'!L21 -> Floor | L63: ='Timber Order'!M21 -> Beam
A64: ='Timber Order'!A22 -> 40 | B64: ='Timber Order'!B22 -> pcs | C64: ='Timber Order'!C22 -> Floor Beam 46 x 146 x 3050 | D64: ='Timber Order'!D22 -> 46 | E64: ='Timber Order'!E22 -> 146 | F64: ='Timber Order'!F22 -> 3050 | G64: ='Timber Order'!G22 -> 0.0204838 | H64: ='Timber Order'!J22 -> 11.491412 | I64: ='Timber Order'!K22 -> 18.510575 | K64: ='Timber Order'!L22 -> Floor | L64: ='Timber Order'!M22 -> Beam
A65: ='Timber Order'!A23 -> 0 | B65: ='Timber Order'!B23 -> pcs | C65: ='Timber Order'!C23 -> Floor Beam 46 x 146 x 5450 | D65: ='Timber Order'!D23 -> 46 | E65: ='Timber Order'!E23 -> 146 | F65: ='Timber Order'!F23 -> 5450 | G65: ='Timber Order'!G23 -> 0.0366022 | H65: ='Timber Order'!J23 -> 20.533834 | I65: ='Timber Order'!K23 -> 33.076273 | K65: ='Timber Order'!L23 -> Floor | L65: ='Timber Order'!M23 -> Beam
A66: ='Timber Order'!A24 -> 0 | B66: ='Timber Order'!B24 -> pcs | C66: ='Timber Order'!C24 -> Timber Column 100 x 100 x 3050 | D66: ='Timber Order'!D24 -> 100 | E66: ='Timber Order'!E24 -> 100 | F66: ='Timber Order'!F24 -> 3050 | G66: ='Timber Order'!G24 -> 0.0305 | H66: ='Timber Order'!J24 -> 17.1105 | I66: ='Timber Order'!K24 -> 27.561905 | K66: ='Timber Order'!L24 -> Timber | L66: ='Timber Order'!M24 -> Column
A67: ='Timber Order'!A25 -> 309 | B67: ='Timber Order'!B25 -> pcs | C67: ='Timber Order'!C25 -> Timber Back Batten 22 x 46 x 2450 | D67: ='Timber Order'!D25 -> 22 | E67: ='Timber Order'!E25 -> 46 | F67: ='Timber Order'!F25 -> 2450 | G67: ='Timber Order'!G25 -> 0.0024794 | H67: ='Timber Order'!J25 -> 1.3909434 | I67: ='Timber Order'!K25 -> 2.2405569 | K67: ='Timber Order'!L25 -> Timber | L67: ='Timber Order'!M25 -> Back Batten
A68: ='Timber Order'!A26 -> 16 | B68: ='Timber Order'!B26 -> pcs | C68: ='Timber Order'!C26 -> Timber Back Batten 22 x 46 x 3050 | D68: ='Timber Order'!D26 -> 22 | E68: ='Timber Order'!E26 -> 46 | F68: ='Timber Order'!F26 -> 3050 | G68: ='Timber Order'!G26 -> 0.0030866 | H68: ='Timber Order'!J26 -> 1.7315826 | I68: ='Timber Order'!K26 -> 2.7892647 | K68: ='Timber Order'!L26 -> Timber | L68: ='Timber Order'!M26 -> Back Batten
A69: ='Timber Order'!A27 -> 550 | B69: ='Timber Order'!B27 -> pcs | C69: ='Timber Order'!C27 -> Timber Floor Plank 22 x 96 x 2450 | D69: ='Timber Order'!D27 -> 22 | E69: ='Timber Order'!E27 -> 96 | F69: ='Timber Order'!F27 -> 2450 | G69: ='Timber Order'!G27 -> 0.0051744 | H69: ='Timber Order'!J27 -> 2.9028384 | I69: ='Timber Order'!K27 -> 4.6759449 | K69: ='Timber Order'!L27 -> Timber | L69: ='Timber Order'!M27 -> Floor Plank
... A75: ='Timber Order'!A33 -> 30 | B75: ='Timber Order'!B33 -> pcs | C75: ='Timber Order'!C33 -> Interior Door Beams 50 x 150 x 2450 | D75: ='Timber Order'!D33 -> 50 | E75: ='Timber Order'!E33 -> 150 | F75: ='Timber Order'!F33 -> 2450 | G75: ='Timber Order'!G33 -> 0.018375 | H75: ='Timber Order'!J33 -> 10.308375 | I75: ='Timber Order'!K33 -> 16.604918 | K75: ='Timber Order'!L33 -> Interior Door | L75: ='Timber Order'!M33 -> Beams
A78: Others
A79: =SUMIF('Structures Database'!B:B,C79,'Structures Database'!W:W) -> 130.62967 | B79: sqm | C79: Roof sheets per sqm | D79: 1000 | E79: 50 | F79: 1000 | G79: =D79*E79*F79/1000000000 -> 0.05 | J79: 30 | M79: =INDEX(79:79,1,MATCH($D$9,$2:$2,0)) -> 10.7 | N79: =J79*$D$19/(8*60) -> 0.9375 | O79: =M79+N79 -> 11.6375 | P79: =A79*O79 -> 1520.2027 | Q79: 10.7 | R79: 10.7 | S79: 11 | T79: 11 | U79: 12 | V79: 12 | W79: =Q79*1.2 -> 12.84
A80: ='Project Costs'!B28 -> 23.7 | B80: sqm | C80: Aluminium window frames per sqm | D80: 1000 | E80: 70 | F80: 1000 | G80: =D80*E80*F80/1000000000 -> 0.07 | H80: =D80*F80/1000000*25 -> 25 | J80: 0 | K80: Windows | L80: Aluminium | M80: =INDEX(80:80,1,MATCH($D$9,$2:$2,0)) -> 160 | N80: =J80*$D$19/(8*60) -> 0 | O80: =M80+N80 -> 160 | P80: =A80*O80 -> 3792 | Q80: 160 | R80: =Q80 -> 160 | S80: 170 | T80: 170 | U80: 170 | V80: 100 | W80: =Q80*1.2 -> 192
A81: =SUMIF('Structures Database'!B:B,C81,'Structures Database'!W:W) -> 0 | B81: sqm | C81: Mosquito net sqm (facades & windows) | D81: 1000 | E81: 0.2 | F81: 1000 | J81: 6 | M81: =6000/3700/1.18 -> 1.3742556 | W81: =Q81*1.2 -> 0
A82: =SUMIF('Structures Database'!B:B,C82,'Structures Database'!W:W) -> 0 | B82: sqm | C82: Building membrane (sqm) | D82: 1000 | E82: 0.2 | F82: 1000 | G82: =D82*E82*F82/1000000000 -> 0.0002 | H82: =G82*920 -> 0.184 | J82: 5 | K82: Membrane | L82: Plastic | M82: =INDEX(82:82,1,MATCH($D$9,$2:$2,0)) -> 1 | N82: =J82*$D$19/(8*60) -> 0.15625 | O82: =M82+N82 -> 1.15625 | Q82: 1 | R82: =Q82 -> 1 | S82: =R82 -> 1 | T82: =S82 -> 1 | U82: =T82 -> 1 | V82: =U82 -> 1 | W82: =Q82*1.2 -> 1.2
A83: =SUMIF('Structures Database'!B:B,C83,'Structures Database'!W:W) -> 108 | B83: sqm | C83: Aluminium roof insulation membrane per sqm | D83: 1000 | E83: 4 | F83: 1000 | G83: =D83*E83*F83/1000000000 -> 0.004 | H83: 0.15 | J83: 6 | K83: Insulation | L83: Membrane | M83: =INDEX(83:83,1,MATCH($D$9,$2:$2,0)) -> 1.6 | N83: =J83*$D$19/(8*60) -> 0.1875 | O83: =M83+N83 -> 1.7875 | P83: =A83*O83 -> 193.05 | Q83: 1.6 | R83: 2.75 | S83: 2.75 | T83: 2.75 | U83: 2.75 | V83: 2.75 | W83: =Q83*1.2 -> 1.92
A84: =SUMIF('Structures Database'!B:B,C84,'Structures Database'!W:W) -> 82.940541 | B84: sqm | C84: Glass wool insulation (per sqm) | D84: 1000 | E84: 50 | F84: 1000 | G84: =D84*E84*F84/1000000000 -> 0.05 | H84: =G84*40 -> 2 | I84: =H84*$D$20 -> 3.666 | J84: 10 | K84: Insulation | L84: Glass wool | M84: =INDEX(84:84,1,MATCH($D$9,$2:$2,0)) -> 3.6 | N84: =J84*$D$19/(8*60) -> 0.3125 | O84: =M84+N84 -> 3.9125 | P84: =A84*O84 -> 324.50486 | Q84: 3.6 | R84: 3.6 | S84: =4.5 -> 4.5 | T84: =4.5 -> 4.5 | U84: =4.5 -> 4.5 | V84: =4.5 -> 4.5 | W84: =Q84*1.2 -> 4.32
A85: =SUMIF('Structures Database'!B:B,C85,'Structures Database'!W:W) -> 0 | B85: cbm | C85: Biobased insulation - papyrus (m3) | D85: 1000 | E85: 1000 | F85: 1000 | G85: =D85*E85*F85/1000000000 -> 1 | H85: =G85*90 -> 90 | I85: =H85*$D$20 -> 164.97 | J85: 180 | K85: Insulation | L85: Papyrus | M85: =INDEX(85:85,1,MATCH($D$9,$2:$2,0)) -> 35 | N85: =J85*$D$19/(8*60) -> 5.625 | O85: =M85+N85 -> 40.625 | Q85: 35 | R85: 35 | S85: 35 | T85: 35 | U85: 35 | V85: 35
A87: Beams and planks
A88: =SUMIF('Structures Database'!B:B,C88,'Structures Database'!W:W) -> 32 | B88: pcs | C88: =K88&" "&L88&" "&D88&" x "&E88&" x "&F88 -> Floor Main Beam 46 x 146 x 2442 | D88: 46 | E88: 146 | F88: 2442 | G88: =D88*E88*F88/1000000000 -> 0.016400472 | H88: =G88*$D$16 -> 9.2006648 | I88: =G88*$D$18*$D$20 -> 14.820598 | J88: 5 | K88: Floor | L88: Main Beam | M88: =AD88*IF(D88>45,$D$14,$D$15) -> 4.1464584 | N88: =J88*$D$19/(8*60) -> 0.15625 | O88: =M88+N88 -> 4.3027084 | P88: =A88*O88 -> 137.68667 | X88: ='Timber Order'!$C$21 -> Floor Beam 46 x 146 x 2450 | Y88: 1 | Z88: =A88*Y88 -> 32 | AA88: {=1-(G88/Y88/INDEX('Timber Order'!G:G,MATCH($X88,'Timber Order'!C:C,0),1))} -> 0.0032653061 | AB88: =A88*G88 -> 0.5248151 | AC88: {=A88*Y88*INDEX('Timber Order'!G:G,MATCH($X88,'Timber Order'!C:C,0),1)} -> 0.5265344 | AD88: {=Y88*INDEX('Timber Order'!G:G,MATCH($X88,'Timber Order'!C:C,0),1)} -> 0.0164542 | AE88: =AC88-AB88 -> 0.001719296
A89: =SUMIF('Structures Database'!B:B,C89,'Structures Database'!W:W) -> 40 | B89: pcs | C89: =K89&" "&L89&" "&D89&" x "&E89&" x "&F89 -> Floor Sub Beam 46 x 146 x 2342 | D89: 46 | E89: 146 | F89: 2342 | G89: =D89*E89*F89/1000000000 -> 0.015728872 | H89: =G89*$D$16 -> 8.8238972 | I89: =G89*$D$18*$D$20 -> 14.213694 | J89: 5 | K89: Floor | L89: Sub Beam | M89: =AD89*IF(D89>45,$D$14,$D$15) -> 4.1464584 | N89: =J89*$D$19/(8*60) -> 0.15625 | O89: =M89+N89 -> 4.3027084 | P89: =A89*O89 -> 172.10834 | X89: ='Timber Order'!$C$21 -> Floor Beam 46 x 146 x 2450 | Y89: 1 | Z89: =A89*Y89 -> 40 | AA89: {=1-(G89/Y89/INDEX('Timber Order'!G:G,MATCH($X89,'Timber Order'!C:C,0),1))} -> 0.044081633 | AB89: =A89*G89 -> 0.62915488 | AC89: {=A89*Y89*INDEX('Timber Order'!G:G,MATCH($X89,'Timber Order'!C:C,0),1)} -> 0.658168 | AD89: {=Y89*INDEX('Timber Order'!G:G,MATCH($X89,'Timber Order'!C:C,0),1)} -> 0.0164542 | AE89: =AC89-AB89 -> 0.02901312
A90: =SUMIF('Structures Database'!B:B,C90,'Structures Database'!W:W) -> 40 | B90: pcs | C90: =K90&" "&L90&" "&D90&" x "&E90&" x "&F90 -> Floor Sub Beam 46 x 146 x 2952 | D90: 46 | E90: 146 | F90: 2952 | G90: =D90*E90*F90/1000000000 -> 0.019825632 | H90: =G90*$D$16 -> 11.12218 | I90: =G90*$D$18*$D$20 -> 17.915809 | J90: 5 | K90: Floor | L90: Sub Beam | M90: =AD90*IF(D90>45,$D$14,$D$15) -> 5.1619176 | N90: =J90*$D$19/(8*60) -> 0.15625 | O90: =M90+N90 -> 5.3181676 | P90: =A90*O90 -> 212.7267 | X90: ='Timber Order'!$C$22 -> Floor Beam 46 x 146 x 3050 | Y90: 1 | Z90: =A90*Y90 -> 40 | AA90: {=1-(G90/Y90/INDEX('Timber Order'!G:G,MATCH($X90,'Timber Order'!C:C,0),1))} -> 0.032131148 | AB90: =A90*G90 -> 0.79302528 | AC90: {=A90*Y90*INDEX('Timber Order'!G:G,MATCH($X90,'Timber Order'!C:C,0),1)} -> 0.819352 | AD90: {=Y90*INDEX('Timber Order'!G:G,MATCH($X90,'Timber Order'!C:C,0),1)} -> 0.0204838 | AE90: =AC90-AB90 -> 0.02632672
A91: =SUMIF('Structures Database'!B:B,C91,'Structures Database'!W:W) -> 0 | B91: pcs | C91: =K91&" "&L91&" "&D91&" x "&E91&" x "&F91 -> Floor Sub Beam 46 x 146 x 1121 | D91: 46 | E91: 146 | F91: 1121 | G91: =D91*E91*F91/1000000000 -> 0.007528636 | H91: =G91*$D$16 -> 4.2235648 | I91: =G91*$D$18*$D$20 -> 6.803395 | J91: 5 | K91: Floor | L91: Sub Beam | M91: =AD91*IF(D91>45,$D$14,$D$15) -> 2.0732292 | N91: =J91*$D$19/(8*60) -> 0.15625 | O91: =M91+N91 -> 2.2294792 | P91: =A91*O91 -> 0 | X91: ='Timber Order'!$C$21 -> Floor Beam 46 x 146 x 2450 | Y91: 0.5 | Z91: =A91*Y91 -> 0 | AA91: {=1-(G91/Y91/INDEX('Timber Order'!G:G,MATCH($X91,'Timber Order'!C:C,0),1))} -> 0.084897959 | AB91: =A91*G91 -> 0 | AC91: {=A91*Y91*INDEX('Timber Order'!G:G,MATCH($X91,'Timber Order'!C:C,0),1)} -> 0 | AD91: {=Y91*INDEX('Timber Order'!G:G,MATCH($X91,'Timber Order'!C:C,0),1)} -> 0.0082271 | AE91: =AC91-AB91 -> 0
A92: =SUMIF('Structures Database'!B:B,C92,'Structures Database'!W:W) -> 96 | B92: pcs | C92: =K92&" "&L92&" "&D92&" x "&E92&" x "&F92 -> Floor Support Block 46 x 146 x 548 | D92: 46 | E92: 146 | F92: 548 | G92: =D92*E92*F92/1000000000 -> 0.003680368 | H92: =G92*$D$16 -> 2.0646864 | I92: =G92*$D$18*$D$20 -> 3.3258345 | J92: 5 | K92: Floor | L92: Support Block | M92: =AD92*IF(D92>45,$D$14,$D$15) -> 1.0366146 | N92: =J92*$D$19/(8*60) -> 0.15625 | O92: =M92+N92 -> 1.1928646 | P92: =A92*O92 -> 114.515 | X92: ='Timber Order'!$C$21 -> Floor Beam 46 x 146 x 2450 | Y92: 0.25 | Z92: =A92*Y92 -> 24 | AA92: {=1-(G92/Y92/INDEX('Timber Order'!G:G,MATCH($X92,'Timber Order'!C:C,0),1))} -> 0.10530612 | AB92: =A92*G92 -> 0.35331533 | AC92: {=A92*Y92*INDEX('Timber Order'!G:G,MATCH($X92,'Timber Order'!C:C,0),1)} -> 0.3949008 | AD92: {=Y92*INDEX('Timber Order'!G:G,MATCH($X92,'Timber Order'!C:C,0),1)} -> 0.00411355 | AE92: =AC92-AB92 -> 0.041585472
A93: =SUMIF('Structures Database'!B:B,C93,'Structures Database'!W:W) -> 520 | B93: pcs | C93: =K93&" "&L93&" "&D93&" x "&E93&" x "&F93 -> Floor Plank Tongue Groove 22 x 96 x 2440 | D93: 22 | E93: 96 | F93: 2440 | G93: =D93*E93*F93/1000000000 -> 0.00515328 | H93: =G93*$D$16 -> 2.8909901 | I93: =G93*$D$18*$D$20 -> 4.6568594 | J93: 5 | K93: Floor | L93: Plank Tongue Groove | M93: =AD93*IF(D93>45,$D$14,$D$15) -> 1.345344 | N93: =J93*$D$19/(8*60) -> 0.15625 | O93: =M93+N93 -> 1.501594 | P93: =A93*O93 -> 780.82888 | X93: ='Timber Order'!$C$27 -> Timber Floor Plank 22 x 96 x 2450 | Y93: 1 | Z93: =A93*Y93 -> 520 | AA93: {=1-(G93/Y93/INDEX('Timber Order'!G:G,MATCH($X93,'Timber Order'!C:C,0),1))} -> 0.0040816327 | AB93: =A93*G93 -> 2.6797056 | AC93: {=A93*Y93*INDEX('Timber Order'!G:G,MATCH($X93,'Timber Order'!C:C,0),1)} -> 2.690688 | AD93: {=Y93*INDEX('Timber Order'!G:G,MATCH($X93,'Timber Order'!C:C,0),1)} -> 0.0051744 | AE93: =AC93-AB93 -> 0.0109824
A94: =SUMIF('Structures Database'!B:B,C94,'Structures Database'!W:W) -> 0 | B94: pcs | C94: =K94&" "&L94&" "&D94&" x "&E94&" x "&F94 -> Floor Decking Profile 22 x 96 x 2440 | D94: 22 | E94: 96 | F94: 2440 | G94: =D94*E94*F94/1000000000 -> 0.00515328 | H94: =G94*$D$16 -> 2.8909901 | I94: =G94*$D$18*$D$20 -> 4.6568594 | J94: 5 | K94: Floor | L94: Decking Profile | M94: =AD94*IF(D94>45,$D$14,$D$15) -> 1.345344 | N94: =J94*$D$19/(8*60) -> 0.15625 | O94: =M94+N94 -> 1.501594 | P94: =A94*O94 -> 0 | X94: ='Timber Order'!$C$28 -> Timber Decking Plank 22 x 96 x 2450 | Y94: 1 | Z94: =A94*Y94 -> 0 | AA94: {=1-(G94/Y94/INDEX('Timber Order'!G:G,MATCH($X94,'Timber Order'!C:C,0),1))} -> 0.0040816327 | AB94: =A94*G94 -> 0 | AC94: {=A94*Y94*INDEX('Timber Order'!G:G,MATCH($X94,'Timber Order'!C:C,0),1)} -> 0 | AD94: {=Y94*INDEX('Timber Order'!G:G,MATCH($X94,'Timber Order'!C:C,0),1)} -> 0.0051744 | AE94: =AC94-AB94 -> 0
M95: =AD95*IF(D95>45,$D$14,$D$15) -> 0 | P95: =A95*O95 -> 0
A96: =SUMIF('Structures Database'!B:B,C96,'Structures Database'!W:W) -> 51.027027 | B96: pcs | C96: =K96&" "&L96&" "&D96&" x "&E96&" x "&F96 -> Wall Batten 46 x 71 x 2442 | D96: 46 | E96: 71 | F96: 2442 | G96: =D96*E96*F96/1000000000 -> 0.007975572 | H96: =G96*$D$16 -> 4.4742959 | I96: =G96*$D$18*$D$20 -> 7.2072772 | J96: 5 | K96: Wall | L96: Batten | M96: =AD96*IF(D96>45,$D$14,$D$15) -> 2.0164284 | N96: =J96*$D$19/(8*60) -> 0.15625 | O96: =M96+N96 -> 2.1726784 | P96: =A96*O96 -> 110.86532 | X96: ='Timber Order'!$C$16 -> Wall Beam 46 x 71 x 2450 | Y96: 1 | Z96: =A96*Y96 -> 51.027027 | AA96: {=1-(G96/Y96/INDEX('Timber Order'!G:G,MATCH($X96,'Timber Order'!C:C,0),1))} -> 0.0032653061 | AB96: =A96*G96 -> 0.40696973 | AC96: {=A96*Y96*INDEX('Timber Order'!G:G,MATCH($X96,'Timber Order'!C:C,0),1)} -> 0.40830296 | AD96: {=Y96*INDEX('Timber Order'!G:G,MATCH($X96,'Timber Order'!C:C,0),1)} -> 0.0080017 | AE96: =AC96-AB96 -> 0.0013332342
A97: =SUMIF('Structures Database'!B:B,C97,'Structures Database'!W:W) -> 8 | B97: pcs | C97: =K97&" "&L97&" "&D97&" x "&E97&" x "&F97 -> Wall Batten 46 x 71 x 3053 | D97: 46 | E97: 71 | F97: 3053 | G97: =D97*E97*F97/1000000000 -> 0.009971098 | H97: =G97*$D$16 -> 5.593786 | I97: =G97*$D$18*$D$20 -> 9.0105722 | J97: 5 | K97: Wall | L97: Batten | M97: =AD97*IF(D97>45,$D$14,$D$15) -> 2.5534568 | N97: =J97*$D$19/(8*60) -> 0.15625 | O97: =M97+N97 -> 2.7097068 | P97: =A97*O97 -> 21.677654 | X97: ='Timber Order'!$C$17 -> Wall Beam 46 x 71 x 3650 | Y97: 0.85 | Z97: =A97*Y97 -> 6.8 | AA97: {=1-(G97/Y97/INDEX('Timber Order'!G:G,MATCH($X97,'Timber Order'!C:C,0),1))} -> 0.015954875 | AB97: =A97*G97 -> 0.079768784 | AC97: {=A97*Y97*INDEX('Timber Order'!G:G,MATCH($X97,'Timber Order'!C:C,0),1)} -> 0.08106212 | AD97: {=Y97*INDEX('Timber Order'!G:G,MATCH($X97,'Timber Order'!C:C,0),1)} -> 0.010132765 | AE97: =AC97-AB97 -> 0.001293336
A98: =SUMIF('Structures Database'!B:B,C98,'Structures Database'!W:W) -> 30 | B98: pcs | C98: =K98&" "&L98&" "&D98&" x "&E98&" x "&F98 -> Interior Door Beam 46 x 146 x 2415 | D98: 46 | E98: 146 | F98: 2415 | G98: =D98*E98*F98/1000000000 -> 0.01621914 | H98: =G98*$D$16 -> 9.0989375 | I98: =G98*$D$18*$D$20 -> 14.656734 | K98: Interior Door | L98: Beam | M98: =AD98*IF(D98>45,$D$14,$D$15) -> 4.6305 | N98: =J98*$D$19/(8*60) -> 0 | O98: =M98+N98 -> 4.6305 | P98: =A98*O98 -> 138.915 | X98: ='Timber Order'!C33 -> Interior Door Beams 50 x 150 x 2450 | Y98: 1 | Z98: =A98*Y98 -> 30 | AA98: {=1-(G98/Y98/INDEX('Timber Order'!G:G,MATCH($X98,'Timber Order'!C:C,0),1))} -> 0.11732571 | AB98: =A98*G98 -> 0.4865742 | AC98: {=A98*Y98*INDEX('Timber Order'!G:G,MATCH($X98,'Timber Order'!C:C,0),1)} -> 0.55125 | AD98: {=Y98*INDEX('Timber Order'!G:G,MATCH($X98,'Timber Order'!C:C,0),1)} -> 0.018375 | AE98: =AC98-AB98 -> 0.0646758
A99: =SUMIF('Structures Database'!B:B,C99,'Structures Database'!W:W) -> 120 | B99: pcs | C99: =K99&" "&L99&" "&D99&" x "&E99&" x "&F99 -> Interior Door T&G Plank 22 x 96 x 550 | D99: 22 | E99: 96 | F99: 550 | G99: =D99*E99*F99/1000000000 -> 0.0011616 | H99: =G99*$D$16 -> 0.6516576 | I99: =G99*$D$18*$D$20 -> 1.0497019 | K99: Interior Door | L99: T&G Plank | M99: =AD99*IF(D99>45,$D$14,$D$15) -> 0.336336 | N99: =J99*$D$19/(8*60) -> 0 | O99: =M99+N99 -> 0.336336 | P99: =A99*O99 -> 40.36032 | X99: ='Timber Order'!$C$27 -> Timber Floor Plank 22 x 96 x 2450 | Y99: 0.25 | Z99: =A99*Y99 -> 30 | AA99: {=1-(G99/Y99/INDEX('Timber Order'!G:G,MATCH($X99,'Timber Order'!C:C,0),1))} -> 0.10204082 | AB99: =A99*G99 -> 0.139392 | AC99: {=A99*Y99*INDEX('Timber Order'!G:G,MATCH($X99,'Timber Order'!C:C,0),1)} -> 0.155232 | AD99: {=Y99*INDEX('Timber Order'!G:G,MATCH($X99,'Timber Order'!C:C,0),1)} -> 0.0012936 | AE99: =AC99-AB99 -> 0.01584
A101: =SUMIF('Structures Database'!B:B,C101,'Structures Database'!W:W) -> 44 | B101: pcs | C101: =K101&" "&L101&" "&D101&" x "&E101&" x "&F101 -> Wall Stud 46 x 71 x 2554 | D101: 46 | E101: 71 | F101: 2554 | G101: =D101*E101*F101/1000000000 -> 0.008341364 | H101: =G101*$D$16 -> 4.6795052 | I101: =G101*$D$18*$D$20 -> 7.5378321 | J101: 5 | K101: Wall | L101: Stud | M101: =AD101*IF(D101>45,$D$14,$D$15) -> 2.1028468 | N101: =J101*$D$19/(8*60) -> 0.15625 | O101: =M101+N101 -> 2.2590968 | P101: =A101*O101 -> 99.400257 | X101: ='Timber Order'!$C$17 -> Wall Beam 46 x 71 x 3650 | Y101: 0.7 | Z101: =A101*Y101 -> 30.8 | AA101: {=1-(G101/Y101/INDEX('Timber Order'!G:G,MATCH($X101,'Timber Order'!C:C,0),1))} -> 0.00039138943 | AB101: =A101*G101 -> 0.36702002 | AC101: {=A101*Y101*INDEX('Timber Order'!G:G,MATCH($X101,'Timber Order'!C:C,0),1)} -> 0.36716372 | AD101: {=Y101*INDEX('Timber Order'!G:G,MATCH($X101,'Timber Order'!C:C,0),1)} -> 0.00834463 | AE101: =AC101-AB101 -> 0.000143704
A102: =SUMIF('Structures Database'!B:B,C102,'Structures Database'!W:W) -> 40 | B102: pcs | C102: =K102&" "&L102&" "&D102&" x "&E102&" x "&F102 -> Wall Stud 46 x 71 x 2899 | D102: 46 | E102: 71 | F102: 2899 | G102: =D102*E102*F102/1000000000 -> 0.009468134 | H102: =G102*$D$16 -> 5.3116232 | I102: =G102*$D$18*$D$20 -> 8.5560592 | J102: 5 | K102: Wall | L102: Stud | M102: =AD102*IF(D102>45,$D$14,$D$15) -> 2.5534568 | N102: =J102*$D$19/(8*60) -> 0.15625 | O102: =M102+N102 -> 2.7097068 | P102: =A102*O102 -> 108.38827 | X102: ='Timber Order'!$C$17 -> Wall Beam 46 x 71 x 3650 | Y102: 0.85 | Z102: =A102*Y102 -> 34 | AA102: {=1-(G102/Y102/INDEX('Timber Order'!G:G,MATCH($X102,'Timber Order'!C:C,0),1))} -> 0.065592264 | AB102: =A102*G102 -> 0.37872536 | AC102: {=A102*Y102*INDEX('Timber Order'!G:G,MATCH($X102,'Timber Order'!C:C,0),1)} -> 0.4053106 | AD102: {=Y102*INDEX('Timber Order'!G:G,MATCH($X102,'Timber Order'!C:C,0),1)} -> 0.010132765 | AE102: =AC102-AB102 -> 0.02658524
A103: =SUMIF('Structures Database'!B:B,C103,'Structures Database'!W:W) -> 67.567568 | B103: pcs | C103: =K103&" "&L103&" "&D103&" x "&E103&" x "&F103 -> Wall Stud 46 x 71 x 2960 | D103: 46 | E103: 71 | F103: 2960 | G103: =D103*E103*F103/1000000000 -> 0.00966736 | H103: =G103*$D$16 -> 5.423389 | I103: =G103*$D$18*$D$20 -> 8.7360935 | J103: 5 | K103: Wall | L103: Stud | M103: =AD103*IF(D103>45,$D$14,$D$15) -> 2.5534568 | N103: =J103*$D$19/(8*60) -> 0.15625 | O103: =M103+N103 -> 2.7097068 | P103: =A103*O103 -> 183.0883 | X103: ='Timber Order'!$C$17 -> Wall Beam 46 x 71 x 3650 | Y103: 0.85 | Z103: =A103*Y103 -> 57.432432 | AA103: {=1-(G103/Y103/INDEX('Timber Order'!G:G,MATCH($X103,'Timber Order'!C:C,0),1))} -> 0.045930701 | AB103: =A103*G103 -> 0.6532 | AC103: {=A103*Y103*INDEX('Timber Order'!G:G,MATCH($X103,'Timber Order'!C:C,0),1)} -> 0.68464628 | AD103: {=Y103*INDEX('Timber Order'!G:G,MATCH($X103,'Timber Order'!C:C,0),1)} -> 0.010132765 | AE103: =AC103-AB103 -> 0.031446284
M104: =AD104*IF(D104>45,$D$14,$D$15) -> 0 | P104: =A104*O104 -> 0
A105: =SUMIF('Structures Database'!B:B,C105,'Structures Database'!W:W) -> 16 | B105: pcs | C105: =K105&" "&L105&" "&D105&" x "&E105&" x "&F105 -> Wall Bracing 46 x 71 x 2416 | D105: 46 | E105: 71 | F105: 2416 | G105: =D105*E105*F105/1000000000 -> 0.007890656 | H105: =G105*$D$16 -> 4.426658 | I105: =G105*$D$18*$D$20 -> 7.1305412 | J105: 5 | K105: Wall | L105: Bracing | M105: =AD105*IF(D105>45,$D$14,$D$15) -> 2.0164284 | N105: =J105*$D$19/(8*60) -> 0.15625 | O105: =M105+N105 -> 2.1726784 | P105: =A105*O105 -> 34.762854 | X105: ='Timber Order'!$C$16 -> Wall Beam 46 x 71 x 2450 | Y105: 1 | Z105: =A105*Y105 -> 16 | AA105: {=1-(G105/Y105/INDEX('Timber Order'!G:G,MATCH($X105,'Timber Order'!C:C,0),1))} -> 0.013877551 | AB105: =A105*G105 -> 0.1262505 | AC105: {=A105*Y105*INDEX('Timber Order'!G:G,MATCH($X105,'Timber Order'!C:C,0),1)} -> 0.1280272 | AD105: {=Y105*INDEX('Timber Order'!G:G,MATCH($X105,'Timber Order'!C:C,0),1)} -> 0.0080017 | AE105: =AC105-AB105 -> 0.001776704
A106: =SUMIF('Structures Database'!B:B,C106,'Structures Database'!W:W) -> 122.05405 | B106: pcs | C106: =K106&" "&L106&" "&D106&" x "&E106&" x "&F106 -> Wall Support Block 46 x 71 x 548 | D106: 46 | E106: 71 | F106: 548 | G106: =D106*E106*F106/1000000000 -> 0.001789768 | H106: =G106*$D$16 -> 1.0040598 | I106: =G106*$D$18*$D$20 -> 1.6173579 | J106: 5 | K106: Wall | L106: Support Block | M106: =AD106*IF(D106>45,$D$14,$D$15) -> 0.5041071 | N106: =J106*$D$19/(8*60) -> 0.15625 | O106: =M106+N106 -> 0.6603571 | P106: =A106*O106 -> 80.599261 | X106: ='Timber Order'!$C$16 -> Wall Beam 46 x 71 x 2450 | Y106: 0.25 | Z106: =A106*Y106 -> 30.513514 | AA106: {=1-(G106/Y106/INDEX('Timber Order'!G:G,MATCH($X106,'Timber Order'!C:C,0),1))} -> 0.10530612 | AB106: =A106*G106 -> 0.21844844 | AC106: {=A106*Y106*INDEX('Timber Order'!G:G,MATCH($X106,'Timber Order'!C:C,0),1)} -> 0.24415998 | AD106: {=Y106*INDEX('Timber Order'!G:G,MATCH($X106,'Timber Order'!C:C,0),1)} -> 0.002000425 | AE106: =AC106-AB106 -> 0.025711541
M107: =AD107*IF(D107>45,$D$14,$D$15) -> 0 | P107: =A107*O107 -> 0
A108: =SUMIF('Structures Database'!B:B,C108,'Structures Database'!W:W) -> 182 | B108: pcs | C108: =K108&" "&L108&" "&D108&" x "&E108&" x "&F108 -> Back Batten 22 x 46 x 1220 | D108: 22 | E108: 46 | F108: 1220 | G108: =D108*E108*F108/1000000000 -> 0.00123464 | H108: =G108*$D$16 -> 0.69263304 | I108: =G108*$D$18*$D$20 -> 1.1157059 | J108: 5 | K108: Back | L108: Batten | M108: =AD108*IF(D108>45,$D$14,$D$15) -> 0.322322 | N108: =J108*$D$19/(8*60) -> 0.15625 | O108: =M108+N108 -> 0.478572 | P108: =A108*O108 -> 87.100104 | X108: ='Timber Order'!$C$25 -> Timber Back Batten 22 x 46 x 2450 | Y108: 0.5 | Z108: =A108*Y108 -> 91 | AA108: {=1-(G108/Y108/INDEX('Timber Order'!G:G,MATCH($X108,'Timber Order'!C:C,0),1))} -> 0.0040816327 | AB108: =A108*G108 -> 0.22470448 | AC108: {=A108*Y108*INDEX('Timber Order'!G:G,MATCH($X108,'Timber Order'!C:C,0),1)} -> 0.2256254 | AD108: {=Y108*INDEX('Timber Order'!G:G,MATCH($X108,'Timber Order'!C:C,0),1)} -> 0.0012397 | AE108: =AC108-AB108 -> 0.00092092
A109: =SUMIF('Structures Database'!B:B,C109,'Structures Database'!W:W) -> 0 | B109: pcs | C109: =K109&" "&L109&" "&D109&" x "&E109&" x "&F109 -> Back Batten 22 x 46 x 1598 | D109: 22 | E109: 46 | F109: 1598 | G109: =D109*E109*F109/1000000000 -> 0.001617176 | H109: =G109*$D$16 -> 0.90723574 | I109: =G109*$D$18*$D$20 -> 1.4613918 | J109: 5 | K109: Back | L109: Batten | M109: =AD109*IF(D109>45,$D$14,$D$15) -> 0.42546504 | N109: =J109*$D$19/(8*60) -> 0.15625 | O109: =M109+N109 -> 0.58171504 | P109: =A109*O109 -> 0 | X109: ='Timber Order'!$C$25 -> Timber Back Batten 22 x 46 x 2450 | Y109: 0.66 | Z109: =A109*Y109 -> 0 | AA109: {=1-(G109/Y109/INDEX('Timber Order'!G:G,MATCH($X109,'Timber Order'!C:C,0),1))} -> 0.011750155 | AB109: =A109*G109 -> 0 | AC109: {=A109*Y109*INDEX('Timber Order'!G:G,MATCH($X109,'Timber Order'!C:C,0),1)} -> 0 | AD109: {=Y109*INDEX('Timber Order'!G:G,MATCH($X109,'Timber Order'!C:C,0),1)} -> 0.001636404 | AE109: =AC109-AB109 -> 0
A110: =SUMIF('Structures Database'!B:B,C110,'Structures Database'!W:W) -> 52 | B110: pcs | C110: =K110&" "&L110&" "&D110&" x "&E110&" x "&F110 -> Back Batten 22 x 46 x 1689 | D110: 22 | E110: 46 | F110: 1689 | G110: =D110*E110*F110/1000000000 -> 0.001709268 | H110: =G110*$D$16 -> 0.95889935 | I110: =G110*$D$18*$D$20 -> 1.5446125 | J110: 5 | K110: Back | L110: Batten | M110: =AD110*IF(D110>45,$D$14,$D$15) -> 0.42546504 | N110: =J110*$D$19/(8*60) -> 0.15625 | O110: =M110+N110 -> 0.58171504 | P110: =A110*O110 -> 30.249182 | X110: ='Timber Order'!$C$25 -> Timber Back Batten 22 x 46 x 2450 | Y110: 0.66 | Z110: =A110*Y110 -> 34.32 | AA110: {=1-(G110/Y110/INDEX('Timber Order'!G:G,MATCH($X110,'Timber Order'!C:C,0),1))} -> -0.044526902 | AB110: =A110*G110 -> 0.088881936 | AC110: {=A110*Y110*INDEX('Timber Order'!G:G,MATCH($X110,'Timber Order'!C:C,0),1)} -> 0.085093008 | AD110: {=Y110*INDEX('Timber Order'!G:G,MATCH($X110,'Timber Order'!C:C,0),1)} -> 0.001636404 | AE110: =AC110-AB110 -> -0.003788928
A111: =SUMIF('Structures Database'!B:B,C111,'Structures Database'!W:W) -> 0 | B111: pcs | C111: =K111&" "&L111&" "&D111&" x "&E111&" x "&F111 -> Back Batten 22 x 46 x 1880 | D111: 22 | E111: 46 | F111: 1880 | G111: =D111*E111*F111/1000000000 -> 0.00190256 | H111: =G111*$D$16 -> 1.0673362 | I111: =G111*$D$18*$D$20 -> 1.7192845 | J111: 5 | K111: Back | L111: Batten | M111: =AD111*IF(D111>45,$D$14,$D$15) -> 0.644644 | N111: =J111*$D$19/(8*60) -> 0.15625 | O111: =M111+N111 -> 0.800894 | P111: =A111*O111 -> 0 | X111: ='Timber Order'!$C$25 -> Timber Back Batten 22 x 46 x 2450 | Y111: 1 | Z111: =A111*Y111 -> 0 | AA111: {=1-(G111/Y111/INDEX('Timber Order'!G:G,MATCH($X111,'Timber Order'!C:C,0),1))} -> 0.23265306 | AB111: =A111*G111 -> 0 | AC111: {=A111*Y111*INDEX('Timber Order'!G:G,MATCH($X111,'Timber Order'!C:C,0),1)} -> 0 | AD111: {=Y111*INDEX('Timber Order'!G:G,MATCH($X111,'Timber Order'!C:C,0),1)} -> 0.0024794 | AE111: =AC111-AB111 -> 0
A112: =SUMIF('Structures Database'!B:B,C112,'Structures Database'!W:W) -> 183.42721 | B112: pcs | C112: =K112&" "&L112&" "&D112&" x "&E112&" x "&F112 -> Back Batten 22 x 46 x 2440 | D112: 22 | E112: 46 | F112: 2440 | G112: =D112*E112*F112/1000000000 -> 0.00246928 | H112: =G112*$D$16 -> 1.3852661 | I112: =G112*$D$18*$D$20 -> 2.2314118 | J112: 5 | K112: Back | L112: Batten | M112: =AD112*IF(D112>45,$D$14,$D$15) -> 0.644644 | N112: =J112*$D$19/(8*60) -> 0.15625 | O112: =M112+N112 -> 0.800894 | P112: =A112*O112 -> 146.90575 | X112: ='Timber Order'!$C$25 -> Timber Back Batten 22 x 46 x 2450 | Y112: 1 | Z112: =A112*Y112 -> 183.42721 | AA112: {=1-(G112/Y112/INDEX('Timber Order'!G:G,MATCH($X112,'Timber Order'!C:C,0),1))} -> 0.0040816327 | AB112: =A112*G112 -> 0.45293314 | AC112: {=A112*Y112*INDEX('Timber Order'!G:G,MATCH($X112,'Timber Order'!C:C,0),1)} -> 0.45478942 | AD112: {=Y112*INDEX('Timber Order'!G:G,MATCH($X112,'Timber Order'!C:C,0),1)} -> 0.0024794 | AE112: =AC112-AB112 -> 0.0018562834
A113: =SUMIF('Structures Database'!B:B,C113,'Structures Database'!W:W) -> 16 | B113: pcs | C113: =K113&" "&L113&" "&D113&" x "&E113&" x "&F113 -> Back Batten 22 x 46 x 3053 | D113: 22 | E113: 46 | F113: 3053 | G113: =D113*E113*F113/1000000000 -> 0.003089636 | H113: =G113*$D$16 -> 1.7332858 | I113: =G113*$D$18*$D$20 -> 2.7920083 | J113: 5 | K113: Back | L113: Batten | M113: =AD113*IF(D113>45,$D$14,$D$15) -> 0.802516 | N113: =J113*$D$19/(8*60) -> 0.15625 | O113: =M113+N113 -> 0.958766 | P113: =A113*O113 -> 15.340256 | X113: ='Timber Order'!$C$26 -> Timber Back Batten 22 x 46 x 3050 | Y113: 1 | Z113: =A113*Y113 -> 16 | AA113: {=1-(G113/Y113/INDEX('Timber Order'!G:G,MATCH($X113,'Timber Order'!C:C,0),1))} -> -0.00098360656 | AB113: =A113*G113 -> 0.049434176 | AC113: {=A113*Y113*INDEX('Timber Order'!G:G,MATCH($X113,'Timber Order'!C:C,0),1)} -> 0.0493856 | AD113: {=Y113*INDEX('Timber Order'!G:G,MATCH($X113,'Timber Order'!C:C,0),1)} -> 0.0030866 | AE113: =AC113-AB113 -> -4.8576e-05
A114: =SUMIF('Structures Database'!B:B,C114,'Structures Database'!W:W) -> 188 | B114: pcs | C114: =K114&" "&L114&" "&D114&" x "&E114&" x "&F114 -> Facade Vertical Shiplap 22 x 96 x 1221 | D114: 22 | E114: 96 | F114: 1221 | G114: =D114*E114*F114/1000000000 -> 0.002578752 | H114: =G114*$D$16 -> 1.4466799 | I114: =G114*$D$18*$D$20 -> 2.3303382 | J114: 10 | K114: Facade | L114: Vertical Shiplap | M114: =AD114*IF(D114>45,$D$14,$D$15) -> 0.837408 | N114: =J114*$D$19/(8*60) -> 0.3125 | O114: =M114+N114 -> 1.149908 | P114: =A114*O114 -> 216.1827 | X114: =X115 -> Timber Facade Plank 22 x 96 x 3050 | Y114: 0.5 | Z114: =A114*Y114 -> 94 | AA114: {=1-(G114/Y114/INDEX('Timber Order'!G:G,MATCH($X114,'Timber Order'!C:C,0),1))} -> 0.19934426 | AB114: =A114*G114 -> 0.48480538 | AC114: {=A114*Y114*INDEX('Timber Order'!G:G,MATCH($X114,'Timber Order'!C:C,0),1)} -> 0.6055104 | AD114: {=Y114*INDEX('Timber Order'!G:G,MATCH($X114,'Timber Order'!C:C,0),1)} -> 0.0032208 | AE114: =AC114-AB114 -> 0.12070502
A115: =SUMIF('Structures Database'!B:B,C115,'Structures Database'!W:W) -> 418.11499 | B115: pcs | C115: =K115&" "&L115&" "&D115&" x "&E115&" x "&F115 -> Facade Vertical Shiplap 22 x 96 x 2826 | D115: 22 | E115: 96 | F115: 2826 | G115: =D115*E115*F115/1000000000 -> 0.005968512 | H115: =G115*$D$16 -> 3.3483352 | I115: =G115*$D$18*$D$20 -> 5.3935593 | J115: 10 | K115: Facade | L115: Vertical Shiplap | M115: =AD115*IF(D115>45,$D$14,$D$15) -> 1.674816 | N115: =J115*$D$19/(8*60) -> 0.3125 | O115: =M115+N115 -> 1.987316 | P115: =A115*O115 -> 830.92661 | X115: ='Timber Order'!$C$29 -> Timber Facade Plank 22 x 96 x 3050 | Y115: 1 | Z115: =A115*Y115 -> 418.11499 | AA115: {=1-(G115/Y115/INDEX('Timber Order'!G:G,MATCH($X115,'Timber Order'!C:C,0),1))} -> 0.073442623 | AB115: =A115*G115 -> 2.4955243 | AC115: {=A115*Y115*INDEX('Timber Order'!G:G,MATCH($X115,'Timber Order'!C:C,0),1)} -> 2.6933295 | AD115: {=Y115*INDEX('Timber Order'!G:G,MATCH($X115,'Timber Order'!C:C,0),1)} -> 0.0064416 | AE115: =AC115-AB115 -> 0.19780518
...

Sheet Timber Order
A3: Timber Procurement Order List
A4: Order date: | B4: Date
A5: By: | B5: Wolf Bierens - Easy Housing
A6: For: | B6: Contact Name - Company
A9: Timber quality and sustainability criteria
A10: Timber must be well seasoned, kiln dried, at specified dimensions within 2-3 mm tolerance and CCA treated. T&G, decking and shiplap planks must be planed and profiled properly.
A11: Timber must be sustainably sourced. This means with FSC (controlled) certification or under EUTR regulation.
A12: Easy Housing holds the legal claim to the construction stored carbon credits realised through its buildings. These credits do not conflict with any REDD+ or comparable forest conservation credits.
A14: Timber orderlist | D14: Specifications
A15: # | B15: Unit | C15: Item | D15: Width (mm) | E15: Height (mm) | F15: Length (mm) | G15: Volume (m3) | H15: Volume total | J15: Weight (kg) | K15: Carbon storage (kg CO2) | L15: Structure | M15: Type
A16: =ROUNDUP(SUMIF('Bill of Quantities'!X:X,C16,'Bill of Quantities'!Z:Z),0) -> 98 | B16: pcs | C16: =L16&" "&M16&" "&D16&" x "&E16&" x "&F16 -> Wall Beam 46 x 71 x 2450 | D16: 46 | E16: 71 | F16: 2450 | G16: =D16*E16*F16*0.000000001 -> 0.0080017 | H16: =A16*G16 -> 0.7841666 | J16: =G16*'Bill of Quantities'!$D$16 -> 4.4889537 | K16: =G16*'Bill of Quantities'!$D$18*'Bill of Quantities'!$D$20 -> 7.2308882 | L16: Wall | M16: Beam
A17: =ROUNDUP(SUMIF('Bill of Quantities'!X:X,C17,'Bill of Quantities'!Z:Z),0) -> 130 | B17: pcs | C17: =L17&" "&M17&" "&D17&" x "&E17&" x "&F17 -> Wall Beam 46 x 71 x 3650 | D17: 46 | E17: 71 | F17: 3650 | G17: =D17*E17*F17*0.000000001 -> 0.0119209 | H17: =A17*G17 -> 1.549717 | J17: =G17*'Bill of Quantities'!$D$16 -> 6.6876249 | K17: =G17*'Bill of Quantities'!$D$18*'Bill of Quantities'!$D$20 -> 10.772548 | L17: Wall | M17: Beam
A18: =ROUNDUP(SUMIF('Bill of Quantities'!X:X,C18,'Bill of Quantities'!Z:Z),0) -> 55 | B18: pcs | C18: =L18&" "&M18&" "&D18&" x "&E18&" x "&F18 -> Roof Beam 46 x 96 x 2450 | D18: 46 | E18: 96 | F18: 2450 | G18: =D18*E18*F18*0.000000001 -> 0.0108192 | H18: =A18*G18 -> 0.595056 | J18: =G18*'Bill of Quantities'!$D$16 -> 6.0695712 | K18: =G18*'Bill of Quantities'!$D$18*'Bill of Quantities'!$D$20 -> 9.7769756 | L18: Roof | M18: Beam
A19: =ROUNDUP(SUMIF('Bill of Quantities'!X:X,C19,'Bill of Quantities'!Z:Z),0) -> 3 | B19: pcs | C19: =L19&" "&M19&" "&D19&" x "&E19&" x "&F19 -> Roof Beam 46 x 96 x 4250 | D19: 46 | E19: 96 | F19: 4250 | G19: =D19*E19*F19*0.000000001 -> 0.018768 | H19: =A19*G19 -> 0.056304 | J19: =G19*'Bill of Quantities'!$D$16 -> 10.528848 | K19: =G19*'Bill of Quantities'!$D$18*'Bill of Quantities'!$D$20 -> 16.96006 | L19: Roof | M19: Beam
A20: =ROUNDUP(SUMIF('Bill of Quantities'!X:X,C20,'Bill of Quantities'!Z:Z),0) -> 61 | B20: pcs | C20: =L20&" "&M20&" "&D20&" x "&E20&" x "&F20 -> Roof Beam 46 x 96 x 5750 | D20: 46 | E20: 96 | F20: 5750 | G20: =D20*E20*F20*0.000000001 -> 0.025392 | H20: =A20*G20 -> 1.548912 | J20: =G20*'Bill of Quantities'!$D$16 -> 14.244912 | K20: =G20*'Bill of Quantities'!$D$18*'Bill of Quantities'!$D$20 -> 22.945963 | L20: Roof | M20: Beam
A21: =ROUNDUP(SUMIF('Bill of Quantities'!X:X,C21,'Bill of Quantities'!Z:Z),0) -> 96 | B21: pcs | C21: =L21&" "&M21&" "&D21&" x "&E21&" x "&F21 -> Floor Beam 46 x 146 x 2450 | D21: 46 | E21: 146 | F21: 2450 | G21: =D21*E21*F21*0.000000001 -> 0.0164542 | H21: =A21*G21 -> 1.5796032 | J21: =G21*'Bill of Quantities'!$D$16 -> 9.2308062 | K21: =G21*'Bill of Quantities'!$D$18*'Bill of Quantities'!$D$20 -> 14.86915 | L21: Floor | M21: Beam
A22: =ROUNDUP(SUMIF('Bill of Quantities'!X:X,C22,'Bill of Quantities'!Z:Z),0) -> 40 | B22: pcs | C22: =L22&" "&M22&" "&D22&" x "&E22&" x "&F22 -> Floor Beam 46 x 146 x 3050 | D22: 46 | E22: 146 | F22: 3050 | G22: =D22*E22*F22*0.000000001 -> 0.0204838 | H22: =A22*G22 -> 0.819352 | J22: =G22*'Bill of Quantities'!$D$16 -> 11.491412 | K22: =G22*'Bill of Quantities'!$D$18*'Bill of Quantities'!$D$20 -> 18.510575 | L22: Floor | M22: Beam
A23: =ROUNDUP(SUMIF('Bill of Quantities'!X:X,C23,'Bill of Quantities'!Z:Z),0) -> 0 | B23: pcs | C23: =L23&" "&M23&" "&D23&" x "&E23&" x "&F23 -> Floor Beam 46 x 146 x 5450 | D23: 46 | E23: 146 | F23: 5450 | G23: =D23*E23*F23*0.000000001 -> 0.0366022 | H23: =A23*G23 -> 0 | J23: =G23*'Bill of Quantities'!$D$16 -> 20.533834 | K23: =G23*'Bill of Quantities'!$D$18*'Bill of Quantities'!$D$20 -> 33.076273 | L23: Floor | M23: Beam
A24: =ROUNDUP(SUMIF('Bill of Quantities'!X:X,C24,'Bill of Quantities'!Z:Z),0) -> 0 | B24: pcs | C24: =L24&" "&M24&" "&D24&" x "&E24&" x "&F24 -> Timber Column 100 x 100 x 3050 | D24: 100 | E24: 100 | F24: 3050 | G24: =D24*E24*F24*0.000000001 -> 0.0305 | H24: =A24*G24 -> 0 | J24: =G24*'Bill of Quantities'!$D$16 -> 17.1105 | K24: =G24*'Bill of Quantities'!$D$18*'Bill of Quantities'!$D$20 -> 27.561905 | L24: Timber | M24: Column
A25: =ROUNDUP(SUMIF('Bill of Quantities'!X:X,C25,'Bill of Quantities'!Z:Z),0) -> 309 | B25: pcs | C25: =L25&" "&M25&" "&D25&" x "&E25&" x "&F25 -> Timber Back Batten 22 x 46 x 2450 | D25: 22 | E25: 46 | F25: 2450 | G25: =D25*E25*F25*0.000000001 -> 0.0024794 | H25: =A25*G25 -> 0.7661346 | J25: =G25*'Bill of Quantities'!$D$16 -> 1.3909434 | K25: =G25*'Bill of Quantities'!$D$18*'Bill of Quantities'!$D$20 -> 2.2405569 | L25: Timber | M25: Back Batten
A26: =ROUNDUP(SUMIF('Bill of Quantities'!X:X,C26,'Bill of Quantities'!Z:Z),0) -> 16 | B26: pcs | C26: =L26&" "&M26&" "&D26&" x "&E26&" x "&F26 -> Timber Back Batten 22 x 46 x 3050 | D26: 22 | E26: 46 | F26: 3050 | G26: =D26*E26*F26*0.000000001 -> 0.0030866 | H26: =A26*G26 -> 0.0493856 | J26: =G26*'Bill of Quantities'!$D$16 -> 1.7315826 | K26: =G26*'Bill of Quantities'!$D$18*'Bill of Quantities'!$D$20 -> 2.7892647 | L26: Timber | M26: Back Batten
A27: =ROUNDUP(SUMIF('Bill of Quantities'!X:X,C27,'Bill of Quantities'!Z:Z),0) -> 550 | B27: pcs | C27: =L27&" "&M27&" "&D27&" x "&E27&" x "&F27 -> Timber Floor Plank 22 x 96 x 2450 | D27: 22 | E27: 96 | F27: 2450 | G27: =D27*E27*F27*0.000000001 -> 0.0051744 | H27: =A27*G27 -> 2.84592 | J27: =G27*'Bill of Quantities'!$D$16 -> 2.9028384 | K27: =G27*'Bill of Quantities'!$D$18*'Bill of Quantities'!$D$20 -> 4.6759449 | L27: Timber | M27: Floor Plank
... A33: =ROUNDUP(SUMIF('Bill of Quantities'!X:X,C33,'Bill of Quantities'!Z:Z),0) -> 30 | B33: pcs | C33: =L33&" "&M33&" "&D33&" x "&E33&" x "&F33 -> Interior Door Beams 50 x 150 x 2450 | D33: 50 | E33: 150 | F33: 2450 | G33: =D33*E33*F33*0.000000001 -> 0.018375 | H33: =A33*G33 -> 0.55125 | J33: =G33*'Bill of Quantities'!$D$16 -> 10.308375 | K33: =G33*'Bill of Quantities'!$D$18*'Bill of Quantities'!$D$20 -> 16.604918 | L33: Interior Door | M33: Beams
A35: Total amounts | H35: =SUM(H16:H34) -> 15.141925 | I35: cbm
D44: Timber Standard Lengths
D45: Millimetre * | E45: Feet
D46: 2450 | E46: =ROUND(D46/300,0) -> 8
D47: 2750 | E47: =ROUND(D47/300,0) -> 9
D48: 3050 | E48: =ROUND(D48/300,0) -> 10
D49: 3650 | E49: =ROUND(D49/300,0) -> 12
D50: 3950 | E50: =ROUND(D50/300,0) -> 13
D51: 4250 | E51: =ROUND(D51/300,0) -> 14
D52: 5450 | E52: =ROUND(D52/300,0) -> 18
D53: 5750 | E53: =ROUND(D53/300,0) -> 19
D54: 6050 | E54: =ROUND(D54/300,0) -> 20
D56: * default lengths at Busoga, but 6m not always available

Sheet Input Database
A1: Hier komt een database van inputs met behulp van een macro
A2: Macro knop die automatisch een PDF genereert van de project outputs en dan ook hier de inputs in opslaat
B4: Instructions: Copy Cells B20:B46 and paste special here as values only!
B5: Database
B6: Date
A8: Project input | B8: Project Input Database
A9: Client input
A10: ='Price Calc'!A13 -> Client Name | B10: One Bed Mono | C10: John's | D10: Alex Michael Thiaka | E10: Ziwa Rhino Sanctuary | F10: Tamsin Scurfield | G10: Jesse & Naomi | H10: Maureen | I10: Tamsin test | J10: Soul Agri Business Company Ltd | K10: Anwar
A11: ='Price Calc'!A14 -> Contact Details | B11: Example | C11: Test | D11: bolossatestates@gmail.com | E11: Captain Joe Roy | F11: tamsaway@gmail.com | G11: nduksk@gmail.com | H11: 254 722 808352 | I11: 0 | J11: +256 759 740888 | K11: +256 759 740888
A12: ='Price Calc'!A23 -> Project Location | B12: Greater Kampala | C12: Greater Kampala | D12: Olkalau | E12: Ziwa | F12: Jinja | G12: Nairobi | H12: Nairobi | I12: Kampala | J12: Kiryandongo | K12: Kiryandongo
A13: ='Price Calc'!A24 -> Distance from factory | B13: 50 | C13: 50 | D13: 150 | E13: 177 | F13: 89 | G13: 50 | H13: 180 | I13: 150 | J13: 213 | K13: 213
A14: Date of input
A15: ='Price Calc'!A15 -> Created by | B15: Wolf Bierens | C15: Wolf Bierens | D15: Monicah Migwi | E15: Wolf Bierens | F15: Brian Kulubya | G15: Wolf Bierens | H15: Branton | I15: Wolf | J15: Aaron | K15: Aaron
A17: Building input (structure parameters)
A18: ='Price Calc'!A18 -> Easy Housing Typology | B18: Mono Pitch | C18: Compact Gable | D18: Large Clerestory | E18: Compact Gable | F18: Large Clerestory | G18: Large Clerestory | H18: Mono Pitch | I18: Large Clerestory | J18: Large Clerestory | K18: Compact Gable
A19: Number of units (of exactly this type) | B19: 1 | C19: 1 | D19: 1 | E19: 4 | F19: 1 | G19: 1 | H19: 1 | I19: 1 | J19: 1 | K19: 1
A20: ='Price Calc'!A60 -> Columns A (1221) | B20: 0 | C20: 0 | D20: 2 | E20: 0 | F20: 2 | G20: 2 | H20: 0 | I20: 2 | J20: 3 | K20: 0
A21: ='Price Calc'!A61 -> Columns B (2442) | B21: 3 | C21: 4 | D21: 4 | E21: 4 | F21: 0 | G21: 2 | H21: 2 | I21: 2 | J21: 0 | K21: 4
A22: ='Price Calc'!A62 -> Columns C (3053) | B22: 0 | C22: 0 | D22: 0 | E22: 0 | F22: 2 | G22: 1 | H22: 3 | I22: 0 | J22: 3 | K22: 0
A23: ='Price Calc'!A65 -> Interior doors | B23: 2 | C23: 4 | D23: 6 | E23: 2 | F23: 3 | G23: 5 | H23: 4 | I23: 3 | J23: 1 | K23: 4
A24: ='Price Calc'!A66 -> Partitions (length) | B24: 6 | C24: 19.5 | D24: 37.7 | E24: 9 | F24: 15 | G24: 32 | H24: 6 | I24: 16 | J24: 39 | K24: 18.2
A25: ='Price Calc'!A67 -> External doors & windows (area) | B25: 7.9 | C25: 15 | D25: 28.8 | E25: 22 | F25: 30.3 | G25: 27.2 | H25: 9.4 | I25: 23.3 | J25: 27 | K25: 14.7
A26: Bedrooms | B26: 1 | C26: 2 | D26: 3 | E26: 2 | F26: 2 | G26: 3 | H26: 3 | I26: 2 | J26: 4 | K26: 2
A27: Bathrooms | B27: 1 | C27: 2 | D27: 4 | E27: 1 | F27: 1 | G27: 2 | H27: 2 | I27: 1 | J27: 4 | K27: 2
A28: Kitchen areas | B28: 1 | C28: 1 | D28: 1 | E28: 0 | F28: 0 | G28: 1 | H28: 1 | I28: 1 | J28: 1 | K28: 1
A30: Additional options
A31: ='Price Calc'!A41 -> Terrace | B31: 0 | C31: 6 | D31: 18.5 | E31: 4 | F31: 27 | G31: 19 | H31: 4 | I31: 25.8 | J31: 11 | K31: 0
A32: ='Price Calc'!A42 -> Pergola | B32: 0 | C32: 6 | D32: 18.5 | E32: 0 | F32: 27 | G32: 17 | H32: 4 | I32: 25.8 | J32: 11 | K32: 0
A33: ='Price Calc'!A43 -> Railing open | B33: 0 | C33: 0 | D33: 11 | E33: 0 | F33: 14.7 | G33: 17 | H33: 0 | I33: 13 | J33: 0 | K33: 0
A34: ='Price Calc'!A44 -> Railing semi-closed | B34: 0 | C34: 0 | D34: 0 | E34: 10 | F34: 0 | G34: 0 | H34: 0 | I34: 0 | J34: 0 | K34: 0
A35: ='Price Calc'!A68 -> Extra staircase (beyond the first) | B35: 0 | C35: 0 | D35: 1 | E35: 0 | F35: 1 | G35: 1 | H35: 0 | I35: 0 | J35: 0 | K35: 0
A36: ='Price Calc'!A40 -> Burglar bars | B36: 0 | C36: 10 | D36: 0 | E36: 0 | F36: 0 | G36: 0 | H36: 0 | I36: 0 | J36: 0 | K36: 0
A37: ='Price Calc'!A45 -> Wheelchair ramp | B37: 0 | C37: 0 | D37: 0 | E37: 0 | F37: 0 | G37: 0 | H37: 0 | I37: 0 | J37: 0 | K37: 0
A38: ='Price Calc'!A46 -> Tiles | B38: 0 | C38: 0 | D38: 0 | E38: 1350000 | F38: 1500000 | G38: 0 | H38: 0 | I38: 2000000 | J38: 6400000 | K38: 0
A39: ='Price Calc'!A47 -> Sanitary wares | B39: 0 | C39: 0 | D39: 0 | E39: 2800000 | F39: 3500000 | G39: 0 | H39: 0 | I39: 3000000 | J39: 14000000 | K39: 0
A40: ='Price Calc'!A48 -> Biodigester | B40: 0 | C40: 0 | D40: 0 | E40: 0 | F40: 3100000 | G40: 0 | H40: 0 | I40: 3000000 | J40: 3200000 | K40: 0
A41: Other option(s) description | F41: Foundation extra height | G41: Foundation height at 1.2m | J41: Kitchen
A42: Other option(s) price | F42: 2500000 | G42: 150000 | J42: 5000000
K48: Amount
K49: 0
K50: 0
K51: 0
K52: 0
K53: 0
K54: 0
K55: 0
K56: 2
K57: 0
K58: 0
K59: 5
K60: 0
... K68: 0

Sheet Structures Database
A1: Structures database | C1: Per element | L1: Project cost item | O1: Totals per frame | V1: Calculation columns for building input
A2: # | B2: Element name | C2: ='Bill of Quantities'!D2 -> Width (mm) | D2: ='Bill of Quantities'!E2 -> Height (mm) | E2: ='Bill of Quantities'!F2 -> Length (mm) | F2: ='Bill of Quantities'!G2 -> Volume (m3) | G2: ='Bill of Quantities'!H2 -> Weight (kg) | H2: ='Bill of Quantities'!I2 -> Carbon storage (kg CO2) | I2: ='Bill of Quantities'!J2 -> Labour (min) | J2: ='Bill of Quantities'!K2 -> Structure | ... N2: ='Bill of Quantities'!O2 -> Total cost ($) | O2: Volume (m3) | P2: Weight (kg) | Q2: =H2 -> Carbon storage (kg CO2) | R2: =I2 -> Labour (min) | S2: =L2 -> Item cost ($) | T2: =M2 -> Labour cost ($) | U2: =N2 -> Total cost ($) | V2: Frame name | W2: Items in building | X2: Labour hours | Y2: Surface per frame
A4: Floor frames
A6: Foundation point | V6: =V7 -> Foundation point | Y6: =C6*E6*0.000001 -> 0
A7: 1 | B7: ='Bill of Quantities'!C35 -> Foundation block | C7: {=INDEX('Bill of Quantities'!$D:$O,MATCH($B7,'Bill of Quantities'!$C:$C,0),MATCH(C$2,'Bill of Quantities'!$D$2:$O$2,0))} -> 300 | D7: {=INDEX('Bill of Quantities'!$D:$O,MATCH($B7,'Bill of Quantities'!$C:$C,0),MATCH(D$2,'Bill of Quantities'!$D$2:$O$2,0))} -> 400 | E7: {=INDEX('Bill of Quantities'!$D:$O,MATCH($B7,'Bill of Quantities'!$C:$C,0),MATCH(E$2,'Bill of Quantities'!$D$2:$O$2,0))} -> 300 | F7: {=INDEX('Bill of Quantities'!$D:$O,MATCH($B7,'Bill of Quantities'!$C:$C,0),MATCH(F$2,'Bill of Quantities'!$D$2:$O$2,0))} -> 0.036 | G7: {=INDEX('Bill of Quantities'!$D:$O,MATCH($B7,'Bill of Quantities'!$C:$C,0),MATCH(G$2,'Bill of Quantities'!$D$2:$O$2,0))} -> 86.4 | H7: {=INDEX('Bill of Quantities'!$D:$O,MATCH($B7,'Bill of Quantities'!$C:$C,0),MATCH(H$2,'Bill of Quantities'!$D$2:$O$2,0))} -> 0 | I7: {=INDEX('Bill of Quantities'!$D:$O,MATCH($B7,'Bill of Quantities'!$C:$C,0),MATCH(I$2,'Bill of Quantities'!$D$2:$O$2,0))} -> 180 | J7: {=INDEX('Bill of Quantities'!$D:$O,MATCH($B7,'Bill of Quantities'!$C:$C,0),MATCH(J$2,'Bill of Quantities'!$D$2:$O$2,0))} -> Foundation | ... N7: {=INDEX('Bill of Quantities'!$D:$O,MATCH($B7,'Bill of Quantities'!$C:$C,0),MATCH(N$2,'Bill of Quantities'!$D$2:$O$2,0))} -> 5.625 | O7: =$A7*F7 -> 0.036 | P7: =$A7*G7 -> 86.4 | Q7: =$A7*H7 -> 0 | R7: =$A7*I7 -> 180 | S7: =$A7*L7 -> 0 | T7: =$A7*M7 -> 5.625 | U7: =$A7*N7 -> 5.625 | V7: =$A$6 -> Foundation point | W7: {=A7*INDEX('Project Costs'!A:A,MATCH(V7,'Project Costs'!B:B,0),1)} -> 25 | X7: =W7*R7/60 -> 75
A8: 0.3 | B8: ='Bill of Quantities'!C36 -> Cement Bag 50 kg | C8: {=INDEX('Bill of Quantities'!$D:$O,MATCH($B8,'Bill of Quantities'!$C:$C,0),MATCH(C$2,'Bill of Quantities'!$D$2:$O$2,0))} | D8: {=INDEX('Bill of Quantities'!$D:$O,MATCH($B8,'Bill of Quantities'!$C:$C,0),MATCH(D$2,'Bill of Quantities'!$D$2:$O$2,0))} | E8: {=INDEX('Bill of Quantities'!$D:$O,MATCH($B8,'Bill of Quantities'!$C:$C,0),MATCH(E$2,'Bill of Quantities'!$D$2:$O$2,0))} | F8: {=INDEX('Bill of Quantities'!$D:$O,MATCH($B8,'Bill of Quantities'!$C:$C,0),MATCH(F$2,'Bill of Quantities'!$D$2:$O$2,0))} | G8: {=INDEX('Bill of Quantities'!$D:$O,MATCH($B8,'Bill of Quantities'!$C:$C,0),MATCH(G$2,'Bill of Quantities'!$D$2:$O$2,0))} | H8: {=INDEX('Bill of Quantities'!$D:$O,MATCH($B8,'Bill of Quantities'!$C:$C,0),MATCH(H$2,'Bill of Quantities'!$D$2:$O$2,0))} -> -0.6 | I8: {=INDEX('Bill of Quantities'!$D:$O,MATCH($B8,'Bill of Quantities'!$C:$C,0),MATCH(I$2,'Bill of Quantities'!$D$2:$O$2,0))} | J8: {=INDEX('Bill of Quantities'!$D:$O,MATCH($B8,'Bill of Quantities'!$C:$C,0),MATCH(J$2,'Bill of Quantities'!$D$2:$O$2,0))} -> Foundation | ... N8: {=INDEX('Bill of Quantities'!$D:$O,MATCH($B8,'Bill of Quantities'!$C:$C,0),MATCH(N$2,'Bill of Quantities'!$D$2:$O$2,0))} -> 8.5890976 | O8: =$A8*F8 -> 0 | P8: =$A8*G8 -> 0 | Q8: =$A8*H8 -> -0.18 | R8: =$A8*I8 -> 0 | S8: =$A8*L8 -> 2.5767293 | T8: =$A8*M8 -> 0 | U8: =$A8*N8 -> 2.5767293 | V8: =$A$6 -> Foundation point | W8: {=A8*INDEX('Project Costs'!A:A,MATCH(V8,'Project Costs'!B:B,0),1)} -> 7.5 | X8: =W8*R8/60 -> 0
A9: =30/1000 -> 0.03 | B9: ='Bill of Quantities'!C37 -> Sand per tonne | C9: {=INDEX('Bill of Quantities'!$D:$O,MATCH($B9,'Bill of Quantities'!$C:$C,0),MATCH(C$2,'Bill of Quantities'!$D$2:$O$2,0))} | D9: {=INDEX('Bill of Quantities'!$D:$O,MATCH($B9,'Bill of Quantities'!$C:$C,0),MATCH(D$2,'Bill of Quantities'!$D$2:$O$2,0))} | E9: {=INDEX('Bill of Quantities'!$D:$O,MATCH($B9,'Bill of Quantities'!$C:$C,0),MATCH(E$2,'Bill of Quantities'!$D$2:$O$2,0))} | F9: {=INDEX('Bill of Quantities'!$D:$O,MATCH($B9,'Bill of Quantities'!$C:$C,0),MATCH(F$2,'Bill of Quantities'!$D$2:$O$2,0))} | G9: {=INDEX('Bill of Quantities'!$D:$O,MATCH($B9,'Bill of Quantities'!$C:$C,0),MATCH(G$2,'Bill of Quantities'!$D$2:$O$2,0))} | H9: {=INDEX('Bill of Quantities'!$D:$O,MATCH($B9,'Bill of Quantities'!$C:$C,0),MATCH(H$2,'Bill of Quantities'!$D$2:$O$2,0))} | I9: {=INDEX('Bill of Quantities'!$D:$O,MATCH($B9,'Bill of Quantities'!$C:$C,0),MATCH(I$2,'Bill of Quantities'!$D$2:$O$2,0))} | J9: {=INDEX('Bill of Quantities'!$D:$O,MATCH($B9,'Bill of Quantities'!$C:$C,0),MATCH(J$2,'Bill of Quantities'!$D$2:$O$2,0))} -> Foundation | ... N9: {=INDEX('Bill of Quantities'!$D:$O,MATCH($B9,'Bill of Quantities'!$C:$C,0),MATCH(N$2,'Bill of Quantities'!$D$2:$O$2,0))} -> 12.162162 | O9: =$A9*F9 -> 0 | P9: =$A9*G9 -> 0 | Q9: =$A9*H9 -> 0 | R9: =$A9*I9 -> 0 | S9: =$A9*L9 -> 0.36486486 | T9: =$A9*M9 -> 0 | U9: =$A9*N9 -> 0.36486486 | V9: =$A$6 -> Foundation point | W9: {=A9*INDEX('Project Costs'!A:A,MATCH(V9,'Project Costs'!B:B,0),1)} -> 0.75 | X9: =W9*R9/60 -> 0
A10: =40/1000 -> 0.04 | B10: ='Bill of Quantities'!C38 -> Aggregates per tonne | C10: {=INDEX('Bill of Quantities'!$D:$O,MATCH($B10,'Bill of Quantities'!$C:$C,0),MATCH(C$2,'Bill of Quantities'!$D$2:$O$2,0))} | D10: {=INDEX('Bill of Quantities'!$D:$O,MATCH($B10,'Bill of Quantities'!$C:$C,0),MATCH(D$2,'Bill of Quantities'!$D$2:$O$2,0))} | E10: {=INDEX('Bill of Quantities'!$D:$O,MATCH($B10,'Bill of Quantities'!$C:$C,0),MATCH(E$2,'Bill of Quantities'!$D$2:$O$2,0))} | F10: {=INDEX('Bill of Quantities'!$D:$O,MATCH($B10,'Bill of Quantities'!$C:$C,0),MATCH(F$2,'Bill of Quantities'!$D$2:$O$2,0))} | G10: {=INDEX('Bill of Quantities'!$D:$O,MATCH($B10,'Bill of Quantities'!$C:$C,0),MATCH(G$2,'Bill of Quantities'!$D$2:$O$2,0))} | H10: {=INDEX('Bill of Quantities'!$D:$O,MATCH($B10,'Bill of Quantities'!$C:$C,0),MATCH(H$2,'Bill of Quantities'!$D$2:$O$2,0))} | I10: {=INDEX('Bill of Quantities'!$D:$O,MATCH($B10,'Bill of Quantities'!$C:$C,0),MATCH(I$2,'Bill of Quantities'!$D$2:$O$2,0))} | J10: {=INDEX('Bill of Quantities'!$D:$O,MATCH($B10,'Bill of Quantities'!$C:$C,0),MATCH(J$2,'Bill of Quantities'!$D$2:$O$2,0))} -> Foundation | ... N10: {=INDEX('Bill of Quantities'!$D:$O,MATCH($B10,'Bill of Quantities'!$C:$C,0),MATCH(N$2,'Bill of Quantities'!$D$2:$O$2,0))} -> 62.162162 | O10: =$A10*F10 -> 0 | P10: =$A10*G10 -> 0 | Q10: =$A10*H10 -> 0 | R10: =$A10*I10 -> 0 | S10: =$A10*L10 -> 2.4864865 | T10: =$A10*M10 -> 0 | U10: =$A10*N10 -> 2.4864865 | V10: =$A$6 -> Foundation point | W10: {=A10*INDEX('Project Costs'!A:A,MATCH(V10,'Project Costs'!B:B,0),1)} -> 1 | X10: =W10*R10/60 -> 0
A11: 4 | B11: ='Bill of Quantities'!C39 -> M12 rod 200 mm (stainless steel) | C11: {=INDEX('Bill of Quantities'!$D:$O,MATCH($B11,'Bill of Quantities'!$C:$C,0),MATCH(C$2,'Bill of Quantities'!$D$2:$O$2,0))} -> 16 | D11: {=INDEX('Bill of Quantities'!$D:$O,MATCH($B11,'Bill of Quantities'!$C:$C,0),MATCH(D$2,'Bill of Quantities'!$D$2:$O$2,0))} | E11: {=INDEX('Bill of Quantities'!$D:$O,MATCH($B11,'Bill of Quantities'!$C:$C,0),MATCH(E$2,'Bill of Quantities'!$D$2:$O$2,0))} -> 250 | F11: {=INDEX('Bill of Quantities'!$D:$O,MATCH($B11,'Bill of Quantities'!$C:$C,0),MATCH(F$2,'Bill of Quantities'!$D$2:$O$2,0))} -> 5.0265482e-05 | G11: {=INDEX('Bill of Quantities'!$D:$O,MATCH($B11,'Bill of Quantities'!$C:$C,0),MATCH(G$2,'Bill of Quantities'!$D$2:$O$2,0))} | H11: {=INDEX('Bill of Quantities'!$D:$O,MATCH($B11,'Bill of Quantities'!$C:$C,0),MATCH(H$2,'Bill of Quantities'!$D$2:$O$2,0))} | I11: {=INDEX('Bill of Quantities'!$D:$O,MATCH($B11,'Bill of Quantities'!$C:$C,0),MATCH(I$2,'Bill of Quantities'!$D$2:$O$2,0))} | J11: {=INDEX('Bill of Quantities'!$D:$O,MATCH($B11,'Bill of Quantities'!$C:$C,0),MATCH(J$2,'Bill of Quantities'!$D$2:$O$2,0))} -> Foundation | ... N11: {=INDEX('Bill of Quantities'!$D:$O,MATCH($B11,'Bill of Quantities'!$C:$C,0),MATCH(N$2,'Bill of Quantities'!$D$2:$O$2,0))} -> 3 | O11: =$A11*F11 -> 0.00020106193 | P11: =$A11*G11 -> 0 | Q11: =$A11*H11 -> 0 | R11: =$A11*I11 -> 0 | S11: =$A11*L11 -> 12 | T11: =$A11*M11 -> 0 | U11: =$A11*N11 -> 12 | V11: =$A$6 -> Foundation point | W11: {=A11*INDEX('Project Costs'!A:A,MATCH(V11,'Project Costs'!B:B,0),1)} -> 100 | X11: =W11*R11/60 -> 0
A12: 8 | B12: ='Bill of Quantities'!C40 -> M12 nut (stainless steel) | C12: {=INDEX('Bill of Quantities'!$D:$O,MATCH($B12,'Bill of Quantities'!$C:$C,0),MATCH(C$2,'Bill of Quantities'!$D$2:$O$2,0))} -> 24 | D12: {=INDEX('Bill of Quantities'!$D:$O,MATCH($B12,'Bill of Quantities'!$C:$C,0),MATCH(D$2,'Bill of Quantities'!$D$2:$O$2,0))} -> 24 | E12: {=INDEX('Bill of Quantities'!$D:$O,MATCH($B12,'Bill of Quantities'!$C:$C,0),MATCH(E$2,'Bill of Quantities'!$D$2:$O$2,0))} -> 13 | F12: {=INDEX('Bill of Quantities'!$D:$O,MATCH($B12,'Bill of Quantities'!$C:$C,0),MATCH(F$2,'Bill of Quantities'!$D$2:$O$2,0))} | G12: {=INDEX('Bill of Quantities'!$D:$O,MATCH($B12,'Bill of Quantities'!$C:$C,0),MATCH(G$2,'Bill of Quantities'!$D$2:$O$2,0))} | H12: {=INDEX('Bill of Quantities'!$D:$O,MATCH($B12,'Bill of Quantities'!$C:$C,0),MATCH(H$2,'Bill of Quantities'!$D$2:$O$2,0))} | I12: {=INDEX('Bill of Quantities'!$D:$O,MATCH($B12,'Bill of Quantities'!$C:$C,0),MATCH(I$2,'Bill of Quantities'!$D$2:$O$2,0))} | J12: {=INDEX('Bill of Quantities'!$D:$O,MATCH($B12,'Bill of Quantities'!$C:$C,0),MATCH(J$2,'Bill of Quantities'!$D$2:$O$2,0))} -> Foundation | ... N12: {=INDEX('Bill of Quantities'!$D:$O,MATCH($B12,'Bill of Quantities'!$C:$C,0),MATCH(N$2,'Bill of Quantities'!$D$2:$O$2,0))} -> 0.4 | O12: =$A12*F12 -> 0 | P12: =$A12*G12 -> 0 | Q12: =$A12*H12 -> 0 | R12: =$A12*I12 -> 0 | S12: =$A12*L12 -> 3.2 | T12: =$A12*M12 -> 0 | U12: =$A12*N12 -> 3.2 | V12: =$A$6 -> Foundation point | W12: {=A12*INDEX('Project Costs'!A:A,MATCH(V12,'Project Costs'!B:B,0),1)} -> 200 | X12: =W12*R12/60 -> 0
A13: 8 | B13: ='Bill of Quantities'!C41 -> M12 washer (stainless steel) | C13: {=INDEX('Bill of Quantities'!$D:$O,MATCH($B13,'Bill of Quantities'!$C:$C,0),MATCH(C$2,'Bill of Quantities'!$D$2:$O$2,0))} -> 30 | D13: {=INDEX('Bill of Quantities'!$D:$O,MATCH($B13,'Bill of Quantities'!$C:$C,0),MATCH(D$2,'Bill of Quantities'!$D$2:$O$2,0))} | E13: {=INDEX('Bill of Quantities'!$D:$O,MATCH($B13,'Bill of Quantities'!$C:$C,0),MATCH(E$2,'Bill of Quantities'!$D$2:$O$2,0))} -> 3 | F13: {=INDEX('Bill of Quantities'!$D:$O,MATCH($B13,'Bill of Quantities'!$C:$C,0),MATCH(F$2,'Bill of Quantities'!$D$2:$O$2,0))} | G13: {=INDEX('Bill of Quantities'!$D:$O,MATCH($B13,'Bill of Quantities'!$C:$C,0),MATCH(G$2,'Bill of Quantities'!$D$2:$O$2,0))} | H13: {=INDEX('Bill of Quantities'!$D:$O,MATCH($B13,'Bill of Quantities'!$C:$C,0),MATCH(H$2,'Bill of Quantities'!$D$2:$O$2,0))} | I13: {=INDEX('Bill of Quantities'!$D:$O,MATCH($B13,'Bill of Quantities'!$C:$C,0),MATCH(I$2,'Bill of Quantities'!$D$2:$O$2,0))} | J13: {=INDEX('Bill of Quantities'!$D:$O,MATCH($B13,'Bill of Quantities'!$C:$C,0),MATCH(J$2,'Bill of Quantities'!$D$2:$O$2,0))} -> Foundation | ... N13: {=INDEX('Bill of Quantities'!$D:$O,MATCH($B13,'Bill of Quantities'!$C:$C,0),MATCH(N$2,'Bill of Quantities'!$D$2:$O$2,0))} -> 0.2 | O13: =$A13*F13 -> 0 | P13: =$A13*G13 -> 0 | Q13: =$A13*H13 -> 0 | R13: =$A13*I13 -> 0 | S13: =$A13*L13 -> 1.6 | T13: =$A13*M13 -> 0 | U13: =$A13*N13 -> 1.6 | V13: =$A$6 -> Foundation point | W13: {=A13*INDEX('Project Costs'!A:A,MATCH(V13,'Project Costs'!B:B,0),1)} -> 200 | X13: =W13*R13/60 -> 0
A14: 4 | B14: ='Bill of Quantities'!C42 -> M12 drop anchor | C14: {=INDEX('Bill of Quantities'!$D:$O,MATCH($B14,'Bill of Quantities'!$C:$C,0),MATCH(C$2,'Bill of Quantities'!$D$2:$O$2,0))} -> 20 | D14: {=INDEX('Bill of Quantities'!$D:$O,MATCH($B14,'Bill of Quantities'!$C:$C,0),MATCH(D$2,'Bill of Quantities'!$D$2:$O$2,0))} | E14: {=INDEX('Bill of Quantities'!$D:$O,MATCH($B14,'Bill of Quantities'!$C:$C,0),MATCH(E$2,'Bill of Quantities'!$D$2:$O$2,0))} -> 65 | F14: {=INDEX('Bill of Quantities'!$D:$O,MATCH($B14,'Bill of Quantities'!$C:$C,0),MATCH(F$2,'Bill of Quantities'!$D$2:$O$2,0))} | G14: {=INDEX('Bill of Quantities'!$D:$O,MATCH($B14,'Bill of Quantities'!$C:$C,0),MATCH(G$2,'Bill of Quantities'!$D$2:$O$2,0))} | H14: {=INDEX('Bill of Quantities'!$D:$O,MATCH($B14,'Bill of Quantities'!$C:$C,0),MATCH(H$2,'Bill of Quantities'!$D$2:$O$2,0))} | I14: {=INDEX('Bill of Quantities'!$D:$O,MATCH($B14,'Bill of Quantities'!$C:$C,0),MATCH(I$2,'Bill of Quantities'!$D$2:$O$2,0))} | J14: {=INDEX('Bill of Quantities'!$D:$O,MATCH($B14,'Bill of Quantities'!$C:$C,0),MATCH(J$2,'Bill of Quantities'!$D$2:$O$2,0))} -> Foundation | ... N14: {=INDEX('Bill of Quantities'!$D:$O,MATCH($B14,'Bill of Quantities'!$C:$C,0),MATCH(N$2,'Bill of Quantities'!$D$2:$O$2,0))} -> 1 | O14: =$A14*F14 -> 0 | P14: =$A14*G14 -> 0 | Q14: =$A14*H14 -> 0 | R14: =$A14*I14 -> 0 | S14: =$A14*L14 -> 4 | T14: =$A14*M14 -> 0 | U14: =$A14*N14 -> 4 | V14: =$A$6 -> Foundation point | W14: {=A14*INDEX('Project Costs'!A:A,MATCH(V14,'Project Costs'!B:B,0),1)} -> 100 | X14: =W14*R14/60 -> 0
